Workbook

Sheet READ ME
A2: READ ME — 1 MINUTE
A3: The ONLY tab you use is MATCHDAY. (Bets = engine audit · Dashboard = scoreboard · Method = settings & rules · Model vs Market = context.)
A5: YELLOW CELLS = YOU TYPE. There are only 5 things, all on the Matchday tab:
A6: 1. Odds 1 / X / 2 — the three DECIMAL prices from your betting app (1 = home, X = draw, 2 = away). 21/50 → 1.42 · 7/2 → 4.50 · 15/2 → 8.50. Bet365: Settings → Odds format → Decimal.
A7: 2. Team news OK? — Y or N. Only needed when DECISION says BET.
A8: 3. Placed? + Backed (H/D/A) + Odds you got + Stake you placed — your log AFTER you bet. "Backed" = the outcome on your slip; P&L grades against it, so model updates can never rewrite your record.
A9: 4. Result — H, D, A or Void, after full time.
A10: 5. Closing odds (optional) — the price just before kickoff, for the CLV homework.
A12: EVERYTHING ELSE IS AUTOMATIC: PICK, DECISION, ENGINE STAKE, WHY, FINAL ACTION, STATUS, CLV, the whole Dashboard and your bankroll.
A14: HOW TO READ THE ANSWER
A15: · ENGINE STAKE "–" + FINAL ACTION "❌ NO BET" → the engine DID respond: do not bet this match. Example: South Korea v Czechia at 2.70 / 3.10 / 2.80 → EV +1.6%, below the 2.5% bar → NO BET. Nothing is broken.
A16: · FINAL ACTION "🟢 PLACE £x on [pick]" → bet exactly that amount on exactly that pick, after the team-news check.
... A32: v2.2 — last-mile hardening: pause can no longer distort the STATUS text for un-snapshotted bets; First-time setup now retro-snapshots any bet placed before the script existed; snapshot cells stay writable for shared editors (share view-only with friends regardless — they scale stakes via "£ / £100 bank").

Sheet Goal Grid
A1: GOAL GRID — fair P for O/U, BTTS, AH from λ_h/λ_a · Poisson + Dixon-Coles τ=-0.13 · MAX_GOALS=15 · ⚠ DRIFT: Poisson vs prod NB+DC ≈2-9pp on OU2.5/BTTS; BET? uses Method!B8 edge threshold (raise B8 to 0.08 for an 8pp drift buffer)
A2: Source: /predictions_live.json · match_predictions[] · type Over 2.5 book odds in K for BET? signal
A3: #m | B3: Date | C3: Home | D3: Away | E3: λ_home | F3: λ_away | G3: Fair O/U 2.5 | H3: Fair BTTS | I3: Fair O/U 1.5 | J3: Fair O/U 3.5 | K3: Book O 2.5 | L3: Book U 2.5 | M3: Book BTTS Y | N3: Implied O 2.5 | O3: Edge % | P3: BET?
A4: 1 | B4: 46184 | C4: Mexico | D4: South Africa | E4: 2.5240228 | F4: 0.49607706 | G4: =IFERROR(GOAL_GRID(E4,F4,"ou25"),"") -> 0.59686922 | H4: =IFERROR(GOAL_GRID(E4,F4,"btts"),"") -> 0.37753708 | I4: =IFERROR(GOAL_GRID(E4,F4,"ou15"),"") -> 0.83352165 | J4: =IFERROR(GOAL_GRID(E4,F4,"ou35"),"") -> 0.36684143 | N4: =IF(K4="","",1/K4) | O4: =IF(OR(G4="",N4=""),"",G4-N4) | P4: =IF(Method!$B$55=TRUE(),"🛑 PAUSED",IF(O4="","",IF(O4<Method!$B$8,"PASS","BET")))
A5: 2 | B5: 46184 | C5: South Korea | D5: Czechia | E5: 1.4271605 | F5: 1.0216546 | G5: =IFERROR(GOAL_GRID(E5,F5,"ou25"),"") -> 0.44381124 | H5: =IFERROR(GOAL_GRID(E5,F5,"btts"),"") -> 0.50371419 | I5: =IFERROR(GOAL_GRID(E5,F5,"ou15"),"") -> 0.71974199 | J5: =IFERROR(GOAL_GRID(E5,F5,"ou35"),"") -> 0.23196895 | N5: =IF(K5="","",1/K5) | O5: =IF(OR(G5="",N5=""),"",G5-N5) | P5: =IF(Method!$B$55=TRUE(),"🛑 PAUSED",IF(O5="","",IF(O5<Method!$B$8,"PASS","BET")))
A6: 3 | B6: 46185 | C6: Canada | D6: Bosnia and Herzegovina | E6: 2.2224662 | F6: 0.52223951 | G6: =IFERROR(GOAL_GRID(E6,F6,"ou25"),"") -> 0.53006453 | H6: =IFERROR(GOAL_GRID(E6,F6,"btts"),"") -> 0.38164948 | I6: =IFERROR(GOAL_GRID(E6,F6,"ou15"),"") -> 0.78806835 | J6: =IFERROR(GOAL_GRID(E6,F6,"ou35"),"") -> 0.30310771 | N6: =IF(K6="","",1/K6) | O6: =IF(OR(G6="",N6=""),"",G6-N6) | P6: =IF(Method!$B$55=TRUE(),"🛑 PAUSED",IF(O6="","",IF(O6<Method!$B$8,"PASS","BET")))
A7: 4 | B7: 46185 | C7: United States | D7: Paraguay | E7: 1.5587058 | F7: 0.95105469 | G7: =IFERROR(GOAL_GRID(E7,F7,"ou25"),"") -> 0.46048492 | H7: =IFERROR(GOAL_GRID(E7,F7,"btts"),"") -> 0.50217085 | I7: =IFERROR(GOAL_GRID(E7,F7,"ou15"),"") -> 0.73322587 | J7: =IFERROR(GOAL_GRID(E7,F7,"ou35"),"") -> 0.24547012 | N7: =IF(K7="","",1/K7) | O7: =IF(OR(G7="",N7=""),"",G7-N7) | P7: =IF(Method!$B$55=TRUE(),"🛑 PAUSED",IF(O7="","",IF(O7<Method!$B$8,"PASS","BET")))
A8: 5 | B8: 46186 | C8: Qatar | D8: Switzerland | E8: 0.46476638 | F8: 2.7748048 | G8: =IFERROR(GOAL_GRID(E8,F8,"ou25"),"") -> 0.64584779 | H8: =IFERROR(GOAL_GRID(E8,F8,"btts"),"") -> 0.36502748 | I8: =IFERROR(GOAL_GRID(E8,F8,"ou15"),"") -> 0.86394158 | J8: =IFERROR(GOAL_GRID(E8,F8,"ou35"),"") -> 0.41762916 | N8: =IF(K8="","",1/K8) | O8: =IF(OR(G8="",N8=""),"",G8-N8) | P8: =IF(Method!$B$55=TRUE(),"🛑 PAUSED",IF(O8="","",IF(O8<Method!$B$8,"PASS","BET")))
A9: 6 | B9: 46186 | C9: Brazil | D9: Morocco | E9: 1.3950821 | F9: 1.1852653 | G9: =IFERROR(GOAL_GRID(E9,F9,"ou25"),"") -> 0.47683235 | H9: =IFERROR(GOAL_GRID(E9,F9,"btts"),"") -> 0.53878625 | I9: =IFERROR(GOAL_GRID(E9,F9,"ou15"),"") -> 0.74540287 | J9: =IFERROR(GOAL_GRID(E9,F9,"ou35"),"") -> 0.25984173 | N9: =IF(K9="","",1/K9) | O9: =IF(OR(G9="",N9=""),"",G9-N9) | P9: =IF(Method!$B$55=TRUE(),"🛑 PAUSED",IF(O9="","",IF(O9<Method!$B$8,"PASS","BET")))
A10: 7 | B10: 46186 | C10: Haiti | D10: Scotland | E10: 0.9333598 | F10: 1.7620295 | G10: =IFERROR(GOAL_GRID(E10,F10,"ou25"),"") -> 0.50830905 | H10: =IFERROR(GOAL_GRID(E10,F10,"btts"),"") -> 0.52015969 | I10: =IFERROR(GOAL_GRID(E10,F10,"ou15"),"") -> 0.76957499 | J10: =IFERROR(GOAL_GRID(E10,F10,"ou35"),"") -> 0.28661908 | N10: =IF(K10="","",1/K10) | O10: =IF(OR(G10="",N10=""),"",G10-N10) | P10: =IF(Method!$B$55=TRUE(),"🛑 PAUSED",IF(O10="","",IF(O10<Method!$B$8,"PASS","BET")))
A11: 8 | B11: 46186 | C11: Australia | D11: Turkey | E11: 1.0624391 | F11: 1.1295289 | G11: =IFERROR(GOAL_GRID(E11,F11,"ou25"),"") -> 0.37515625 | H11: =IFERROR(GOAL_GRID(E11,F11,"btts"),"") -> 0.46035502 | I11: =IFERROR(GOAL_GRID(E11,F11,"ou15"),"") -> 0.66093635 | J11: =IFERROR(GOAL_GRID(E11,F11,"ou35"),"") -> 0.17908219 | N11: =IF(K11="","",1/K11) | O11: =IF(OR(G11="",N11=""),"",G11-N11) | P11: =IF(Method!$B$55=TRUE(),"🛑 PAUSED",IF(O11="","",IF(O11<Method!$B$8,"PASS","BET")))
A12: 9 | B12: 46187 | C12: Germany | D12: Curacao | E12: 2.9122472 | F12: 0.61247241 | G12: =IFERROR(GOAL_GRID(E12,F12,"ou25"),"") -> 0.69783585 | H12: =IFERROR(GOAL_GRID(E12,F12,"btts"),"") -> 0.4490239 | I12: =IFERROR(GOAL_GRID(E12,F12,"ou15"),"") -> 0.89159241 | J12: =IFERROR(GOAL_GRID(E12,F12,"ou35"),"") -> 0.47838185 | N12: =IF(K12="","",1/K12) | O12: =IF(OR(G12="",N12=""),"",G12-N12) | P12: =IF(Method!$B$55=TRUE(),"🛑 PAUSED",IF(O12="","",IF(O12<Method!$B$8,"PASS","BET")))
A13: 10 | B13: 46187 | C13: Netherlands | D13: Japan | E13: 1.5585992 | F13: 0.96455956 | G13: =IFERROR(GOAL_GRID(E13,F13,"ou25"),"") -> 0.46382016 | H13: =IFERROR(GOAL_GRID(E13,F13,"btts"),"") -> 0.50616176 | I13: =IFERROR(GOAL_GRID(E13,F13,"ou15"),"") -> 0.73580458 | J13: =IFERROR(GOAL_GRID(E13,F13,"ou35"),"") -> 0.24829923 | N13: =IF(K13="","",1/K13) | O13: =IF(OR(G13="",N13=""),"",G13-N13) | P13: =IF(Method!$B$55=TRUE(),"🛑 PAUSED",IF(O13="","",IF(O13<Method!$B$8,"PASS","BET")))
A14: 11 | B14: 46187 | C14: Ivory Coast | D14: Ecuador | E14: 0.92886335 | F14: 1.5627021 | G14: =IFERROR(GOAL_GRID(E14,F14,"ou25"),"") -> 0.45599291 | H14: =IFERROR(GOAL_GRID(E14,F14,"btts"),"") -> 0.49597373 | I14: =IFERROR(GOAL_GRID(E14,F14,"ou15"),"") -> 0.72974284 | J14: =IFERROR(GOAL_GRID(E14,F14,"ou35"),"") -> 0.24166722 | N14: =IF(K14="","",1/K14) | O14: =IF(OR(G14="",N14=""),"",G14-N14) | P14: =IF(Method!$B$55=TRUE(),"🛑 PAUSED",IF(O14="","",IF(O14<Method!$B$8,"PASS","BET")))
A15: 12 | B15: 46187 | C15: Sweden | D15: Tunisia | E15: 1.4041743 | F15: 1.1511817 | G15: =IFERROR(GOAL_GRID(E15,F15,"ou25"),"") -> 0.4706101 | H15: =IFERROR(GOAL_GRID(E15,F15,"btts"),"") -> 0.53249655 | I15: =IFERROR(GOAL_GRID(E15,F15,"ou15"),"") -> 0.74067384 | J15: =IFERROR(GOAL_GRID(E15,F15,"ou35"),"") -> 0.25448424 | N15: =IF(K15="","",1/K15) | O15: =IF(OR(G15="",N15=""),"",G15-N15) | P15: =IF(Method!$B$55=TRUE(),"🛑 PAUSED",IF(O15="","",IF(O15<Method!$B$8,"PASS","BET")))
... A103: 100 | B103: 46214 | C103: Argentina | D103: Switzerland | E103: 2.0778609 | F103: 0.53434993 | G103: =IFERROR(GOAL_GRID(E103,F103,"ou25"),"") -> 0.49590064 | H103: =IFERROR(GOAL_GRID(E103,F103,"btts"),"") -> 0.38138148 | I103: =IFERROR(GOAL_GRID(E103,F103,"ou15"),"") -> 0.76289114 | J103: =IFERROR(GOAL_GRID(E103,F103,"ou35"),"") -> 0.27285812 | N103: =IF(K103="","",1/K103) | O103: =IF(OR(G103="",N103=""),"",G103-N103) | P103: =IF(Method!$B$55=TRUE(),"🛑 PAUSED",IF(O103="","",IF(O103<Method!$B$8,"PASS","BET")))
A104: 101 | B104: 46217 | C104: W97 | D104: W98
A105: 102 | B105: 46218 | C105: W99 | D105: W100
A106: 103 | B106: 46221 | C106: L101 | D106: L102
A107: 104 | B107: 46222 | C107: W101 | D107: W102

Sheet CLV
A1: CLV — closing-line-value tracker · rolling 20-bet average · positive CLV = beating the close | B1: CLV tracked for 1X2 picks only — O/U and BTTS coming in v2.4
A2: Source: Bets!AO backed odds + AW:AY snapshot block · type closing odds in col F after market closes
A3: Bet # | B3: #m | C3: Pick | D3: Stake | E3: Taken odds | F3: Closing odds | G3: CLV % | H3: Rolling 20 CLV % | I3: Status
A4: 1 | B4: 2 | C4: H | D4: 3 | E4: 2.6 | G4: =IF(OR(E4="",F4="",NOT(ISNUMBER(E4)),NOT(ISNUMBER(F4)),E4<=0,F4<=0),"",(E4-F4)/F4) | H4: =IFERROR(IF(COUNT(G4)<20,"n="&COUNT(G4)&": "&AVERAGE(G4),AVERAGE(G4)),"") | I4: =IFERROR(__xludf.DUMMYFUNCTION("IF(H4="""","""",IF(ISNUMBER(H4),IF(H4>0,""BEATING CLOSE"",""BELOW CLOSE""),IF(IFERROR(VALUE(REGEXEXTRACT(H4,"": (.*)$"")),0)>0,""BEATING CLOSE (n<20)"",""BELOW CLOSE (n<20)"")))"),"")
A5: 2 | B5: 3 | C5: H | D5: 12 | E5: 1.85 | G5: =IF(OR(E5="",F5="",NOT(ISNUMBER(E5)),NOT(ISNUMBER(F5)),E5<=0,F5<=0),"",(E5-F5)/F5) | H5: =IFERROR(IF(COUNT(G4:G5)<20,"n="&COUNT(G4:G5)&": "&AVERAGE(G4:G5),AVERAGE(G4:G5)),"") | I5: =IFERROR(__xludf.DUMMYFUNCTION("IF(H5="""","""",IF(ISNUMBER(H5),IF(H5>0,""BEATING CLOSE"",""BELOW CLOSE""),IF(IFERROR(VALUE(REGEXEXTRACT(H5,"": (.*)$"")),0)>0,""BEATING CLOSE (n<20)"",""BELOW CLOSE (n<20)"")))"),"")
A6: 3 | B6: 6 | C6: A | D6: 5 | E6: 1.68 | G6: =IF(OR(E6="",F6="",NOT(ISNUMBER(E6)),NOT(ISNUMBER(F6)),E6<=0,F6<=0),"",(E6-F6)/F6) | H6: =IFERROR(IF(COUNT(G4:G6)<20,"n="&COUNT(G4:G6)&": "&AVERAGE(G4:G6),AVERAGE(G4:G6)),"") | I6: =IFERROR(__xludf.DUMMYFUNCTION("IF(H6="""","""",IF(ISNUMBER(H6),IF(H6>0,""BEATING CLOSE"",""BELOW CLOSE""),IF(IFERROR(VALUE(REGEXEXTRACT(H6,"": (.*)$"")),0)>0,""BEATING CLOSE (n<20)"",""BELOW CLOSE (n<20)"")))"),"")
A7: 4 | B7: 8 | C7: H | D7: 0 | E7: 5.25 | G7: =IF(OR(E7="",F7="",NOT(ISNUMBER(E7)),NOT(ISNUMBER(F7)),E7<=0,F7<=0),"",(E7-F7)/F7) | H7: =IFERROR(IF(COUNT(G4:G7)<20,"n="&COUNT(G4:G7)&": "&AVERAGE(G4:G7),AVERAGE(G4:G7)),"") | I7: =IFERROR(__xludf.DUMMYFUNCTION("IF(H7="""","""",IF(ISNUMBER(H7),IF(H7>0,""BEATING CLOSE"",""BELOW CLOSE""),IF(IFERROR(VALUE(REGEXEXTRACT(H7,"": (.*)$"")),0)>0,""BEATING CLOSE (n<20)"",""BELOW CLOSE (n<20)"")))"),"")
A8: 5 | B8: 9 | C8: D | D8: 6 | E8: 19 | G8: =IF(OR(E8="",F8="",NOT(ISNUMBER(E8)),NOT(ISNUMBER(F8)),E8<=0,F8<=0),"",(E8-F8)/F8) | H8: =IFERROR(IF(COUNT(G4:G8)<20,"n="&COUNT(G4:G8)&": "&AVERAGE(G4:G8),AVERAGE(G4:G8)),"") | I8: =IFERROR(__xludf.DUMMYFUNCTION("IF(H8="""","""",IF(ISNUMBER(H8),IF(H8>0,""BEATING CLOSE"",""BELOW CLOSE""),IF(IFERROR(VALUE(REGEXEXTRACT(H8,"": (.*)$"")),0)>0,""BEATING CLOSE (n<20)"",""BELOW CLOSE (n<20)"")))"),"")
A9: 6 | B9: 51 | C9: H | D9: 12 | E9: 7.5 | G9: =IF(OR(E9="",F9="",NOT(ISNUMBER(E9)),NOT(ISNUMBER(F9)),E9<=0,F9<=0),"",(E9-F9)/F9) | H9: =IFERROR(IF(COUNT(G4:G9)<20,"n="&COUNT(G4:G9)&": "&AVERAGE(G4:G9),AVERAGE(G4:G9)),"") | I9: =IFERROR(__xludf.DUMMYFUNCTION("IF(H9="""","""",IF(ISNUMBER(H9),IF(H9>0,""BEATING CLOSE"",""BELOW CLOSE""),IF(IFERROR(VALUE(REGEXEXTRACT(H9,"": (.*)$"")),0)>0,""BEATING CLOSE (n<20)"",""BELOW CLOSE (n<20)"")))"),"")
A10: 7 | B10: 69 | C10: H | D10: 19 | E10: 4.2 | G10: =IF(OR(E10="",F10="",NOT(ISNUMBER(E10)),NOT(ISNUMBER(F10)),E10<=0,F10<=0),"",(E10-F10)/F10) | H10: =IFERROR(IF(COUNT(G4:G10)<20,"n="&COUNT(G4:G10)&": "&AVERAGE(G4:G10),AVERAGE(G4:G10)),"") | I10: =IFERROR(__xludf.DUMMYFUNCTION("IF(H10="""","""",IF(ISNUMBER(H10),IF(H10>0,""BEATING CLOSE"",""BELOW CLOSE""),IF(IFERROR(VALUE(REGEXEXTRACT(H10,"": (.*)$"")),0)>0,""BEATING CLOSE (n<20)"",""BELOW CLOSE (n<20)"")))"),"")
A11: 8 | B11: 70 | C11: A | D11: 16 | E11: 5 | G11: =IF(OR(E11="",F11="",NOT(ISNUMBER(E11)),NOT(ISNUMBER(F11)),E11<=0,F11<=0),"",(E11-F11)/F11) | H11: =IFERROR(IF(COUNT(G4:G11)<20,"n="&COUNT(G4:G11)&": "&AVERAGE(G4:G11),AVERAGE(G4:G11)),"") | I11: =IFERROR(__xludf.DUMMYFUNCTION("IF(H11="""","""",IF(ISNUMBER(H11),IF(H11>0,""BEATING CLOSE"",""BELOW CLOSE""),IF(IFERROR(VALUE(REGEXEXTRACT(H11,"": (.*)$"")),0)>0,""BEATING CLOSE (n<20)"",""BELOW CLOSE (n<20)"")))"),"")

Sheet Dashboard
A1: WC26 GROUP STAGE — VALUE BETTING DASHBOARD
A2: Model snapshot 2026-06-10 14:10 UTC · type odds on the MATCHDAY tab on game day · stakes auto-size from current bankroll
A4: Current bankroll | B4: =Method!B10 -> 969.4 | C4: Matches today | D4: =COUNTIF(Bets!B2:B105,TODAY()) -> 1 | E4: Engine bets placed | F4: =SUMPRODUCT(--(Bets!AN2:AN105="Y"),--(Bets!AZ2:AZ105="BET")) -> 8 | G4: =IF(F5=0,"","⚠ "&F5&" fun bet(s) logged — excluded from engine quality. Judge the engine on Engine P&L and ✓ rows only.") -> ⚠ 4 fun bet(s) logged — excluded from engine quality. Judge the engine on Engine P&L and ✓ rows only.
A5: Staked (placed) | B5: =SUMIF(Bets!AN2:AN105,"Y",Bets!AP2:AP105) -> 178.5 | C5: Next match day | D5: =IFERROR(SMALL(Bets!B2:B105,COUNTIF(Bets!B2:B105,"<"&TODAY())+1),"finished") -> 46212 | E5: Fun bets placed | F5: =SUMPRODUCT(--(Bets!AN2:AN105="Y"),--(Bets!AZ2:AZ105<>"BET")) -> 4
A6: Settled P&L | B6: =SUM(Bets!AR2:AR105) -> -30.6 | C6: BET signals live | D6: =COUNTIF(Bets!AH2:AH105,"BET") -> 41 | E6: Avg CLV (logged) | F6: =IFERROR(AVERAGE(Matchday!U4:U107),"–") -> 0.86505467
A7: ROI (settled) | B7: =IF(SUMPRODUCT(--(Bets!AN2:AN105="Y"),--(Bets!AQ2:AQ105<>""),Bets!AP2:AP105)=0,"–",B6/SUMPRODUCT(--(Bets!AN2:AN105="Y"),--(Bets!AQ2:AQ105<>""),Bets!AP2:AP105)) -> -0.17142857 | C7: PASS | D7: =COUNTIF(Bets!AH2:AH105,"PASS") -> 59 | E7: Engine P&L | F7: =SUMIF(Bets!AZ2:AZ105,"BET",Bets!AR2:AR105) -> -40
A8: Record W–L | B8: =COUNTIF(Bets!AR2:AR105,">0")&" – "&COUNTIF(Bets!AR2:AR105,"<0") -> 4 – 7 | C8: Awaiting odds | D8: =COUNTIF(Bets!AH2:AH105,"· enter odds") -> 4 | E8: Fun-bet P&L | F8: =SUMIFS(Bets!AR2:AR105,Bets!AN2:AN105,"Y",Bets!AZ2:AZ105,"<>BET") -> 9.4
A9: Open bets | B9: =SUMPRODUCT(--(Bets!AN2:AN105="Y"),--(Bets!AQ2:AQ105="")) -> 0 | C9: Sum of BET stakes | D9: =SUM(Bets!AJ2:AJ105) -> 459
A11: LIVE VALUE BOARD — top BET signals right now (fills as you enter odds)
A12: # | B12: Date | C12: Group | D12: Match | E12: Pick | F12: Odds | G12: EV | H12: Edge | I12: Stake £
A13: {=IFERROR(INDEX(Bets!$A$2:$A$105,MATCH(LARGE(Bets!$AM$2:$AM$105,1),Bets!$AM$2:$AM$105,0)),"")} -> 97 | B13: {=IFERROR(INDEX(Bets!$B$2:$B$105,MATCH(LARGE(Bets!$AM$2:$AM$105,1),Bets!$AM$2:$AM$105,0)),"")} -> 46212 | C13: {=IFERROR(INDEX(Bets!$C$2:$C$105,MATCH(LARGE(Bets!$AM$2:$AM$105,1),Bets!$AM$2:$AM$105,0)),"")} -> QF | D13: {=IFERROR(INDEX(Bets!$D$2:$D$105,MATCH(LARGE(Bets!$AM$2:$AM$105,1),Bets!$AM$2:$AM$105,0))&" v "&INDEX(Bets!$E$2:$E$105,MATCH(LARGE(Bets!$AM$2:$AM$105,1),Bets!$AM$2:$AM$105,0)),"")} -> France v Morocco | E13: {=IFERROR(INDEX(Bets!$AD$2:$AD$105,MATCH(LARGE(Bets!$AM$2:$AM$105,1),Bets!$AM$2:$AM$105,0)),"")} -> 2 Morocco | F13: {=IFERROR(INDEX(Bets!$AE$2:$AE$105,MATCH(LARGE(Bets!$AM$2:$AM$105,1),Bets!$AM$2:$AM$105,0)),"")} -> 6.5 | G13: {=IFERROR(INDEX(Bets!$AF$2:$AF$105,MATCH(LARGE(Bets!$AM$2:$AM$105,1),Bets!$AM$2:$AM$105,0)),"")} -> 0.29746604 | H13: {=IFERROR(INDEX(Bets!$AG$2:$AG$105,MATCH(LARGE(Bets!$AM$2:$AM$105,1),Bets!$AM$2:$AM$105,0)),"")} -> 0.059174952 | I13: {=IFERROR(INDEX(Bets!$AJ$2:$AJ$105,MATCH(LARGE(Bets!$AM$2:$AM$105,1),Bets!$AM$2:$AM$105,0)),"")} -> 14
A14: {=IFERROR(INDEX(Bets!$A$2:$A$105,MATCH(LARGE(Bets!$AM$2:$AM$105,2),Bets!$AM$2:$AM$105,0)),"")} -> 56 | B14: {=IFERROR(INDEX(Bets!$B$2:$B$105,MATCH(LARGE(Bets!$AM$2:$AM$105,2),Bets!$AM$2:$AM$105,0)),"")} -> 46198 | C14: {=IFERROR(INDEX(Bets!$C$2:$C$105,MATCH(LARGE(Bets!$AM$2:$AM$105,2),Bets!$AM$2:$AM$105,0)),"")} -> E | D14: {=IFERROR(INDEX(Bets!$D$2:$D$105,MATCH(LARGE(Bets!$AM$2:$AM$105,2),Bets!$AM$2:$AM$105,0))&" v "&INDEX(Bets!$E$2:$E$105,MATCH(LARGE(Bets!$AM$2:$AM$105,2),Bets!$AM$2:$AM$105,0)),"")} -> Curacao v Ivory Coast | E14: {=IFERROR(INDEX(Bets!$AD$2:$AD$105,MATCH(LARGE(Bets!$AM$2:$AM$105,2),Bets!$AM$2:$AM$105,0)),"")} -> X Draw | F14: {=IFERROR(INDEX(Bets!$AE$2:$AE$105,MATCH(LARGE(Bets!$AM$2:$AM$105,2),Bets!$AM$2:$AM$105,0)),"")} -> 7.5 | G14: {=IFERROR(INDEX(Bets!$AF$2:$AF$105,MATCH(LARGE(Bets!$AM$2:$AM$105,2),Bets!$AM$2:$AM$105,0)),"")} -> 0.27230886 | H14: {=IFERROR(INDEX(Bets!$AG$2:$AG$105,MATCH(LARGE(Bets!$AM$2:$AM$105,2),Bets!$AM$2:$AM$105,0)),"")} -> 0.052771394 | I14: {=IFERROR(INDEX(Bets!$AJ$2:$AJ$105,MATCH(LARGE(Bets!$AM$2:$AM$105,2),Bets!$AM$2:$AM$105,0)),"")} -> 10
A15: {=IFERROR(INDEX(Bets!$A$2:$A$105,MATCH(LARGE(Bets!$AM$2:$AM$105,3),Bets!$AM$2:$AM$105,0)),"")} -> 8 | B15: {=IFERROR(INDEX(Bets!$B$2:$B$105,MATCH(LARGE(Bets!$AM$2:$AM$105,3),Bets!$AM$2:$AM$105,0)),"")} -> 46186 | C15: {=IFERROR(INDEX(Bets!$C$2:$C$105,MATCH(LARGE(Bets!$AM$2:$AM$105,3),Bets!$AM$2:$AM$105,0)),"")} -> D | D15: {=IFERROR(INDEX(Bets!$D$2:$D$105,MATCH(LARGE(Bets!$AM$2:$AM$105,3),Bets!$AM$2:$AM$105,0))&" v "&INDEX(Bets!$E$2:$E$105,MATCH(LARGE(Bets!$AM$2:$AM$105,3),Bets!$AM$2:$AM$105,0)),"")} -> Australia v Turkey | E15: {=IFERROR(INDEX(Bets!$AD$2:$AD$105,MATCH(LARGE(Bets!$AM$2:$AM$105,3),Bets!$AM$2:$AM$105,0)),"")} -> 1 Australia | F15: {=IFERROR(INDEX(Bets!$AE$2:$AE$105,MATCH(LARGE(Bets!$AM$2:$AM$105,3),Bets!$AM$2:$AM$105,0)),"")} -> 5.25 | G15: {=IFERROR(INDEX(Bets!$AF$2:$AF$105,MATCH(LARGE(Bets!$AM$2:$AM$105,3),Bets!$AM$2:$AM$105,0)),"")} -> 0.26943859 | H15: {=IFERROR(INDEX(Bets!$AG$2:$AG$105,MATCH(LARGE(Bets!$AM$2:$AM$105,3),Bets!$AM$2:$AM$105,0)),"")} -> 0.067747853 | I15: {=IFERROR(INDEX(Bets!$AJ$2:$AJ$105,MATCH(LARGE(Bets!$AM$2:$AM$105,3),Bets!$AM$2:$AM$105,0)),"")} -> 16
A16: {=IFERROR(INDEX(Bets!$A$2:$A$105,MATCH(LARGE(Bets!$AM$2:$AM$105,4),Bets!$AM$2:$AM$105,0)),"")} -> 44 | B16: {=IFERROR(INDEX(Bets!$B$2:$B$105,MATCH(LARGE(Bets!$AM$2:$AM$105,4),Bets!$AM$2:$AM$105,0)),"")} -> 46195 | C16: {=IFERROR(INDEX(Bets!$C$2:$C$105,MATCH(LARGE(Bets!$AM$2:$AM$105,4),Bets!$AM$2:$AM$105,0)),"")} -> J | D16: {=IFERROR(INDEX(Bets!$D$2:$D$105,MATCH(LARGE(Bets!$AM$2:$AM$105,4),Bets!$AM$2:$AM$105,0))&" v "&INDEX(Bets!$E$2:$E$105,MATCH(LARGE(Bets!$AM$2:$AM$105,4),Bets!$AM$2:$AM$105,0)),"")} -> Jordan v Algeria | E16: {=IFERROR(INDEX(Bets!$AD$2:$AD$105,MATCH(LARGE(Bets!$AM$2:$AM$105,4),Bets!$AM$2:$AM$105,0)),"")} -> 1 Jordan | F16: {=IFERROR(INDEX(Bets!$AE$2:$AE$105,MATCH(LARGE(Bets!$AM$2:$AM$105,4),Bets!$AM$2:$AM$105,0)),"")} -> 7.5 | G16: {=IFERROR(INDEX(Bets!$AF$2:$AF$105,MATCH(LARGE(Bets!$AM$2:$AM$105,4),Bets!$AM$2:$AM$105,0)),"")} -> 0.26022035 | H16: {=IFERROR(INDEX(Bets!$AG$2:$AG$105,MATCH(LARGE(Bets!$AM$2:$AM$105,4),Bets!$AM$2:$AM$105,0)),"")} -> 0.054694802 | I16: {=IFERROR(INDEX(Bets!$AJ$2:$AJ$105,MATCH(LARGE(Bets!$AM$2:$AM$105,4),Bets!$AM$2:$AM$105,0)),"")} -> 10
A17: {=IFERROR(INDEX(Bets!$A$2:$A$105,MATCH(LARGE(Bets!$AM$2:$AM$105,5),Bets!$AM$2:$AM$105,0)),"")} -> 55 | B17: {=IFERROR(INDEX(Bets!$B$2:$B$105,MATCH(LARGE(Bets!$AM$2:$AM$105,5),Bets!$AM$2:$AM$105,0)),"")} -> 46198 | C17: {=IFERROR(INDEX(Bets!$C$2:$C$105,MATCH(LARGE(Bets!$AM$2:$AM$105,5),Bets!$AM$2:$AM$105,0)),"")} -> E | D17: {=IFERROR(INDEX(Bets!$D$2:$D$105,MATCH(LARGE(Bets!$AM$2:$AM$105,5),Bets!$AM$2:$AM$105,0))&" v "&INDEX(Bets!$E$2:$E$105,MATCH(LARGE(Bets!$AM$2:$AM$105,5),Bets!$AM$2:$AM$105,0)),"")} -> Ecuador v Germany | E17: {=IFERROR(INDEX(Bets!$AD$2:$AD$105,MATCH(LARGE(Bets!$AM$2:$AM$105,5),Bets!$AM$2:$AM$105,0)),"")} -> 1 Ecuador | F17: {=IFERROR(INDEX(Bets!$AE$2:$AE$105,MATCH(LARGE(Bets!$AM$2:$AM$105,5),Bets!$AM$2:$AM$105,0)),"")} -> 5.25 | G17: {=IFERROR(INDEX(Bets!$AF$2:$AF$105,MATCH(LARGE(Bets!$AM$2:$AM$105,5),Bets!$AM$2:$AM$105,0)),"")} -> 0.24733004 | H17: {=IFERROR(INDEX(Bets!$AG$2:$AG$105,MATCH(LARGE(Bets!$AM$2:$AM$105,5),Bets!$AM$2:$AM$105,0)),"")} -> 0.058303159 | I17: {=IFERROR(INDEX(Bets!$AJ$2:$AJ$105,MATCH(LARGE(Bets!$AM$2:$AM$105,5),Bets!$AM$2:$AM$105,0)),"")} -> 15
A18: {=IFERROR(INDEX(Bets!$A$2:$A$105,MATCH(LARGE(Bets!$AM$2:$AM$105,6),Bets!$AM$2:$AM$105,0)),"")} -> 46 | B18: {=IFERROR(INDEX(Bets!$B$2:$B$105,MATCH(LARGE(Bets!$AM$2:$AM$105,6),Bets!$AM$2:$AM$105,0)),"")} -> 46196 | C18: {=IFERROR(INDEX(Bets!$C$2:$C$105,MATCH(LARGE(Bets!$AM$2:$AM$105,6),Bets!$AM$2:$AM$105,0)),"")} -> L | D18: {=IFERROR(INDEX(Bets!$D$2:$D$105,MATCH(LARGE(Bets!$AM$2:$AM$105,6),Bets!$AM$2:$AM$105,0))&" v "&INDEX(Bets!$E$2:$E$105,MATCH(LARGE(Bets!$AM$2:$AM$105,6),Bets!$AM$2:$AM$105,0)),"")} -> England v Ghana | E18: {=IFERROR(INDEX(Bets!$AD$2:$AD$105,MATCH(LARGE(Bets!$AM$2:$AM$105,6),Bets!$AM$2:$AM$105,0)),"")} -> X Draw | F18: {=IFERROR(INDEX(Bets!$AE$2:$AE$105,MATCH(LARGE(Bets!$AM$2:$AM$105,6),Bets!$AM$2:$AM$105,0)),"")} -> 8 | G18: {=IFERROR(INDEX(Bets!$AF$2:$AF$105,MATCH(LARGE(Bets!$AM$2:$AM$105,6),Bets!$AM$2:$AM$105,0)),"")} -> 0.2384812 | H18: {=IFERROR(INDEX(Bets!$AG$2:$AG$105,MATCH(LARGE(Bets!$AM$2:$AM$105,6),Bets!$AM$2:$AM$105,0)),"")} -> 0.032906225 | I18: {=IFERROR(INDEX(Bets!$AJ$2:$AJ$105,MATCH(LARGE(Bets!$AM$2:$AM$105,6),Bets!$AM$2:$AM$105,0)),"")} -> 9
A19: {=IFERROR(INDEX(Bets!$A$2:$A$105,MATCH(LARGE(Bets!$AM$2:$AM$105,7),Bets!$AM$2:$AM$105,0)),"")} -> 29 | B19: {=IFERROR(INDEX(Bets!$B$2:$B$105,MATCH(LARGE(Bets!$AM$2:$AM$105,7),Bets!$AM$2:$AM$105,0)),"")} -> 46192 | C19: {=IFERROR(INDEX(Bets!$C$2:$C$105,MATCH(LARGE(Bets!$AM$2:$AM$105,7),Bets!$AM$2:$AM$105,0)),"")} -> D | D19: {=IFERROR(INDEX(Bets!$D$2:$D$105,MATCH(LARGE(Bets!$AM$2:$AM$105,7),Bets!$AM$2:$AM$105,0))&" v "&INDEX(Bets!$E$2:$E$105,MATCH(LARGE(Bets!$AM$2:$AM$105,7),Bets!$AM$2:$AM$105,0)),"")} -> United States v Australia | E19: {=IFERROR(INDEX(Bets!$AD$2:$AD$105,MATCH(LARGE(Bets!$AM$2:$AM$105,7),Bets!$AM$2:$AM$105,0)),"")} -> 2 Australia | F19: {=IFERROR(INDEX(Bets!$AE$2:$AE$105,MATCH(LARGE(Bets!$AM$2:$AM$105,7),Bets!$AM$2:$AM$105,0)),"")} -> 6.5 | G19: {=IFERROR(INDEX(Bets!$AF$2:$AF$105,MATCH(LARGE(Bets!$AM$2:$AM$105,7),Bets!$AM$2:$AM$105,0)),"")} -> 0.22482113 | H19: {=IFERROR(INDEX(Bets!$AG$2:$AG$105,MATCH(LARGE(Bets!$AM$2:$AM$105,7),Bets!$AM$2:$AM$105,0)),"")} -> 0.035232701 | I19: {=IFERROR(INDEX(Bets!$AJ$2:$AJ$105,MATCH(LARGE(Bets!$AM$2:$AM$105,7),Bets!$AM$2:$AM$105,0)),"")} -> 10
A20: {=IFERROR(INDEX(Bets!$A$2:$A$105,MATCH(LARGE(Bets!$AM$2:$AM$105,8),Bets!$AM$2:$AM$105,0)),"")} -> 59 | B20: {=IFERROR(INDEX(Bets!$B$2:$B$105,MATCH(LARGE(Bets!$AM$2:$AM$105,8),Bets!$AM$2:$AM$105,0)),"")} -> 46198 | C20: {=IFERROR(INDEX(Bets!$C$2:$C$105,MATCH(LARGE(Bets!$AM$2:$AM$105,8),Bets!$AM$2:$AM$105,0)),"")} -> D | D20: {=IFERROR(INDEX(Bets!$D$2:$D$105,MATCH(LARGE(Bets!$AM$2:$AM$105,8),Bets!$AM$2:$AM$105,0))&" v "&INDEX(Bets!$E$2:$E$105,MATCH(LARGE(Bets!$AM$2:$AM$105,8),Bets!$AM$2:$AM$105,0)),"")} -> Turkey v United States | E20: {=IFERROR(INDEX(Bets!$AD$2:$AD$105,MATCH(LARGE(Bets!$AM$2:$AM$105,8),Bets!$AM$2:$AM$105,0)),"")} -> 1 Turkey | F20: {=IFERROR(INDEX(Bets!$AE$2:$AE$105,MATCH(LARGE(Bets!$AM$2:$AM$105,8),Bets!$AM$2:$AM$105,0)),"")} -> 3.7 | G20: {=IFERROR(INDEX(Bets!$AF$2:$AF$105,MATCH(LARGE(Bets!$AM$2:$AM$105,8),Bets!$AM$2:$AM$105,0)),"")} -> 0.2118303 | H20: {=IFERROR(INDEX(Bets!$AG$2:$AG$105,MATCH(LARGE(Bets!$AM$2:$AM$105,8),Bets!$AM$2:$AM$105,0)),"")} -> 0.07450892 | I20: {=IFERROR(INDEX(Bets!$AJ$2:$AJ$105,MATCH(LARGE(Bets!$AM$2:$AM$105,8),Bets!$AM$2:$AM$105,0)),"")} -> 19
A22: MATCHDAY LEDGER — stakes & P&L by day | G22: HOUSE RULES
A23: Date | B23: Games | C23: Staked £ | D23: P&L £ | G23: · Only stake when FINAL ACTION shows 🟢 PLACE.
A24: 46184 | B24: =COUNTIF(Bets!$B$2:$B$105,$A24) -> 2 | C24: =SUMIFS(Bets!$AP$2:$AP$105,Bets!$B$2:$B$105,$A24,Bets!$AN$2:$AN$105,"Y") -> 30 | D24: =SUMIFS(Bets!$AR$2:$AR$105,Bets!$B$2:$B$105,$A24) -> 24.4 | E24: =IF(D24>0,REPT("█",MIN(25,ROUND(D24/4,0))),REPT("░",MIN(25,ROUND(-D24/4,0)))) -> ██████ | G24: · "—" or PASS on most matches = the filter working, not a fault.
A25: 46185 | B25: =COUNTIF(Bets!$B$2:$B$105,$A25) -> 2 | C25: =SUMIFS(Bets!$AP$2:$AP$105,Bets!$B$2:$B$105,$A25,Bets!$AN$2:$AN$105,"Y") -> 44 | D25: =SUMIFS(Bets!$AR$2:$AR$105,Bets!$B$2:$B$105,$A25) -> -3 | E25: =IF(D25>0,REPT("█",MIN(25,ROUND(D25/4,0))),REPT("░",MIN(25,ROUND(-D25/4,0)))) -> ░ | G25: · Fun bets are allowed — small (≤ £5), and STATUS labels them honestly.
A26: 46186 | B26: =COUNTIF(Bets!$B$2:$B$105,$A26) -> 4 | C26: =SUMIFS(Bets!$AP$2:$AP$105,Bets!$B$2:$B$105,$A26,Bets!$AN$2:$AN$105,"Y") -> 60 | D26: =SUMIFS(Bets!$AR$2:$AR$105,Bets!$B$2:$B$105,$A26) -> -7.5 | E26: =IF(D26>0,REPT("█",MIN(25,ROUND(D26/4,0))),REPT("░",MIN(25,ROUND(-D26/4,0)))) -> ░░ | G26: · Never exceed the stake shown. Never chase a loss.
A27: 46187 | B27: =COUNTIF(Bets!$B$2:$B$105,$A27) -> 4 | C27: =SUMIFS(Bets!$AP$2:$AP$105,Bets!$B$2:$B$105,$A27,Bets!$AN$2:$AN$105,"Y") -> 6 | D27: =SUMIFS(Bets!$AR$2:$AR$105,Bets!$B$2:$B$105,$A27) -> -6 | E27: =IF(D27>0,REPT("█",MIN(25,ROUND(D27/4,0))),REPT("░",MIN(25,ROUND(-D27/4,0)))) -> ░░ | G27: · Friends: stake = "£ per £100" × (their bankroll ÷ 100).
A28: 46188 | B28: =COUNTIF(Bets!$B$2:$B$105,$A28) -> 4 | C28: =SUMIFS(Bets!$AP$2:$AP$105,Bets!$B$2:$B$105,$A28,Bets!$AN$2:$AN$105,"Y") -> 0 | D28: =SUMIFS(Bets!$AR$2:$AR$105,Bets!$B$2:$B$105,$A28) -> 0 | E28: =IF(D28>0,REPT("█",MIN(25,ROUND(D28/4,0))),REPT("░",MIN(25,ROUND(-D28/4,0)))) | G28: · 18+ · not financial advice · BeGambleAware.org
A29: 46189 | B29: =COUNTIF(Bets!$B$2:$B$105,$A29) -> 4 | C29: =SUMIFS(Bets!$AP$2:$AP$105,Bets!$B$2:$B$105,$A29,Bets!$AN$2:$AN$105,"Y") -> 0 | D29: =SUMIFS(Bets!$AR$2:$AR$105,Bets!$B$2:$B$105,$A29) -> 0 | E29: =IF(D29>0,REPT("█",MIN(25,ROUND(D29/4,0))),REPT("░",MIN(25,ROUND(-D29/4,0))))
A30: 46190 | B30: =COUNTIF(Bets!$B$2:$B$105,$A30) -> 4 | C30: =SUMIFS(Bets!$AP$2:$AP$105,Bets!$B$2:$B$105,$A30,Bets!$AN$2:$AN$105,"Y") -> 0 | D30: =SUMIFS(Bets!$AR$2:$AR$105,Bets!$B$2:$B$105,$A30) -> 0 | E30: =IF(D30>0,REPT("█",MIN(25,ROUND(D30/4,0))),REPT("░",MIN(25,ROUND(-D30/4,0))))
A31: 46191 | B31: =COUNTIF(Bets!$B$2:$B$105,$A31) -> 4 | C31: =SUMIFS(Bets!$AP$2:$AP$105,Bets!$B$2:$B$105,$A31,Bets!$AN$2:$AN$105,"Y") -> 0 | D31: =SUMIFS(Bets!$AR$2:$AR$105,Bets!$B$2:$B$105,$A31) -> 0 | E31: =IF(D31>0,REPT("█",MIN(25,ROUND(D31/4,0))),REPT("░",MIN(25,ROUND(-D31/4,0))))
A32: 46192 | B32: =COUNTIF(Bets!$B$2:$B$105,$A32) -> 4 | C32: =SUMIFS(Bets!$AP$2:$AP$105,Bets!$B$2:$B$105,$A32,Bets!$AN$2:$AN$105,"Y") -> 0 | D32: =SUMIFS(Bets!$AR$2:$AR$105,Bets!$B$2:$B$105,$A32) -> 0 | E32: =IF(D32>0,REPT("█",MIN(25,ROUND(D32/4,0))),REPT("░",MIN(25,ROUND(-D32/4,0))))
A33: 46193 | B33: =COUNTIF(Bets!$B$2:$B$105,$A33) -> 4 | C33: =SUMIFS(Bets!$AP$2:$AP$105,Bets!$B$2:$B$105,$A33,Bets!$AN$2:$AN$105,"Y") -> 0 | D33: =SUMIFS(Bets!$AR$2:$AR$105,Bets!$B$2:$B$105,$A33) -> 0 | E33: =IF(D33>0,REPT("█",MIN(25,ROUND(D33/4,0))),REPT("░",MIN(25,ROUND(-D33/4,0))))
A34: 46194 | B34: =COUNTIF(Bets!$B$2:$B$105,$A34) -> 4 | C34: =SUMIFS(Bets!$AP$2:$AP$105,Bets!$B$2:$B$105,$A34,Bets!$AN$2:$AN$105,"Y") -> 0 | D34: =SUMIFS(Bets!$AR$2:$AR$105,Bets!$B$2:$B$105,$A34) -> 0 | E34: =IF(D34>0,REPT("█",MIN(25,ROUND(D34/4,0))),REPT("░",MIN(25,ROUND(-D34/4,0))))
A35: 46195 | B35: =COUNTIF(Bets!$B$2:$B$105,$A35) -> 4 | C35: =SUMIFS(Bets!$AP$2:$AP$105,Bets!$B$2:$B$105,$A35,Bets!$AN$2:$AN$105,"Y") -> 0 | D35: =SUMIFS(Bets!$AR$2:$AR$105,Bets!$B$2:$B$105,$A35) -> 0 | E35: =IF(D35>0,REPT("█",MIN(25,ROUND(D35/4,0))),REPT("░",MIN(25,ROUND(-D35/4,0))))
A36: 46196 | B36: =COUNTIF(Bets!$B$2:$B$105,$A36) -> 4 | C36: =SUMIFS(Bets!$AP$2:$AP$105,Bets!$B$2:$B$105,$A36,Bets!$AN$2:$AN$105,"Y") -> 0 | D36: =SUMIFS(Bets!$AR$2:$AR$105,Bets!$B$2:$B$105,$A36) -> 0 | E36: =IF(D36>0,REPT("█",MIN(25,ROUND(D36/4,0))),REPT("░",MIN(25,ROUND(-D36/4,0))))
A37: 46197 | B37: =COUNTIF(Bets!$B$2:$B$105,$A37) -> 6 | C37: =SUMIFS(Bets!$AP$2:$AP$105,Bets!$B$2:$B$105,$A37,Bets!$AN$2:$AN$105,"Y") -> 7.5 | D37: =SUMIFS(Bets!$AR$2:$AR$105,Bets!$B$2:$B$105,$A37) -> -7.5 | E37: =IF(D37>0,REPT("█",MIN(25,ROUND(D37/4,0))),REPT("░",MIN(25,ROUND(-D37/4,0)))) -> ░░
A38: 46198 | B38: =COUNTIF(Bets!$B$2:$B$105,$A38) -> 6 | C38: =SUMIFS(Bets!$AP$2:$AP$105,Bets!$B$2:$B$105,$A38,Bets!$AN$2:$AN$105,"Y") -> 0 | D38: =SUMIFS(Bets!$AR$2:$AR$105,Bets!$B$2:$B$105,$A38) -> 0 | E38: =IF(D38>0,REPT("█",MIN(25,ROUND(D38/4,0))),REPT("░",MIN(25,ROUND(-D38/4,0))))
A39: 46199 | B39: =COUNTIF(Bets!$B$2:$B$105,$A39) -> 6 | C39: =SUMIFS(Bets!$AP$2:$AP$105,Bets!$B$2:$B$105,$A39,Bets!$AN$2:$AN$105,"Y") -> 0 | D39: =SUMIFS(Bets!$AR$2:$AR$105,Bets!$B$2:$B$105,$A39) -> 0 | E39: =IF(D39>0,REPT("█",MIN(25,ROUND(D39/4,0))),REPT("░",MIN(25,ROUND(-D39/4,0))))
A40: 46200 | B40: =COUNTIF(Bets!$B$2:$B$105,$A40) -> 6 | C40: =SUMIFS(Bets!$AP$2:$AP$105,Bets!$B$2:$B$105,$A40,Bets!$AN$2:$AN$105,"Y") -> 31 | D40: =SUMIFS(Bets!$AR$2:$AR$105,Bets!$B$2:$B$105,$A40) -> -31 | E40: =IF(D40>0,REPT("█",MIN(25,ROUND(D40/4,0))),REPT("░",MIN(25,ROUND(-D40/4,0)))) -> ░░░░░░░░

Sheet Live
A1: LIVE STATE — auto-polled from /live_state.json
A3: Source URL | B3: https://wc26-matchday-intelligence.vercel.app/live_state.json
A4: Predictions URL | B4: https://wc26-matchday-intelligence.vercel.app/predictions_live.json
A5: Intel URL | B5: https://wc26-matchday-intelligence.vercel.app/matchday_intelligence.json
A6: Field | B6: Value | C6: Mirrors to Method
A7: Last poll (UTC) | B7: 46212.365 | C7: B58
A8: Mode | B8: live | C8: B59
A9: Completed matches | B9: 96 | C9: B60
A10: Provider mode | B10: active | C10: B61
A11: Warnings (joined) | C11: B62
A12: Source | B12: api_football
A13: Last model refresh (UTC) | C13: B57
A14: Simulation rerun this tick | B14: FALSE
A15: live_state last_updated_utc | B15: 2026-07-09T15:40:48.645956+00:00
A17: STATUS | B17: =IF(B7="","⚠ Apps Script not run yet — open Extensions ▸ Apps Script ▸ run installEngine()","✓ live polling active · last poll "&TEXT(B7,"yyyy-mm-dd hh:mm")) -> ✓ live polling active · last poll 2026-07-09 08:45
A18: — MATCHDAY INTELLIGENCE (auto) —
A19: Intel generated at (UTC) | B19: 2026-07-09T14:37:39.132850+00:00 | C19: mirrors to Method!B67
A20: Intel total components | B20: 236 | C20: B68
A21: Intel teams affected | B21: 48 | C21: B69
A22: Intel matches affected | B22: 23 | C22: B70
A23: Intel aggregate caps hit | B23: 2 | C23: B71
A24: Intel warnings
A25: Matches in play right now | B25: 0 | C25: see In-Play sheet
A26: Stale-feed warning | C26: >15 min trips PAUSE
B27: ⚠ calibration OOB (clamp to last bin): home=1/72 draw=6/72 away=2/72 · 32 knockout row(s) skipped
A28: Endpoints — clear B3/B4/B5 to revert to v2.3 defaults.
A30: This sheet is read-only output from the Apps Script poller. If the values stay blank, open Extensions ▸ Apps Script and run installEngine() once. The script then refreshes model probabilities into Bets!I:K (skipping any row already flagged as Placed=Y) and writes a snapshot of /live_state.json here every 5 minutes.

Sheet Bets
A1: # | B1: Date | C1: Grp | D1: Home | E1: Away | F1: Venue | G1: KO local | H1: KO UK | I1: Model pH | J1: Model pD | K1: Model pA | L1: Odds H | M1: Odds D | N1: Odds A | O1: imp H | P1: imp D | Q1: imp A | R1: Overround | S1: mkt H | T1: mkt D | U1: mkt A | V1: blend H | W1: blend D | X1: blend A | Y1: EV H | Z1: EV D | AA1: EV A | AB1: pick# | AC1: code | AD1: PICK | AE1: Odds | AF1: EV % | AG1: Edge pp | AH1: DECISION | AI1: £ / £100 bank | AJ1: ENGINE STAKE £ | AK1: p(blend) | AL1: Kelly f | AM1: rankkey | AN1: Placed? | AO1: Odds taken | AP1: Stake £ | AQ1: Result | AR1: P&L £ | AS1: Cum P&L | AT1: WHY (plain English) | AU1: STATUS | AV1: Backed | AW1: dec@bet | AX1: eng£@bet | AY1: pick@bet | AZ1: class | BA1: eng£ eff | BB1: intel Δ | BC1: pH (cal) | BD1: pD (cal) | BE1: pA (cal) | BF1: intel breakdown | BG1: altitude m | BH1: climate | BI1: home travel km
A2: 1 | B2: 46184 | C2: A | D2: Mexico | E2: South Africa | F2: Mexico City | G2: 0.54166667 | H2: 0.83333333 | I2: 0.7008 | J2: 0.2117 | K2: 0.0876 | L2: =IF(Matchday!E4="","",Matchday!E4) -> 1.42 | M2: =IF(Matchday!F4="","",Matchday!F4) -> 4.5 | N2: =IF(Matchday!G4="","",Matchday!G4) -> 8.5 | O2: =IF(L2="","",1/L2) -> 0.70422535 | P2: =IF(M2="","",1/M2) -> 0.22222222 | Q2: =IF(N2="","",1/N2) -> 0.11764706 | R2: =IF(COUNT(L2:N2)<3,"",O2+P2+Q2) -> 1.0440946 | S2: {=IF($R2="","",IF(Method!$B$56="proportional",O2/$R2,IF(Method!$B$56="power",IFERROR(INDEX(power_devig($L2,$M2,$N2),1,1),O2/$R2),IFERROR(INDEX(shin($L2,$M2,$N2),1,1),O2/$R2))))} -> 0.68567733 | T2: {=IF($R2="","",IF(Method!$B$56="proportional",P2/$R2,IF(Method!$B$56="power",IFERROR(INDEX(power_devig($L2,$M2,$N2),2,1),P2/$R2),IFERROR(INDEX(shin($L2,$M2,$N2),2,1),P2/$R2))))} -> 0.20878432 | U2: {=IF($R2="","",IF(Method!$B$56="proportional",Q2/$R2,IF(Method!$B$56="power",IFERROR(INDEX(power_devig($L2,$M2,$N2),3,1),Q2/$R2),IFERROR(INDEX(shin($L2,$M2,$N2),3,1),Q2/$R2))))} -> 0.10553835 | V2: =IF(S2="","",Method!$B$4*IF(BC2="",I2,BC2)+(1-Method!$B$4)*S2/($S2+$T2+$U2)) -> 0.68044333 | W2: =IF(T2="","",Method!$B$4*IF(BD2="",J2,BD2)+(1-Method!$B$4)*T2/($S2+$T2+$U2)) -> 0.21958232 | X2: =IF(U2="","",Method!$B$4*IF(BE2="",K2,BE2)+(1-Method!$B$4)*U2/($S2+$T2+$U2)) -> 0.099974353 | Y2: =IF(V2="","",V2*L2-1) -> -0.033770477 | Z2: =IF(W2="","",W2*M2-1) -> -0.011879559 | AA2: =IF(X2="","",X2*N2-1) -> -0.150218 | AB2: =IF(Y2="","",MATCH(MAX(Y2:AA2),Y2:AA2,0)) -> 2 | AC2: =IF(AB2="","",CHOOSE(AB2,"H","D","A")) -> D | AD2: =IF(AB2="","",CHOOSE(AB2,"1 "&D2,"X Draw","2 "&E2)) -> X Draw | AE2: =IF(AB2="","",INDEX(L2:N2,1,AB2)) -> 4.5 | AF2: =IF(AB2="","",INDEX(Y2:AA2,1,AB2)) -> -0.011879559 | AG2: =IF(AB2="","",INDEX(V2:X2,1,AB2)-INDEX(S2:U2,1,AB2)) -> 0.010798002 | AH2: {=IF(AB2="","· enter odds",IF(OR(AF2>Method!$B$87,IFERROR(INDEX(BC2:BE2,1,AB2)/INDEX(S2:U2,1,AB2),0)>Method!$B$88),"PASS",IF(AND(AF2>=Method!$B$7,AG2>=Method!$B$8),"BET","PASS")))} -> PASS | AI2: =IF(AH2<>"BET",0,ROUND(MIN(Method!$B$6,Method!$B$5*AL2)*100,1)) -> 0 | AJ2: =IF(OR(AH2<>"BET",Method!$B$55=TRUE()),0,IF(AI2*Method!$B$10/100<Method!$B$9,0,ROUND(AI2*Method!$B$10/100,0))) -> 0 | AK2: =IF(AB2="","",INDEX(V2:X2,1,AB2)) -> 0.21958232 | AL2: =IF(AH2<>"BET","",MAX(0,(AK2*AE2-1)/(AE2-1))) | AM2: =IF(AH2="BET",AF2+A2/1000000,"") | AN2: =IF(Matchday!N4="","",Matchday!N4) -> Y | AO2: =IF(Matchday!P4="","",Matchday!P4) -> 1.42 | AP2: =IF(Matchday!Q4="","",Matchday!Q4) -> 20 | AQ2: =IF(Matchday!R4="","",Matchday!R4) -> H | AR2: =IF(OR(AN2<>"Y",AQ2="",AV2=""),"",IF(AQ2="Void",0,IF(AQ2=AV2,ROUND(AP2*(AO2-1),2),-AP2))) -> 8.4 | AS2: =IF(AR2="","",SUM($AR$2:AR2)) -> 8.4 | AT2: =IFERROR(__xludf.DUMMYFUNCTION("IF(AB2="""",""Type the 3 odds on the Matchday tab"",IF(Method!$B$55=TRUE(),IF(Method!$B$81=TRUE(),IF(REGEXMATCH(LOWER(Method!$B$63),""circuit""),""🛑 PAUSED — circuit breaker upstream; wait for a clean live refresh."",IF(REGEXMATCH(LOWER(Method!$B$63),""p"&"ipeline""),""🛑 PAUSED — live pipeline warning; check Live!B11/Method!B62 before betting."",IF(REGEXMATCH(LOWER(Method!$B$63),""missing""),""🛑 PAUSED — feed timestamp missing; refresh feed before betting."",""🛑 PAUSED — feed stale > 25 min — check Live "&"tab; refresh feed before betting.""))),IF(Method!$B$51>=Method!$B$52,""🛑 PAUSED — drawdown ""&TEXT(Method!$B$51,""0.0%"")&"" ≥ ""&TEXT(Method!$B$52,""0.0%"")&"". Set Method!B54=Y to override."",""🛑 PAUSED — see Method!B62/B63/B81 for cause; do not overr"&"ide stale/circuit-breaker/pipeline pauses."")),IF(AH2=""BET"",IF(AJ2=0,""Edge found but stake rounds under £""&Method!$B$9&"" — skip"",IF(AND(AE2>=6,AG2>=0.15),""🟡 WAIT — long-shot review: odds ""&TEXT(AE2,""0.00"")&"" + edge ""&TEXT(AG2,""0.0%"")&"" — v"&"erify sharp-book + team news + stake comfort before Placed=Y"",""Value found: EV ""&TEXT(AF2,""0.0%"")&"", edge ""&TEXT(AG2,""0.0%""))),IF(OR(AF2>Method!$B$87,IFERROR(INDEX(BC2:BE2,1,AB2)/INDEX(S2:U2,1,AB2),0)>Method!$B$88),""🛑 Tail trap — auto-PASS · EV"&" ""&TEXT(AF2,""0.0%"")&"" (cap ""&TEXT(Method!$B$87,""0%"")&"") · model/market ""&TEXT(IFERROR(INDEX(BC2:BE2,1,AB2)/INDEX(S2:U2,1,AB2),0),""0.0"")&""× (cap ""&TEXT(Method!$B$88,""0.0"")&""×)"",IF(AF2<Method!$B$7,""Price too short — EV ""&TEXT(AF2,""0.0%"""&")&"" (need ""&TEXT(Method!$B$7,""0.0%"")&""+)"",""Model ≈ market — edge ""&TEXT(AG2,""0.0%"")&"" (need ""&TEXT(Method!$B$8,""0.0%"")&""+)"")))))"),"Price too short — EV -1.2% (need 2.5%+)") -> Price too short — EV -1.2% (need 2.5%+) | AU2: =IF(AN2<>"Y","",IF(AH2="· enter odds","⚠ type the 3 odds (1/X/2) to grade this bet",IF(OR(AV2="",AO2="",AP2=""),"⚠ log backed pick, odds & stake",IF(AZ2<>"BET","⚠ FUN BET — engine said pass · staked £"&AP2&" vs engine £"&BA2,IF(AV2<>IF(AY2="",AC2,AY2),"⚠ backed "&AV2&" but engine pick was "&IF(AY2="",AC2,AY2),IF(AP2>BA2,"⚠ stake over engine £"&BA2,IF(ABS(AO2-IFERROR(INDEX(L2:N2,1,MATCH(AV2,{"H","D","A"},0)),AE2))>0.02,"⚠ odds moved — re-check value","✓ engine bet"))))))) -> ⚠ FUN BET — engine said pass · staked £20 vs engine £0 | AV2: =IF(Matchday!O4="","",Matchday!O4) -> H | AW2: PASS | AX2: 0 | AY2: H | AZ2: =IF(AW2="",AH2,AW2) -> PASS | BA2: =IF(AX2<>"",AX2,IF(AH2<>"BET",0,IF(AI2*Method!$B$10/100<Method!$B$9,0,ROUND(AI2*Method!$B$10/100,0)))) -> 0 | BB2: -22.38 | BC2: 0.67072304 | BD2: 0.23963575 | BE2: 0.089641212 | BF2: Mexico team-wide: +7 · South Africa team-wide: -29 | BG2: 2240 | BH2: high_altitude_mild | BI2: 0
A3: 2 | B3: 46184 | C3: A | D3: South Korea | E3: Czechia | F3: Zapopan | G3: 0.83333333 | H3: 03:00 +1d | I3: 0.44370918 | J3: 0.29067093 | K3: 0.26561988 | L3: =IF(Matchday!E5="","",Matchday!E5) -> 2.7 | M3: =IF(Matchday!F5="","",Matchday!F5) -> 3.1 | N3: =IF(Matchday!G5="","",Matchday!G5) -> 2.8 | O3: =IF(L3="","",1/L3) -> 0.37037037 | P3: =IF(M3="","",1/M3) -> 0.32258065 | Q3: =IF(N3="","",1/N3) -> 0.35714286 | R3: =IF(COUNT(L3:N3)<3,"",O3+P3+Q3) -> 1.0500939 | S3: {=IF($R3="","",IF(Method!$B$56="proportional",O3/$R3,IF(Method!$B$56="power",IFERROR(INDEX(power_devig($L3,$M3,$N3),1,1),O3/$R3),IFERROR(INDEX(shin($L3,$M3,$N3),1,1),O3/$R3))))} -> 0.35342082 | T3: {=IF($R3="","",IF(Method!$B$56="proportional",P3/$R3,IF(Method!$B$56="power",IFERROR(INDEX(power_devig($L3,$M3,$N3),2,1),P3/$R3),IFERROR(INDEX(shin($L3,$M3,$N3),2,1),P3/$R3))))} -> 0.30622296 | U3: {=IF($R3="","",IF(Method!$B$56="proportional",Q3/$R3,IF(Method!$B$56="power",IFERROR(INDEX(power_devig($L3,$M3,$N3),3,1),Q3/$R3),IFERROR(INDEX(shin($L3,$M3,$N3),3,1),Q3/$R3))))} -> 0.34035623 | V3: =IF(S3="","",Method!$B$4*IF(BC3="",I3,BC3)+(1-Method!$B$4)*S3/($S3+$T3+$U3)) -> 0.38650219 | W3: =IF(T3="","",Method!$B$4*IF(BD3="",J3,BD3)+(1-Method!$B$4)*T3/($S3+$T3+$U3)) -> 0.29234075 | X3: =IF(U3="","",Method!$B$4*IF(BE3="",K3,BE3)+(1-Method!$B$4)*U3/($S3+$T3+$U3)) -> 0.32115706 | Y3: =IF(V3="","",V3*L3-1) -> 0.043555918 | Z3: =IF(W3="","",W3*M3-1) -> -0.09374369 | AA3: =IF(X3="","",X3*N3-1) -> -0.10076022 | AB3: =IF(Y3="","",MATCH(MAX(Y3:AA3),Y3:AA3,0)) -> 1 | AC3: =IF(AB3="","",CHOOSE(AB3,"H","D","A")) -> H | AD3: =IF(AB3="","",CHOOSE(AB3,"1 "&D3,"X Draw","2 "&E3)) -> 1 South Korea | AE3: =IF(AB3="","",INDEX(L3:N3,1,AB3)) -> 2.7 | AF3: =IF(AB3="","",INDEX(Y3:AA3,1,AB3)) -> 0.043555918 | AG3: =IF(AB3="","",INDEX(V3:X3,1,AB3)-INDEX(S3:U3,1,AB3)) -> 0.033081377 | AH3: {=IF(AB3="","· enter odds",IF(OR(AF3>Method!$B$87,IFERROR(INDEX(BC3:BE3,1,AB3)/INDEX(S3:U3,1,AB3),0)>Method!$B$88),"PASS",IF(AND(AF3>=Method!$B$7,AG3>=Method!$B$8),"BET","PASS")))} -> BET | AI3: =IF(AH3<>"BET",0,ROUND(MIN(Method!$B$6,Method!$B$5*AL3)*100,1)) -> 0.6 | AJ3: =IF(OR(AH3<>"BET",Method!$B$55=TRUE()),0,IF(AI3*Method!$B$10/100<Method!$B$9,0,ROUND(AI3*Method!$B$10/100,0))) -> 6 | AK3: =IF(AB3="","",INDEX(V3:X3,1,AB3)) -> 0.38650219 | AL3: =IF(AH3<>"BET","",MAX(0,(AK3*AE3-1)/(AE3-1))) -> 0.025621128 | AM3: =IF(AH3="BET",AF3+A3/1000000,"") -> 0.043557918 | AN3: =IF(Matchday!N5="","",Matchday!N5) -> Y | AO3: =IF(Matchday!P5="","",Matchday!P5) -> 2.6 | AP3: =IF(Matchday!Q5="","",Matchday!Q5) -> 10 | AQ3: =IF(Matchday!R5="","",Matchday!R5) -> H | AR3: =IF(OR(AN3<>"Y",AQ3="",AV3=""),"",IF(AQ3="Void",0,IF(AQ3=AV3,ROUND(AP3*(AO3-1),2),-AP3))) -> 16 | AS3: =IF(AR3="","",SUM($AR$2:AR3)) -> 24.4 | AT3: =IFERROR(__xludf.DUMMYFUNCTION("IF(AB3="""",""Type the 3 odds on the Matchday tab"",IF(Method!$B$55=TRUE(),IF(Method!$B$81=TRUE(),IF(REGEXMATCH(LOWER(Method!$B$63),""circuit""),""🛑 PAUSED — circuit breaker upstream; wait for a clean live refresh."",IF(REGEXMATCH(LOWER(Method!$B$63),""p"&"ipeline""),""🛑 PAUSED — live pipeline warning; check Live!B11/Method!B62 before betting."",IF(REGEXMATCH(LOWER(Method!$B$63),""missing""),""🛑 PAUSED — feed timestamp missing; refresh feed before betting."",""🛑 PAUSED — feed stale > 25 min — check Live "&"tab; refresh feed before betting.""))),IF(Method!$B$51>=Method!$B$52,""🛑 PAUSED — drawdown ""&TEXT(Method!$B$51,""0.0%"")&"" ≥ ""&TEXT(Method!$B$52,""0.0%"")&"". Set Method!B54=Y to override."",""🛑 PAUSED — see Method!B62/B63/B81 for cause; do not overr"&"ide stale/circuit-breaker/pipeline pauses."")),IF(AH3=""BET"",IF(AJ3=0,""Edge found but stake rounds under £""&Method!$B$9&"" — skip"",IF(AND(AE3>=6,AG3>=0.15),""🟡 WAIT — long-shot review: odds ""&TEXT(AE3,""0.00"")&"" + edge ""&TEXT(AG3,""0.0%"")&"" — v"&"erify sharp-book + team news + stake comfort before Placed=Y"",""Value found: EV ""&TEXT(AF3,""0.0%"")&"", edge ""&TEXT(AG3,""0.0%""))),IF(OR(AF3>Method!$B$87,IFERROR(INDEX(BC3:BE3,1,AB3)/INDEX(S3:U3,1,AB3),0)>Method!$B$88),""🛑 Tail trap — auto-PASS · EV"&" ""&TEXT(AF3,""0.0%"")&"" (cap ""&TEXT(Method!$B$87,""0%"")&"") · model/market ""&TEXT(IFERROR(INDEX(BC3:BE3,1,AB3)/INDEX(S3:U3,1,AB3),0),""0.0"")&""× (cap ""&TEXT(Method!$B$88,""0.0"")&""×)"",IF(AF3<Method!$B$7,""Price too short — EV ""&TEXT(AF3,""0.0%"""&")&"" (need ""&TEXT(Method!$B$7,""0.0%"")&""+)"",""Model ≈ market — edge ""&TEXT(AG3,""0.0%"")&"" (need ""&TEXT(Method!$B$8,""0.0%"")&""+)"")))))"),"Value found: EV 4.4%, edge 3.3%") -> Value found: EV 4.4%, edge 3.3% | AU3: =IF(AN3<>"Y","",IF(AH3="· enter odds","⚠ type the 3 odds (1/X/2) to grade this bet",IF(OR(AV3="",AO3="",AP3=""),"⚠ log backed pick, odds & stake",IF(AZ3<>"BET","⚠ FUN BET — engine said pass · staked £"&AP3&" vs engine £"&BA3,IF(AV3<>IF(AY3="",AC3,AY3),"⚠ backed "&AV3&" but engine pick was "&IF(AY3="",AC3,AY3),IF(AP3>BA3,"⚠ stake over engine £"&BA3,IF(ABS(AO3-IFERROR(INDEX(L3:N3,1,MATCH(AV3,{"H","D","A"},0)),AE3))>0.02,"⚠ odds moved — re-check value","✓ engine bet"))))))) -> ⚠ stake over engine £3 | AV3: =IF(Matchday!O5="","",Matchday!O5) -> H | AW3: BET | AX3: 3 | AY3: H | AZ3: =IF(AW3="",AH3,AW3) -> BET | BA3: =IF(AX3<>"",AX3,IF(AH3<>"BET",0,IF(AI3*Method!$B$10/100<Method!$B$9,0,ROUND(AI3*Method!$B$10/100,0)))) -> 3 | BB3: -20.33 | BC3: 0.44793903 | BD3: 0.2665595 | BE3: 0.28550147 | BF3: Czechia team-wide: -16 · Czechia weather: -4 · South Korea team-wide: +1 · South Korea weather: -1 | BG3: 1560 | BH3: warm_humid | BI3: 0
A4: 3 | B4: 46185 | C4: B | D4: Canada | E4: Bosnia and Herzegovina | F4: Toronto | G4: 0.625 | H4: 0.83333333 | I4: 0.69750662 | J4: 0.2132834 | K4: 0.089209979 | L4: =IF(Matchday!E6="","",Matchday!E6) -> 1.85 | M4: =IF(Matchday!F6="","",Matchday!F6) -> 3.5 | N4: =IF(Matchday!G6="","",Matchday!G6) -> 4.5 | O4: =IF(L4="","",1/L4) -> 0.54054054 | P4: =IF(M4="","",1/M4) -> 0.28571429 | Q4: =IF(N4="","",1/N4) -> 0.22222222 | R4: =IF(COUNT(L4:N4)<3,"",O4+P4+Q4) -> 1.048477 | S4: {=IF($R4="","",IF(Method!$B$56="proportional",O4/$R4,IF(Method!$B$56="power",IFERROR(INDEX(power_devig($L4,$M4,$N4),1,1),O4/$R4),IFERROR(INDEX(shin($L4,$M4,$N4),1,1),O4/$R4))))} -> 0.52211289 | T4: {=IF($R4="","",IF(Method!$B$56="proportional",P4/$R4,IF(Method!$B$56="power",IFERROR(INDEX(power_devig($L4,$M4,$N4),2,1),P4/$R4),IFERROR(INDEX(shin($L4,$M4,$N4),2,1),P4/$R4))))} -> 0.27029207 | U4: {=IF($R4="","",IF(Method!$B$56="proportional",Q4/$R4,IF(Method!$B$56="power",IFERROR(INDEX(power_devig($L4,$M4,$N4),3,1),Q4/$R4),IFERROR(INDEX(shin($L4,$M4,$N4),3,1),Q4/$R4))))} -> 0.20759504 | V4: =IF(S4="","",Method!$B$4*IF(BC4="",I4,BC4)+(1-Method!$B$4)*S4/($S4+$T4+$U4)) -> 0.57294231 | W4: =IF(T4="","",Method!$B$4*IF(BD4="",J4,BD4)+(1-Method!$B$4)*T4/($S4+$T4+$U4)) -> 0.26015932 | X4: =IF(U4="","",Method!$B$4*IF(BE4="",K4,BE4)+(1-Method!$B$4)*U4/($S4+$T4+$U4)) -> 0.16689837 | Y4: =IF(V4="","",V4*L4-1) -> 0.059943274 | Z4: =IF(W4="","",W4*M4-1) -> -0.089442368 | AA4: =IF(X4="","",X4*N4-1) -> -0.24895735 | AB4: =IF(Y4="","",MATCH(MAX(Y4:AA4),Y4:AA4,0)) -> 1 | AC4: =IF(AB4="","",CHOOSE(AB4,"H","D","A")) -> H | AD4: =IF(AB4="","",CHOOSE(AB4,"1 "&D4,"X Draw","2 "&E4)) -> 1 Canada | AE4: =IF(AB4="","",INDEX(L4:N4,1,AB4)) -> 1.85 | AF4: =IF(AB4="","",INDEX(Y4:AA4,1,AB4)) -> 0.059943274 | AG4: =IF(AB4="","",INDEX(V4:X4,1,AB4)-INDEX(S4:U4,1,AB4)) -> 0.050829423 | AH4: {=IF(AB4="","· enter odds",IF(OR(AF4>Method!$B$87,IFERROR(INDEX(BC4:BE4,1,AB4)/INDEX(S4:U4,1,AB4),0)>Method!$B$88),"PASS",IF(AND(AF4>=Method!$B$7,AG4>=Method!$B$8),"BET","PASS")))} -> BET | AI4: =IF(AH4<>"BET",0,ROUND(MIN(Method!$B$6,Method!$B$5*AL4)*100,1)) -> 1.8 | AJ4: =IF(OR(AH4<>"BET",Method!$B$55=TRUE()),0,IF(AI4*Method!$B$10/100<Method!$B$9,0,ROUND(AI4*Method!$B$10/100,0))) -> 17 | AK4: =IF(AB4="","",INDEX(V4:X4,1,AB4)) -> 0.57294231 | AL4: =IF(AH4<>"BET","",MAX(0,(AK4*AE4-1)/(AE4-1))) -> 0.070521499 | AM4: =IF(AH4="BET",AF4+A4/1000000,"") -> 0.059946274 | AN4: =IF(Matchday!N6="","",Matchday!N6) -> Y | AO4: =IF(Matchday!P6="","",Matchday!P6) -> 1.85 | AP4: =IF(Matchday!Q6="","",Matchday!Q6) -> 24 | AQ4: =IF(Matchday!R6="","",Matchday!R6) -> D | AR4: =IF(OR(AN4<>"Y",AQ4="",AV4=""),"",IF(AQ4="Void",0,IF(AQ4=AV4,ROUND(AP4*(AO4-1),2),-AP4))) -> -24 | AS4: =IF(AR4="","",SUM($AR$2:AR4)) -> 0.4 | AT4: =IFERROR(__xludf.DUMMYFUNCTION("IF(AB4="""",""Type the 3 odds on the Matchday tab"",IF(Method!$B$55=TRUE(),IF(Method!$B$81=TRUE(),IF(REGEXMATCH(LOWER(Method!$B$63),""circuit""),""🛑 PAUSED — circuit breaker upstream; wait for a clean live refresh."",IF(REGEXMATCH(LOWER(Method!$B$63),""p"&"ipeline""),""🛑 PAUSED — live pipeline warning; check Live!B11/Method!B62 before betting."",IF(REGEXMATCH(LOWER(Method!$B$63),""missing""),""🛑 PAUSED — feed timestamp missing; refresh feed before betting."",""🛑 PAUSED — feed stale > 25 min — check Live "&"tab; refresh feed before betting.""))),IF(Method!$B$51>=Method!$B$52,""🛑 PAUSED — drawdown ""&TEXT(Method!$B$51,""0.0%"")&"" ≥ ""&TEXT(Method!$B$52,""0.0%"")&"". Set Method!B54=Y to override."",""🛑 PAUSED — see Method!B62/B63/B81 for cause; do not overr"&"ide stale/circuit-breaker/pipeline pauses."")),IF(AH4=""BET"",IF(AJ4=0,""Edge found but stake rounds under £""&Method!$B$9&"" — skip"",IF(AND(AE4>=6,AG4>=0.15),""🟡 WAIT — long-shot review: odds ""&TEXT(AE4,""0.00"")&"" + edge ""&TEXT(AG4,""0.0%"")&"" — v"&"erify sharp-book + team news + stake comfort before Placed=Y"",""Value found: EV ""&TEXT(AF4,""0.0%"")&"", edge ""&TEXT(AG4,""0.0%""))),IF(OR(AF4>Method!$B$87,IFERROR(INDEX(BC4:BE4,1,AB4)/INDEX(S4:U4,1,AB4),0)>Method!$B$88),""🛑 Tail trap — auto-PASS · EV"&" ""&TEXT(AF4,""0.0%"")&"" (cap ""&TEXT(Method!$B$87,""0%"")&"") · model/market ""&TEXT(IFERROR(INDEX(BC4:BE4,1,AB4)/INDEX(S4:U4,1,AB4),0),""0.0"")&""× (cap ""&TEXT(Method!$B$88,""0.0"")&""×)"",IF(AF4<Method!$B$7,""Price too short — EV ""&TEXT(AF4,""0.0%"""&")&"" (need ""&TEXT(Method!$B$7,""0.0%"")&""+)"",""Model ≈ market — edge ""&TEXT(AG4,""0.0%"")&"" (need ""&TEXT(Method!$B$8,""0.0%"")&""+)"")))))"),"Value found: EV 6.0%, edge 5.1%") -> Value found: EV 6.0%, edge 5.1% | AU4: =IF(AN4<>"Y","",IF(AH4="· enter odds","⚠ type the 3 odds (1/X/2) to grade this bet",IF(OR(AV4="",AO4="",AP4=""),"⚠ log backed pick, odds & stake",IF(AZ4<>"BET","⚠ FUN BET — engine said pass · staked £"&AP4&" vs engine £"&BA4,IF(AV4<>IF(AY4="",AC4,AY4),"⚠ backed "&AV4&" but engine pick was "&IF(AY4="",AC4,AY4),IF(AP4>BA4,"⚠ stake over engine £"&BA4,IF(ABS(AO4-IFERROR(INDEX(L4:N4,1,MATCH(AV4,{"H","D","A"},0)),AE4))>0.02,"⚠ odds moved — re-check value","✓ engine bet"))))))) -> ⚠ stake over engine £12 | AV4: =IF(Matchday!O6="","",Matchday!O6) -> H | AW4: BET | AX4: 12 | AY4: H | AZ4: =IF(AW4="",AH4,AW4) -> BET | BA4: =IF(AX4<>"",AX4,IF(AH4<>"BET",0,IF(AI4*Method!$B$10/100<Method!$B$9,0,ROUND(AI4*Method!$B$10/100,0)))) -> 12 | BB4: -27.24 | BC4: 0.66733981 | BD4: 0.24134137 | BE4: 0.091318821 | BF4: Bosnia and Herzegovina team-wide: -18 · Canada team-wide: -9 | BG4: 76 | BH4: mild | BI4: 0
A5: 4 | B5: 46185 | C5: D | D5: United States | E5: Paraguay | F5: Inglewood | G5: 0.75 | H5: 02:00 +1d | I5: 0.48548732 | J5: 0.2800987 | K5: 0.23441398 | L5: =IF(Matchday!E7="","",Matchday!E7) -> 2.18 | M5: =IF(Matchday!F7="","",Matchday!F7) -> 3.3 | N5: =IF(Matchday!G7="","",Matchday!G7) -> 4.1 | O5: =IF(L5="","",1/L5) -> 0.4587156 | P5: =IF(M5="","",1/M5) -> 0.3030303 | Q5: =IF(N5="","",1/N5) -> 0.24390244 | R5: =IF(COUNT(L5:N5)<3,"",O5+P5+Q5) -> 1.0056483 | S5: {=IF($R5="","",IF(Method!$B$56="proportional",O5/$R5,IF(Method!$B$56="power",IFERROR(INDEX(power_devig($L5,$M5,$N5),1,1),O5/$R5),IFERROR(INDEX(shin($L5,$M5,$N5),1,1),O5/$R5))))} -> 0.4566588 | T5: {=IF($R5="","",IF(Method!$B$56="proportional",P5/$R5,IF(Method!$B$56="power",IFERROR(INDEX(power_devig($L5,$M5,$N5),2,1),P5/$R5),IFERROR(INDEX(shin($L5,$M5,$N5),2,1),P5/$R5))))} -> 0.30119272 | U5: {=IF($R5="","",IF(Method!$B$56="proportional",Q5/$R5,IF(Method!$B$56="power",IFERROR(INDEX(power_devig($L5,$M5,$N5),3,1),Q5/$R5),IFERROR(INDEX(shin($L5,$M5,$N5),3,1),Q5/$R5))))} -> 0.24214849 | V5: =IF(S5="","",Method!$B$4*IF(BC5="",I5,BC5)+(1-Method!$B$4)*S5/($S5+$T5+$U5)) -> 0.46585091 | W5: =IF(T5="","",Method!$B$4*IF(BD5="",J5,BD5)+(1-Method!$B$4)*T5/($S5+$T5+$U5)) -> 0.29055699 | X5: =IF(U5="","",Method!$B$4*IF(BE5="",K5,BE5)+(1-Method!$B$4)*U5/($S5+$T5+$U5)) -> 0.24359209 | Y5: =IF(V5="","",V5*L5-1) -> 0.015554992 | Z5: =IF(W5="","",W5*M5-1) -> -0.041161927 | AA5: =IF(X5="","",X5*N5-1) -> -0.0012724128 | AB5: =IF(Y5="","",MATCH(MAX(Y5:AA5),Y5:AA5,0)) -> 1 | AC5: =IF(AB5="","",CHOOSE(AB5,"H","D","A")) -> H | AD5: =IF(AB5="","",CHOOSE(AB5,"1 "&D5,"X Draw","2 "&E5)) -> 1 United States | AE5: =IF(AB5="","",INDEX(L5:N5,1,AB5)) -> 2.18 | AF5: =IF(AB5="","",INDEX(Y5:AA5,1,AB5)) -> 0.015554992 | AG5: =IF(AB5="","",INDEX(V5:X5,1,AB5)-INDEX(S5:U5,1,AB5)) -> 0.0091921177 | AH5: {=IF(AB5="","· enter odds",IF(OR(AF5>Method!$B$87,IFERROR(INDEX(BC5:BE5,1,AB5)/INDEX(S5:U5,1,AB5),0)>Method!$B$88),"PASS",IF(AND(AF5>=Method!$B$7,AG5>=Method!$B$8),"BET","PASS")))} -> PASS | AI5: =IF(AH5<>"BET",0,ROUND(MIN(Method!$B$6,Method!$B$5*AL5)*100,1)) -> 0 | AJ5: =IF(OR(AH5<>"BET",Method!$B$55=TRUE()),0,IF(AI5*Method!$B$10/100<Method!$B$9,0,ROUND(AI5*Method!$B$10/100,0))) -> 0 | AK5: =IF(AB5="","",INDEX(V5:X5,1,AB5)) -> 0.46585091 | AL5: =IF(AH5<>"BET","",MAX(0,(AK5*AE5-1)/(AE5-1))) | AM5: =IF(AH5="BET",AF5+A5/1000000,"") | AN5: =IF(Matchday!N7="","",Matchday!N7) -> Y | AO5: =IF(Matchday!P7="","",Matchday!P7) -> 2.05 | AP5: =IF(Matchday!Q7="","",Matchday!Q7) -> 20 | AQ5: =IF(Matchday!R7="","",Matchday!R7) -> H | AR5: =IF(OR(AN5<>"Y",AQ5="",AV5=""),"",IF(AQ5="Void",0,IF(AQ5=AV5,ROUND(AP5*(AO5-1),2),-AP5))) -> 21 | AS5: =IF(AR5="","",SUM($AR$2:AR5)) -> 21.4 | AT5: =IFERROR(__xludf.DUMMYFUNCTION("IF(AB5="""",""Type the 3 odds on the Matchday tab"",IF(Method!$B$55=TRUE(),IF(Method!$B$81=TRUE(),IF(REGEXMATCH(LOWER(Method!$B$63),""circuit""),""🛑 PAUSED — circuit breaker upstream; wait for a clean live refresh."",IF(REGEXMATCH(LOWER(Method!$B$63),""p"&"ipeline""),""🛑 PAUSED — live pipeline warning; check Live!B11/Method!B62 before betting."",IF(REGEXMATCH(LOWER(Method!$B$63),""missing""),""🛑 PAUSED — feed timestamp missing; refresh feed before betting."",""🛑 PAUSED — feed stale > 25 min — check Live "&"tab; refresh feed before betting.""))),IF(Method!$B$51>=Method!$B$52,""🛑 PAUSED — drawdown ""&TEXT(Method!$B$51,""0.0%"")&"" ≥ ""&TEXT(Method!$B$52,""0.0%"")&"". Set Method!B54=Y to override."",""🛑 PAUSED — see Method!B62/B63/B81 for cause; do not overr"&"ide stale/circuit-breaker/pipeline pauses."")),IF(AH5=""BET"",IF(AJ5=0,""Edge found but stake rounds under £""&Method!$B$9&"" — skip"",IF(AND(AE5>=6,AG5>=0.15),""🟡 WAIT — long-shot review: odds ""&TEXT(AE5,""0.00"")&"" + edge ""&TEXT(AG5,""0.0%"")&"" — v"&"erify sharp-book + team news + stake comfort before Placed=Y"",""Value found: EV ""&TEXT(AF5,""0.0%"")&"", edge ""&TEXT(AG5,""0.0%""))),IF(OR(AF5>Method!$B$87,IFERROR(INDEX(BC5:BE5,1,AB5)/INDEX(S5:U5,1,AB5),0)>Method!$B$88),""🛑 Tail trap — auto-PASS · EV"&" ""&TEXT(AF5,""0.0%"")&"" (cap ""&TEXT(Method!$B$87,""0%"")&"") · model/market ""&TEXT(IFERROR(INDEX(BC5:BE5,1,AB5)/INDEX(S5:U5,1,AB5),0),""0.0"")&""× (cap ""&TEXT(Method!$B$88,""0.0"")&""×)"",IF(AF5<Method!$B$7,""Price too short — EV ""&TEXT(AF5,""0.0%"""&")&"" (need ""&TEXT(Method!$B$7,""0.0%"")&""+)"",""Model ≈ market — edge ""&TEXT(AG5,""0.0%"")&"" (need ""&TEXT(Method!$B$8,""0.0%"")&""+)"")))))"),"Price too short — EV 1.6% (need 2.5%+)") -> Price too short — EV 1.6% (need 2.5%+) | AU5: =IF(AN5<>"Y","",IF(AH5="· enter odds","⚠ type the 3 odds (1/X/2) to grade this bet",IF(OR(AV5="",AO5="",AP5=""),"⚠ log backed pick, odds & stake",IF(AZ5<>"BET","⚠ FUN BET — engine said pass · staked £"&AP5&" vs engine £"&BA5,IF(AV5<>IF(AY5="",AC5,AY5),"⚠ backed "&AV5&" but engine pick was "&IF(AY5="",AC5,AY5),IF(AP5>BA5,"⚠ stake over engine £"&BA5,IF(ABS(AO5-IFERROR(INDEX(L5:N5,1,MATCH(AV5,{"H","D","A"},0)),AE5))>0.02,"⚠ odds moved — re-check value","✓ engine bet"))))))) -> ⚠ FUN BET — engine said pass · staked £20 vs engine £0 | AV5: =IF(Matchday!O7="","",Matchday!O7) -> H | AW5: PASS | AX5: 0 | AY5: H | AZ5: =IF(AW5="",AH5,AW5) -> PASS | BA5: =IF(AX5<>"",AX5,IF(AH5<>"BET",0,IF(AI5*Method!$B$10/100<Method!$B$9,0,ROUND(AI5*Method!$B$10/100,0)))) -> 0 | BB5: -56.01 | BC5: 0.48292199 | BD5: 0.27080493 | BE5: 0.24627308 | BF5: Paraguay team-wide: -35 · United States team-wide: -21 | BG5: 30 | BH5: warm_dry_indoor | BI5: 0
A6: 5 | B6: 46186 | C6: B | D6: Qatar | E6: Switzerland | F6: Santa Clara | G6: 0.5 | H6: 0.83333333 | I6: 0.07585287 | J6: 0.19789443 | K6: 0.7262527 | L6: =IF(Matchday!E8="","",Matchday!E8) -> 14 | M6: =IF(Matchday!F8="","",Matchday!F8) -> 7.5 | N6: =IF(Matchday!G8="","",Matchday!G8) -> 1.2 | O6: =IF(L6="","",1/L6) -> 0.071428571 | P6: =IF(M6="","",1/M6) -> 0.13333333 | Q6: =IF(N6="","",1/N6) -> 0.83333333 | R6: =IF(COUNT(L6:N6)<3,"",O6+P6+Q6) -> 1.0380952 | S6: {=IF($R6="","",IF(Method!$B$56="proportional",O6/$R6,IF(Method!$B$56="power",IFERROR(INDEX(power_devig($L6,$M6,$N6),1,1),O6/$R6),IFERROR(INDEX(shin($L6,$M6,$N6),1,1),O6/$R6))))} -> 0.061439258 | T6: {=IF($R6="","",IF(Method!$B$56="proportional",P6/$R6,IF(Method!$B$56="power",IFERROR(INDEX(power_devig($L6,$M6,$N6),2,1),P6/$R6),IFERROR(INDEX(shin($L6,$M6,$N6),2,1),P6/$R6))))} -> 0.12247683 | U6: {=IF($R6="","",IF(Method!$B$56="proportional",Q6/$R6,IF(Method!$B$56="power",IFERROR(INDEX(power_devig($L6,$M6,$N6),3,1),Q6/$R6),IFERROR(INDEX(shin($L6,$M6,$N6),3,1),Q6/$R6))))} -> 0.81608391 | V6: =IF(S6="","",Method!$B$4*IF(BC6="",I6,BC6)+(1-Method!$B$4)*S6/($S6+$T6+$U6)) -> 0.066429991 | W6: =IF(T6="","",Method!$B$4*IF(BD6="",J6,BD6)+(1-Method!$B$4)*T6/($S6+$T6+$U6)) -> 0.15615122 | X6: =IF(U6="","",Method!$B$4*IF(BE6="",K6,BE6)+(1-Method!$B$4)*U6/($S6+$T6+$U6)) -> 0.77741879 | Y6: =IF(V6="","",V6*L6-1) -> -0.069980126 | Z6: =IF(W6="","",W6*M6-1) -> 0.17113412 | AA6: =IF(X6="","",X6*N6-1) -> -0.067097448 | AB6: =IF(Y6="","",MATCH(MAX(Y6:AA6),Y6:AA6,0)) -> 2 | AC6: =IF(AB6="","",CHOOSE(AB6,"H","D","A")) -> D | AD6: =IF(AB6="","",CHOOSE(AB6,"1 "&D6,"X Draw","2 "&E6)) -> X Draw | AE6: =IF(AB6="","",INDEX(L6:N6,1,AB6)) -> 7.5 | AF6: =IF(AB6="","",INDEX(Y6:AA6,1,AB6)) -> 0.17113412 | AG6: =IF(AB6="","",INDEX(V6:X6,1,AB6)-INDEX(S6:U6,1,AB6)) -> 0.033674381 | AH6: {=IF(AB6="","· enter odds",IF(OR(AF6>Method!$B$87,IFERROR(INDEX(BC6:BE6,1,AB6)/INDEX(S6:U6,1,AB6),0)>Method!$B$88),"PASS",IF(AND(AF6>=Method!$B$7,AG6>=Method!$B$8),"BET","PASS")))} -> BET | AI6: =IF(AH6<>"BET",0,ROUND(MIN(Method!$B$6,Method!$B$5*AL6)*100,1)) -> 0.7 | AJ6: =IF(OR(AH6<>"BET",Method!$B$55=TRUE()),0,IF(AI6*Method!$B$10/100<Method!$B$9,0,ROUND(AI6*Method!$B$10/100,0))) -> 7 | AK6: =IF(AB6="","",INDEX(V6:X6,1,AB6)) -> 0.15615122 | AL6: =IF(AH6<>"BET","",MAX(0,(AK6*AE6-1)/(AE6-1))) -> 0.026328325 | AM6: =IF(AH6="BET",AF6+A6/1000000,"") -> 0.17113912 | AN6: =IF(Matchday!N8="","",Matchday!N8) -> Y | AO6: =IF(Matchday!P8="","",Matchday!P8) -> 7.5 | AP6: =IF(Matchday!Q8="","",Matchday!Q8) -> 20 | AQ6: =IF(Matchday!R8="","",Matchday!R8) -> D | AR6: =IF(OR(AN6<>"Y",AQ6="",AV6=""),"",IF(AQ6="Void",0,IF(AQ6=AV6,ROUND(AP6*(AO6-1),2),-AP6))) -> -20 | AS6: =IF(AR6="","",SUM($AR$2:AR6)) -> 1.4 | AT6: =IFERROR(__xludf.DUMMYFUNCTION("IF(AB6="""",""Type the 3 odds on the Matchday tab"",IF(Method!$B$55=TRUE(),IF(Method!$B$81=TRUE(),IF(REGEXMATCH(LOWER(Method!$B$63),""circuit""),""🛑 PAUSED — circuit breaker upstream; wait for a clean live refresh."",IF(REGEXMATCH(LOWER(Method!$B$63),""p"&"ipeline""),""🛑 PAUSED — live pipeline warning; check Live!B11/Method!B62 before betting."",IF(REGEXMATCH(LOWER(Method!$B$63),""missing""),""🛑 PAUSED — feed timestamp missing; refresh feed before betting."",""🛑 PAUSED — feed stale > 25 min — check Live "&"tab; refresh feed before betting.""))),IF(Method!$B$51>=Method!$B$52,""🛑 PAUSED — drawdown ""&TEXT(Method!$B$51,""0.0%"")&"" ≥ ""&TEXT(Method!$B$52,""0.0%"")&"". Set Method!B54=Y to override."",""🛑 PAUSED — see Method!B62/B63/B81 for cause; do not overr"&"ide stale/circuit-breaker/pipeline pauses."")),IF(AH6=""BET"",IF(AJ6=0,""Edge found but stake rounds under £""&Method!$B$9&"" — skip"",IF(AND(AE6>=6,AG6>=0.15),""🟡 WAIT — long-shot review: odds ""&TEXT(AE6,""0.00"")&"" + edge ""&TEXT(AG6,""0.0%"")&"" — v"&"erify sharp-book + team news + stake comfort before Placed=Y"",""Value found: EV ""&TEXT(AF6,""0.0%"")&"", edge ""&TEXT(AG6,""0.0%""))),IF(OR(AF6>Method!$B$87,IFERROR(INDEX(BC6:BE6,1,AB6)/INDEX(S6:U6,1,AB6),0)>Method!$B$88),""🛑 Tail trap — auto-PASS · EV"&" ""&TEXT(AF6,""0.0%"")&"" (cap ""&TEXT(Method!$B$87,""0%"")&"") · model/market ""&TEXT(IFERROR(INDEX(BC6:BE6,1,AB6)/INDEX(S6:U6,1,AB6),0),""0.0"")&""× (cap ""&TEXT(Method!$B$88,""0.0"")&""×)"",IF(AF6<Method!$B$7,""Price too short — EV ""&TEXT(AF6,""0.0%"""&")&"" (need ""&TEXT(Method!$B$7,""0.0%"")&""+)"",""Model ≈ market — edge ""&TEXT(AG6,""0.0%"")&"" (need ""&TEXT(Method!$B$8,""0.0%"")&""+)"")))))"),"Value found: EV 17.1%, edge 3.4%") -> Value found: EV 17.1%, edge 3.4% | AU6: =IF(AN6<>"Y","",IF(AH6="· enter odds","⚠ type the 3 odds (1/X/2) to grade this bet",IF(OR(AV6="",AO6="",AP6=""),"⚠ log backed pick, odds & stake",IF(AZ6<>"BET","⚠ FUN BET — engine said pass · staked £"&AP6&" vs engine £"&BA6,IF(AV6<>IF(AY6="",AC6,AY6),"⚠ backed "&AV6&" but engine pick was "&IF(AY6="",AC6,AY6),IF(AP6>BA6,"⚠ stake over engine £"&BA6,IF(ABS(AO6-IFERROR(INDEX(L6:N6,1,MATCH(AV6,{"H","D","A"},0)),AE6))>0.02,"⚠ odds moved — re-check value","✓ engine bet"))))))) -> ⚠ FUN BET — engine said pass · staked £20 vs engine £0 | AV6: =IF(Matchday!O8="","",Matchday!O8) -> A | AW6: PASS | AX6: 0 | AY6: D | AZ6: =IF(AW6="",AH6,AW6) -> PASS | BA6: =IF(AX6<>"",AX6,IF(AH6<>"BET",0,IF(AI6*Method!$B$10/100<Method!$B$9,0,ROUND(AI6*Method!$B$10/100,0)))) -> 0 | BB6: -53.4 | BC6: 0.075698495 | BD6: 0.21868935 | BE6: 0.70561215 | BF6: Qatar team-wide: -35 · Switzerland team-wide: -18 | BG6: 8 | BH6: mild_dry | BI6: 0
A7: 6 | B7: 46186 | C7: C | D7: Brazil | E7: Morocco | F7: East Rutherford | G7: 0.75 | H7: 0.95833333 | I7: 0.45124668 | J7: 0.29136359 | K7: 0.25738973 | L7: =IF(Matchday!E9="","",Matchday!E9) -> 1.7 | M7: =IF(Matchday!F9="","",Matchday!F9) -> 3.75 | N7: =IF(Matchday!G9="","",Matchday!G9) -> 5.5 | O7: =IF(L7="","",1/L7) -> 0.58823529 | P7: =IF(M7="","",1/M7) -> 0.26666667 | Q7: =IF(N7="","",1/N7) -> 0.18181818 | R7: =IF(COUNT(L7:N7)<3,"",O7+P7+Q7) -> 1.0367201 | S7: {=IF($R7="","",IF(Method!$B$56="proportional",O7/$R7,IF(Method!$B$56="power",IFERROR(INDEX(power_devig($L7,$M7,$N7),1,1),O7/$R7),IFERROR(INDEX(shin($L7,$M7,$N7),1,1),O7/$R7))))} -> 0.57380303 | T7: {=IF($R7="","",IF(Method!$B$56="proportional",P7/$R7,IF(Method!$B$56="power",IFERROR(INDEX(power_devig($L7,$M7,$N7),2,1),P7/$R7),IFERROR(INDEX(shin($L7,$M7,$N7),2,1),P7/$R7))))} -> 0.25511569 | U7: {=IF($R7="","",IF(Method!$B$56="proportional",Q7/$R7,IF(Method!$B$56="power",IFERROR(INDEX(power_devig($L7,$M7,$N7),3,1),Q7/$R7),IFERROR(INDEX(shin($L7,$M7,$N7),3,1),Q7/$R7))))} -> 0.17108129 | V7: =IF(S7="","",Method!$B$4*IF(BC7="",I7,BC7)+(1-Method!$B$4)*S7/($S7+$T7+$U7)) -> 0.53293643 | W7: =IF(T7="","",Method!$B$4*IF(BD7="",J7,BD7)+(1-Method!$B$4)*T7/($S7+$T7+$U7)) -> 0.25924918 | X7: =IF(U7="","",Method!$B$4*IF(BE7="",K7,BE7)+(1-Method!$B$4)*U7/($S7+$T7+$U7)) -> 0.20781439 | Y7: =IF(V7="","",V7*L7-1) -> -0.094008073 | Z7: =IF(W7="","",W7*M7-1) -> -0.027815562 | AA7: =IF(X7="","",X7*N7-1) -> 0.14297914 | AB7: =IF(Y7="","",MATCH(MAX(Y7:AA7),Y7:AA7,0)) -> 3 | AC7: =IF(AB7="","",CHOOSE(AB7,"H","D","A")) -> A | AD7: =IF(AB7="","",CHOOSE(AB7,"1 "&D7,"X Draw","2 "&E7)) -> 2 Morocco | AE7: =IF(AB7="","",INDEX(L7:N7,1,AB7)) -> 5.5 | AF7: =IF(AB7="","",INDEX(Y7:AA7,1,AB7)) -> 0.14297914 | AG7: =IF(AB7="","",INDEX(V7:X7,1,AB7)-INDEX(S7:U7,1,AB7)) -> 0.036733101 | AH7: {=IF(AB7="","· enter odds",IF(OR(AF7>Method!$B$87,IFERROR(INDEX(BC7:BE7,1,AB7)/INDEX(S7:U7,1,AB7),0)>Method!$B$88),"PASS",IF(AND(AF7>=Method!$B$7,AG7>=Method!$B$8),"BET","PASS")))} -> BET | AI7: =IF(AH7<>"BET",0,ROUND(MIN(Method!$B$6,Method!$B$5*AL7)*100,1)) -> 0.8 | AJ7: =IF(OR(AH7<>"BET",Method!$B$55=TRUE()),0,IF(AI7*Method!$B$10/100<Method!$B$9,0,ROUND(AI7*Method!$B$10/100,0))) -> 8 | AK7: =IF(AB7="","",INDEX(V7:X7,1,AB7)) -> 0.20781439 | AL7: =IF(AH7<>"BET","",MAX(0,(AK7*AE7-1)/(AE7-1))) -> 0.031773142 | AM7: =IF(AH7="BET",AF7+A7/1000000,"") -> 0.14298514 | AN7: =IF(Matchday!N9="","",Matchday!N9) -> Y | AO7: =IF(Matchday!P9="","",Matchday!P9) -> 1.68 | AP7: =IF(Matchday!Q9="","",Matchday!Q9) -> 30 | AQ7: =IF(Matchday!R9="","",Matchday!R9) -> D | AR7: =IF(OR(AN7<>"Y",AQ7="",AV7=""),"",IF(AQ7="Void",0,IF(AQ7=AV7,ROUND(AP7*(AO7-1),2),-AP7))) -> -30 | AS7: =IF(AR7="","",SUM($AR$2:AR7)) -> -28.6 | AT7: =IFERROR(__xludf.DUMMYFUNCTION("IF(AB7="""",""Type the 3 odds on the Matchday tab"",IF(Method!$B$55=TRUE(),IF(Method!$B$81=TRUE(),IF(REGEXMATCH(LOWER(Method!$B$63),""circuit""),""🛑 PAUSED — circuit breaker upstream; wait for a clean live refresh."",IF(REGEXMATCH(LOWER(Method!$B$63),""p"&"ipeline""),""🛑 PAUSED — live pipeline warning; check Live!B11/Method!B62 before betting."",IF(REGEXMATCH(LOWER(Method!$B$63),""missing""),""🛑 PAUSED — feed timestamp missing; refresh feed before betting."",""🛑 PAUSED — feed stale > 25 min — check Live "&"tab; refresh feed before betting.""))),IF(Method!$B$51>=Method!$B$52,""🛑 PAUSED — drawdown ""&TEXT(Method!$B$51,""0.0%"")&"" ≥ ""&TEXT(Method!$B$52,""0.0%"")&"". Set Method!B54=Y to override."",""🛑 PAUSED — see Method!B62/B63/B81 for cause; do not overr"&"ide stale/circuit-breaker/pipeline pauses."")),IF(AH7=""BET"",IF(AJ7=0,""Edge found but stake rounds under £""&Method!$B$9&"" — skip"",IF(AND(AE7>=6,AG7>=0.15),""🟡 WAIT — long-shot review: odds ""&TEXT(AE7,""0.00"")&"" + edge ""&TEXT(AG7,""0.0%"")&"" — v"&"erify sharp-book + team news + stake comfort before Placed=Y"",""Value found: EV ""&TEXT(AF7,""0.0%"")&"", edge ""&TEXT(AG7,""0.0%""))),IF(OR(AF7>Method!$B$87,IFERROR(INDEX(BC7:BE7,1,AB7)/INDEX(S7:U7,1,AB7),0)>Method!$B$88),""🛑 Tail trap — auto-PASS · EV"&" ""&TEXT(AF7,""0.0%"")&"" (cap ""&TEXT(Method!$B$87,""0%"")&"") · model/market ""&TEXT(IFERROR(INDEX(BC7:BE7,1,AB7)/INDEX(S7:U7,1,AB7),0),""0.0"")&""× (cap ""&TEXT(Method!$B$88,""0.0"")&""×)"",IF(AF7<Method!$B$7,""Price too short — EV ""&TEXT(AF7,""0.0%"""&")&"" (need ""&TEXT(Method!$B$7,""0.0%"")&""+)"",""Model ≈ market — edge ""&TEXT(AG7,""0.0%"")&"" (need ""&TEXT(Method!$B$8,""0.0%"")&""+)"")))))"),"Value found: EV 14.3%, edge 3.7%") -> Value found: EV 14.3%, edge 3.7% | AU7: =IF(AN7<>"Y","",IF(AH7="· enter odds","⚠ type the 3 odds (1/X/2) to grade this bet",IF(OR(AV7="",AO7="",AP7=""),"⚠ log backed pick, odds & stake",IF(AZ7<>"BET","⚠ FUN BET — engine said pass · staked £"&AP7&" vs engine £"&BA7,IF(AV7<>IF(AY7="",AC7,AY7),"⚠ backed "&AV7&" but engine pick was "&IF(AY7="",AC7,AY7),IF(AP7>BA7,"⚠ stake over engine £"&BA7,IF(ABS(AO7-IFERROR(INDEX(L7:N7,1,MATCH(AV7,{"H","D","A"},0)),AE7))>0.02,"⚠ odds moved — re-check value","✓ engine bet"))))))) -> ⚠ backed H but engine pick was A | AV7: =IF(Matchday!O9="","",Matchday!O9) -> H | AW7: BET | AX7: 5 | AY7: A | AZ7: =IF(AW7="",AH7,AW7) -> BET | BA7: =IF(AX7<>"",AX7,IF(AH7<>"BET",0,IF(AI7*Method!$B$10/100<Method!$B$9,0,ROUND(AI7*Method!$B$10/100,0)))) -> 5 | BB7: -23.53 | BC7: 0.45704131 | BD7: 0.26692568 | BE7: 0.276033 | BF7: Brazil team-wide: -17 · Morocco team-wide: -7 | BG7: 7 | BH7: warm_humid | BI7: 0
A8: 7 | B8: 46186 | C8: C | D8: Haiti | E8: Scotland | F8: Foxborough | G8: 0.875 | H8: 02:00 +1d | I8: 0.21112157 | J8: 0.26889892 | K8: 0.51997951 | L8: =IF(Matchday!E10="","",Matchday!E10) -> 6 | M8: =IF(Matchday!F10="","",Matchday!F10) -> 4.5 | N8: =IF(Matchday!G10="","",Matchday!G10) -> 0.53 | O8: =IF(L8="","",1/L8) -> 0.16666667 | P8: =IF(M8="","",1/M8) -> 0.22222222 | Q8: =IF(N8="","",1/N8) -> 1.8867925 | R8: =IF(COUNT(L8:N8)<3,"",O8+P8+Q8) -> 2.2756813 | S8: {=IF($R8="","",IF(Method!$B$56="proportional",O8/$R8,IF(Method!$B$56="power",IFERROR(INDEX(power_devig($L8,$M8,$N8),1,1),O8/$R8),IFERROR(INDEX(shin($L8,$M8,$N8),1,1),O8/$R8))))} -> 0.073238139 | T8: {=IF($R8="","",IF(Method!$B$56="proportional",P8/$R8,IF(Method!$B$56="power",IFERROR(INDEX(power_devig($L8,$M8,$N8),2,1),P8/$R8),IFERROR(INDEX(shin($L8,$M8,$N8),2,1),P8/$R8))))} -> 0.097650852 | U8: {=IF($R8="","",IF(Method!$B$56="proportional",Q8/$R8,IF(Method!$B$56="power",IFERROR(INDEX(power_devig($L8,$M8,$N8),3,1),Q8/$R8),IFERROR(INDEX(shin($L8,$M8,$N8),3,1),Q8/$R8))))} -> 0.82911101 | V8: =IF(S8="","",Method!$B$4*IF(BC8="",I8,BC8)+(1-Method!$B$4)*S8/($S8+$T8+$U8)) -> 0.11617321 | W8: =IF(T8="","",Method!$B$4*IF(BD8="",J8,BD8)+(1-Method!$B$4)*T8/($S8+$T8+$U8)) -> 0.16128192 | X8: =IF(U8="","",Method!$B$4*IF(BE8="",K8,BE8)+(1-Method!$B$4)*U8/($S8+$T8+$U8)) -> 0.72254487 | Y8: =IF(V8="","",V8*L8-1) -> -0.30296074 | Z8: =IF(W8="","",W8*M8-1) -> -0.27423134 | AA8: =IF(X8="","",X8*N8-1) -> -0.61705122 | AB8: =IF(Y8="","",MATCH(MAX(Y8:AA8),Y8:AA8,0)) -> 2 | AC8: =IF(AB8="","",CHOOSE(AB8,"H","D","A")) -> D | AD8: =IF(AB8="","",CHOOSE(AB8,"1 "&D8,"X Draw","2 "&E8)) -> X Draw | AE8: =IF(AB8="","",INDEX(L8:N8,1,AB8)) -> 4.5 | AF8: =IF(AB8="","",INDEX(Y8:AA8,1,AB8)) -> -0.27423134 | AG8: =IF(AB8="","",INDEX(V8:X8,1,AB8)-INDEX(S8:U8,1,AB8)) -> 0.063631073 | AH8: {=IF(AB8="","· enter odds",IF(OR(AF8>Method!$B$87,IFERROR(INDEX(BC8:BE8,1,AB8)/INDEX(S8:U8,1,AB8),0)>Method!$B$88),"PASS",IF(AND(AF8>=Method!$B$7,AG8>=Method!$B$8),"BET","PASS")))} -> PASS | AI8: =IF(AH8<>"BET",0,ROUND(MIN(Method!$B$6,Method!$B$5*AL8)*100,1)) -> 0 | AJ8: =IF(OR(AH8<>"BET",Method!$B$55=TRUE()),0,IF(AI8*Method!$B$10/100<Method!$B$9,0,ROUND(AI8*Method!$B$10/100,0))) -> 0 | AK8: =IF(AB8="","",INDEX(V8:X8,1,AB8)) -> 0.16128192 | AL8: =IF(AH8<>"BET","",MAX(0,(AK8*AE8-1)/(AE8-1))) | AM8: =IF(AH8="BET",AF8+A8/1000000,"") | AN8: =IF(Matchday!N10="","",Matchday!N10) -> N | AO8: =IF(Matchday!P10="","",Matchday!P10) | AP8: =IF(Matchday!Q10="","",Matchday!Q10) | AQ8: =IF(Matchday!R10="","",Matchday!R10) -> A | AR8: =IF(OR(AN8<>"Y",AQ8="",AV8=""),"",IF(AQ8="Void",0,IF(AQ8=AV8,ROUND(AP8*(AO8-1),2),-AP8))) | AS8: =IF(AR8="","",SUM($AR$2:AR8)) | AT8: =IFERROR(__xludf.DUMMYFUNCTION("IF(AB8="""",""Type the 3 odds on the Matchday tab"",IF(Method!$B$55=TRUE(),IF(Method!$B$81=TRUE(),IF(REGEXMATCH(LOWER(Method!$B$63),""circuit""),""🛑 PAUSED — circuit breaker upstream; wait for a clean live refresh."",IF(REGEXMATCH(LOWER(Method!$B$63),""p"&"ipeline""),""🛑 PAUSED — live pipeline warning; check Live!B11/Method!B62 before betting."",IF(REGEXMATCH(LOWER(Method!$B$63),""missing""),""🛑 PAUSED — feed timestamp missing; refresh feed before betting."",""🛑 PAUSED — feed stale > 25 min — check Live "&"tab; refresh feed before betting.""))),IF(Method!$B$51>=Method!$B$52,""🛑 PAUSED — drawdown ""&TEXT(Method!$B$51,""0.0%"")&"" ≥ ""&TEXT(Method!$B$52,""0.0%"")&"". Set Method!B54=Y to override."",""🛑 PAUSED — see Method!B62/B63/B81 for cause; do not overr"&"ide stale/circuit-breaker/pipeline pauses."")),IF(AH8=""BET"",IF(AJ8=0,""Edge found but stake rounds under £""&Method!$B$9&"" — skip"",IF(AND(AE8>=6,AG8>=0.15),""🟡 WAIT — long-shot review: odds ""&TEXT(AE8,""0.00"")&"" + edge ""&TEXT(AG8,""0.0%"")&"" — v"&"erify sharp-book + team news + stake comfort before Placed=Y"",""Value found: EV ""&TEXT(AF8,""0.0%"")&"", edge ""&TEXT(AG8,""0.0%""))),IF(OR(AF8>Method!$B$87,IFERROR(INDEX(BC8:BE8,1,AB8)/INDEX(S8:U8,1,AB8),0)>Method!$B$88),""🛑 Tail trap — auto-PASS · EV"&" ""&TEXT(AF8,""0.0%"")&"" (cap ""&TEXT(Method!$B$87,""0%"")&"") · model/market ""&TEXT(IFERROR(INDEX(BC8:BE8,1,AB8)/INDEX(S8:U8,1,AB8),0),""0.0"")&""× (cap ""&TEXT(Method!$B$88,""0.0"")&""×)"",IF(AF8<Method!$B$7,""Price too short — EV ""&TEXT(AF8,""0.0%"""&")&"" (need ""&TEXT(Method!$B$7,""0.0%"")&""+)"",""Model ≈ market — edge ""&TEXT(AG8,""0.0%"")&"" (need ""&TEXT(Method!$B$8,""0.0%"")&""+)"")))))"),"🛑 Tail trap — auto-PASS · EV -27.4% (cap 30%) · model/market 2.9× (cap 2.5×)") -> 🛑 Tail trap — auto-PASS · EV -27.4% (cap 30%) · model/market 2.9× (cap 2.5×) | AU8: =IF(AN8<>"Y","",IF(AH8="· enter odds","⚠ type the 3 odds (1/X/2) to grade this bet",IF(OR(AV8="",AO8="",AP8=""),"⚠ log backed pick, odds & stake",IF(AZ8<>"BET","⚠ FUN BET — engine said pass · staked £"&AP8&" vs engine £"&BA8,IF(AV8<>IF(AY8="",AC8,AY8),"⚠ backed "&AV8&" but engine pick was "&IF(AY8="",AC8,AY8),IF(AP8>BA8,"⚠ stake over engine £"&BA8,IF(ABS(AO8-IFERROR(INDEX(L8:N8,1,MATCH(AV8,{"H","D","A"},0)),AE8))>0.02,"⚠ odds moved — re-check value","✓ engine bet"))))))) | AV8: =IF(Matchday!O10="","",Matchday!O10) | AZ8: =IF(AW8="",AH8,AW8) -> PASS | BA8: =IF(AX8<>"",AX8,IF(AH8<>"BET",0,IF(AI8*Method!$B$10/100<Method!$B$9,0,ROUND(AI8*Method!$B$10/100,0)))) -> 0 | BB8: -11.28 | BC8: 0.19590977 | BD8: 0.27945392 | BE8: 0.52463631 | BF8: Haiti team-wide: -7 · Scotland team-wide: -4 | BG8: 40 | BH8: warm | BI8: 0
A9: 8 | B9: 46186 | C9: D | D9: Australia | E9: Turkey | F9: Vancouver | G9: 0.875 | H9: 05:00 +1d | I9: 0.3613933 | J9: 0.30639872 | K9: 0.33220798 | L9: =IF(Matchday!E11="","",Matchday!E11) -> 5.25 | M9: =IF(Matchday!F11="","",Matchday!F11) -> 3.8 | N9: =IF(Matchday!G11="","",Matchday!G11) -> 1.66 | O9: =IF(L9="","",1/L9) -> 0.19047619 | P9: =IF(M9="","",1/M9) -> 0.26315789 | Q9: =IF(N9="","",1/N9) -> 0.60240964 | R9: =IF(COUNT(L9:N9)<3,"",O9+P9+Q9) -> 1.0560437 | S9: {=IF($R9="","",IF(Method!$B$56="proportional",O9/$R9,IF(Method!$B$56="power",IFERROR(INDEX(power_devig($L9,$M9,$N9),1,1),O9/$R9),IFERROR(INDEX(shin($L9,$M9,$N9),1,1),O9/$R9))))} -> 0.17404997 | T9: {=IF($R9="","",IF(Method!$B$56="proportional",P9/$R9,IF(Method!$B$56="power",IFERROR(INDEX(power_devig($L9,$M9,$N9),2,1),P9/$R9),IFERROR(INDEX(shin($L9,$M9,$N9),2,1),P9/$R9))))} -> 0.24564306 | U9: {=IF($R9="","",IF(Method!$B$56="proportional",Q9/$R9,IF(Method!$B$56="power",IFERROR(INDEX(power_devig($L9,$M9,$N9),3,1),Q9/$R9),IFERROR(INDEX(shin($L9,$M9,$N9),3,1),Q9/$R9))))} -> 0.58030697 | V9: =IF(S9="","",Method!$B$4*IF(BC9="",I9,BC9)+(1-Method!$B$4)*S9/($S9+$T9+$U9)) -> 0.24179783 | W9: =IF(T9="","",Method!$B$4*IF(BD9="",J9,BD9)+(1-Method!$B$4)*T9/($S9+$T9+$U9)) -> 0.25017993 | X9: =IF(U9="","",Method!$B$4*IF(BE9="",K9,BE9)+(1-Method!$B$4)*U9/($S9+$T9+$U9)) -> 0.50802224 | Y9: =IF(V9="","",V9*L9-1) -> 0.26943859 | Z9: =IF(W9="","",W9*M9-1) -> -0.049316254 | AA9: =IF(X9="","",X9*N9-1) -> -0.15668308 | AB9: =IF(Y9="","",MATCH(MAX(Y9:AA9),Y9:AA9,0)) -> 1 | AC9: =IF(AB9="","",CHOOSE(AB9,"H","D","A")) -> H | AD9: =IF(AB9="","",CHOOSE(AB9,"1 "&D9,"X Draw","2 "&E9)) -> 1 Australia | AE9: =IF(AB9="","",INDEX(L9:N9,1,AB9)) -> 5.25 | AF9: =IF(AB9="","",INDEX(Y9:AA9,1,AB9)) -> 0.26943859 | AG9: =IF(AB9="","",INDEX(V9:X9,1,AB9)-INDEX(S9:U9,1,AB9)) -> 0.067747853 | AH9: {=IF(AB9="","· enter odds",IF(OR(AF9>Method!$B$87,IFERROR(INDEX(BC9:BE9,1,AB9)/INDEX(S9:U9,1,AB9),0)>Method!$B$88),"PASS",IF(AND(AF9>=Method!$B$7,AG9>=Method!$B$8),"BET","PASS")))} -> BET | AI9: =IF(AH9<>"BET",0,ROUND(MIN(Method!$B$6,Method!$B$5*AL9)*100,1)) -> 1.6 | AJ9: =IF(OR(AH9<>"BET",Method!$B$55=TRUE()),0,IF(AI9*Method!$B$10/100<Method!$B$9,0,ROUND(AI9*Method!$B$10/100,0))) -> 16 | AK9: =IF(AB9="","",INDEX(V9:X9,1,AB9)) -> 0.24179783 | AL9: =IF(AH9<>"BET","",MAX(0,(AK9*AE9-1)/(AE9-1))) -> 0.063397316 | AM9: =IF(AH9="BET",AF9+A9/1000000,"") -> 0.26944659 | AN9: =IF(Matchday!N11="","",Matchday!N11) -> Y | AO9: =IF(Matchday!P11="","",Matchday!P11) -> 5.25 | AP9: =IF(Matchday!Q11="","",Matchday!Q11) -> 10 | AQ9: =IF(Matchday!R11="","",Matchday!R11) -> H | AR9: =IF(OR(AN9<>"Y",AQ9="",AV9=""),"",IF(AQ9="Void",0,IF(AQ9=AV9,ROUND(AP9*(AO9-1),2),-AP9))) -> 42.5 | AS9: =IF(AR9="","",SUM($AR$2:AR9)) -> 13.9 | AT9: =IFERROR(__xludf.DUMMYFUNCTION("IF(AB9="""",""Type the 3 odds on the Matchday tab"",IF(Method!$B$55=TRUE(),IF(Method!$B$81=TRUE(),IF(REGEXMATCH(LOWER(Method!$B$63),""circuit""),""🛑 PAUSED — circuit breaker upstream; wait for a clean live refresh."",IF(REGEXMATCH(LOWER(Method!$B$63),""p"&"ipeline""),""🛑 PAUSED — live pipeline warning; check Live!B11/Method!B62 before betting."",IF(REGEXMATCH(LOWER(Method!$B$63),""missing""),""🛑 PAUSED — feed timestamp missing; refresh feed before betting."",""🛑 PAUSED — feed stale > 25 min — check Live "&"tab; refresh feed before betting.""))),IF(Method!$B$51>=Method!$B$52,""🛑 PAUSED — drawdown ""&TEXT(Method!$B$51,""0.0%"")&"" ≥ ""&TEXT(Method!$B$52,""0.0%"")&"". Set Method!B54=Y to override."",""🛑 PAUSED — see Method!B62/B63/B81 for cause; do not overr"&"ide stale/circuit-breaker/pipeline pauses."")),IF(AH9=""BET"",IF(AJ9=0,""Edge found but stake rounds under £""&Method!$B$9&"" — skip"",IF(AND(AE9>=6,AG9>=0.15),""🟡 WAIT — long-shot review: odds ""&TEXT(AE9,""0.00"")&"" + edge ""&TEXT(AG9,""0.0%"")&"" — v"&"erify sharp-book + team news + stake comfort before Placed=Y"",""Value found: EV ""&TEXT(AF9,""0.0%"")&"", edge ""&TEXT(AG9,""0.0%""))),IF(OR(AF9>Method!$B$87,IFERROR(INDEX(BC9:BE9,1,AB9)/INDEX(S9:U9,1,AB9),0)>Method!$B$88),""🛑 Tail trap — auto-PASS · EV"&" ""&TEXT(AF9,""0.0%"")&"" (cap ""&TEXT(Method!$B$87,""0%"")&"") · model/market ""&TEXT(IFERROR(INDEX(BC9:BE9,1,AB9)/INDEX(S9:U9,1,AB9),0),""0.0"")&""× (cap ""&TEXT(Method!$B$88,""0.0"")&""×)"",IF(AF9<Method!$B$7,""Price too short — EV ""&TEXT(AF9,""0.0%"""&")&"" (need ""&TEXT(Method!$B$7,""0.0%"")&""+)"",""Model ≈ market — edge ""&TEXT(AG9,""0.0%"")&"" (need ""&TEXT(Method!$B$8,""0.0%"")&""+)"")))))"),"Value found: EV 26.9%, edge 6.8%") -> Value found: EV 26.9%, edge 6.8% | AU9: =IF(AN9<>"Y","",IF(AH9="· enter odds","⚠ type the 3 odds (1/X/2) to grade this bet",IF(OR(AV9="",AO9="",AP9=""),"⚠ log backed pick, odds & stake",IF(AZ9<>"BET","⚠ FUN BET — engine said pass · staked £"&AP9&" vs engine £"&BA9,IF(AV9<>IF(AY9="",AC9,AY9),"⚠ backed "&AV9&" but engine pick was "&IF(AY9="",AC9,AY9),IF(AP9>BA9,"⚠ stake over engine £"&BA9,IF(ABS(AO9-IFERROR(INDEX(L9:N9,1,MATCH(AV9,{"H","D","A"},0)),AE9))>0.02,"⚠ odds moved — re-check value","✓ engine bet"))))))) -> ⚠ stake over engine £0 | AV9: =IF(Matchday!O11="","",Matchday!O11) -> H | AW9: BET | AX9: 0 | AY9: H | AZ9: =IF(AW9="",AH9,AW9) -> BET | BA9: =IF(AX9<>"",AX9,IF(AH9<>"BET",0,IF(AI9*Method!$B$10/100<Method!$B$9,0,ROUND(AI9*Method!$B$10/100,0)))) -> 0 | BB9: -21.66 | BC9: 0.36761527 | BD9: 0.25860556 | BE9: 0.37377917 | BF9: Australia team-wide: -26 · Turkey team-wide: +4 | BG9: 0 | BH9: mild_indoor | BI9: 0
A10: 9 | B10: 46187 | C10: E | D10: Germany | E10: Curacao | F10: Houston | G10: 0.5 | H10: 0.75 | I10: 0.73873705 | J10: 0.17963937 | K10: 0.081623574 | L10: =IF(Matchday!E12="","",Matchday!E12) -> 1.03 | M10: =IF(Matchday!F12="","",Matchday!F12) -> 19 | N10: =IF(Matchday!G12="","",Matchday!G12) -> 34 | O10: =IF(L10="","",1/L10) -> 0.97087379 | P10: =IF(M10="","",1/M10) -> 0.052631579 | Q10: =IF(N10="","",1/N10) -> 0.029411765 | R10: =IF(COUNT(L10:N10)<3,"",O10+P10+Q10) -> 1.0529171 | S10: {=IF($R10="","",IF(Method!$B$56="proportional",O10/$R10,IF(Method!$B$56="power",IFERROR(INDEX(power_devig($L10,$M10,$N10),1,1),O10/$R10),IFERROR(INDEX(shin($L10,$M10,$N10),1,1),O10/$R10))))} -> 0.94526903 | T10: {=IF($R10="","",IF(Method!$B$56="proportional",P10/$R10,IF(Method!$B$56="power",IFERROR(INDEX(power_devig($L10,$M10,$N10),2,1),P10/$R10),IFERROR(INDEX(shin($L10,$M10,$N10),2,1),P10/$R10))))} -> 0.037933235 | U10: {=IF($R10="","",IF(Method!$B$56="proportional",Q10/$R10,IF(Method!$B$56="power",IFERROR(INDEX(power_devig($L10,$M10,$N10),3,1),Q10/$R10),IFERROR(INDEX(shin($L10,$M10,$N10),3,1),Q10/$R10))))} -> 0.016797735 | V10: =IF(S10="","",Method!$B$4*IF(BC10="",I10,BC10)+(1-Method!$B$4)*S10/($S10+$T10+$U10)) -> 0.8634901 | W10: =IF(T10="","",Method!$B$4*IF(BD10="",J10,BD10)+(1-Method!$B$4)*T10/($S10+$T10+$U10)) -> 0.096232006 | X10: =IF(U10="","",Method!$B$4*IF(BE10="",K10,BE10)+(1-Method!$B$4)*U10/($S10+$T10+$U10)) -> 0.040277896 | Y10: =IF(V10="","",V10*L10-1) -> -0.1106052 | Z10: =IF(W10="","",W10*M10-1) -> 0.82840812 | AA10: =IF(X10="","",X10*N10-1) -> 0.36944846 | AB10: =IF(Y10="","",MATCH(MAX(Y10:AA10),Y10:AA10,0)) -> 2 | AC10: =IF(AB10="","",CHOOSE(AB10,"H","D","A")) -> D | AD10: =IF(AB10="","",CHOOSE(AB10,"1 "&D10,"X Draw","2 "&E10)) -> X Draw | AE10: =IF(AB10="","",INDEX(L10:N10,1,AB10)) -> 19 | AF10: =IF(AB10="","",INDEX(Y10:AA10,1,AB10)) -> 0.82840812 | AG10: =IF(AB10="","",INDEX(V10:X10,1,AB10)-INDEX(S10:U10,1,AB10)) -> 0.058298771 | AH10: {=IF(AB10="","· enter odds",IF(OR(AF10>Method!$B$87,IFERROR(INDEX(BC10:BE10,1,AB10)/INDEX(S10:U10,1,AB10),0)>Method!$B$88),"PASS",IF(AND(AF10>=Method!$B$7,AG10>=Method!$B$8),"BET","PASS")))} -> PASS | AI10: =IF(AH10<>"BET",0,ROUND(MIN(Method!$B$6,Method!$B$5*AL10)*100,1)) -> 0 | AJ10: =IF(OR(AH10<>"BET",Method!$B$55=TRUE()),0,IF(AI10*Method!$B$10/100<Method!$B$9,0,ROUND(AI10*Method!$B$10/100,0))) -> 0 | AK10: =IF(AB10="","",INDEX(V10:X10,1,AB10)) -> 0.096232006 | AL10: =IF(AH10<>"BET","",MAX(0,(AK10*AE10-1)/(AE10-1))) | AM10: =IF(AH10="BET",AF10+A10/1000000,"") | AN10: =IF(Matchday!N12="","",Matchday!N12) -> Y | AO10: =IF(Matchday!P12="","",Matchday!P12) -> 19 | AP10: =IF(Matchday!Q12="","",Matchday!Q12) -> 6 | AQ10: =IF(Matchday!R12="","",Matchday!R12) -> H | AR10: =IF(OR(AN10<>"Y",AQ10="",AV10=""),"",IF(AQ10="Void",0,IF(AQ10=AV10,ROUND(AP10*(AO10-1),2),-AP10))) -> -6 | AS10: =IF(AR10="","",SUM($AR$2:AR10)) -> 7.9 | AT10: =IFERROR(__xludf.DUMMYFUNCTION("IF(AB10="""",""Type the 3 odds on the Matchday tab"",IF(Method!$B$55=TRUE(),IF(Method!$B$81=TRUE(),IF(REGEXMATCH(LOWER(Method!$B$63),""circuit""),""🛑 PAUSED — circuit breaker upstream; wait for a clean live refresh."",IF(REGEXMATCH(LOWER(Method!$B$63),"""&"pipeline""),""🛑 PAUSED — live pipeline warning; check Live!B11/Method!B62 before betting."",IF(REGEXMATCH(LOWER(Method!$B$63),""missing""),""🛑 PAUSED — feed timestamp missing; refresh feed before betting."",""🛑 PAUSED — feed stale > 25 min — check Live"&" tab; refresh feed before betting.""))),IF(Method!$B$51>=Method!$B$52,""🛑 PAUSED — drawdown ""&TEXT(Method!$B$51,""0.0%"")&"" ≥ ""&TEXT(Method!$B$52,""0.0%"")&"". Set Method!B54=Y to override."",""🛑 PAUSED — see Method!B62/B63/B81 for cause; do not over"&"ride stale/circuit-breaker/pipeline pauses."")),IF(AH10=""BET"",IF(AJ10=0,""Edge found but stake rounds under £""&Method!$B$9&"" — skip"",IF(AND(AE10>=6,AG10>=0.15),""🟡 WAIT — long-shot review: odds ""&TEXT(AE10,""0.00"")&"" + edge ""&TEXT(AG10,""0.0%"")"&"&"" — verify sharp-book + team news + stake comfort before Placed=Y"",""Value found: EV ""&TEXT(AF10,""0.0%"")&"", edge ""&TEXT(AG10,""0.0%""))),IF(OR(AF10>Method!$B$87,IFERROR(INDEX(BC10:BE10,1,AB10)/INDEX(S10:U10,1,AB10),0)>Method!$B$88),""🛑 Tail trap "&"— auto-PASS · EV ""&TEXT(AF10,""0.0%"")&"" (cap ""&TEXT(Method!$B$87,""0%"")&"") · model/market ""&TEXT(IFERROR(INDEX(BC10:BE10,1,AB10)/INDEX(S10:U10,1,AB10),0),""0.0"")&""× (cap ""&TEXT(Method!$B$88,""0.0"")&""×)"",IF(AF10<Method!$B$7,""Price too short —"&" EV ""&TEXT(AF10,""0.0%"")&"" (need ""&TEXT(Method!$B$7,""0.0%"")&""+)"",""Model ≈ market — edge ""&TEXT(AG10,""0.0%"")&"" (need ""&TEXT(Method!$B$8,""0.0%"")&""+)"")))))"),"🛑 Tail trap — auto-PASS · EV 82.8% (cap 30%) · model/market 5.4× (cap 2.5×)") -> 🛑 Tail trap — auto-PASS · EV 82.8% (cap 30%) · model/market 5.4× (cap 2.5×) | AU10: =IF(AN10<>"Y","",IF(AH10="· enter odds","⚠ type the 3 odds (1/X/2) to grade this bet",IF(OR(AV10="",AO10="",AP10=""),"⚠ log backed pick, odds & stake",IF(AZ10<>"BET","⚠ FUN BET — engine said pass · staked £"&AP10&" vs engine £"&BA10,IF(AV10<>IF(AY10="",AC10,AY10),"⚠ backed "&AV10&" but engine pick was "&IF(AY10="",AC10,AY10),IF(AP10>BA10,"⚠ stake over engine £"&BA10,IF(ABS(AO10-IFERROR(INDEX(L10:N10,1,MATCH(AV10,{"H","D","A"},0)),AE10))>0.02,"⚠ odds moved — re-check value","✓ engine bet"))))))) -> ✓ engine bet | AV10: =IF(Matchday!O12="","",Matchday!O12) -> D | AW10: BET | AX10: 6 | AY10: D | AZ10: =IF(AW10="",AH10,AW10) -> BET | BA10: =IF(AX10<>"",AX10,IF(AH10<>"BET",0,IF(AI10*Method!$B$10/100<Method!$B$9,0,ROUND(AI10*Method!$B$10/100,0)))) -> 6 | BB10: -27.21 | BC10: 0.71161494 | BD10: 0.20450115 | BE10: 0.083883909 | BF10: Curacao team-wide: -13 · Germany team-wide: -14 | BG10: 15 | BH10: very_hot_humid_indoor | BI10: 0
A11: 10 | B11: 46187 | C11: F | D11: Netherlands | E11: Japan | F11: Arlington | G11: 0.625 | H11: 0.875 | I11: 0.43212683 | J11: 0.28878547 | K11: 0.2790877 | L11: =IF(Matchday!E13="","",Matchday!E13) -> 2.05 | M11: =IF(Matchday!F13="","",Matchday!F13) -> 3.5 | N11: =IF(Matchday!G13="","",Matchday!G13) -> 3.7 | O11: =IF(L11="","",1/L11) -> 0.48780488 | P11: =IF(M11="","",1/M11) -> 0.28571429 | Q11: =IF(N11="","",1/N11) -> 0.27027027 | R11: =IF(COUNT(L11:N11)<3,"",O11+P11+Q11) -> 1.0437894 | S11: {=IF($R11="","",IF(Method!$B$56="proportional",O11/$R11,IF(Method!$B$56="power",IFERROR(INDEX(power_devig($L11,$M11,$N11),1,1),O11/$R11),IFERROR(INDEX(shin($L11,$M11,$N11),1,1),O11/$R11))))} -> 0.47170405 | T11: {=IF($R11="","",IF(Method!$B$56="proportional",P11/$R11,IF(Method!$B$56="power",IFERROR(INDEX(power_devig($L11,$M11,$N11),2,1),P11/$R11),IFERROR(INDEX(shin($L11,$M11,$N11),2,1),P11/$R11))))} -> 0.27178421 | U11: {=IF($R11="","",IF(Method!$B$56="proportional",Q11/$R11,IF(Method!$B$56="power",IFERROR(INDEX(power_devig($L11,$M11,$N11),3,1),Q11/$R11),IFERROR(INDEX(shin($L11,$M11,$N11),3,1),Q11/$R11))))} -> 0.25651174 | V11: =IF(S11="","",Method!$B$4*IF(BC11="",I11,BC11)+(1-Method!$B$4)*S11/($S11+$T11+$U11)) -> 0.45824863 | W11: =IF(T11="","",Method!$B$4*IF(BD11="",J11,BD11)+(1-Method!$B$4)*T11/($S11+$T11+$U11)) -> 0.2698312 | X11: =IF(U11="","",Method!$B$4*IF(BE11="",K11,BE11)+(1-Method!$B$4)*U11/($S11+$T11+$U11)) -> 0.27192017 | Y11: =IF(V11="","",V11*L11-1) -> -0.06059031 | Z11: =IF(W11="","",W11*M11-1) -> -0.055590791 | AA11: =IF(X11="","",X11*N11-1) -> 0.0061046226 | AB11: =IF(Y11="","",MATCH(MAX(Y11:AA11),Y11:AA11,0)) -> 3 | AC11: =IF(AB11="","",CHOOSE(AB11,"H","D","A")) -> A | AD11: =IF(AB11="","",CHOOSE(AB11,"1 "&D11,"X Draw","2 "&E11)) -> 2 Japan | AE11: =IF(AB11="","",INDEX(L11:N11,1,AB11)) -> 3.7 | AF11: =IF(AB11="","",INDEX(Y11:AA11,1,AB11)) -> 0.0061046226 | AG11: =IF(AB11="","",INDEX(V11:X11,1,AB11)-INDEX(S11:U11,1,AB11)) -> 0.015408425 | AH11: {=IF(AB11="","· enter odds",IF(OR(AF11>Method!$B$87,IFERROR(INDEX(BC11:BE11,1,AB11)/INDEX(S11:U11,1,AB11),0)>Method!$B$88),"PASS",IF(AND(AF11>=Method!$B$7,AG11>=Method!$B$8),"BET","PASS")))} -> PASS | AI11: =IF(AH11<>"BET",0,ROUND(MIN(Method!$B$6,Method!$B$5*AL11)*100,1)) -> 0 | AJ11: =IF(OR(AH11<>"BET",Method!$B$55=TRUE()),0,IF(AI11*Method!$B$10/100<Method!$B$9,0,ROUND(AI11*Method!$B$10/100,0))) -> 0 | AK11: =IF(AB11="","",INDEX(V11:X11,1,AB11)) -> 0.27192017 | AL11: =IF(AH11<>"BET","",MAX(0,(AK11*AE11-1)/(AE11-1))) | AM11: =IF(AH11="BET",AF11+A11/1000000,"") | AN11: =IF(Matchday!N13="","",Matchday!N13) -> Y | AO11: =IF(Matchday!P13="","",Matchday!P13) -> 1 | AP11: =IF(Matchday!Q13="","",Matchday!Q13) | AQ11: =IF(Matchday!R13="","",Matchday!R13) -> D | AR11: =IF(OR(AN11<>"Y",AQ11="",AV11=""),"",IF(AQ11="Void",0,IF(AQ11=AV11,ROUND(AP11*(AO11-1),2),-AP11))) -> 0 | AS11: =IF(AR11="","",SUM($AR$2:AR11)) -> 7.9 | AT11: =IFERROR(__xludf.DUMMYFUNCTION("IF(AB11="""",""Type the 3 odds on the Matchday tab"",IF(Method!$B$55=TRUE(),IF(Method!$B$81=TRUE(),IF(REGEXMATCH(LOWER(Method!$B$63),""circuit""),""🛑 PAUSED — circuit breaker upstream; wait for a clean live refresh."",IF(REGEXMATCH(LOWER(Method!$B$63),"""&"pipeline""),""🛑 PAUSED — live pipeline warning; check Live!B11/Method!B62 before betting."",IF(REGEXMATCH(LOWER(Method!$B$63),""missing""),""🛑 PAUSED — feed timestamp missing; refresh feed before betting."",""🛑 PAUSED — feed stale > 25 min — check Live"&" tab; refresh feed before betting.""))),IF(Method!$B$51>=Method!$B$52,""🛑 PAUSED — drawdown ""&TEXT(Method!$B$51,""0.0%"")&"" ≥ ""&TEXT(Method!$B$52,""0.0%"")&"". Set Method!B54=Y to override."",""🛑 PAUSED — see Method!B62/B63/B81 for cause; do not over"&"ride stale/circuit-breaker/pipeline pauses."")),IF(AH11=""BET"",IF(AJ11=0,""Edge found but stake rounds under £""&Method!$B$9&"" — skip"",IF(AND(AE11>=6,AG11>=0.15),""🟡 WAIT — long-shot review: odds ""&TEXT(AE11,""0.00"")&"" + edge ""&TEXT(AG11,""0.0%"")"&"&"" — verify sharp-book + team news + stake comfort before Placed=Y"",""Value found: EV ""&TEXT(AF11,""0.0%"")&"", edge ""&TEXT(AG11,""0.0%""))),IF(OR(AF11>Method!$B$87,IFERROR(INDEX(BC11:BE11,1,AB11)/INDEX(S11:U11,1,AB11),0)>Method!$B$88),""🛑 Tail trap "&"— auto-PASS · EV ""&TEXT(AF11,""0.0%"")&"" (cap ""&TEXT(Method!$B$87,""0%"")&"") · model/market ""&TEXT(IFERROR(INDEX(BC11:BE11,1,AB11)/INDEX(S11:U11,1,AB11),0),""0.0"")&""× (cap ""&TEXT(Method!$B$88,""0.0"")&""×)"",IF(AF11<Method!$B$7,""Price too short —"&" EV ""&TEXT(AF11,""0.0%"")&"" (need ""&TEXT(Method!$B$7,""0.0%"")&""+)"",""Model ≈ market — edge ""&TEXT(AG11,""0.0%"")&"" (need ""&TEXT(Method!$B$8,""0.0%"")&""+)"")))))"),"Price too short — EV 0.6% (need 2.5%+)") -> Price too short — EV 0.6% (need 2.5%+) | AU11: =IF(AN11<>"Y","",IF(AH11="· enter odds","⚠ type the 3 odds (1/X/2) to grade this bet",IF(OR(AV11="",AO11="",AP11=""),"⚠ log backed pick, odds & stake",IF(AZ11<>"BET","⚠ FUN BET — engine said pass · staked £"&AP11&" vs engine £"&BA11,IF(AV11<>IF(AY11="",AC11,AY11),"⚠ backed "&AV11&" but engine pick was "&IF(AY11="",AC11,AY11),IF(AP11>BA11,"⚠ stake over engine £"&BA11,IF(ABS(AO11-IFERROR(INDEX(L11:N11,1,MATCH(AV11,{"H","D","A"},0)),AE11))>0.02,"⚠ odds moved — re-check value","✓ engine bet"))))))) -> ⚠ log backed pick, odds & stake | AV11: =IF(Matchday!O13="","",Matchday!O13) -> H | AW11: PASS | AX11: 0 | AY11: A | AZ11: =IF(AW11="",AH11,AW11) -> PASS | BA11: =IF(AX11<>"",AX11,IF(AH11<>"BET",0,IF(AI11*Method!$B$10/100<Method!$B$9,0,ROUND(AI11*Method!$B$10/100,0)))) -> 0 | BB11: -26.08 | BC11: 0.43326 | BD11: 0.26620419 | BE11: 0.30053582 | BF11: Japan team-wide: -30 · Netherlands team-wide: +4 | BG11: 175 | BH11: very_hot_indoor | BI11: 0
A12: 11 | B12: 46187 | C12: E | D12: Ivory Coast | E12: Ecuador | F12: Philadelphia | G12: 0.79166667 | H12: 00:00 +1d | I12: 0.23205288 | J12: 0.28884326 | K12: 0.47910385 | L12: =IF(Matchday!E14="","",Matchday!E14) -> 2.1 | M12: =IF(Matchday!F14="","",Matchday!F14) -> 1.75 | N12: =IF(Matchday!G14="","",Matchday!G14) -> 1.6 | O12: =IF(L12="","",1/L12) -> 0.47619048 | P12: =IF(M12="","",1/M12) -> 0.57142857 | Q12: =IF(N12="","",1/N12) -> 0.625 | R12: =IF(COUNT(L12:N12)<3,"",O12+P12+Q12) -> 1.672619 | S12: {=IF($R12="","",IF(Method!$B$56="proportional",O12/$R12,IF(Method!$B$56="power",IFERROR(INDEX(power_devig($L12,$M12,$N12),1,1),O12/$R12),IFERROR(INDEX(shin($L12,$M12,$N12),1,1),O12/$R12))))} -> 0.2642016 | T12: {=IF($R12="","",IF(Method!$B$56="proportional",P12/$R12,IF(Method!$B$56="power",IFERROR(INDEX(power_devig($L12,$M12,$N12),2,1),P12/$R12),IFERROR(INDEX(shin($L12,$M12,$N12),2,1),P12/$R12))))} -> 0.34468019 | U12: {=IF($R12="","",IF(Method!$B$56="proportional",Q12/$R12,IF(Method!$B$56="power",IFERROR(INDEX(power_devig($L12,$M12,$N12),3,1),Q12/$R12),IFERROR(INDEX(shin($L12,$M12,$N12),3,1),Q12/$R12))))} -> 0.3911182 | V12: =IF(S12="","",Method!$B$4*IF(BC12="",I12,BC12)+(1-Method!$B$4)*S12/($S12+$T12+$U12)) -> 0.25155987 | W12: =IF(T12="","",Method!$B$4*IF(BD12="",J12,BD12)+(1-Method!$B$4)*T12/($S12+$T12+$U12)) -> 0.32059867 | X12: =IF(U12="","",Method!$B$4*IF(BE12="",K12,BE12)+(1-Method!$B$4)*U12/($S12+$T12+$U12)) -> 0.42784146 | Y12: =IF(V12="","",V12*L12-1) -> -0.47172428 | Z12: =IF(W12="","",W12*M12-1) -> -0.43895233 | AA12: =IF(X12="","",X12*N12-1) -> -0.31545366 | AB12: =IF(Y12="","",MATCH(MAX(Y12:AA12),Y12:AA12,0)) -> 3 | AC12: =IF(AB12="","",CHOOSE(AB12,"H","D","A")) -> A | AD12: =IF(AB12="","",CHOOSE(AB12,"1 "&D12,"X Draw","2 "&E12)) -> 2 Ecuador | AE12: =IF(AB12="","",INDEX(L12:N12,1,AB12)) -> 1.6 | AF12: =IF(AB12="","",INDEX(Y12:AA12,1,AB12)) -> -0.31545366 | AG12: =IF(AB12="","",INDEX(V12:X12,1,AB12)-INDEX(S12:U12,1,AB12)) -> 0.036723257 | AH12: {=IF(AB12="","· enter odds",IF(OR(AF12>Method!$B$87,IFERROR(INDEX(BC12:BE12,1,AB12)/INDEX(S12:U12,1,AB12),0)>Method!$B$88),"PASS",IF(AND(AF12>=Method!$B$7,AG12>=Method!$B$8),"BET","PASS")))} -> PASS | AI12: =IF(AH12<>"BET",0,ROUND(MIN(Method!$B$6,Method!$B$5*AL12)*100,1)) -> 0 | AJ12: =IF(OR(AH12<>"BET",Method!$B$55=TRUE()),0,IF(AI12*Method!$B$10/100<Method!$B$9,0,ROUND(AI12*Method!$B$10/100,0))) -> 0 | AK12: =IF(AB12="","",INDEX(V12:X12,1,AB12)) -> 0.42784146 | AL12: =IF(AH12<>"BET","",MAX(0,(AK12*AE12-1)/(AE12-1))) | AM12: =IF(AH12="BET",AF12+A12/1000000,"") | AN12: =IF(Matchday!N14="","",Matchday!N14) | AO12: =IF(Matchday!P14="","",Matchday!P14) | AP12: =IF(Matchday!Q14="","",Matchday!Q14) | AQ12: =IF(Matchday!R14="","",Matchday!R14) -> H | AR12: =IF(OR(AN12<>"Y",AQ12="",AV12=""),"",IF(AQ12="Void",0,IF(AQ12=AV12,ROUND(AP12*(AO12-1),2),-AP12))) | AS12: =IF(AR12="","",SUM($AR$2:AR12)) | AT12: =IFERROR(__xludf.DUMMYFUNCTION("IF(AB12="""",""Type the 3 odds on the Matchday tab"",IF(Method!$B$55=TRUE(),IF(Method!$B$81=TRUE(),IF(REGEXMATCH(LOWER(Method!$B$63),""circuit""),""🛑 PAUSED — circuit breaker upstream; wait for a clean live refresh."",IF(REGEXMATCH(LOWER(Method!$B$63),"""&"pipeline""),""🛑 PAUSED — live pipeline warning; check Live!B11/Method!B62 before betting."",IF(REGEXMATCH(LOWER(Method!$B$63),""missing""),""🛑 PAUSED — feed timestamp missing; refresh feed before betting."",""🛑 PAUSED — feed stale > 25 min — check Live"&" tab; refresh feed before betting.""))),IF(Method!$B$51>=Method!$B$52,""🛑 PAUSED — drawdown ""&TEXT(Method!$B$51,""0.0%"")&"" ≥ ""&TEXT(Method!$B$52,""0.0%"")&"". Set Method!B54=Y to override."",""🛑 PAUSED — see Method!B62/B63/B81 for cause; do not over"&"ride stale/circuit-breaker/pipeline pauses."")),IF(AH12=""BET"",IF(AJ12=0,""Edge found but stake rounds under £""&Method!$B$9&"" — skip"",IF(AND(AE12>=6,AG12>=0.15),""🟡 WAIT — long-shot review: odds ""&TEXT(AE12,""0.00"")&"" + edge ""&TEXT(AG12,""0.0%"")"&"&"" — verify sharp-book + team news + stake comfort before Placed=Y"",""Value found: EV ""&TEXT(AF12,""0.0%"")&"", edge ""&TEXT(AG12,""0.0%""))),IF(OR(AF12>Method!$B$87,IFERROR(INDEX(BC12:BE12,1,AB12)/INDEX(S12:U12,1,AB12),0)>Method!$B$88),""🛑 Tail trap "&"— auto-PASS · EV ""&TEXT(AF12,""0.0%"")&"" (cap ""&TEXT(Method!$B$87,""0%"")&"") · model/market ""&TEXT(IFERROR(INDEX(BC12:BE12,1,AB12)/INDEX(S12:U12,1,AB12),0),""0.0"")&""× (cap ""&TEXT(Method!$B$88,""0.0"")&""×)"",IF(AF12<Method!$B$7,""Price too short —"&" EV ""&TEXT(AF12,""0.0%"")&"" (need ""&TEXT(Method!$B$7,""0.0%"")&""+)"",""Model ≈ market — edge ""&TEXT(AG12,""0.0%"")&"" (need ""&TEXT(Method!$B$8,""0.0%"")&""+)"")))))"),"Price too short — EV -31.5% (need 2.5%+)") -> Price too short — EV -31.5% (need 2.5%+) | AU12: =IF(AN12<>"Y","",IF(AH12="· enter odds","⚠ type the 3 odds (1/X/2) to grade this bet",IF(OR(AV12="",AO12="",AP12=""),"⚠ log backed pick, odds & stake",IF(AZ12<>"BET","⚠ FUN BET — engine said pass · staked £"&AP12&" vs engine £"&BA12,IF(AV12<>IF(AY12="",AC12,AY12),"⚠ backed "&AV12&" but engine pick was "&IF(AY12="",AC12,AY12),IF(AP12>BA12,"⚠ stake over engine £"&BA12,IF(ABS(AO12-IFERROR(INDEX(L12:N12,1,MATCH(AV12,{"H","D","A"},0)),AE12))>0.02,"⚠ odds moved — re-check value","✓ engine bet"))))))) | AV12: =IF(Matchday!O14="","",Matchday!O14) | AZ12: =IF(AW12="",AH12,AW12) -> PASS | BA12: =IF(AX12<>"",AX12,IF(AH12<>"BET",0,IF(AI12*Method!$B$10/100<Method!$B$9,0,ROUND(AI12*Method!$B$10/100,0)))) -> 0 | BB12: 6.06 | BC12: 0.22808236 | BD12: 0.27587584 | BE12: 0.49604179 | BF12: Ecuador team-wide: +4 · Ivory Coast team-wide: +2 | BG12: 12 | BH12: warm_humid | BI12: 0
A13: 12 | B13: 46187 | C13: F | D13: Sweden | E13: Tunisia | F13: Guadalupe | G13: 0.83333333 | H13: 03:00 +1d | I13: 0.40251957 | J13: 0.29316075 | K13: 0.30431968 | L13: =IF(Matchday!E15="","",Matchday!E15) -> 1.9 | M13: =IF(Matchday!F15="","",Matchday!F15) -> 3.4 | N13: =IF(Matchday!G15="","",Matchday!G15) -> 4.33 | O13: =IF(L13="","",1/L13) -> 0.52631579 | P13: =IF(M13="","",1/M13) -> 0.29411765 | Q13: =IF(N13="","",1/N13) -> 0.23094688 | R13: =IF(COUNT(L13:N13)<3,"",O13+P13+Q13) -> 1.0513803 | S13: {=IF($R13="","",IF(Method!$B$56="proportional",O13/$R13,IF(Method!$B$56="power",IFERROR(INDEX(power_devig($L13,$M13,$N13),1,1),O13/$R13),IFERROR(INDEX(shin($L13,$M13,$N13),1,1),O13/$R13))))} -> 0.50697717 | T13: {=IF($R13="","",IF(Method!$B$56="proportional",P13/$R13,IF(Method!$B$56="power",IFERROR(INDEX(power_devig($L13,$M13,$N13),2,1),P13/$R13),IFERROR(INDEX(shin($L13,$M13,$N13),2,1),P13/$R13))))} -> 0.27767923 | U13: {=IF($R13="","",IF(Method!$B$56="proportional",Q13/$R13,IF(Method!$B$56="power",IFERROR(INDEX(power_devig($L13,$M13,$N13),3,1),Q13/$R13),IFERROR(INDEX(shin($L13,$M13,$N13),3,1),Q13/$R13))))} -> 0.21534361 | V13: =IF(S13="","",Method!$B$4*IF(BC13="",I13,BC13)+(1-Method!$B$4)*S13/($S13+$T13+$U13)) -> 0.47083309 | W13: =IF(T13="","",Method!$B$4*IF(BD13="",J13,BD13)+(1-Method!$B$4)*T13/($S13+$T13+$U13)) -> 0.27275221 | X13: =IF(U13="","",Method!$B$4*IF(BE13="",K13,BE13)+(1-Method!$B$4)*U13/($S13+$T13+$U13)) -> 0.2564147 | Y13: =IF(V13="","",V13*L13-1) -> -0.10541714 | Z13: =IF(W13="","",W13*M13-1) -> -0.072642485 | AA13: =IF(X13="","",X13*N13-1) -> 0.11027566 | AB13: =IF(Y13="","",MATCH(MAX(Y13:AA13),Y13:AA13,0)) -> 3 | AC13: =IF(AB13="","",CHOOSE(AB13,"H","D","A")) -> A | AD13: =IF(AB13="","",CHOOSE(AB13,"1 "&D13,"X Draw","2 "&E13)) -> 2 Tunisia | AE13: =IF(AB13="","",INDEX(L13:N13,1,AB13)) -> 4.33 | AF13: =IF(AB13="","",INDEX(Y13:AA13,1,AB13)) -> 0.11027566 | AG13: =IF(AB13="","",INDEX(V13:X13,1,AB13)-INDEX(S13:U13,1,AB13)) -> 0.041071097 | AH13: {=IF(AB13="","· enter odds",IF(OR(AF13>Method!$B$87,IFERROR(INDEX(BC13:BE13,1,AB13)/INDEX(S13:U13,1,AB13),0)>Method!$B$88),"PASS",IF(AND(AF13>=Method!$B$7,AG13>=Method!$B$8),"BET","PASS")))} -> BET | AI13: =IF(AH13<>"BET",0,ROUND(MIN(Method!$B$6,Method!$B$5*AL13)*100,1)) -> 0.8 | AJ13: =IF(OR(AH13<>"BET",Method!$B$55=TRUE()),0,IF(AI13*Method!$B$10/100<Method!$B$9,0,ROUND(AI13*Method!$B$10/100,0))) -> 8 | AK13: =IF(AB13="","",INDEX(V13:X13,1,AB13)) -> 0.2564147 | AL13: =IF(AH13<>"BET","",MAX(0,(AK13*AE13-1)/(AE13-1))) -> 0.033115815 | AM13: =IF(AH13="BET",AF13+A13/1000000,"") -> 0.11028766 | AN13: =IF(Matchday!N15="","",Matchday!N15) | AO13: =IF(Matchday!P15="","",Matchday!P15) | AP13: =IF(Matchday!Q15="","",Matchday!Q15) | AQ13: =IF(Matchday!R15="","",Matchday!R15) -> H | AR13: =IF(OR(AN13<>"Y",AQ13="",AV13=""),"",IF(AQ13="Void",0,IF(AQ13=AV13,ROUND(AP13*(AO13-1),2),-AP13))) | AS13: =IF(AR13="","",SUM($AR$2:AR13)) | AT13: =IFERROR(__xludf.DUMMYFUNCTION("IF(AB13="""",""Type the 3 odds on the Matchday tab"",IF(Method!$B$55=TRUE(),IF(Method!$B$81=TRUE(),IF(REGEXMATCH(LOWER(Method!$B$63),""circuit""),""🛑 PAUSED — circuit breaker upstream; wait for a clean live refresh."",IF(REGEXMATCH(LOWER(Method!$B$63),"""&"pipeline""),""🛑 PAUSED — live pipeline warning; check Live!B11/Method!B62 before betting."",IF(REGEXMATCH(LOWER(Method!$B$63),""missing""),""🛑 PAUSED — feed timestamp missing; refresh feed before betting."",""🛑 PAUSED — feed stale > 25 min — check Live"&" tab; refresh feed before betting.""))),IF(Method!$B$51>=Method!$B$52,""🛑 PAUSED — drawdown ""&TEXT(Method!$B$51,""0.0%"")&"" ≥ ""&TEXT(Method!$B$52,""0.0%"")&"". Set Method!B54=Y to override."",""🛑 PAUSED — see Method!B62/B63/B81 for cause; do not over"&"ride stale/circuit-breaker/pipeline pauses."")),IF(AH13=""BET"",IF(AJ13=0,""Edge found but stake rounds under £""&Method!$B$9&"" — skip"",IF(AND(AE13>=6,AG13>=0.15),""🟡 WAIT — long-shot review: odds ""&TEXT(AE13,""0.00"")&"" + edge ""&TEXT(AG13,""0.0%"")"&"&"" — verify sharp-book + team news + stake comfort before Placed=Y"",""Value found: EV ""&TEXT(AF13,""0.0%"")&"", edge ""&TEXT(AG13,""0.0%""))),IF(OR(AF13>Method!$B$87,IFERROR(INDEX(BC13:BE13,1,AB13)/INDEX(S13:U13,1,AB13),0)>Method!$B$88),""🛑 Tail trap "&"— auto-PASS · EV ""&TEXT(AF13,""0.0%"")&"" (cap ""&TEXT(Method!$B$87,""0%"")&"") · model/market ""&TEXT(IFERROR(INDEX(BC13:BE13,1,AB13)/INDEX(S13:U13,1,AB13),0),""0.0"")&""× (cap ""&TEXT(Method!$B$88,""0.0"")&""×)"",IF(AF13<Method!$B$7,""Price too short —"&" EV ""&TEXT(AF13,""0.0%"")&"" (need ""&TEXT(Method!$B$7,""0.0%"")&""+)"",""Model ≈ market — edge ""&TEXT(AG13,""0.0%"")&"" (need ""&TEXT(Method!$B$8,""0.0%"")&""+)"")))))"),"Value found: EV 11.0%, edge 4.1%") -> Value found: EV 11.0%, edge 4.1% | AU13: =IF(AN13<>"Y","",IF(AH13="· enter odds","⚠ type the 3 odds (1/X/2) to grade this bet",IF(OR(AV13="",AO13="",AP13=""),"⚠ log backed pick, odds & stake",IF(AZ13<>"BET","⚠ FUN BET — engine said pass · staked £"&AP13&" vs engine £"&BA13,IF(AV13<>IF(AY13="",AC13,AY13),"⚠ backed "&AV13&" but engine pick was "&IF(AY13="",AC13,AY13),IF(AP13>BA13,"⚠ stake over engine £"&BA13,IF(ABS(AO13-IFERROR(INDEX(L13:N13,1,MATCH(AV13,{"H","D","A"},0)),AE13))>0.02,"⚠ odds moved — re-check value","✓ engine bet"))))))) | AV13: =IF(Matchday!O15="","",Matchday!O15) | AZ13: =IF(AW13="",AH13,AW13) -> BET | BA13: =IF(AX13<>"",AX13,IF(AH13<>"BET",0,IF(AI13*Method!$B$10/100<Method!$B$9,0,ROUND(AI13*Method!$B$10/100,0)))) -> 8 | BB13: -48.94 | BC13: 0.40370837 | BD13: 0.26360203 | BE13: 0.3326896 | BF13: Sweden team-wide: -12 · Sweden weather: -4 · Tunisia team-wide: -33 | BG13: 540 | BH13: very_hot | BI13: 0
A14: 13 | B14: 46188 | C14: H | D14: Spain | E14: Cape Verde | F14: Atlanta | G14: 0.5 | H14: 0.70833333 | I14: 0.85919314 | J14: 0.10076913 | K14: 0.040037724 | L14: =IF(Matchday!E16="","",Matchday!E16) -> 1.11 | M14: =IF(Matchday!F16="","",Matchday!F16) -> 14 | N14: =IF(Matchday!G16="","",Matchday!G16) -> 36 | O14: =IF(L14="","",1/L14) -> 0.9009009 | P14: =IF(M14="","",1/M14) -> 0.071428571 | Q14: =IF(N14="","",1/N14) -> 0.027777778 | R14: =IF(COUNT(L14:N14)<3,"",O14+P14+Q14) -> 1.0001072 | S14: {=IF($R14="","",IF(Method!$B$56="proportional",O14/$R14,IF(Method!$B$56="power",IFERROR(INDEX(power_devig($L14,$M14,$N14),1,1),O14/$R14),IFERROR(INDEX(shin($L14,$M14,$N14),1,1),O14/$R14))))} -> 0.90084993 | T14: {=IF($R14="","",IF(Method!$B$56="proportional",P14/$R14,IF(Method!$B$56="power",IFERROR(INDEX(power_devig($L14,$M14,$N14),2,1),P14/$R14),IFERROR(INDEX(shin($L14,$M14,$N14),2,1),P14/$R14))))} -> 0.071399841 | U14: {=IF($R14="","",IF(Method!$B$56="proportional",Q14/$R14,IF(Method!$B$56="power",IFERROR(INDEX(power_devig($L14,$M14,$N14),3,1),Q14/$R14),IFERROR(INDEX(shin($L14,$M14,$N14),3,1),Q14/$R14))))} -> 0.027750225 | V14: =IF(S14="","",Method!$B$4*IF(BC14="",I14,BC14)+(1-Method!$B$4)*S14/($S14+$T14+$U14)) -> 0.88103104 | W14: =IF(T14="","",Method!$B$4*IF(BD14="",J14,BD14)+(1-Method!$B$4)*T14/($S14+$T14+$U14)) -> 0.084439862 | X14: =IF(U14="","",Method!$B$4*IF(BE14="",K14,BE14)+(1-Method!$B$4)*U14/($S14+$T14+$U14)) -> 0.034529097 | Y14: =IF(V14="","",V14*L14-1) -> -0.022055544 | Z14: =IF(W14="","",W14*M14-1) -> 0.18215806 | AA14: =IF(X14="","",X14*N14-1) -> 0.2430475 | AB14: =IF(Y14="","",MATCH(MAX(Y14:AA14),Y14:AA14,0)) -> 3 | AC14: =IF(AB14="","",CHOOSE(AB14,"H","D","A")) -> A | AD14: =IF(AB14="","",CHOOSE(AB14,"1 "&D14,"X Draw","2 "&E14)) -> 2 Cape Verde | AE14: =IF(AB14="","",INDEX(L14:N14,1,AB14)) -> 36 | AF14: =IF(AB14="","",INDEX(Y14:AA14,1,AB14)) -> 0.2430475 | AG14: =IF(AB14="","",INDEX(V14:X14,1,AB14)-INDEX(S14:U14,1,AB14)) -> 0.0067788725 | AH14: {=IF(AB14="","· enter odds",IF(OR(AF14>Method!$B$87,IFERROR(INDEX(BC14:BE14,1,AB14)/INDEX(S14:U14,1,AB14),0)>Method!$B$88),"PASS",IF(AND(AF14>=Method!$B$7,AG14>=Method!$B$8),"BET","PASS")))} -> PASS | AI14: =IF(AH14<>"BET",0,ROUND(MIN(Method!$B$6,Method!$B$5*AL14)*100,1)) -> 0 | AJ14: =IF(OR(AH14<>"BET",Method!$B$55=TRUE()),0,IF(AI14*Method!$B$10/100<Method!$B$9,0,ROUND(AI14*Method!$B$10/100,0))) -> 0 | AK14: =IF(AB14="","",INDEX(V14:X14,1,AB14)) -> 0.034529097 | AL14: =IF(AH14<>"BET","",MAX(0,(AK14*AE14-1)/(AE14-1))) | AM14: =IF(AH14="BET",AF14+A14/1000000,"") | AN14: =IF(Matchday!N16="","",Matchday!N16) | AO14: =IF(Matchday!P16="","",Matchday!P16) | AP14: =IF(Matchday!Q16="","",Matchday!Q16) | AQ14: =IF(Matchday!R16="","",Matchday!R16) -> D | AR14: =IF(OR(AN14<>"Y",AQ14="",AV14=""),"",IF(AQ14="Void",0,IF(AQ14=AV14,ROUND(AP14*(AO14-1),2),-AP14))) | AS14: =IF(AR14="","",SUM($AR$2:AR14)) | AT14: =IFERROR(__xludf.DUMMYFUNCTION("IF(AB14="""",""Type the 3 odds on the Matchday tab"",IF(Method!$B$55=TRUE(),IF(Method!$B$81=TRUE(),IF(REGEXMATCH(LOWER(Method!$B$63),""circuit""),""🛑 PAUSED — circuit breaker upstream; wait for a clean live refresh."",IF(REGEXMATCH(LOWER(Method!$B$63),"""&"pipeline""),""🛑 PAUSED — live pipeline warning; check Live!B11/Method!B62 before betting."",IF(REGEXMATCH(LOWER(Method!$B$63),""missing""),""🛑 PAUSED — feed timestamp missing; refresh feed before betting."",""🛑 PAUSED — feed stale > 25 min — check Live"&" tab; refresh feed before betting.""))),IF(Method!$B$51>=Method!$B$52,""🛑 PAUSED — drawdown ""&TEXT(Method!$B$51,""0.0%"")&"" ≥ ""&TEXT(Method!$B$52,""0.0%"")&"". Set Method!B54=Y to override."",""🛑 PAUSED — see Method!B62/B63/B81 for cause; do not over"&"ride stale/circuit-breaker/pipeline pauses."")),IF(AH14=""BET"",IF(AJ14=0,""Edge found but stake rounds under £""&Method!$B$9&"" — skip"",IF(AND(AE14>=6,AG14>=0.15),""🟡 WAIT — long-shot review: odds ""&TEXT(AE14,""0.00"")&"" + edge ""&TEXT(AG14,""0.0%"")"&"&"" — verify sharp-book + team news + stake comfort before Placed=Y"",""Value found: EV ""&TEXT(AF14,""0.0%"")&"", edge ""&TEXT(AG14,""0.0%""))),IF(OR(AF14>Method!$B$87,IFERROR(INDEX(BC14:BE14,1,AB14)/INDEX(S14:U14,1,AB14),0)>Method!$B$88),""🛑 Tail trap "&"— auto-PASS · EV ""&TEXT(AF14,""0.0%"")&"" (cap ""&TEXT(Method!$B$87,""0%"")&"") · model/market ""&TEXT(IFERROR(INDEX(BC14:BE14,1,AB14)/INDEX(S14:U14,1,AB14),0),""0.0"")&""× (cap ""&TEXT(Method!$B$88,""0.0"")&""×)"",IF(AF14<Method!$B$7,""Price too short —"&" EV ""&TEXT(AF14,""0.0%"")&"" (need ""&TEXT(Method!$B$7,""0.0%"")&""+)"",""Model ≈ market — edge ""&TEXT(AG14,""0.0%"")&"" (need ""&TEXT(Method!$B$8,""0.0%"")&""+)"")))))"),"Model ≈ market — edge 0.7% (need 2.5%+)") -> Model ≈ market — edge 0.7% (need 2.5%+) | AU14: =IF(AN14<>"Y","",IF(AH14="· enter odds","⚠ type the 3 odds (1/X/2) to grade this bet",IF(OR(AV14="",AO14="",AP14=""),"⚠ log backed pick, odds & stake",IF(AZ14<>"BET","⚠ FUN BET — engine said pass · staked £"&AP14&" vs engine £"&BA14,IF(AV14<>IF(AY14="",AC14,AY14),"⚠ backed "&AV14&" but engine pick was "&IF(AY14="",AC14,AY14),IF(AP14>BA14,"⚠ stake over engine £"&BA14,IF(ABS(AO14-IFERROR(INDEX(L14:N14,1,MATCH(AV14,{"H","D","A"},0)),AE14))>0.02,"⚠ odds moved — re-check value","✓ engine bet"))))))) | AV14: =IF(Matchday!O16="","",Matchday!O16) | AZ14: =IF(AW14="",AH14,AW14) -> PASS | BA14: =IF(AX14<>"",AX14,IF(AH14<>"BET",0,IF(AI14*Method!$B$10/100<Method!$B$9,0,ROUND(AI14*Method!$B$10/100,0)))) -> 0 | BB14: 1.88 | BC14: 0.84422452 | BD14: 0.10865704 | BE14: 0.047118432 | BF14: Cape Verde team-wide: -18 · Spain team-wide: +20 | BG14: 320 | BH14: hot_humid_indoor | BI14: 0
A15: 14 | B15: 46188 | C15: G | D15: Belgium | E15: Egypt | F15: Seattle | G15: 0.625 | H15: 0.95833333 | I15: 0.52118709 | J15: 0.28201181 | K15: 0.1968011 | L15: =IF(Matchday!E17="","",Matchday!E17) -> 1.57 | M15: =IF(Matchday!F17="","",Matchday!F17) -> 4.33 | N15: =IF(Matchday!G17="","",Matchday!G17) -> 7 | O15: =IF(L15="","",1/L15) -> 0.63694268 | P15: =IF(M15="","",1/M15) -> 0.23094688 | Q15: =IF(N15="","",1/N15) -> 0.14285714 | R15: =IF(COUNT(L15:N15)<3,"",O15+P15+Q15) -> 1.0107467 | S15: {=IF($R15="","",IF(Method!$B$56="proportional",O15/$R15,IF(Method!$B$56="power",IFERROR(INDEX(power_devig($L15,$M15,$N15),1,1),O15/$R15),IFERROR(INDEX(shin($L15,$M15,$N15),1,1),O15/$R15))))} -> 0.63255837 | T15: {=IF($R15="","",IF(Method!$B$56="proportional",P15/$R15,IF(Method!$B$56="power",IFERROR(INDEX(power_devig($L15,$M15,$N15),2,1),P15/$R15),IFERROR(INDEX(shin($L15,$M15,$N15),2,1),P15/$R15))))} -> 0.2276445 | U15: {=IF($R15="","",IF(Method!$B$56="proportional",Q15/$R15,IF(Method!$B$56="power",IFERROR(INDEX(power_devig($L15,$M15,$N15),3,1),Q15/$R15),IFERROR(INDEX(shin($L15,$M15,$N15),3,1),Q15/$R15))))} -> 0.13979713 | V15: =IF(S15="","",Method!$B$4*IF(BC15="",I15,BC15)+(1-Method!$B$4)*S15/($S15+$T15+$U15)) -> 0.59346518 | W15: =IF(T15="","",Method!$B$4*IF(BD15="",J15,BD15)+(1-Method!$B$4)*T15/($S15+$T15+$U15)) -> 0.2429726 | X15: =IF(U15="","",Method!$B$4*IF(BE15="",K15,BE15)+(1-Method!$B$4)*U15/($S15+$T15+$U15)) -> 0.16356222 | Y15: =IF(V15="","",V15*L15-1) -> -0.068259674 | Z15: =IF(W15="","",W15*M15-1) -> 0.052071373 | AA15: =IF(X15="","",X15*N15-1) -> 0.14493554 | AB15: =IF(Y15="","",MATCH(MAX(Y15:AA15),Y15:AA15,0)) -> 3 | AC15: =IF(AB15="","",CHOOSE(AB15,"H","D","A")) -> A | AD15: =IF(AB15="","",CHOOSE(AB15,"1 "&D15,"X Draw","2 "&E15)) -> 2 Egypt | AE15: =IF(AB15="","",INDEX(L15:N15,1,AB15)) -> 7 | AF15: =IF(AB15="","",INDEX(Y15:AA15,1,AB15)) -> 0.14493554 | AG15: =IF(AB15="","",INDEX(V15:X15,1,AB15)-INDEX(S15:U15,1,AB15)) -> 0.023765094 | AH15: {=IF(AB15="","· enter odds",IF(OR(AF15>Method!$B$87,IFERROR(INDEX(BC15:BE15,1,AB15)/INDEX(S15:U15,1,AB15),0)>Method!$B$88),"PASS",IF(AND(AF15>=Method!$B$7,AG15>=Method!$B$8),"BET","PASS")))} -> PASS | AI15: =IF(AH15<>"BET",0,ROUND(MIN(Method!$B$6,Method!$B$5*AL15)*100,1)) -> 0 | AJ15: =IF(OR(AH15<>"BET",Method!$B$55=TRUE()),0,IF(AI15*Method!$B$10/100<Method!$B$9,0,ROUND(AI15*Method!$B$10/100,0))) -> 0 | AK15: =IF(AB15="","",INDEX(V15:X15,1,AB15)) -> 0.16356222 | AL15: =IF(AH15<>"BET","",MAX(0,(AK15*AE15-1)/(AE15-1))) | AM15: =IF(AH15="BET",AF15+A15/1000000,"") | AN15: =IF(Matchday!N17="","",Matchday!N17) | AO15: =IF(Matchday!P17="","",Matchday!P17) | AP15: =IF(Matchday!Q17="","",Matchday!Q17) | AQ15: =IF(Matchday!R17="","",Matchday!R17) -> D | AR15: =IF(OR(AN15<>"Y",AQ15="",AV15=""),"",IF(AQ15="Void",0,IF(AQ15=AV15,ROUND(AP15*(AO15-1),2),-AP15))) | AS15: =IF(AR15="","",SUM($AR$2:AR15)) | AT15: =IFERROR(__xludf.DUMMYFUNCTION("IF(AB15="""",""Type the 3 odds on the Matchday tab"",IF(Method!$B$55=TRUE(),IF(Method!$B$81=TRUE(),IF(REGEXMATCH(LOWER(Method!$B$63),""circuit""),""🛑 PAUSED — circuit breaker upstream; wait for a clean live refresh."",IF(REGEXMATCH(LOWER(Method!$B$63),"""&"pipeline""),""🛑 PAUSED — live pipeline warning; check Live!B11/Method!B62 before betting."",IF(REGEXMATCH(LOWER(Method!$B$63),""missing""),""🛑 PAUSED — feed timestamp missing; refresh feed before betting."",""🛑 PAUSED — feed stale > 25 min — check Live"&" tab; refresh feed before betting.""))),IF(Method!$B$51>=Method!$B$52,""🛑 PAUSED — drawdown ""&TEXT(Method!$B$51,""0.0%"")&"" ≥ ""&TEXT(Method!$B$52,""0.0%"")&"". Set Method!B54=Y to override."",""🛑 PAUSED — see Method!B62/B63/B81 for cause; do not over"&"ride stale/circuit-breaker/pipeline pauses."")),IF(AH15=""BET"",IF(AJ15=0,""Edge found but stake rounds under £""&Method!$B$9&"" — skip"",IF(AND(AE15>=6,AG15>=0.15),""🟡 WAIT — long-shot review: odds ""&TEXT(AE15,""0.00"")&"" + edge ""&TEXT(AG15,""0.0%"")"&"&"" — verify sharp-book + team news + stake comfort before Placed=Y"",""Value found: EV ""&TEXT(AF15,""0.0%"")&"", edge ""&TEXT(AG15,""0.0%""))),IF(OR(AF15>Method!$B$87,IFERROR(INDEX(BC15:BE15,1,AB15)/INDEX(S15:U15,1,AB15),0)>Method!$B$88),""🛑 Tail trap "&"— auto-PASS · EV ""&TEXT(AF15,""0.0%"")&"" (cap ""&TEXT(Method!$B$87,""0%"")&"") · model/market ""&TEXT(IFERROR(INDEX(BC15:BE15,1,AB15)/INDEX(S15:U15,1,AB15),0),""0.0"")&""× (cap ""&TEXT(Method!$B$88,""0.0"")&""×)"",IF(AF15<Method!$B$7,""Price too short —"&" EV ""&TEXT(AF15,""0.0%"")&"" (need ""&TEXT(Method!$B$7,""0.0%"")&""+)"",""Model ≈ market — edge ""&TEXT(AG15,""0.0%"")&"" (need ""&TEXT(Method!$B$8,""0.0%"")&""+)"")))))"),"Model ≈ market — edge 2.4% (need 2.5%+)") -> Model ≈ market — edge 2.4% (need 2.5%+) | AU15: =IF(AN15<>"Y","",IF(AH15="· enter odds","⚠ type the 3 odds (1/X/2) to grade this bet",IF(OR(AV15="",AO15="",AP15=""),"⚠ log backed pick, odds & stake",IF(AZ15<>"BET","⚠ FUN BET — engine said pass · staked £"&AP15&" vs engine £"&BA15,IF(AV15<>IF(AY15="",AC15,AY15),"⚠ backed "&AV15&" but engine pick was "&IF(AY15="",AC15,AY15),IF(AP15>BA15,"⚠ stake over engine £"&BA15,IF(ABS(AO15-IFERROR(INDEX(L15:N15,1,MATCH(AV15,{"H","D","A"},0)),AE15))>0.02,"⚠ odds moved — re-check value","✓ engine bet"))))))) | AV15: =IF(Matchday!O17="","",Matchday!O17) | AZ15: =IF(AW15="",AH15,AW15) -> PASS | BA15: =IF(AX15<>"",AX15,IF(AH15<>"BET",0,IF(AI15*Method!$B$10/100<Method!$B$9,0,ROUND(AI15*Method!$B$10/100,0)))) -> 0 | BB15: -40.79 | BC15: 0.52086353 | BD15: 0.27143908 | BE15: 0.20769739 | BF15: Belgium team-wide: -14 · Egypt team-wide: -27 | BG15: 5 | BH15: mild | BI15: 0
A16: 15 | B16: 46188 | C16: H | D16: Saudi Arabia | E16: Uruguay | F16: Miami Gardens | G16: 0.75 | H16: 0.95833333 | I16: 0.16914686 | J16: 0.26071743 | K16: 0.5701357 | L16: =IF(Matchday!E18="","",Matchday!E18) -> 8 | M16: =IF(Matchday!F18="","",Matchday!F18) -> 4.5 | N16: =IF(Matchday!G18="","",Matchday!G18) -> 1.5 | O16: =IF(L16="","",1/L16) -> 0.125 | P16: =IF(M16="","",1/M16) -> 0.22222222 | Q16: =IF(N16="","",1/N16) -> 0.66666667 | R16: =IF(COUNT(L16:N16)<3,"",O16+P16+Q16) -> 1.0138889 | S16: {=IF($R16="","",IF(Method!$B$56="proportional",O16/$R16,IF(Method!$B$56="power",IFERROR(INDEX(power_devig($L16,$M16,$N16),1,1),O16/$R16),IFERROR(INDEX(shin($L16,$M16,$N16),1,1),O16/$R16))))} -> 0.12111306 | T16: {=IF($R16="","",IF(Method!$B$56="proportional",P16/$R16,IF(Method!$B$56="power",IFERROR(INDEX(power_devig($L16,$M16,$N16),2,1),P16/$R16),IFERROR(INDEX(shin($L16,$M16,$N16),2,1),P16/$R16))))} -> 0.21798399 | U16: {=IF($R16="","",IF(Method!$B$56="proportional",Q16/$R16,IF(Method!$B$56="power",IFERROR(INDEX(power_devig($L16,$M16,$N16),3,1),Q16/$R16),IFERROR(INDEX(shin($L16,$M16,$N16),3,1),Q16/$R16))))} -> 0.66090295 | V16: =IF(S16="","",Method!$B$4*IF(BC16="",I16,BC16)+(1-Method!$B$4)*S16/($S16+$T16+$U16)) -> 0.13029566 | W16: =IF(T16="","",Method!$B$4*IF(BD16="",J16,BD16)+(1-Method!$B$4)*T16/($S16+$T16+$U16)) -> 0.24060392 | X16: =IF(U16="","",Method!$B$4*IF(BE16="",K16,BE16)+(1-Method!$B$4)*U16/($S16+$T16+$U16)) -> 0.62910042 | Y16: =IF(V16="","",V16*L16-1) -> 0.04236526 | Z16: =IF(W16="","",W16*M16-1) -> 0.082717654 | AA16: =IF(X16="","",X16*N16-1) -> -0.056349371 | AB16: =IF(Y16="","",MATCH(MAX(Y16:AA16),Y16:AA16,0)) -> 2 | AC16: =IF(AB16="","",CHOOSE(AB16,"H","D","A")) -> D | AD16: =IF(AB16="","",CHOOSE(AB16,"1 "&D16,"X Draw","2 "&E16)) -> X Draw | AE16: =IF(AB16="","",INDEX(L16:N16,1,AB16)) -> 4.5 | AF16: =IF(AB16="","",INDEX(Y16:AA16,1,AB16)) -> 0.082717654 | AG16: =IF(AB16="","",INDEX(V16:X16,1,AB16)-INDEX(S16:U16,1,AB16)) -> 0.022619936 | AH16: {=IF(AB16="","· enter odds",IF(OR(AF16>Method!$B$87,IFERROR(INDEX(BC16:BE16,1,AB16)/INDEX(S16:U16,1,AB16),0)>Method!$B$88),"PASS",IF(AND(AF16>=Method!$B$7,AG16>=Method!$B$8),"BET","PASS")))} -> PASS | AI16: =IF(AH16<>"BET",0,ROUND(MIN(Method!$B$6,Method!$B$5*AL16)*100,1)) -> 0 | AJ16: =IF(OR(AH16<>"BET",Method!$B$55=TRUE()),0,IF(AI16*Method!$B$10/100<Method!$B$9,0,ROUND(AI16*Method!$B$10/100,0))) -> 0 | AK16: =IF(AB16="","",INDEX(V16:X16,1,AB16)) -> 0.24060392 | AL16: =IF(AH16<>"BET","",MAX(0,(AK16*AE16-1)/(AE16-1))) | AM16: =IF(AH16="BET",AF16+A16/1000000,"") | AN16: =IF(Matchday!N18="","",Matchday!N18) | AO16: =IF(Matchday!P18="","",Matchday!P18) | AP16: =IF(Matchday!Q18="","",Matchday!Q18) | AQ16: =IF(Matchday!R18="","",Matchday!R18) -> D | AR16: =IF(OR(AN16<>"Y",AQ16="",AV16=""),"",IF(AQ16="Void",0,IF(AQ16=AV16,ROUND(AP16*(AO16-1),2),-AP16))) | AS16: =IF(AR16="","",SUM($AR$2:AR16)) | AT16: =IFERROR(__xludf.DUMMYFUNCTION("IF(AB16="""",""Type the 3 odds on the Matchday tab"",IF(Method!$B$55=TRUE(),IF(Method!$B$81=TRUE(),IF(REGEXMATCH(LOWER(Method!$B$63),""circuit""),""🛑 PAUSED — circuit breaker upstream; wait for a clean live refresh."",IF(REGEXMATCH(LOWER(Method!$B$63),"""&"pipeline""),""🛑 PAUSED — live pipeline warning; check Live!B11/Method!B62 before betting."",IF(REGEXMATCH(LOWER(Method!$B$63),""missing""),""🛑 PAUSED — feed timestamp missing; refresh feed before betting."",""🛑 PAUSED — feed stale > 25 min — check Live"&" tab; refresh feed before betting.""))),IF(Method!$B$51>=Method!$B$52,""🛑 PAUSED — drawdown ""&TEXT(Method!$B$51,""0.0%"")&"" ≥ ""&TEXT(Method!$B$52,""0.0%"")&"". Set Method!B54=Y to override."",""🛑 PAUSED — see Method!B62/B63/B81 for cause; do not over"&"ride stale/circuit-breaker/pipeline pauses."")),IF(AH16=""BET"",IF(AJ16=0,""Edge found but stake rounds under £""&Method!$B$9&"" — skip"",IF(AND(AE16>=6,AG16>=0.15),""🟡 WAIT — long-shot review: odds ""&TEXT(AE16,""0.00"")&"" + edge ""&TEXT(AG16,""0.0%"")"&"&"" — verify sharp-book + team news + stake comfort before Placed=Y"",""Value found: EV ""&TEXT(AF16,""0.0%"")&"", edge ""&TEXT(AG16,""0.0%""))),IF(OR(AF16>Method!$B$87,IFERROR(INDEX(BC16:BE16,1,AB16)/INDEX(S16:U16,1,AB16),0)>Method!$B$88),""🛑 Tail trap "&"— auto-PASS · EV ""&TEXT(AF16,""0.0%"")&"" (cap ""&TEXT(Method!$B$87,""0%"")&"") · model/market ""&TEXT(IFERROR(INDEX(BC16:BE16,1,AB16)/INDEX(S16:U16,1,AB16),0),""0.0"")&""× (cap ""&TEXT(Method!$B$88,""0.0"")&""×)"",IF(AF16<Method!$B$7,""Price too short —"&" EV ""&TEXT(AF16,""0.0%"")&"" (need ""&TEXT(Method!$B$7,""0.0%"")&""+)"",""Model ≈ market — edge ""&TEXT(AG16,""0.0%"")&"" (need ""&TEXT(Method!$B$8,""0.0%"")&""+)"")))))"),"Model ≈ market — edge 2.3% (need 2.5%+)") -> Model ≈ market — edge 2.3% (need 2.5%+) | AU16: =IF(AN16<>"Y","",IF(AH16="· enter odds","⚠ type the 3 odds (1/X/2) to grade this bet",IF(OR(AV16="",AO16="",AP16=""),"⚠ log backed pick, odds & stake",IF(AZ16<>"BET","⚠ FUN BET — engine said pass · staked £"&AP16&" vs engine £"&BA16,IF(AV16<>IF(AY16="",AC16,AY16),"⚠ backed "&AV16&" but engine pick was "&IF(AY16="",AC16,AY16),IF(AP16>BA16,"⚠ stake over engine £"&BA16,IF(ABS(AO16-IFERROR(INDEX(L16:N16,1,MATCH(AV16,{"H","D","A"},0)),AE16))>0.02,"⚠ odds moved — re-check value","✓ engine bet"))))))) | AV16: =IF(Matchday!O18="","",Matchday!O18) | AZ16: =IF(AW16="",AH16,AW16) -> PASS | BA16: =IF(AX16<>"",AX16,IF(AH16<>"BET",0,IF(AI16*Method!$B$10/100<Method!$B$9,0,ROUND(AI16*Method!$B$10/100,0)))) -> 0 | BB16: -30.97 | BC16: 0.14734905 | BD16: 0.28261238 | BE16: 0.57003857 | BF16: Saudi Arabia team-wide: -11 · Uruguay team-wide: -20 | BG16: 2 | BH16: very_hot_humid | BI16: 0
A17: 16 | B17: 46188 | C17: G | D17: Iran | E17: New Zealand | F17: Inglewood | G17: 0.875 | H17: 05:00 +1d | I17: 0.53164062 | J17: 0.28086449 | K17: 0.18749489 | L17: =IF(Matchday!E19="","",Matchday!E19) -> 1.93 | M17: =IF(Matchday!F19="","",Matchday!F19) -> 3.5 | N17: =IF(Matchday!G19="","",Matchday!G19) -> 5 | O17: =IF(L17="","",1/L17) -> 0.51813471 | P17: =IF(M17="","",1/M17) -> 0.28571429 | Q17: =IF(N17="","",1/N17) -> 0.2 | R17: =IF(COUNT(L17:N17)<3,"",O17+P17+Q17) -> 1.003849 | S17: {=IF($R17="","",IF(Method!$B$56="proportional",O17/$R17,IF(Method!$B$56="power",IFERROR(INDEX(power_devig($L17,$M17,$N17),1,1),O17/$R17),IFERROR(INDEX(shin($L17,$M17,$N17),1,1),O17/$R17))))} -> 0.5166754 | T17: {=IF($R17="","",IF(Method!$B$56="proportional",P17/$R17,IF(Method!$B$56="power",IFERROR(INDEX(power_devig($L17,$M17,$N17),2,1),P17/$R17),IFERROR(INDEX(shin($L17,$M17,$N17),2,1),P17/$R17))))} -> 0.28447809 | U17: {=IF($R17="","",IF(Method!$B$56="proportional",Q17/$R17,IF(Method!$B$56="power",IFERROR(INDEX(power_devig($L17,$M17,$N17),3,1),Q17/$R17),IFERROR(INDEX(shin($L17,$M17,$N17),3,1),Q17/$R17))))} -> 0.19884651 | V17: =IF(S17="","",Method!$B$4*IF(BC17="",I17,BC17)+(1-Method!$B$4)*S17/($S17+$T17+$U17)) -> 0.52150129 | W17: =IF(T17="","",Method!$B$4*IF(BD17="",J17,BD17)+(1-Method!$B$4)*T17/($S17+$T17+$U17)) -> 0.28011295 | X17: =IF(U17="","",Method!$B$4*IF(BE17="",K17,BE17)+(1-Method!$B$4)*U17/($S17+$T17+$U17)) -> 0.19838577 | Y17: =IF(V17="","",V17*L17-1) -> 0.0064974816 | Z17: =IF(W17="","",W17*M17-1) -> -0.019604683 | AA17: =IF(X17="","",X17*N17-1) -> -0.0080711681 | AB17: =IF(Y17="","",MATCH(MAX(Y17:AA17),Y17:AA17,0)) -> 1 | AC17: =IF(AB17="","",CHOOSE(AB17,"H","D","A")) -> H | AD17: =IF(AB17="","",CHOOSE(AB17,"1 "&D17,"X Draw","2 "&E17)) -> 1 Iran | AE17: =IF(AB17="","",INDEX(L17:N17,1,AB17)) -> 1.93 | AF17: =IF(AB17="","",INDEX(Y17:AA17,1,AB17)) -> 0.0064974816 | AG17: =IF(AB17="","",INDEX(V17:X17,1,AB17)-INDEX(S17:U17,1,AB17)) -> 0.0048258867 | AH17: {=IF(AB17="","· enter odds",IF(OR(AF17>Method!$B$87,IFERROR(INDEX(BC17:BE17,1,AB17)/INDEX(S17:U17,1,AB17),0)>Method!$B$88),"PASS",IF(AND(AF17>=Method!$B$7,AG17>=Method!$B$8),"BET","PASS")))} -> PASS | AI17: =IF(AH17<>"BET",0,ROUND(MIN(Method!$B$6,Method!$B$5*AL17)*100,1)) -> 0 | AJ17: =IF(OR(AH17<>"BET",Method!$B$55=TRUE()),0,IF(AI17*Method!$B$10/100<Method!$B$9,0,ROUND(AI17*Method!$B$10/100,0))) -> 0 | AK17: =IF(AB17="","",INDEX(V17:X17,1,AB17)) -> 0.52150129 | AL17: =IF(AH17<>"BET","",MAX(0,(AK17*AE17-1)/(AE17-1))) | AM17: =IF(AH17="BET",AF17+A17/1000000,"") | AN17: =IF(Matchday!N19="","",Matchday!N19) | AO17: =IF(Matchday!P19="","",Matchday!P19) | AP17: =IF(Matchday!Q19="","",Matchday!Q19) | AQ17: =IF(Matchday!R19="","",Matchday!R19) -> D | AR17: =IF(OR(AN17<>"Y",AQ17="",AV17=""),"",IF(AQ17="Void",0,IF(AQ17=AV17,ROUND(AP17*(AO17-1),2),-AP17))) | AS17: =IF(AR17="","",SUM($AR$2:AR17)) | AT17: =IFERROR(__xludf.DUMMYFUNCTION("IF(AB17="""",""Type the 3 odds on the Matchday tab"",IF(Method!$B$55=TRUE(),IF(Method!$B$81=TRUE(),IF(REGEXMATCH(LOWER(Method!$B$63),""circuit""),""🛑 PAUSED — circuit breaker upstream; wait for a clean live refresh."",IF(REGEXMATCH(LOWER(Method!$B$63),"""&"pipeline""),""🛑 PAUSED — live pipeline warning; check Live!B11/Method!B62 before betting."",IF(REGEXMATCH(LOWER(Method!$B$63),""missing""),""🛑 PAUSED — feed timestamp missing; refresh feed before betting."",""🛑 PAUSED — feed stale > 25 min — check Live"&" tab; refresh feed before betting.""))),IF(Method!$B$51>=Method!$B$52,""🛑 PAUSED — drawdown ""&TEXT(Method!$B$51,""0.0%"")&"" ≥ ""&TEXT(Method!$B$52,""0.0%"")&"". Set Method!B54=Y to override."",""🛑 PAUSED — see Method!B62/B63/B81 for cause; do not over"&"ride stale/circuit-breaker/pipeline pauses."")),IF(AH17=""BET"",IF(AJ17=0,""Edge found but stake rounds under £""&Method!$B$9&"" — skip"",IF(AND(AE17>=6,AG17>=0.15),""🟡 WAIT — long-shot review: odds ""&TEXT(AE17,""0.00"")&"" + edge ""&TEXT(AG17,""0.0%"")"&"&"" — verify sharp-book + team news + stake comfort before Placed=Y"",""Value found: EV ""&TEXT(AF17,""0.0%"")&"", edge ""&TEXT(AG17,""0.0%""))),IF(OR(AF17>Method!$B$87,IFERROR(INDEX(BC17:BE17,1,AB17)/INDEX(S17:U17,1,AB17),0)>Method!$B$88),""🛑 Tail trap "&"— auto-PASS · EV ""&TEXT(AF17,""0.0%"")&"" (cap ""&TEXT(Method!$B$87,""0%"")&"") · model/market ""&TEXT(IFERROR(INDEX(BC17:BE17,1,AB17)/INDEX(S17:U17,1,AB17),0),""0.0"")&""× (cap ""&TEXT(Method!$B$88,""0.0"")&""×)"",IF(AF17<Method!$B$7,""Price too short —"&" EV ""&TEXT(AF17,""0.0%"")&"" (need ""&TEXT(Method!$B$7,""0.0%"")&""+)"",""Model ≈ market — edge ""&TEXT(AG17,""0.0%"")&"" (need ""&TEXT(Method!$B$8,""0.0%"")&""+)"")))))"),"Price too short — EV 0.6% (need 2.5%+)") -> Price too short — EV 0.6% (need 2.5%+) | AU17: =IF(AN17<>"Y","",IF(AH17="· enter odds","⚠ type the 3 odds (1/X/2) to grade this bet",IF(OR(AV17="",AO17="",AP17=""),"⚠ log backed pick, odds & stake",IF(AZ17<>"BET","⚠ FUN BET — engine said pass · staked £"&AP17&" vs engine £"&BA17,IF(AV17<>IF(AY17="",AC17,AY17),"⚠ backed "&AV17&" but engine pick was "&IF(AY17="",AC17,AY17),IF(AP17>BA17,"⚠ stake over engine £"&BA17,IF(ABS(AO17-IFERROR(INDEX(L17:N17,1,MATCH(AV17,{"H","D","A"},0)),AE17))>0.02,"⚠ odds moved — re-check value","✓ engine bet"))))))) | AV17: =IF(Matchday!O19="","",Matchday!O19) | AZ17: =IF(AW17="",AH17,AW17) -> PASS | BA17: =IF(AX17<>"",AX17,IF(AH17<>"BET",0,IF(AI17*Method!$B$10/100<Method!$B$9,0,ROUND(AI17*Method!$B$10/100,0)))) -> 0 | BB17: -9.96 | BC17: 0.53046365 | BD17: 0.27200626 | BE17: 0.19753009 | BF17: Iran team-wide: -6 · New Zealand team-wide: -4 | BG17: 30 | BH17: warm_dry_indoor | BI17: 0
A18: 17 | B18: 46189 | C18: I | D18: France | E18: Senegal | F18: East Rutherford | G18: 0.625 | H18: 0.83333333 | I18: 0.75431407 | J18: 0.16377887 | K18: 0.081907055 | L18: =IF(Matchday!E20="","",Matchday!E20) -> 1.52 | M18: =IF(Matchday!F20="","",Matchday!F20) -> 4.55 | N18: =IF(Matchday!G20="","",Matchday!G20) -> 7.2 | O18: =IF(L18="","",1/L18) -> 0.65789474 | P18: =IF(M18="","",1/M18) -> 0.21978022 | Q18: =IF(N18="","",1/N18) -> 0.13888889 | R18: =IF(COUNT(L18:N18)<3,"",O18+P18+Q18) -> 1.0165638 | S18: {=IF($R18="","",IF(Method!$B$56="proportional",O18/$R18,IF(Method!$B$56="power",IFERROR(INDEX(power_devig($L18,$M18,$N18),1,1),O18/$R18),IFERROR(INDEX(shin($L18,$M18,$N18),1,1),O18/$R18))))} -> 0.65106271 | T18: {=IF($R18="","",IF(Method!$B$56="proportional",P18/$R18,IF(Method!$B$56="power",IFERROR(INDEX(power_devig($L18,$M18,$N18),2,1),P18/$R18),IFERROR(INDEX(shin($L18,$M18,$N18),2,1),P18/$R18))))} -> 0.21473969 | U18: {=IF($R18="","",IF(Method!$B$56="proportional",Q18/$R18,IF(Method!$B$56="power",IFERROR(INDEX(power_devig($L18,$M18,$N18),3,1),Q18/$R18),IFERROR(INDEX(shin($L18,$M18,$N18),3,1),Q18/$R18))))} -> 0.13419759 | V18: =IF(S18="","",Method!$B$4*IF(BC18="",I18,BC18)+(1-Method!$B$4)*S18/($S18+$T18+$U18)) -> 0.67861544 | W18: =IF(T18="","",Method!$B$4*IF(BD18="",J18,BD18)+(1-Method!$B$4)*T18/($S18+$T18+$U18)) -> 0.20471374 | X18: =IF(U18="","",Method!$B$4*IF(BE18="",K18,BE18)+(1-Method!$B$4)*U18/($S18+$T18+$U18)) -> 0.11667083 | Y18: =IF(V18="","",V18*L18-1) -> 0.031495466 | Z18: =IF(W18="","",W18*M18-1) -> -0.068552502 | AA18: =IF(X18="","",X18*N18-1) -> -0.15997005 | AB18: =IF(Y18="","",MATCH(MAX(Y18:AA18),Y18:AA18,0)) -> 1 | AC18: =IF(AB18="","",CHOOSE(AB18,"H","D","A")) -> H | AD18: =IF(AB18="","",CHOOSE(AB18,"1 "&D18,"X Draw","2 "&E18)) -> 1 France | AE18: =IF(AB18="","",INDEX(L18:N18,1,AB18)) -> 1.52 | AF18: =IF(AB18="","",INDEX(Y18:AA18,1,AB18)) -> 0.031495466 | AG18: =IF(AB18="","",INDEX(V18:X18,1,AB18)-INDEX(S18:U18,1,AB18)) -> 0.027552723 | AH18: {=IF(AB18="","· enter odds",IF(OR(AF18>Method!$B$87,IFERROR(INDEX(BC18:BE18,1,AB18)/INDEX(S18:U18,1,AB18),0)>Method!$B$88),"PASS",IF(AND(AF18>=Method!$B$7,AG18>=Method!$B$8),"BET","PASS")))} -> BET | AI18: =IF(AH18<>"BET",0,ROUND(MIN(Method!$B$6,Method!$B$5*AL18)*100,1)) -> 1.5 | AJ18: =IF(OR(AH18<>"BET",Method!$B$55=TRUE()),0,IF(AI18*Method!$B$10/100<Method!$B$9,0,ROUND(AI18*Method!$B$10/100,0))) -> 15 | AK18: =IF(AB18="","",INDEX(V18:X18,1,AB18)) -> 0.67861544 | AL18: =IF(AH18<>"BET","",MAX(0,(AK18*AE18-1)/(AE18-1))) -> 0.060568204 | AM18: =IF(AH18="BET",AF18+A18/1000000,"") -> 0.031512466 | AN18: =IF(Matchday!N20="","",Matchday!N20) | AO18: =IF(Matchday!P20="","",Matchday!P20) | AP18: =IF(Matchday!Q20="","",Matchday!Q20) | AQ18: =IF(Matchday!R20="","",Matchday!R20) -> H | AR18: =IF(OR(AN18<>"Y",AQ18="",AV18=""),"",IF(AQ18="Void",0,IF(AQ18=AV18,ROUND(AP18*(AO18-1),2),-AP18))) | AS18: =IF(AR18="","",SUM($AR$2:AR18)) | AT18: =IFERROR(__xludf.DUMMYFUNCTION("IF(AB18="""",""Type the 3 odds on the Matchday tab"",IF(Method!$B$55=TRUE(),IF(Method!$B$81=TRUE(),IF(REGEXMATCH(LOWER(Method!$B$63),""circuit""),""🛑 PAUSED — circuit breaker upstream; wait for a clean live refresh."",IF(REGEXMATCH(LOWER(Method!$B$63),"""&"pipeline""),""🛑 PAUSED — live pipeline warning; check Live!B11/Method!B62 before betting."",IF(REGEXMATCH(LOWER(Method!$B$63),""missing""),""🛑 PAUSED — feed timestamp missing; refresh feed before betting."",""🛑 PAUSED — feed stale > 25 min — check Live"&" tab; refresh feed before betting.""))),IF(Method!$B$51>=Method!$B$52,""🛑 PAUSED — drawdown ""&TEXT(Method!$B$51,""0.0%"")&"" ≥ ""&TEXT(Method!$B$52,""0.0%"")&"". Set Method!B54=Y to override."",""🛑 PAUSED — see Method!B62/B63/B81 for cause; do not over"&"ride stale/circuit-breaker/pipeline pauses."")),IF(AH18=""BET"",IF(AJ18=0,""Edge found but stake rounds under £""&Method!$B$9&"" — skip"",IF(AND(AE18>=6,AG18>=0.15),""🟡 WAIT — long-shot review: odds ""&TEXT(AE18,""0.00"")&"" + edge ""&TEXT(AG18,""0.0%"")"&"&"" — verify sharp-book + team news + stake comfort before Placed=Y"",""Value found: EV ""&TEXT(AF18,""0.0%"")&"", edge ""&TEXT(AG18,""0.0%""))),IF(OR(AF18>Method!$B$87,IFERROR(INDEX(BC18:BE18,1,AB18)/INDEX(S18:U18,1,AB18),0)>Method!$B$88),""🛑 Tail trap "&"— auto-PASS · EV ""&TEXT(AF18,""0.0%"")&"" (cap ""&TEXT(Method!$B$87,""0%"")&"") · model/market ""&TEXT(IFERROR(INDEX(BC18:BE18,1,AB18)/INDEX(S18:U18,1,AB18),0),""0.0"")&""× (cap ""&TEXT(Method!$B$88,""0.0"")&""×)"",IF(AF18<Method!$B$7,""Price too short —"&" EV ""&TEXT(AF18,""0.0%"")&"" (need ""&TEXT(Method!$B$7,""0.0%"")&""+)"",""Model ≈ market — edge ""&TEXT(AG18,""0.0%"")&"" (need ""&TEXT(Method!$B$8,""0.0%"")&""+)"")))))"),"Value found: EV 3.1%, edge 2.8%") -> Value found: EV 3.1%, edge 2.8% | AU18: =IF(AN18<>"Y","",IF(AH18="· enter odds","⚠ type the 3 odds (1/X/2) to grade this bet",IF(OR(AV18="",AO18="",AP18=""),"⚠ log backed pick, odds & stake",IF(AZ18<>"BET","⚠ FUN BET — engine said pass · staked £"&AP18&" vs engine £"&BA18,IF(AV18<>IF(AY18="",AC18,AY18),"⚠ backed "&AV18&" but engine pick was "&IF(AY18="",AC18,AY18),IF(AP18>BA18,"⚠ stake over engine £"&BA18,IF(ABS(AO18-IFERROR(INDEX(L18:N18,1,MATCH(AV18,{"H","D","A"},0)),AE18))>0.02,"⚠ odds moved — re-check value","✓ engine bet"))))))) | AV18: =IF(Matchday!O20="","",Matchday!O20) | AZ18: =IF(AW18="",AH18,AW18) -> BET | BA18: =IF(AX18<>"",AX18,IF(AH18<>"BET",0,IF(AI18*Method!$B$10/100<Method!$B$9,0,ROUND(AI18*Method!$B$10/100,0)))) -> 15 | BB18: 4.24 | BC18: 0.72978478 | BD18: 0.18609411 | BE18: 0.084121113 | BF18: France team-wide: +20 · France weather: -4 · Senegal team-wide: -12 | BG18: 7 | BH18: warm_humid | BI18: 0
A19: 18 | B19: 46189 | C19: I | D19: Iraq | E19: Norway | F19: Foxborough | G19: 0.75 | H19: 0.95833333 | I19: 0.11606846 | J19: 0.26310177 | K19: 0.62082977 | L19: =IF(Matchday!E21="","",Matchday!E21) -> 15 | M19: =IF(Matchday!F21="","",Matchday!F21) -> 7.5 | N19: =IF(Matchday!G21="","",Matchday!G21) -> 1.24 | O19: =IF(L19="","",1/L19) -> 0.066666667 | P19: =IF(M19="","",1/M19) -> 0.13333333 | Q19: =IF(N19="","",1/N19) -> 0.80645161 | R19: =IF(COUNT(L19:N19)<3,"",O19+P19+Q19) -> 1.0064516 | S19: {=IF($R19="","",IF(Method!$B$56="proportional",O19/$R19,IF(Method!$B$56="power",IFERROR(INDEX(power_devig($L19,$M19,$N19),1,1),O19/$R19),IFERROR(INDEX(shin($L19,$M19,$N19),1,1),O19/$R19))))} -> 0.064952632 | T19: {=IF($R19="","",IF(Method!$B$56="proportional",P19/$R19,IF(Method!$B$56="power",IFERROR(INDEX(power_devig($L19,$M19,$N19),2,1),P19/$R19),IFERROR(INDEX(shin($L19,$M19,$N19),2,1),P19/$R19))))} -> 0.13150343 | U19: {=IF($R19="","",IF(Method!$B$56="proportional",Q19/$R19,IF(Method!$B$56="power",IFERROR(INDEX(power_devig($L19,$M19,$N19),3,1),Q19/$R19),IFERROR(INDEX(shin($L19,$M19,$N19),3,1),Q19/$R19))))} -> 0.80354394 | V19: =IF(S19="","",Method!$B$4*IF(BC19="",I19,BC19)+(1-Method!$B$4)*S19/($S19+$T19+$U19)) -> 0.078724214 | W19: =IF(T19="","",Method!$B$4*IF(BD19="",J19,BD19)+(1-Method!$B$4)*T19/($S19+$T19+$U19)) -> 0.18391772 | X19: =IF(U19="","",Method!$B$4*IF(BE19="",K19,BE19)+(1-Method!$B$4)*U19/($S19+$T19+$U19)) -> 0.73735807 | Y19: =IF(V19="","",V19*L19-1) -> 0.1808632 | Z19: =IF(W19="","",W19*M19-1) -> 0.37938286 | AA19: =IF(X19="","",X19*N19-1) -> -0.085675992 | AB19: =IF(Y19="","",MATCH(MAX(Y19:AA19),Y19:AA19,0)) -> 2 | AC19: =IF(AB19="","",CHOOSE(AB19,"H","D","A")) -> D | AD19: =IF(AB19="","",CHOOSE(AB19,"1 "&D19,"X Draw","2 "&E19)) -> X Draw | AE19: =IF(AB19="","",INDEX(L19:N19,1,AB19)) -> 7.5 | AF19: =IF(AB19="","",INDEX(Y19:AA19,1,AB19)) -> 0.37938286 | AG19: =IF(AB19="","",INDEX(V19:X19,1,AB19)-INDEX(S19:U19,1,AB19)) -> 0.05241429 | AH19: {=IF(AB19="","· enter odds",IF(OR(AF19>Method!$B$87,IFERROR(INDEX(BC19:BE19,1,AB19)/INDEX(S19:U19,1,AB19),0)>Method!$B$88),"PASS",IF(AND(AF19>=Method!$B$7,AG19>=Method!$B$8),"BET","PASS")))} -> PASS | AI19: =IF(AH19<>"BET",0,ROUND(MIN(Method!$B$6,Method!$B$5*AL19)*100,1)) -> 0 | AJ19: =IF(OR(AH19<>"BET",Method!$B$55=TRUE()),0,IF(AI19*Method!$B$10/100<Method!$B$9,0,ROUND(AI19*Method!$B$10/100,0))) -> 0 | AK19: =IF(AB19="","",INDEX(V19:X19,1,AB19)) -> 0.18391772 | AL19: =IF(AH19<>"BET","",MAX(0,(AK19*AE19-1)/(AE19-1))) | AM19: =IF(AH19="BET",AF19+A19/1000000,"") | AN19: =IF(Matchday!N21="","",Matchday!N21) | AO19: =IF(Matchday!P21="","",Matchday!P21) | AP19: =IF(Matchday!Q21="","",Matchday!Q21) | AQ19: =IF(Matchday!R21="","",Matchday!R21) -> A | AR19: =IF(OR(AN19<>"Y",AQ19="",AV19=""),"",IF(AQ19="Void",0,IF(AQ19=AV19,ROUND(AP19*(AO19-1),2),-AP19))) | AS19: =IF(AR19="","",SUM($AR$2:AR19)) | AT19: =IFERROR(__xludf.DUMMYFUNCTION("IF(AB19="""",""Type the 3 odds on the Matchday tab"",IF(Method!$B$55=TRUE(),IF(Method!$B$81=TRUE(),IF(REGEXMATCH(LOWER(Method!$B$63),""circuit""),""🛑 PAUSED — circuit breaker upstream; wait for a clean live refresh."",IF(REGEXMATCH(LOWER(Method!$B$63),"""&"pipeline""),""🛑 PAUSED — live pipeline warning; check Live!B11/Method!B62 before betting."",IF(REGEXMATCH(LOWER(Method!$B$63),""missing""),""🛑 PAUSED — feed timestamp missing; refresh feed before betting."",""🛑 PAUSED — feed stale > 25 min — check Live"&" tab; refresh feed before betting.""))),IF(Method!$B$51>=Method!$B$52,""🛑 PAUSED — drawdown ""&TEXT(Method!$B$51,""0.0%"")&"" ≥ ""&TEXT(Method!$B$52,""0.0%"")&"". Set Method!B54=Y to override."",""🛑 PAUSED — see Method!B62/B63/B81 for cause; do not over"&"ride stale/circuit-breaker/pipeline pauses."")),IF(AH19=""BET"",IF(AJ19=0,""Edge found but stake rounds under £""&Method!$B$9&"" — skip"",IF(AND(AE19>=6,AG19>=0.15),""🟡 WAIT — long-shot review: odds ""&TEXT(AE19,""0.00"")&"" + edge ""&TEXT(AG19,""0.0%"")"&"&"" — verify sharp-book + team news + stake comfort before Placed=Y"",""Value found: EV ""&TEXT(AF19,""0.0%"")&"", edge ""&TEXT(AG19,""0.0%""))),IF(OR(AF19>Method!$B$87,IFERROR(INDEX(BC19:BE19,1,AB19)/INDEX(S19:U19,1,AB19),0)>Method!$B$88),""🛑 Tail trap "&"— auto-PASS · EV ""&TEXT(AF19,""0.0%"")&"" (cap ""&TEXT(Method!$B$87,""0%"")&"") · model/market ""&TEXT(IFERROR(INDEX(BC19:BE19,1,AB19)/INDEX(S19:U19,1,AB19),0),""0.0"")&""× (cap ""&TEXT(Method!$B$88,""0.0"")&""×)"",IF(AF19<Method!$B$7,""Price too short —"&" EV ""&TEXT(AF19,""0.0%"")&"" (need ""&TEXT(Method!$B$7,""0.0%"")&""+)"",""Model ≈ market — edge ""&TEXT(AG19,""0.0%"")&"" (need ""&TEXT(Method!$B$8,""0.0%"")&""+)"")))))"),"🛑 Tail trap — auto-PASS · EV 37.9% (cap 30%) · model/market 2.1× (cap 2.5×)") -> 🛑 Tail trap — auto-PASS · EV 37.9% (cap 30%) · model/market 2.1× (cap 2.5×) | AU19: =IF(AN19<>"Y","",IF(AH19="· enter odds","⚠ type the 3 odds (1/X/2) to grade this bet",IF(OR(AV19="",AO19="",AP19=""),"⚠ log backed pick, odds & stake",IF(AZ19<>"BET","⚠ FUN BET — engine said pass · staked £"&AP19&" vs engine £"&BA19,IF(AV19<>IF(AY19="",AC19,AY19),"⚠ backed "&AV19&" but engine pick was "&IF(AY19="",AC19,AY19),IF(AP19>BA19,"⚠ stake over engine £"&BA19,IF(ABS(AO19-IFERROR(INDEX(L19:N19,1,MATCH(AV19,{"H","D","A"},0)),AE19))>0.02,"⚠ odds moved — re-check value","✓ engine bet"))))))) | AV19: =IF(Matchday!O21="","",Matchday!O21) | AZ19: =IF(AW19="",AH19,AW19) -> PASS | BA19: =IF(AX19<>"",AX19,IF(AH19<>"BET",0,IF(AI19*Method!$B$10/100<Method!$B$9,0,ROUND(AI19*Method!$B$10/100,0)))) -> 0 | BB19: -24 | BC19: 0.10430001 | BD19: 0.28125854 | BE19: 0.61444145 | BF19: Iraq team-wide: -12 · Norway team-wide: -12 | BG19: 40 | BH19: warm | BI19: 0
A20: 19 | B20: 46189 | C20: J | D20: Argentina | E20: Algeria | F20: Kansas City | G20: 0.83333333 | H20: 02:00 +1d | I20: 0.76686552 | J20: 0.16396844 | K20: 0.069166039 | L20: =IF(Matchday!E22="","",Matchday!E22) -> 1.55 | M20: =IF(Matchday!F22="","",Matchday!F22) -> 4.2 | N20: =IF(Matchday!G22="","",Matchday!G22) -> 7.1 | O20: =IF(L20="","",1/L20) -> 0.64516129 | P20: =IF(M20="","",1/M20) -> 0.23809524 | Q20: =IF(N20="","",1/N20) -> 0.14084507 | R20: =IF(COUNT(L20:N20)<3,"",O20+P20+Q20) -> 1.0241016 | S20: {=IF($R20="","",IF(Method!$B$56="proportional",O20/$R20,IF(Method!$B$56="power",IFERROR(INDEX(power_devig($L20,$M20,$N20),1,1),O20/$R20),IFERROR(INDEX(shin($L20,$M20,$N20),1,1),O20/$R20))))} -> 0.63531672 | T20: {=IF($R20="","",IF(Method!$B$56="proportional",P20/$R20,IF(Method!$B$56="power",IFERROR(INDEX(power_devig($L20,$M20,$N20),2,1),P20/$R20),IFERROR(INDEX(shin($L20,$M20,$N20),2,1),P20/$R20))))} -> 0.23065774 | U20: {=IF($R20="","",IF(Method!$B$56="proportional",Q20/$R20,IF(Method!$B$56="power",IFERROR(INDEX(power_devig($L20,$M20,$N20),3,1),Q20/$R20),IFERROR(INDEX(shin($L20,$M20,$N20),3,1),Q20/$R20))))} -> 0.13402554 | V20: =IF(S20="","",Method!$B$4*IF(BC20="",I20,BC20)+(1-Method!$B$4)*S20/($S20+$T20+$U20)) -> 0.67367147 | W20: =IF(T20="","",Method!$B$4*IF(BD20="",J20,BD20)+(1-Method!$B$4)*T20/($S20+$T20+$U20)) -> 0.21471557 | X20: =IF(U20="","",Method!$B$4*IF(BE20="",K20,BE20)+(1-Method!$B$4)*U20/($S20+$T20+$U20)) -> 0.11161296 | Y20: =IF(V20="","",V20*L20-1) -> 0.044190783 | Z20: =IF(W20="","",W20*M20-1) -> -0.098194613 | AA20: =IF(X20="","",X20*N20-1) -> -0.20754799 | AB20: =IF(Y20="","",MATCH(MAX(Y20:AA20),Y20:AA20,0)) -> 1 | AC20: =IF(AB20="","",CHOOSE(AB20,"H","D","A")) -> H | AD20: =IF(AB20="","",CHOOSE(AB20,"1 "&D20,"X Draw","2 "&E20)) -> 1 Argentina | AE20: =IF(AB20="","",INDEX(L20:N20,1,AB20)) -> 1.55 | AF20: =IF(AB20="","",INDEX(Y20:AA20,1,AB20)) -> 0.044190783 | AG20: =IF(AB20="","",INDEX(V20:X20,1,AB20)-INDEX(S20:U20,1,AB20)) -> 0.038354754 | AH20: {=IF(AB20="","· enter odds",IF(OR(AF20>Method!$B$87,IFERROR(INDEX(BC20:BE20,1,AB20)/INDEX(S20:U20,1,AB20),0)>Method!$B$88),"PASS",IF(AND(AF20>=Method!$B$7,AG20>=Method!$B$8),"BET","PASS")))} -> BET | AI20: =IF(AH20<>"BET",0,ROUND(MIN(Method!$B$6,Method!$B$5*AL20)*100,1)) -> 2 | AJ20: =IF(OR(AH20<>"BET",Method!$B$55=TRUE()),0,IF(AI20*Method!$B$10/100<Method!$B$9,0,ROUND(AI20*Method!$B$10/100,0))) -> 19 | AK20: =IF(AB20="","",INDEX(V20:X20,1,AB20)) -> 0.67367147 | AL20: =IF(AH20<>"BET","",MAX(0,(AK20*AE20-1)/(AE20-1))) -> 0.080346877 | AM20: =IF(AH20="BET",AF20+A20/1000000,"") -> 0.044209783 | AN20: =IF(Matchday!N22="","",Matchday!N22) | AO20: =IF(Matchday!P22="","",Matchday!P22) | AP20: =IF(Matchday!Q22="","",Matchday!Q22) | AQ20: =IF(Matchday!R22="","",Matchday!R22) -> H | AR20: =IF(OR(AN20<>"Y",AQ20="",AV20=""),"",IF(AQ20="Void",0,IF(AQ20=AV20,ROUND(AP20*(AO20-1),2),-AP20))) | AS20: =IF(AR20="","",SUM($AR$2:AR20)) | AT20: =IFERROR(__xludf.DUMMYFUNCTION("IF(AB20="""",""Type the 3 odds on the Matchday tab"",IF(Method!$B$55=TRUE(),IF(Method!$B$81=TRUE(),IF(REGEXMATCH(LOWER(Method!$B$63),""circuit""),""🛑 PAUSED — circuit breaker upstream; wait for a clean live refresh."",IF(REGEXMATCH(LOWER(Method!$B$63),"""&"pipeline""),""🛑 PAUSED — live pipeline warning; check Live!B11/Method!B62 before betting."",IF(REGEXMATCH(LOWER(Method!$B$63),""missing""),""🛑 PAUSED — feed timestamp missing; refresh feed before betting."",""🛑 PAUSED — feed stale > 25 min — check Live"&" tab; refresh feed before betting.""))),IF(Method!$B$51>=Method!$B$52,""🛑 PAUSED — drawdown ""&TEXT(Method!$B$51,""0.0%"")&"" ≥ ""&TEXT(Method!$B$52,""0.0%"")&"". Set Method!B54=Y to override."",""🛑 PAUSED — see Method!B62/B63/B81 for cause; do not over"&"ride stale/circuit-breaker/pipeline pauses."")),IF(AH20=""BET"",IF(AJ20=0,""Edge found but stake rounds under £""&Method!$B$9&"" — skip"",IF(AND(AE20>=6,AG20>=0.15),""🟡 WAIT — long-shot review: odds ""&TEXT(AE20,""0.00"")&"" + edge ""&TEXT(AG20,""0.0%"")"&"&"" — verify sharp-book + team news + stake comfort before Placed=Y"",""Value found: EV ""&TEXT(AF20,""0.0%"")&"", edge ""&TEXT(AG20,""0.0%""))),IF(OR(AF20>Method!$B$87,IFERROR(INDEX(BC20:BE20,1,AB20)/INDEX(S20:U20,1,AB20),0)>Method!$B$88),""🛑 Tail trap "&"— auto-PASS · EV ""&TEXT(AF20,""0.0%"")&"" (cap ""&TEXT(Method!$B$87,""0%"")&"") · model/market ""&TEXT(IFERROR(INDEX(BC20:BE20,1,AB20)/INDEX(S20:U20,1,AB20),0),""0.0"")&""× (cap ""&TEXT(Method!$B$88,""0.0"")&""×)"",IF(AF20<Method!$B$7,""Price too short —"&" EV ""&TEXT(AF20,""0.0%"")&"" (need ""&TEXT(Method!$B$7,""0.0%"")&""+)"",""Model ≈ market — edge ""&TEXT(AG20,""0.0%"")&"" (need ""&TEXT(Method!$B$8,""0.0%"")&""+)"")))))"),"Value found: EV 4.4%, edge 3.8%") -> Value found: EV 4.4%, edge 3.8% | AU20: =IF(AN20<>"Y","",IF(AH20="· enter odds","⚠ type the 3 odds (1/X/2) to grade this bet",IF(OR(AV20="",AO20="",AP20=""),"⚠ log backed pick, odds & stake",IF(AZ20<>"BET","⚠ FUN BET — engine said pass · staked £"&AP20&" vs engine £"&BA20,IF(AV20<>IF(AY20="",AC20,AY20),"⚠ backed "&AV20&" but engine pick was "&IF(AY20="",AC20,AY20),IF(AP20>BA20,"⚠ stake over engine £"&BA20,IF(ABS(AO20-IFERROR(INDEX(L20:N20,1,MATCH(AV20,{"H","D","A"},0)),AE20))>0.02,"⚠ odds moved — re-check value","✓ engine bet"))))))) | AV20: =IF(Matchday!O22="","",Matchday!O22) | AZ20: =IF(AW20="",AH20,AW20) -> BET | BA20: =IF(AX20<>"",AX20,IF(AH20<>"BET",0,IF(AI20*Method!$B$10/100<Method!$B$9,0,ROUND(AI20*Method!$B$10/100,0)))) -> 19 | BB20: -11.73 | BC20: 0.74490173 | BD20: 0.18510868 | BE20: 0.069989589 | BF20: Algeria team-wide: -24 · Argentina team-wide: +13 | BG20: 270 | BH20: hot | BI20: 0
A21: 20 | B21: 46189 | C21: J | D21: Austria | E21: Jordan | F21: Santa Clara | G21: 0.875 | H21: 05:00 +1d | I21: 0.45611192 | J21: 0.30288181 | K21: 0.24100627 | L21: =IF(Matchday!E23="","",Matchday!E23) -> 1.4 | M21: =IF(Matchday!F23="","",Matchday!F23) -> 4.8 | N21: =IF(Matchday!G23="","",Matchday!G23) -> 9.2 | O21: =IF(L21="","",1/L21) -> 0.71428571 | P21: =IF(M21="","",1/M21) -> 0.20833333 | Q21: =IF(N21="","",1/N21) -> 0.10869565 | R21: =IF(COUNT(L21:N21)<3,"",O21+P21+Q21) -> 1.0313147 | S21: {=IF($R21="","",IF(Method!$B$56="proportional",O21/$R21,IF(Method!$B$56="power",IFERROR(INDEX(power_devig($L21,$M21,$N21),1,1),O21/$R21),IFERROR(INDEX(shin($L21,$M21,$N21),1,1),O21/$R21))))} -> 0.70098813 | T21: {=IF($R21="","",IF(Method!$B$56="proportional",P21/$R21,IF(Method!$B$56="power",IFERROR(INDEX(power_devig($L21,$M21,$N21),2,1),P21/$R21),IFERROR(INDEX(shin($L21,$M21,$N21),2,1),P21/$R21))))} -> 0.19888481 | U21: {=IF($R21="","",IF(Method!$B$56="proportional",Q21/$R21,IF(Method!$B$56="power",IFERROR(INDEX(power_devig($L21,$M21,$N21),3,1),Q21/$R21),IFERROR(INDEX(shin($L21,$M21,$N21),3,1),Q21/$R21))))} -> 0.10012706 | V21: =IF(S21="","",Method!$B$4*IF(BC21="",I21,BC21)+(1-Method!$B$4)*S21/($S21+$T21+$U21)) -> 0.62095293 | W21: =IF(T21="","",Method!$B$4*IF(BD21="",J21,BD21)+(1-Method!$B$4)*T21/($S21+$T21+$U21)) -> 0.22189951 | X21: =IF(U21="","",Method!$B$4*IF(BE21="",K21,BE21)+(1-Method!$B$4)*U21/($S21+$T21+$U21)) -> 0.15714757 | Y21: =IF(V21="","",V21*L21-1) -> -0.1306659 | Z21: =IF(W21="","",W21*M21-1) -> 0.065117625 | AA21: =IF(X21="","",X21*N21-1) -> 0.44575763 | AB21: =IF(Y21="","",MATCH(MAX(Y21:AA21),Y21:AA21,0)) -> 3 | AC21: =IF(AB21="","",CHOOSE(AB21,"H","D","A")) -> A | AD21: =IF(AB21="","",CHOOSE(AB21,"1 "&D21,"X Draw","2 "&E21)) -> 2 Jordan | AE21: =IF(AB21="","",INDEX(L21:N21,1,AB21)) -> 9.2 | AF21: =IF(AB21="","",INDEX(Y21:AA21,1,AB21)) -> 0.44575763 | AG21: =IF(AB21="","",INDEX(V21:X21,1,AB21)-INDEX(S21:U21,1,AB21)) -> 0.05702051 | AH21: {=IF(AB21="","· enter odds",IF(OR(AF21>Method!$B$87,IFERROR(INDEX(BC21:BE21,1,AB21)/INDEX(S21:U21,1,AB21),0)>Method!$B$88),"PASS",IF(AND(AF21>=Method!$B$7,AG21>=Method!$B$8),"BET","PASS")))} -> PASS | AI21: =IF(AH21<>"BET",0,ROUND(MIN(Method!$B$6,Method!$B$5*AL21)*100,1)) -> 0 | AJ21: =IF(OR(AH21<>"BET",Method!$B$55=TRUE()),0,IF(AI21*Method!$B$10/100<Method!$B$9,0,ROUND(AI21*Method!$B$10/100,0))) -> 0 | AK21: =IF(AB21="","",INDEX(V21:X21,1,AB21)) -> 0.15714757 | AL21: =IF(AH21<>"BET","",MAX(0,(AK21*AE21-1)/(AE21-1))) | AM21: =IF(AH21="BET",AF21+A21/1000000,"") | AN21: =IF(Matchday!N23="","",Matchday!N23) | AO21: =IF(Matchday!P23="","",Matchday!P23) | AP21: =IF(Matchday!Q23="","",Matchday!Q23) | AQ21: =IF(Matchday!R23="","",Matchday!R23) -> H | AR21: =IF(OR(AN21<>"Y",AQ21="",AV21=""),"",IF(AQ21="Void",0,IF(AQ21=AV21,ROUND(AP21*(AO21-1),2),-AP21))) | AS21: =IF(AR21="","",SUM($AR$2:AR21)) | AT21: =IFERROR(__xludf.DUMMYFUNCTION("IF(AB21="""",""Type the 3 odds on the Matchday tab"",IF(Method!$B$55=TRUE(),IF(Method!$B$81=TRUE(),IF(REGEXMATCH(LOWER(Method!$B$63),""circuit""),""🛑 PAUSED — circuit breaker upstream; wait for a clean live refresh."",IF(REGEXMATCH(LOWER(Method!$B$63),"""&"pipeline""),""🛑 PAUSED — live pipeline warning; check Live!B11/Method!B62 before betting."",IF(REGEXMATCH(LOWER(Method!$B$63),""missing""),""🛑 PAUSED — feed timestamp missing; refresh feed before betting."",""🛑 PAUSED — feed stale > 25 min — check Live"&" tab; refresh feed before betting.""))),IF(Method!$B$51>=Method!$B$52,""🛑 PAUSED — drawdown ""&TEXT(Method!$B$51,""0.0%"")&"" ≥ ""&TEXT(Method!$B$52,""0.0%"")&"". Set Method!B54=Y to override."",""🛑 PAUSED — see Method!B62/B63/B81 for cause; do not over"&"ride stale/circuit-breaker/pipeline pauses."")),IF(AH21=""BET"",IF(AJ21=0,""Edge found but stake rounds under £""&Method!$B$9&"" — skip"",IF(AND(AE21>=6,AG21>=0.15),""🟡 WAIT — long-shot review: odds ""&TEXT(AE21,""0.00"")&"" + edge ""&TEXT(AG21,""0.0%"")"&"&"" — verify sharp-book + team news + stake comfort before Placed=Y"",""Value found: EV ""&TEXT(AF21,""0.0%"")&"", edge ""&TEXT(AG21,""0.0%""))),IF(OR(AF21>Method!$B$87,IFERROR(INDEX(BC21:BE21,1,AB21)/INDEX(S21:U21,1,AB21),0)>Method!$B$88),""🛑 Tail trap "&"— auto-PASS · EV ""&TEXT(AF21,""0.0%"")&"" (cap ""&TEXT(Method!$B$87,""0%"")&"") · model/market ""&TEXT(IFERROR(INDEX(BC21:BE21,1,AB21)/INDEX(S21:U21,1,AB21),0),""0.0"")&""× (cap ""&TEXT(Method!$B$88,""0.0"")&""×)"",IF(AF21<Method!$B$7,""Price too short —"&" EV ""&TEXT(AF21,""0.0%"")&"" (need ""&TEXT(Method!$B$7,""0.0%"")&""+)"",""Model ≈ market — edge ""&TEXT(AG21,""0.0%"")&"" (need ""&TEXT(Method!$B$8,""0.0%"")&""+)"")))))"),"🛑 Tail trap — auto-PASS · EV 44.6% (cap 30%) · model/market 2.6× (cap 2.5×)") -> 🛑 Tail trap — auto-PASS · EV 44.6% (cap 30%) · model/market 2.6× (cap 2.5×) | AU21: =IF(AN21<>"Y","",IF(AH21="· enter odds","⚠ type the 3 odds (1/X/2) to grade this bet",IF(OR(AV21="",AO21="",AP21=""),"⚠ log backed pick, odds & stake",IF(AZ21<>"BET","⚠ FUN BET — engine said pass · staked £"&AP21&" vs engine £"&BA21,IF(AV21<>IF(AY21="",AC21,AY21),"⚠ backed "&AV21&" but engine pick was "&IF(AY21="",AC21,AY21),IF(AP21>BA21,"⚠ stake over engine £"&BA21,IF(ABS(AO21-IFERROR(INDEX(L21:N21,1,MATCH(AV21,{"H","D","A"},0)),AE21))>0.02,"⚠ odds moved — re-check value","✓ engine bet"))))))) | AV21: =IF(Matchday!O23="","",Matchday!O23) | AZ21: =IF(AW21="",AH21,AW21) -> PASS | BA21: =IF(AX21<>"",AX21,IF(AH21<>"BET",0,IF(AI21*Method!$B$10/100<Method!$B$9,0,ROUND(AI21*Method!$B$10/100,0)))) -> 0 | BB21: -16.35 | BC21: 0.47231612 | BD21: 0.26464108 | BE21: 0.2630428 | BF21: Austria team-wide: -9 · Jordan team-wide: -8 | BG21: 8 | BH21: mild_dry | BI21: 0
A22: 21 | B22: 46190 | C22: K | D22: Portugal | E22: DR Congo | F22: Houston | G22: 0.5 | H22: 0.75 | I22: 0.61680946 | J22: 0.24827131 | K22: 0.13491922 | L22: =IF(Matchday!E24="","",Matchday!E24) -> 1.29 | M22: =IF(Matchday!F24="","",Matchday!F24) -> 6 | N22: =IF(Matchday!G24="","",Matchday!G24) -> 12 | O22: =IF(L22="","",1/L22) -> 0.7751938 | P22: =IF(M22="","",1/M22) -> 0.16666667 | Q22: =IF(N22="","",1/N22) -> 0.083333333 | R22: =IF(COUNT(L22:N22)<3,"",O22+P22+Q22) -> 1.0251938 | S22: {=IF($R22="","",IF(Method!$B$56="proportional",O22/$R22,IF(Method!$B$56="power",IFERROR(INDEX(power_devig($L22,$M22,$N22),1,1),O22/$R22),IFERROR(INDEX(shin($L22,$M22,$N22),1,1),O22/$R22))))} -> 0.76409875 | T22: {=IF($R22="","",IF(Method!$B$56="proportional",P22/$R22,IF(Method!$B$56="power",IFERROR(INDEX(power_devig($L22,$M22,$N22),2,1),P22/$R22),IFERROR(INDEX(shin($L22,$M22,$N22),2,1),P22/$R22))))} -> 0.15930503 | U22: {=IF($R22="","",IF(Method!$B$56="proportional",Q22/$R22,IF(Method!$B$56="power",IFERROR(INDEX(power_devig($L22,$M22,$N22),3,1),Q22/$R22),IFERROR(INDEX(shin($L22,$M22,$N22),3,1),Q22/$R22))))} -> 0.076596213 | V22: =IF(S22="","",Method!$B$4*IF(BC22="",I22,BC22)+(1-Method!$B$4)*S22/($S22+$T22+$U22)) -> 0.7017571 | W22: =IF(T22="","",Method!$B$4*IF(BD22="",J22,BD22)+(1-Method!$B$4)*T22/($S22+$T22+$U22)) -> 0.20029304 | X22: =IF(U22="","",Method!$B$4*IF(BE22="",K22,BE22)+(1-Method!$B$4)*U22/($S22+$T22+$U22)) -> 0.097949864 | Y22: =IF(V22="","",V22*L22-1) -> -0.09473334 | Z22: =IF(W22="","",W22*M22-1) -> 0.20175821 | AA22: =IF(X22="","",X22*N22-1) -> 0.17539837 | AB22: =IF(Y22="","",MATCH(MAX(Y22:AA22),Y22:AA22,0)) -> 2 | AC22: =IF(AB22="","",CHOOSE(AB22,"H","D","A")) -> D | AD22: =IF(AB22="","",CHOOSE(AB22,"1 "&D22,"X Draw","2 "&E22)) -> X Draw | AE22: =IF(AB22="","",INDEX(L22:N22,1,AB22)) -> 6 | AF22: =IF(AB22="","",INDEX(Y22:AA22,1,AB22)) -> 0.20175821 | AG22: =IF(AB22="","",INDEX(V22:X22,1,AB22)-INDEX(S22:U22,1,AB22)) -> 0.040988001 | AH22: {=IF(AB22="","· enter odds",IF(OR(AF22>Method!$B$87,IFERROR(INDEX(BC22:BE22,1,AB22)/INDEX(S22:U22,1,AB22),0)>Method!$B$88),"PASS",IF(AND(AF22>=Method!$B$7,AG22>=Method!$B$8),"BET","PASS")))} -> BET | AI22: =IF(AH22<>"BET",0,ROUND(MIN(Method!$B$6,Method!$B$5*AL22)*100,1)) -> 1 | AJ22: =IF(OR(AH22<>"BET",Method!$B$55=TRUE()),0,IF(AI22*Method!$B$10/100<Method!$B$9,0,ROUND(AI22*Method!$B$10/100,0))) -> 10 | AK22: =IF(AB22="","",INDEX(V22:X22,1,AB22)) -> 0.20029304 | AL22: =IF(AH22<>"BET","",MAX(0,(AK22*AE22-1)/(AE22-1))) -> 0.040351643 | AM22: =IF(AH22="BET",AF22+A22/1000000,"") -> 0.20177921 | AN22: =IF(Matchday!N24="","",Matchday!N24) | AO22: =IF(Matchday!P24="","",Matchday!P24) | AP22: =IF(Matchday!Q24="","",Matchday!Q24) | AQ22: =IF(Matchday!R24="","",Matchday!R24) -> D | AR22: =IF(OR(AN22<>"Y",AQ22="",AV22=""),"",IF(AQ22="Void",0,IF(AQ22=AV22,ROUND(AP22*(AO22-1),2),-AP22))) | AS22: =IF(AR22="","",SUM($AR$2:AR22)) | AT22: =IFERROR(__xludf.DUMMYFUNCTION("IF(AB22="""",""Type the 3 odds on the Matchday tab"",IF(Method!$B$55=TRUE(),IF(Method!$B$81=TRUE(),IF(REGEXMATCH(LOWER(Method!$B$63),""circuit""),""🛑 PAUSED — circuit breaker upstream; wait for a clean live refresh."",IF(REGEXMATCH(LOWER(Method!$B$63),"""&"pipeline""),""🛑 PAUSED — live pipeline warning; check Live!B11/Method!B62 before betting."",IF(REGEXMATCH(LOWER(Method!$B$63),""missing""),""🛑 PAUSED — feed timestamp missing; refresh feed before betting."",""🛑 PAUSED — feed stale > 25 min — check Live"&" tab; refresh feed before betting.""))),IF(Method!$B$51>=Method!$B$52,""🛑 PAUSED — drawdown ""&TEXT(Method!$B$51,""0.0%"")&"" ≥ ""&TEXT(Method!$B$52,""0.0%"")&"". Set Method!B54=Y to override."",""🛑 PAUSED — see Method!B62/B63/B81 for cause; do not over"&"ride stale/circuit-breaker/pipeline pauses."")),IF(AH22=""BET"",IF(AJ22=0,""Edge found but stake rounds under £""&Method!$B$9&"" — skip"",IF(AND(AE22>=6,AG22>=0.15),""🟡 WAIT — long-shot review: odds ""&TEXT(AE22,""0.00"")&"" + edge ""&TEXT(AG22,""0.0%"")"&"&"" — verify sharp-book + team news + stake comfort before Placed=Y"",""Value found: EV ""&TEXT(AF22,""0.0%"")&"", edge ""&TEXT(AG22,""0.0%""))),IF(OR(AF22>Method!$B$87,IFERROR(INDEX(BC22:BE22,1,AB22)/INDEX(S22:U22,1,AB22),0)>Method!$B$88),""🛑 Tail trap "&"— auto-PASS · EV ""&TEXT(AF22,""0.0%"")&"" (cap ""&TEXT(Method!$B$87,""0%"")&"") · model/market ""&TEXT(IFERROR(INDEX(BC22:BE22,1,AB22)/INDEX(S22:U22,1,AB22),0),""0.0"")&""× (cap ""&TEXT(Method!$B$88,""0.0"")&""×)"",IF(AF22<Method!$B$7,""Price too short —"&" EV ""&TEXT(AF22,""0.0%"")&"" (need ""&TEXT(Method!$B$7,""0.0%"")&""+)"",""Model ≈ market — edge ""&TEXT(AG22,""0.0%"")&"" (need ""&TEXT(Method!$B$8,""0.0%"")&""+)"")))))"),"Value found: EV 20.2%, edge 4.1%") -> Value found: EV 20.2%, edge 4.1% | AU22: =IF(AN22<>"Y","",IF(AH22="· enter odds","⚠ type the 3 odds (1/X/2) to grade this bet",IF(OR(AV22="",AO22="",AP22=""),"⚠ log backed pick, odds & stake",IF(AZ22<>"BET","⚠ FUN BET — engine said pass · staked £"&AP22&" vs engine £"&BA22,IF(AV22<>IF(AY22="",AC22,AY22),"⚠ backed "&AV22&" but engine pick was "&IF(AY22="",AC22,AY22),IF(AP22>BA22,"⚠ stake over engine £"&BA22,IF(ABS(AO22-IFERROR(INDEX(L22:N22,1,MATCH(AV22,{"H","D","A"},0)),AE22))>0.02,"⚠ odds moved — re-check value","✓ engine bet"))))))) | AV22: =IF(Matchday!O24="","",Matchday!O24) | AZ22: =IF(AW22="",AH22,AW22) -> BET | BA22: =IF(AX22<>"",AX22,IF(AH22<>"BET",0,IF(AI22*Method!$B$10/100<Method!$B$9,0,ROUND(AI22*Method!$B$10/100,0)))) -> 10 | BB22: -9.27 | BC22: 0.58597975 | BD22: 0.27641361 | BE22: 0.13760664 | BF22: DR Congo team-wide: -7 · Portugal team-wide: -2 | BG22: 15 | BH22: very_hot_humid_indoor | BI22: 0
A23: 22 | B23: 46190 | C23: L | D23: England | E23: Croatia | F23: Arlington | G23: 0.625 | H23: 0.875 | I23: 0.4391313 | J23: 0.29561722 | K23: 0.26525148 | L23: =IF(Matchday!E25="","",Matchday!E25) -> 1.7 | M23: =IF(Matchday!F25="","",Matchday!F25) -> 3.9 | N23: =IF(Matchday!G25="","",Matchday!G25) -> 5.6 | O23: =IF(L23="","",1/L23) -> 0.58823529 | P23: =IF(M23="","",1/M23) -> 0.25641026 | Q23: =IF(N23="","",1/N23) -> 0.17857143 | R23: =IF(COUNT(L23:N23)<3,"",O23+P23+Q23) -> 1.023217 | S23: {=IF($R23="","",IF(Method!$B$56="proportional",O23/$R23,IF(Method!$B$56="power",IFERROR(INDEX(power_devig($L23,$M23,$N23),1,1),O23/$R23),IFERROR(INDEX(shin($L23,$M23,$N23),1,1),O23/$R23))))} -> 0.57907656 | T23: {=IF($R23="","",IF(Method!$B$56="proportional",P23/$R23,IF(Method!$B$56="power",IFERROR(INDEX(power_devig($L23,$M23,$N23),2,1),P23/$R23),IFERROR(INDEX(shin($L23,$M23,$N23),2,1),P23/$R23))))} -> 0.24914833 | U23: {=IF($R23="","",IF(Method!$B$56="proportional",Q23/$R23,IF(Method!$B$56="power",IFERROR(INDEX(power_devig($L23,$M23,$N23),3,1),Q23/$R23),IFERROR(INDEX(shin($L23,$M23,$N23),3,1),Q23/$R23))))} -> 0.17177511 | V23: =IF(S23="","",Method!$B$4*IF(BC23="",I23,BC23)+(1-Method!$B$4)*S23/($S23+$T23+$U23)) -> 0.53288791 | W23: =IF(T23="","",Method!$B$4*IF(BD23="",J23,BD23)+(1-Method!$B$4)*T23/($S23+$T23+$U23)) -> 0.25482099 | X23: =IF(U23="","",Method!$B$4*IF(BE23="",K23,BE23)+(1-Method!$B$4)*U23/($S23+$T23+$U23)) -> 0.2122911 | Y23: =IF(V23="","",V23*L23-1) -> -0.094090555 | Z23: =IF(W23="","",W23*M23-1) -> -0.0061981522 | AA23: =IF(X23="","",X23*N23-1) -> 0.18883018 | AB23: =IF(Y23="","",MATCH(MAX(Y23:AA23),Y23:AA23,0)) -> 3 | AC23: =IF(AB23="","",CHOOSE(AB23,"H","D","A")) -> A | AD23: =IF(AB23="","",CHOOSE(AB23,"1 "&D23,"X Draw","2 "&E23)) -> 2 Croatia | AE23: =IF(AB23="","",INDEX(L23:N23,1,AB23)) -> 5.6 | AF23: =IF(AB23="","",INDEX(Y23:AA23,1,AB23)) -> 0.18883018 | AG23: =IF(AB23="","",INDEX(V23:X23,1,AB23)-INDEX(S23:U23,1,AB23)) -> 0.040515993 | AH23: {=IF(AB23="","· enter odds",IF(OR(AF23>Method!$B$87,IFERROR(INDEX(BC23:BE23,1,AB23)/INDEX(S23:U23,1,AB23),0)>Method!$B$88),"PASS",IF(AND(AF23>=Method!$B$7,AG23>=Method!$B$8),"BET","PASS")))} -> BET | AI23: =IF(AH23<>"BET",0,ROUND(MIN(Method!$B$6,Method!$B$5*AL23)*100,1)) -> 1 | AJ23: =IF(OR(AH23<>"BET",Method!$B$55=TRUE()),0,IF(AI23*Method!$B$10/100<Method!$B$9,0,ROUND(AI23*Method!$B$10/100,0))) -> 10 | AK23: =IF(AB23="","",INDEX(V23:X23,1,AB23)) -> 0.2122911 | AL23: =IF(AH23<>"BET","",MAX(0,(AK23*AE23-1)/(AE23-1))) -> 0.04105004 | AM23: =IF(AH23="BET",AF23+A23/1000000,"") -> 0.18885218 | AN23: =IF(Matchday!N25="","",Matchday!N25) | AO23: =IF(Matchday!P25="","",Matchday!P25) | AP23: =IF(Matchday!Q25="","",Matchday!Q25) | AQ23: =IF(Matchday!R25="","",Matchday!R25) -> H | AR23: =IF(OR(AN23<>"Y",AQ23="",AV23=""),"",IF(AQ23="Void",0,IF(AQ23=AV23,ROUND(AP23*(AO23-1),2),-AP23))) | AS23: =IF(AR23="","",SUM($AR$2:AR23)) | AT23: =IFERROR(__xludf.DUMMYFUNCTION("IF(AB23="""",""Type the 3 odds on the Matchday tab"",IF(Method!$B$55=TRUE(),IF(Method!$B$81=TRUE(),IF(REGEXMATCH(LOWER(Method!$B$63),""circuit""),""🛑 PAUSED — circuit breaker upstream; wait for a clean live refresh."",IF(REGEXMATCH(LOWER(Method!$B$63),"""&"pipeline""),""🛑 PAUSED — live pipeline warning; check Live!B11/Method!B62 before betting."",IF(REGEXMATCH(LOWER(Method!$B$63),""missing""),""🛑 PAUSED — feed timestamp missing; refresh feed before betting."",""🛑 PAUSED — feed stale > 25 min — check Live"&" tab; refresh feed before betting.""))),IF(Method!$B$51>=Method!$B$52,""🛑 PAUSED — drawdown ""&TEXT(Method!$B$51,""0.0%"")&"" ≥ ""&TEXT(Method!$B$52,""0.0%"")&"". Set Method!B54=Y to override."",""🛑 PAUSED — see Method!B62/B63/B81 for cause; do not over"&"ride stale/circuit-breaker/pipeline pauses."")),IF(AH23=""BET"",IF(AJ23=0,""Edge found but stake rounds under £""&Method!$B$9&"" — skip"",IF(AND(AE23>=6,AG23>=0.15),""🟡 WAIT — long-shot review: odds ""&TEXT(AE23,""0.00"")&"" + edge ""&TEXT(AG23,""0.0%"")"&"&"" — verify sharp-book + team news + stake comfort before Placed=Y"",""Value found: EV ""&TEXT(AF23,""0.0%"")&"", edge ""&TEXT(AG23,""0.0%""))),IF(OR(AF23>Method!$B$87,IFERROR(INDEX(BC23:BE23,1,AB23)/INDEX(S23:U23,1,AB23),0)>Method!$B$88),""🛑 Tail trap "&"— auto-PASS · EV ""&TEXT(AF23,""0.0%"")&"" (cap ""&TEXT(Method!$B$87,""0%"")&"") · model/market ""&TEXT(IFERROR(INDEX(BC23:BE23,1,AB23)/INDEX(S23:U23,1,AB23),0),""0.0"")&""× (cap ""&TEXT(Method!$B$88,""0.0"")&""×)"",IF(AF23<Method!$B$7,""Price too short —"&" EV ""&TEXT(AF23,""0.0%"")&"" (need ""&TEXT(Method!$B$7,""0.0%"")&""+)"",""Model ≈ market — edge ""&TEXT(AG23,""0.0%"")&"" (need ""&TEXT(Method!$B$8,""0.0%"")&""+)"")))))"),"Value found: EV 18.9%, edge 4.1%") -> Value found: EV 18.9%, edge 4.1% | AU23: =IF(AN23<>"Y","",IF(AH23="· enter odds","⚠ type the 3 odds (1/X/2) to grade this bet",IF(OR(AV23="",AO23="",AP23=""),"⚠ log backed pick, odds & stake",IF(AZ23<>"BET","⚠ FUN BET — engine said pass · staked £"&AP23&" vs engine £"&BA23,IF(AV23<>IF(AY23="",AC23,AY23),"⚠ backed "&AV23&" but engine pick was "&IF(AY23="",AC23,AY23),IF(AP23>BA23,"⚠ stake over engine £"&BA23,IF(ABS(AO23-IFERROR(INDEX(L23:N23,1,MATCH(AV23,{"H","D","A"},0)),AE23))>0.02,"⚠ odds moved — re-check value","✓ engine bet"))))))) | AV23: =IF(Matchday!O25="","",Matchday!O25) | AZ23: =IF(AW23="",AH23,AW23) -> BET | BA23: =IF(AX23<>"",AX23,IF(AH23<>"BET",0,IF(AI23*Method!$B$10/100<Method!$B$9,0,ROUND(AI23*Method!$B$10/100,0)))) -> 10 | BB23: -14.17 | BC23: 0.44710898 | BD23: 0.26535593 | BE23: 0.28753509 | BF23: Croatia team-wide: -2 · England team-wide: -13 | BG23: 175 | BH23: very_hot_indoor | BI23: 0
A24: 23 | B24: 46190 | C24: L | D24: Ghana | E24: Panama | F24: Toronto | G24: 0.79166667 | H24: 00:00 +1d | I24: 0.270729 | J24: 0.284414 | K24: 0.444857 | L24: =IF(Matchday!E26="","",Matchday!E26) -> 2.38 | M24: =IF(Matchday!F26="","",Matchday!F26) -> 3.25 | N24: =IF(Matchday!G26="","",Matchday!G26) -> 3.38 | O24: =IF(L24="","",1/L24) -> 0.42016807 | P24: =IF(M24="","",1/M24) -> 0.30769231 | Q24: =IF(N24="","",1/N24) -> 0.29585799 | R24: =IF(COUNT(L24:N24)<3,"",O24+P24+Q24) -> 1.0237184 | S24: {=IF($R24="","",IF(Method!$B$56="proportional",O24/$R24,IF(Method!$B$56="power",IFERROR(INDEX(power_devig($L24,$M24,$N24),1,1),O24/$R24),IFERROR(INDEX(shin($L24,$M24,$N24),1,1),O24/$R24))))} -> 0.41179783 | T24: {=IF($R24="","",IF(Method!$B$56="proportional",P24/$R24,IF(Method!$B$56="power",IFERROR(INDEX(power_devig($L24,$M24,$N24),2,1),P24/$R24),IFERROR(INDEX(shin($L24,$M24,$N24),2,1),P24/$R24))))} -> 0.29998312 | U24: {=IF($R24="","",IF(Method!$B$56="proportional",Q24/$R24,IF(Method!$B$56="power",IFERROR(INDEX(power_devig($L24,$M24,$N24),3,1),Q24/$R24),IFERROR(INDEX(shin($L24,$M24,$N24),3,1),Q24/$R24))))} -> 0.28821905 | V24: =IF(S24="","",Method!$B$4*IF(BC24="",I24,BC24)+(1-Method!$B$4)*S24/($S24+$T24+$U24)) -> 0.36212537 | W24: =IF(T24="","",Method!$B$4*IF(BD24="",J24,BD24)+(1-Method!$B$4)*T24/($S24+$T24+$U24)) -> 0.29174834 | X24: =IF(U24="","",Method!$B$4*IF(BE24="",K24,BE24)+(1-Method!$B$4)*U24/($S24+$T24+$U24)) -> 0.34612629 | Y24: =IF(V24="","",V24*L24-1) -> -0.13814162 | Z24: =IF(W24="","",W24*M24-1) -> -0.051817891 | AA24: =IF(X24="","",X24*N24-1) -> 0.16990685 | AB24: =IF(Y24="","",MATCH(MAX(Y24:AA24),Y24:AA24,0)) -> 3 | AC24: =IF(AB24="","",CHOOSE(AB24,"H","D","A")) -> A | AD24: =IF(AB24="","",CHOOSE(AB24,"1 "&D24,"X Draw","2 "&E24)) -> 2 Panama | AE24: =IF(AB24="","",INDEX(L24:N24,1,AB24)) -> 3.38 | AF24: =IF(AB24="","",INDEX(Y24:AA24,1,AB24)) -> 0.16990685 | AG24: =IF(AB24="","",INDEX(V24:X24,1,AB24)-INDEX(S24:U24,1,AB24)) -> 0.057907237 | AH24: {=IF(AB24="","· enter odds",IF(OR(AF24>Method!$B$87,IFERROR(INDEX(BC24:BE24,1,AB24)/INDEX(S24:U24,1,AB24),0)>Method!$B$88),"PASS",IF(AND(AF24>=Method!$B$7,AG24>=Method!$B$8),"BET","PASS")))} -> BET | AI24: =IF(AH24<>"BET",0,ROUND(MIN(Method!$B$6,Method!$B$5*AL24)*100,1)) -> 1.8 | AJ24: =IF(OR(AH24<>"BET",Method!$B$55=TRUE()),0,IF(AI24*Method!$B$10/100<Method!$B$9,0,ROUND(AI24*Method!$B$10/100,0))) -> 17 | AK24: =IF(AB24="","",INDEX(V24:X24,1,AB24)) -> 0.34612629 | AL24: =IF(AH24<>"BET","",MAX(0,(AK24*AE24-1)/(AE24-1))) -> 0.071389435 | AM24: =IF(AH24="BET",AF24+A24/1000000,"") -> 0.16992985 | AN24: =IF(Matchday!N26="","",Matchday!N26) | AO24: =IF(Matchday!P26="","",Matchday!P26) | AP24: =IF(Matchday!Q26="","",Matchday!Q26) | AQ24: =IF(Matchday!R26="","",Matchday!R26) -> H | AR24: =IF(OR(AN24<>"Y",AQ24="",AV24=""),"",IF(AQ24="Void",0,IF(AQ24=AV24,ROUND(AP24*(AO24-1),2),-AP24))) | AS24: =IF(AR24="","",SUM($AR$2:AR24)) | AT24: =IFERROR(__xludf.DUMMYFUNCTION("IF(AB24="""",""Type the 3 odds on the Matchday tab"",IF(Method!$B$55=TRUE(),IF(Method!$B$81=TRUE(),IF(REGEXMATCH(LOWER(Method!$B$63),""circuit""),""🛑 PAUSED — circuit breaker upstream; wait for a clean live refresh."",IF(REGEXMATCH(LOWER(Method!$B$63),"""&"pipeline""),""🛑 PAUSED — live pipeline warning; check Live!B11/Method!B62 before betting."",IF(REGEXMATCH(LOWER(Method!$B$63),""missing""),""🛑 PAUSED — feed timestamp missing; refresh feed before betting."",""🛑 PAUSED — feed stale > 25 min — check Live"&" tab; refresh feed before betting.""))),IF(Method!$B$51>=Method!$B$52,""🛑 PAUSED — drawdown ""&TEXT(Method!$B$51,""0.0%"")&"" ≥ ""&TEXT(Method!$B$52,""0.0%"")&"". Set Method!B54=Y to override."",""🛑 PAUSED — see Method!B62/B63/B81 for cause; do not over"&"ride stale/circuit-breaker/pipeline pauses."")),IF(AH24=""BET"",IF(AJ24=0,""Edge found but stake rounds under £""&Method!$B$9&"" — skip"",IF(AND(AE24>=6,AG24>=0.15),""🟡 WAIT — long-shot review: odds ""&TEXT(AE24,""0.00"")&"" + edge ""&TEXT(AG24,""0.0%"")"&"&"" — verify sharp-book + team news + stake comfort before Placed=Y"",""Value found: EV ""&TEXT(AF24,""0.0%"")&"", edge ""&TEXT(AG24,""0.0%""))),IF(OR(AF24>Method!$B$87,IFERROR(INDEX(BC24:BE24,1,AB24)/INDEX(S24:U24,1,AB24),0)>Method!$B$88),""🛑 Tail trap "&"— auto-PASS · EV ""&TEXT(AF24,""0.0%"")&"" (cap ""&TEXT(Method!$B$87,""0%"")&"") · model/market ""&TEXT(IFERROR(INDEX(BC24:BE24,1,AB24)/INDEX(S24:U24,1,AB24),0),""0.0"")&""× (cap ""&TEXT(Method!$B$88,""0.0"")&""×)"",IF(AF24<Method!$B$7,""Price too short —"&" EV ""&TEXT(AF24,""0.0%"")&"" (need ""&TEXT(Method!$B$7,""0.0%"")&""+)"",""Model ≈ market — edge ""&TEXT(AG24,""0.0%"")&"" (need ""&TEXT(Method!$B$8,""0.0%"")&""+)"")))))"),"Value found: EV 17.0%, edge 5.8%") -> Value found: EV 17.0%, edge 5.8% | AU24: =IF(AN24<>"Y","",IF(AH24="· enter odds","⚠ type the 3 odds (1/X/2) to grade this bet",IF(OR(AV24="",AO24="",AP24=""),"⚠ log backed pick, odds & stake",IF(AZ24<>"BET","⚠ FUN BET — engine said pass · staked £"&AP24&" vs engine £"&BA24,IF(AV24<>IF(AY24="",AC24,AY24),"⚠ backed "&AV24&" but engine pick was "&IF(AY24="",AC24,AY24),IF(AP24>BA24,"⚠ stake over engine £"&BA24,IF(ABS(AO24-IFERROR(INDEX(L24:N24,1,MATCH(AV24,{"H","D","A"},0)),AE24))>0.02,"⚠ odds moved — re-check value","✓ engine bet"))))))) | AV24: =IF(Matchday!O26="","",Matchday!O26) | AZ24: =IF(AW24="",AH24,AW24) -> BET | BA24: =IF(AX24<>"",AX24,IF(AH24<>"BET",0,IF(AI24*Method!$B$10/100<Method!$B$9,0,ROUND(AI24*Method!$B$10/100,0)))) -> 17 | BB24: -13.35 | BC24: 0.26987652 | BD24: 0.27645518 | BE24: 0.4536683 | BF24: Ghana team-wide: -11 · Panama team-wide: -2 | BG24: 76 | BH24: mild | BI24: 0
A25: 24 | B25: 46190 | C25: K | D25: Uzbekistan | E25: Colombia | F25: Mexico City | G25: 0.83333333 | H25: 03:00 +1d | I25: 0.13317697 | J25: 0.23780852 | K25: 0.62901451 | L25: =IF(Matchday!E27="","",Matchday!E27) -> 11.5 | M25: =IF(Matchday!F27="","",Matchday!F27) -> 5.5 | N25: =IF(Matchday!G27="","",Matchday!G27) -> 1.37 | O25: =IF(L25="","",1/L25) -> 0.086956522 | P25: =IF(M25="","",1/M25) -> 0.18181818 | Q25: =IF(N25="","",1/N25) -> 0.72992701 | R25: =IF(COUNT(L25:N25)<3,"",O25+P25+Q25) -> 0.99870171 | S25: {=IF($R25="","",IF(Method!$B$56="proportional",O25/$R25,IF(Method!$B$56="power",IFERROR(INDEX(power_devig($L25,$M25,$N25),1,1),O25/$R25),IFERROR(INDEX(shin($L25,$M25,$N25),1,1),O25/$R25))))} -> 0.087069563 | T25: {=IF($R25="","",IF(Method!$B$56="proportional",P25/$R25,IF(Method!$B$56="power",IFERROR(INDEX(power_devig($L25,$M25,$N25),2,1),P25/$R25),IFERROR(INDEX(shin($L25,$M25,$N25),2,1),P25/$R25))))} -> 0.18205454 | U25: {=IF($R25="","",IF(Method!$B$56="proportional",Q25/$R25,IF(Method!$B$56="power",IFERROR(INDEX(power_devig($L25,$M25,$N25),3,1),Q25/$R25),IFERROR(INDEX(shin($L25,$M25,$N25),3,1),Q25/$R25))))} -> 0.7308759 | V25: =IF(S25="","",Method!$B$4*IF(BC25="",I25,BC25)+(1-Method!$B$4)*S25/($S25+$T25+$U25)) -> 0.096914467 | W25: =IF(T25="","",Method!$B$4*IF(BD25="",J25,BD25)+(1-Method!$B$4)*T25/($S25+$T25+$U25)) -> 0.21171154 | X25: =IF(U25="","",Method!$B$4*IF(BE25="",K25,BE25)+(1-Method!$B$4)*U25/($S25+$T25+$U25)) -> 0.69137399 | Y25: =IF(V25="","",V25*L25-1) -> 0.11451637 | Z25: =IF(W25="","",W25*M25-1) -> 0.16441347 | AA25: =IF(X25="","",X25*N25-1) -> -0.052817629 | AB25: =IF(Y25="","",MATCH(MAX(Y25:AA25),Y25:AA25,0)) -> 2 | AC25: =IF(AB25="","",CHOOSE(AB25,"H","D","A")) -> D | AD25: =IF(AB25="","",CHOOSE(AB25,"1 "&D25,"X Draw","2 "&E25)) -> X Draw | AE25: =IF(AB25="","",INDEX(L25:N25,1,AB25)) -> 5.5 | AF25: =IF(AB25="","",INDEX(Y25:AA25,1,AB25)) -> 0.16441347 | AG25: =IF(AB25="","",INDEX(V25:X25,1,AB25)-INDEX(S25:U25,1,AB25)) -> 0.029656998 | AH25: {=IF(AB25="","· enter odds",IF(OR(AF25>Method!$B$87,IFERROR(INDEX(BC25:BE25,1,AB25)/INDEX(S25:U25,1,AB25),0)>Method!$B$88),"PASS",IF(AND(AF25>=Method!$B$7,AG25>=Method!$B$8),"BET","PASS")))} -> BET | AI25: =IF(AH25<>"BET",0,ROUND(MIN(Method!$B$6,Method!$B$5*AL25)*100,1)) -> 0.9 | AJ25: =IF(OR(AH25<>"BET",Method!$B$55=TRUE()),0,IF(AI25*Method!$B$10/100<Method!$B$9,0,ROUND(AI25*Method!$B$10/100,0))) -> 9 | AK25: =IF(AB25="","",INDEX(V25:X25,1,AB25)) -> 0.21171154 | AL25: =IF(AH25<>"BET","",MAX(0,(AK25*AE25-1)/(AE25-1))) -> 0.036536326 | AM25: =IF(AH25="BET",AF25+A25/1000000,"") -> 0.16443747 | AN25: =IF(Matchday!N27="","",Matchday!N27) | AO25: =IF(Matchday!P27="","",Matchday!P27) | AP25: =IF(Matchday!Q27="","",Matchday!Q27) | AQ25: =IF(Matchday!R27="","",Matchday!R27) -> A | AR25: =IF(OR(AN25<>"Y",AQ25="",AV25=""),"",IF(AQ25="Void",0,IF(AQ25=AV25,ROUND(AP25*(AO25-1),2),-AP25))) | AS25: =IF(AR25="","",SUM($AR$2:AR25)) | AT25: =IFERROR(__xludf.DUMMYFUNCTION("IF(AB25="""",""Type the 3 odds on the Matchday tab"",IF(Method!$B$55=TRUE(),IF(Method!$B$81=TRUE(),IF(REGEXMATCH(LOWER(Method!$B$63),""circuit""),""🛑 PAUSED — circuit breaker upstream; wait for a clean live refresh."",IF(REGEXMATCH(LOWER(Method!$B$63),"""&"pipeline""),""🛑 PAUSED — live pipeline warning; check Live!B11/Method!B62 before betting."",IF(REGEXMATCH(LOWER(Method!$B$63),""missing""),""🛑 PAUSED — feed timestamp missing; refresh feed before betting."",""🛑 PAUSED — feed stale > 25 min — check Live"&" tab; refresh feed before betting.""))),IF(Method!$B$51>=Method!$B$52,""🛑 PAUSED — drawdown ""&TEXT(Method!$B$51,""0.0%"")&"" ≥ ""&TEXT(Method!$B$52,""0.0%"")&"". Set Method!B54=Y to override."",""🛑 PAUSED — see Method!B62/B63/B81 for cause; do not over"&"ride stale/circuit-breaker/pipeline pauses."")),IF(AH25=""BET"",IF(AJ25=0,""Edge found but stake rounds under £""&Method!$B$9&"" — skip"",IF(AND(AE25>=6,AG25>=0.15),""🟡 WAIT — long-shot review: odds ""&TEXT(AE25,""0.00"")&"" + edge ""&TEXT(AG25,""0.0%"")"&"&"" — verify sharp-book + team news + stake comfort before Placed=Y"",""Value found: EV ""&TEXT(AF25,""0.0%"")&"", edge ""&TEXT(AG25,""0.0%""))),IF(OR(AF25>Method!$B$87,IFERROR(INDEX(BC25:BE25,1,AB25)/INDEX(S25:U25,1,AB25),0)>Method!$B$88),""🛑 Tail trap "&"— auto-PASS · EV ""&TEXT(AF25,""0.0%"")&"" (cap ""&TEXT(Method!$B$87,""0%"")&"") · model/market ""&TEXT(IFERROR(INDEX(BC25:BE25,1,AB25)/INDEX(S25:U25,1,AB25),0),""0.0"")&""× (cap ""&TEXT(Method!$B$88,""0.0"")&""×)"",IF(AF25<Method!$B$7,""Price too short —"&" EV ""&TEXT(AF25,""0.0%"")&"" (need ""&TEXT(Method!$B$7,""0.0%"")&""+)"",""Model ≈ market — edge ""&TEXT(AG25,""0.0%"")&"" (need ""&TEXT(Method!$B$8,""0.0%"")&""+)"")))))"),"Value found: EV 16.4%, edge 3.0%") -> Value found: EV 16.4%, edge 3.0% | AU25: =IF(AN25<>"Y","",IF(AH25="· enter odds","⚠ type the 3 odds (1/X/2) to grade this bet",IF(OR(AV25="",AO25="",AP25=""),"⚠ log backed pick, odds & stake",IF(AZ25<>"BET","⚠ FUN BET — engine said pass · staked £"&AP25&" vs engine £"&BA25,IF(AV25<>IF(AY25="",AC25,AY25),"⚠ backed "&AV25&" but engine pick was "&IF(AY25="",AC25,AY25),IF(AP25>BA25,"⚠ stake over engine £"&BA25,IF(ABS(AO25-IFERROR(INDEX(L25:N25,1,MATCH(AV25,{"H","D","A"},0)),AE25))>0.02,"⚠ odds moved — re-check value","✓ engine bet"))))))) | AV25: =IF(Matchday!O27="","",Matchday!O27) | AZ25: =IF(AW25="",AH25,AW25) -> BET | BA25: =IF(AX25<>"",AX25,IF(AH25<>"BET",0,IF(AI25*Method!$B$10/100<Method!$B$9,0,ROUND(AI25*Method!$B$10/100,0)))) -> 9 | BB25: -5.07 | BC25: 0.11519786 | BD25: 0.26678882 | BE25: 0.61801332 | BF25: Colombia team-wide: +3 · Uzbekistan team-wide: -8 | BG25: 2240 | BH25: high_altitude_mild | BI25: 0
A26: 25 | B26: 46191 | C26: A | D26: Czechia | E26: South Africa | F26: Atlanta | G26: 0.5 | H26: 0.70833333 | I26: 0.49512518 | J26: 0.30227368 | K26: 0.20260114 | L26: =IF(Matchday!E28="","",Matchday!E28) -> 1.9 | M26: =IF(Matchday!F28="","",Matchday!F28) -> 3.55 | N26: =IF(Matchday!G28="","",Matchday!G28) -> 4.55 | O26: =IF(L26="","",1/L26) -> 0.52631579 | P26: =IF(M26="","",1/M26) -> 0.28169014 | Q26: =IF(N26="","",1/N26) -> 0.21978022 | R26: =IF(COUNT(L26:N26)<3,"",O26+P26+Q26) -> 1.0277862 | S26: {=IF($R26="","",IF(Method!$B$56="proportional",O26/$R26,IF(Method!$B$56="power",IFERROR(INDEX(power_devig($L26,$M26,$N26),1,1),O26/$R26),IFERROR(INDEX(shin($L26,$M26,$N26),1,1),O26/$R26))))} -> 0.51579236 | T26: {=IF($R26="","",IF(Method!$B$56="proportional",P26/$R26,IF(Method!$B$56="power",IFERROR(INDEX(power_devig($L26,$M26,$N26),2,1),P26/$R26),IFERROR(INDEX(shin($L26,$M26,$N26),2,1),P26/$R26))))} -> 0.27283977 | U26: {=IF($R26="","",IF(Method!$B$56="proportional",Q26/$R26,IF(Method!$B$56="power",IFERROR(INDEX(power_devig($L26,$M26,$N26),3,1),Q26/$R26),IFERROR(INDEX(shin($L26,$M26,$N26),3,1),Q26/$R26))))} -> 0.21136787 | V26: =IF(S26="","",Method!$B$4*IF(BC26="",I26,BC26)+(1-Method!$B$4)*S26/($S26+$T26+$U26)) -> 0.51473405 | W26: =IF(T26="","",Method!$B$4*IF(BD26="",J26,BD26)+(1-Method!$B$4)*T26/($S26+$T26+$U26)) -> 0.27043285 | X26: =IF(U26="","",Method!$B$4*IF(BE26="",K26,BE26)+(1-Method!$B$4)*U26/($S26+$T26+$U26)) -> 0.2148331 | Y26: =IF(V26="","",V26*L26-1) -> -0.022005314 | Z26: =IF(W26="","",W26*M26-1) -> -0.039963381 | AA26: =IF(X26="","",X26*N26-1) -> -0.022509376 | AB26: =IF(Y26="","",MATCH(MAX(Y26:AA26),Y26:AA26,0)) -> 1 | AC26: =IF(AB26="","",CHOOSE(AB26,"H","D","A")) -> H | AD26: =IF(AB26="","",CHOOSE(AB26,"1 "&D26,"X Draw","2 "&E26)) -> 1 Czechia | AE26: =IF(AB26="","",INDEX(L26:N26,1,AB26)) -> 1.9 | AF26: =IF(AB26="","",INDEX(Y26:AA26,1,AB26)) -> -0.022005314 | AG26: =IF(AB26="","",INDEX(V26:X26,1,AB26)-INDEX(S26:U26,1,AB26)) -> -0.0010583156 | AH26: {=IF(AB26="","· enter odds",IF(OR(AF26>Method!$B$87,IFERROR(INDEX(BC26:BE26,1,AB26)/INDEX(S26:U26,1,AB26),0)>Method!$B$88),"PASS",IF(AND(AF26>=Method!$B$7,AG26>=Method!$B$8),"BET","PASS")))} -> PASS | AI26: =IF(AH26<>"BET",0,ROUND(MIN(Method!$B$6,Method!$B$5*AL26)*100,1)) -> 0 | AJ26: =IF(OR(AH26<>"BET",Method!$B$55=TRUE()),0,IF(AI26*Method!$B$10/100<Method!$B$9,0,ROUND(AI26*Method!$B$10/100,0))) -> 0 | AK26: =IF(AB26="","",INDEX(V26:X26,1,AB26)) -> 0.51473405 | AL26: =IF(AH26<>"BET","",MAX(0,(AK26*AE26-1)/(AE26-1))) | AM26: =IF(AH26="BET",AF26+A26/1000000,"") | AN26: =IF(Matchday!N28="","",Matchday!N28) | AO26: =IF(Matchday!P28="","",Matchday!P28) | AP26: =IF(Matchday!Q28="","",Matchday!Q28) | AQ26: =IF(Matchday!R28="","",Matchday!R28) -> D | AR26: =IF(OR(AN26<>"Y",AQ26="",AV26=""),"",IF(AQ26="Void",0,IF(AQ26=AV26,ROUND(AP26*(AO26-1),2),-AP26))) | AS26: =IF(AR26="","",SUM($AR$2:AR26)) | AT26: =IFERROR(__xludf.DUMMYFUNCTION("IF(AB26="""",""Type the 3 odds on the Matchday tab"",IF(Method!$B$55=TRUE(),IF(Method!$B$81=TRUE(),IF(REGEXMATCH(LOWER(Method!$B$63),""circuit""),""🛑 PAUSED — circuit breaker upstream; wait for a clean live refresh."",IF(REGEXMATCH(LOWER(Method!$B$63),"""&"pipeline""),""🛑 PAUSED — live pipeline warning; check Live!B11/Method!B62 before betting."",IF(REGEXMATCH(LOWER(Method!$B$63),""missing""),""🛑 PAUSED — feed timestamp missing; refresh feed before betting."",""🛑 PAUSED — feed stale > 25 min — check Live"&" tab; refresh feed before betting.""))),IF(Method!$B$51>=Method!$B$52,""🛑 PAUSED — drawdown ""&TEXT(Method!$B$51,""0.0%"")&"" ≥ ""&TEXT(Method!$B$52,""0.0%"")&"". Set Method!B54=Y to override."",""🛑 PAUSED — see Method!B62/B63/B81 for cause; do not over"&"ride stale/circuit-breaker/pipeline pauses."")),IF(AH26=""BET"",IF(AJ26=0,""Edge found but stake rounds under £""&Method!$B$9&"" — skip"",IF(AND(AE26>=6,AG26>=0.15),""🟡 WAIT — long-shot review: odds ""&TEXT(AE26,""0.00"")&"" + edge ""&TEXT(AG26,""0.0%"")"&"&"" — verify sharp-book + team news + stake comfort before Placed=Y"",""Value found: EV ""&TEXT(AF26,""0.0%"")&"", edge ""&TEXT(AG26,""0.0%""))),IF(OR(AF26>Method!$B$87,IFERROR(INDEX(BC26:BE26,1,AB26)/INDEX(S26:U26,1,AB26),0)>Method!$B$88),""🛑 Tail trap "&"— auto-PASS · EV ""&TEXT(AF26,""0.0%"")&"" (cap ""&TEXT(Method!$B$87,""0%"")&"") · model/market ""&TEXT(IFERROR(INDEX(BC26:BE26,1,AB26)/INDEX(S26:U26,1,AB26),0),""0.0"")&""× (cap ""&TEXT(Method!$B$88,""0.0"")&""×)"",IF(AF26<Method!$B$7,""Price too short —"&" EV ""&TEXT(AF26,""0.0%"")&"" (need ""&TEXT(Method!$B$7,""0.0%"")&""+)"",""Model ≈ market — edge ""&TEXT(AG26,""0.0%"")&"" (need ""&TEXT(Method!$B$8,""0.0%"")&""+)"")))))"),"Price too short — EV -2.2% (need 2.5%+)") -> Price too short — EV -2.2% (need 2.5%+) | AU26: =IF(AN26<>"Y","",IF(AH26="· enter odds","⚠ type the 3 odds (1/X/2) to grade this bet",IF(OR(AV26="",AO26="",AP26=""),"⚠ log backed pick, odds & stake",IF(AZ26<>"BET","⚠ FUN BET — engine said pass · staked £"&AP26&" vs engine £"&BA26,IF(AV26<>IF(AY26="",AC26,AY26),"⚠ backed "&AV26&" but engine pick was "&IF(AY26="",AC26,AY26),IF(AP26>BA26,"⚠ stake over engine £"&BA26,IF(ABS(AO26-IFERROR(INDEX(L26:N26,1,MATCH(AV26,{"H","D","A"},0)),AE26))>0.02,"⚠ odds moved — re-check value","✓ engine bet"))))))) | AV26: =IF(Matchday!O28="","",Matchday!O28) | AZ26: =IF(AW26="",AH26,AW26) -> PASS | BA26: =IF(AX26<>"",AX26,IF(AH26<>"BET",0,IF(AI26*Method!$B$10/100<Method!$B$9,0,ROUND(AI26*Method!$B$10/100,0)))) -> 0 | BB26: -50.79 | BC26: 0.5127686 | BD26: 0.26596286 | BE26: 0.22126854 | BF26: Czechia team-wide: -16 · South Africa team-wide: -29 · South Africa suspension: -3 · South Africa suspension: -3 | BG26: 320 | BH26: hot_humid_indoor | BI26: 2373.1
A27: 26 | B27: 46191 | C27: B | D27: Switzerland | E27: Bosnia and Herzegovina | F27: Inglewood | G27: 0.625 | H27: 0.95833333 | I27: 0.6767993 | J27: 0.21804428 | K27: 0.10515642 | L27: =IF(Matchday!E29="","",Matchday!E29) -> 1.58 | M27: =IF(Matchday!F29="","",Matchday!F29) -> 4.2 | N27: =IF(Matchday!G29="","",Matchday!G29) -> 6.5 | O27: =IF(L27="","",1/L27) -> 0.63291139 | P27: =IF(M27="","",1/M27) -> 0.23809524 | Q27: =IF(N27="","",1/N27) -> 0.15384615 | R27: =IF(COUNT(L27:N27)<3,"",O27+P27+Q27) -> 1.0248528 | S27: {=IF($R27="","",IF(Method!$B$56="proportional",O27/$R27,IF(Method!$B$56="power",IFERROR(INDEX(power_devig($L27,$M27,$N27),1,1),O27/$R27),IFERROR(INDEX(shin($L27,$M27,$N27),1,1),O27/$R27))))} -> 0.62283791 | T27: {=IF($R27="","",IF(Method!$B$56="proportional",P27/$R27,IF(Method!$B$56="power",IFERROR(INDEX(power_devig($L27,$M27,$N27),2,1),P27/$R27),IFERROR(INDEX(shin($L27,$M27,$N27),2,1),P27/$R27))))} -> 0.23043102 | U27: {=IF($R27="","",IF(Method!$B$56="proportional",Q27/$R27,IF(Method!$B$56="power",IFERROR(INDEX(power_devig($L27,$M27,$N27),3,1),Q27/$R27),IFERROR(INDEX(shin($L27,$M27,$N27),3,1),Q27/$R27))))} -> 0.14673107 | V27: =IF(S27="","",Method!$B$4*IF(BC27="",I27,BC27)+(1-Method!$B$4)*S27/($S27+$T27+$U27)) -> 0.6309298 | W27: =IF(T27="","",Method!$B$4*IF(BD27="",J27,BD27)+(1-Method!$B$4)*T27/($S27+$T27+$U27)) -> 0.23589665 | X27: =IF(U27="","",Method!$B$4*IF(BE27="",K27,BE27)+(1-Method!$B$4)*U27/($S27+$T27+$U27)) -> 0.13317355 | Y27: =IF(V27="","",V27*L27-1) -> -0.0031309084 | Z27: =IF(W27="","",W27*M27-1) -> -0.0092340781 | AA27: =IF(X27="","",X27*N27-1) -> -0.13437194 | AB27: =IF(Y27="","",MATCH(MAX(Y27:AA27),Y27:AA27,0)) -> 1 | AC27: =IF(AB27="","",CHOOSE(AB27,"H","D","A")) -> H | AD27: =IF(AB27="","",CHOOSE(AB27,"1 "&D27,"X Draw","2 "&E27)) -> 1 Switzerland | AE27: =IF(AB27="","",INDEX(L27:N27,1,AB27)) -> 1.58 | AF27: =IF(AB27="","",INDEX(Y27:AA27,1,AB27)) -> -0.0031309084 | AG27: =IF(AB27="","",INDEX(V27:X27,1,AB27)-INDEX(S27:U27,1,AB27)) -> 0.0080918906 | AH27: {=IF(AB27="","· enter odds",IF(OR(AF27>Method!$B$87,IFERROR(INDEX(BC27:BE27,1,AB27)/INDEX(S27:U27,1,AB27),0)>Method!$B$88),"PASS",IF(AND(AF27>=Method!$B$7,AG27>=Method!$B$8),"BET","PASS")))} -> PASS | AI27: =IF(AH27<>"BET",0,ROUND(MIN(Method!$B$6,Method!$B$5*AL27)*100,1)) -> 0 | AJ27: =IF(OR(AH27<>"BET",Method!$B$55=TRUE()),0,IF(AI27*Method!$B$10/100<Method!$B$9,0,ROUND(AI27*Method!$B$10/100,0))) -> 0 | AK27: =IF(AB27="","",INDEX(V27:X27,1,AB27)) -> 0.6309298 | AL27: =IF(AH27<>"BET","",MAX(0,(AK27*AE27-1)/(AE27-1))) | AM27: =IF(AH27="BET",AF27+A27/1000000,"") | AN27: =IF(Matchday!N29="","",Matchday!N29) | AO27: =IF(Matchday!P29="","",Matchday!P29) | AP27: =IF(Matchday!Q29="","",Matchday!Q29) | AQ27: =IF(Matchday!R29="","",Matchday!R29) -> H | AR27: =IF(OR(AN27<>"Y",AQ27="",AV27=""),"",IF(AQ27="Void",0,IF(AQ27=AV27,ROUND(AP27*(AO27-1),2),-AP27))) | AS27: =IF(AR27="","",SUM($AR$2:AR27)) | AT27: =IFERROR(__xludf.DUMMYFUNCTION("IF(AB27="""",""Type the 3 odds on the Matchday tab"",IF(Method!$B$55=TRUE(),IF(Method!$B$81=TRUE(),IF(REGEXMATCH(LOWER(Method!$B$63),""circuit""),""🛑 PAUSED — circuit breaker upstream; wait for a clean live refresh."",IF(REGEXMATCH(LOWER(Method!$B$63),"""&"pipeline""),""🛑 PAUSED — live pipeline warning; check Live!B11/Method!B62 before betting."",IF(REGEXMATCH(LOWER(Method!$B$63),""missing""),""🛑 PAUSED — feed timestamp missing; refresh feed before betting."",""🛑 PAUSED — feed stale > 25 min — check Live"&" tab; refresh feed before betting.""))),IF(Method!$B$51>=Method!$B$52,""🛑 PAUSED — drawdown ""&TEXT(Method!$B$51,""0.0%"")&"" ≥ ""&TEXT(Method!$B$52,""0.0%"")&"". Set Method!B54=Y to override."",""🛑 PAUSED — see Method!B62/B63/B81 for cause; do not over"&"ride stale/circuit-breaker/pipeline pauses."")),IF(AH27=""BET"",IF(AJ27=0,""Edge found but stake rounds under £""&Method!$B$9&"" — skip"",IF(AND(AE27>=6,AG27>=0.15),""🟡 WAIT — long-shot review: odds ""&TEXT(AE27,""0.00"")&"" + edge ""&TEXT(AG27,""0.0%"")"&"&"" — verify sharp-book + team news + stake comfort before Placed=Y"",""Value found: EV ""&TEXT(AF27,""0.0%"")&"", edge ""&TEXT(AG27,""0.0%""))),IF(OR(AF27>Method!$B$87,IFERROR(INDEX(BC27:BE27,1,AB27)/INDEX(S27:U27,1,AB27),0)>Method!$B$88),""🛑 Tail trap "&"— auto-PASS · EV ""&TEXT(AF27,""0.0%"")&"" (cap ""&TEXT(Method!$B$87,""0%"")&"") · model/market ""&TEXT(IFERROR(INDEX(BC27:BE27,1,AB27)/INDEX(S27:U27,1,AB27),0),""0.0"")&""× (cap ""&TEXT(Method!$B$88,""0.0"")&""×)"",IF(AF27<Method!$B$7,""Price too short —"&" EV ""&TEXT(AF27,""0.0%"")&"" (need ""&TEXT(Method!$B$7,""0.0%"")&""+)"",""Model ≈ market — edge ""&TEXT(AG27,""0.0%"")&"" (need ""&TEXT(Method!$B$8,""0.0%"")&""+)"")))))"),"Price too short — EV -0.3% (need 2.5%+)") -> Price too short — EV -0.3% (need 2.5%+) | AU27: =IF(AN27<>"Y","",IF(AH27="· enter odds","⚠ type the 3 odds (1/X/2) to grade this bet",IF(OR(AV27="",AO27="",AP27=""),"⚠ log backed pick, odds & stake",IF(AZ27<>"BET","⚠ FUN BET — engine said pass · staked £"&AP27&" vs engine £"&BA27,IF(AV27<>IF(AY27="",AC27,AY27),"⚠ backed "&AV27&" but engine pick was "&IF(AY27="",AC27,AY27),IF(AP27>BA27,"⚠ stake over engine £"&BA27,IF(ABS(AO27-IFERROR(INDEX(L27:N27,1,MATCH(AV27,{"H","D","A"},0)),AE27))>0.02,"⚠ odds moved — re-check value","✓ engine bet"))))))) | AV27: =IF(Matchday!O29="","",Matchday!O29) | AZ27: =IF(AW27="",AH27,AW27) -> PASS | BA27: =IF(AX27<>"",AX27,IF(AH27<>"BET",0,IF(AI27*Method!$B$10/100<Method!$B$9,0,ROUND(AI27*Method!$B$10/100,0)))) -> 0 | BB27: -36.58 | BC27: 0.6459576 | BD27: 0.2460471 | BE27: 0.1079953 | BF27: Bosnia and Herzegovina team-wide: -18 · Switzerland team-wide: -18 | BG27: 30 | BH27: warm_dry_indoor | BI27: 504.6
A28: 27 | B28: 46191 | C28: B | D28: Canada | E28: Qatar | F28: Vancouver | G28: 0.75 | H28: 02:00 +1d | I28: 0.76387687 | J28: 0.18604422 | K28: 0.050078909 | L28: =IF(Matchday!E30="","",Matchday!E30) -> 1.29 | M28: =IF(Matchday!F30="","",Matchday!F30) -> 6.5 | N28: =IF(Matchday!G30="","",Matchday!G30) -> 13.5 | O28: =IF(L28="","",1/L28) -> 0.7751938 | P28: =IF(M28="","",1/M28) -> 0.15384615 | Q28: =IF(N28="","",1/N28) -> 0.074074074 | R28: =IF(COUNT(L28:N28)<3,"",O28+P28+Q28) -> 1.003114 | S28: {=IF($R28="","",IF(Method!$B$56="proportional",O28/$R28,IF(Method!$B$56="power",IFERROR(INDEX(power_devig($L28,$M28,$N28),1,1),O28/$R28),IFERROR(INDEX(shin($L28,$M28,$N28),1,1),O28/$R28))))} -> 0.77381313 | T28: {=IF($R28="","",IF(Method!$B$56="proportional",P28/$R28,IF(Method!$B$56="power",IFERROR(INDEX(power_devig($L28,$M28,$N28),2,1),P28/$R28),IFERROR(INDEX(shin($L28,$M28,$N28),2,1),P28/$R28))))} -> 0.15294756 | U28: {=IF($R28="","",IF(Method!$B$56="proportional",Q28/$R28,IF(Method!$B$56="power",IFERROR(INDEX(power_devig($L28,$M28,$N28),3,1),Q28/$R28),IFERROR(INDEX(shin($L28,$M28,$N28),3,1),Q28/$R28))))} -> 0.073239309 | V28: =IF(S28="","",Method!$B$4*IF(BC28="",I28,BC28)+(1-Method!$B$4)*S28/($S28+$T28+$U28)) -> 0.76200249 | W28: =IF(T28="","",Method!$B$4*IF(BD28="",J28,BD28)+(1-Method!$B$4)*T28/($S28+$T28+$U28)) -> 0.17302288 | X28: =IF(U28="","",Method!$B$4*IF(BE28="",K28,BE28)+(1-Method!$B$4)*U28/($S28+$T28+$U28)) -> 0.064974624 | Y28: =IF(V28="","",V28*L28-1) -> -0.017016783 | Z28: =IF(W28="","",W28*M28-1) -> 0.12464873 | AA28: =IF(X28="","",X28*N28-1) -> -0.12284257 | AB28: =IF(Y28="","",MATCH(MAX(Y28:AA28),Y28:AA28,0)) -> 2 | AC28: =IF(AB28="","",CHOOSE(AB28,"H","D","A")) -> D | AD28: =IF(AB28="","",CHOOSE(AB28,"1 "&D28,"X Draw","2 "&E28)) -> X Draw | AE28: =IF(AB28="","",INDEX(L28:N28,1,AB28)) -> 6.5 | AF28: =IF(AB28="","",INDEX(Y28:AA28,1,AB28)) -> 0.12464873 | AG28: =IF(AB28="","",INDEX(V28:X28,1,AB28)-INDEX(S28:U28,1,AB28)) -> 0.02007532 | AH28: {=IF(AB28="","· enter odds",IF(OR(AF28>Method!$B$87,IFERROR(INDEX(BC28:BE28,1,AB28)/INDEX(S28:U28,1,AB28),0)>Method!$B$88),"PASS",IF(AND(AF28>=Method!$B$7,AG28>=Method!$B$8),"BET","PASS")))} -> PASS | AI28: =IF(AH28<>"BET",0,ROUND(MIN(Method!$B$6,Method!$B$5*AL28)*100,1)) -> 0 | AJ28: =IF(OR(AH28<>"BET",Method!$B$55=TRUE()),0,IF(AI28*Method!$B$10/100<Method!$B$9,0,ROUND(AI28*Method!$B$10/100,0))) -> 0 | AK28: =IF(AB28="","",INDEX(V28:X28,1,AB28)) -> 0.17302288 | AL28: =IF(AH28<>"BET","",MAX(0,(AK28*AE28-1)/(AE28-1))) | AM28: =IF(AH28="BET",AF28+A28/1000000,"") | AN28: =IF(Matchday!N30="","",Matchday!N30) | AO28: =IF(Matchday!P30="","",Matchday!P30) | AP28: =IF(Matchday!Q30="","",Matchday!Q30) | AQ28: =IF(Matchday!R30="","",Matchday!R30) -> H | AR28: =IF(OR(AN28<>"Y",AQ28="",AV28=""),"",IF(AQ28="Void",0,IF(AQ28=AV28,ROUND(AP28*(AO28-1),2),-AP28))) | AS28: =IF(AR28="","",SUM($AR$2:AR28)) | AT28: =IFERROR(__xludf.DUMMYFUNCTION("IF(AB28="""",""Type the 3 odds on the Matchday tab"",IF(Method!$B$55=TRUE(),IF(Method!$B$81=TRUE(),IF(REGEXMATCH(LOWER(Method!$B$63),""circuit""),""🛑 PAUSED — circuit breaker upstream; wait for a clean live refresh."",IF(REGEXMATCH(LOWER(Method!$B$63),"""&"pipeline""),""🛑 PAUSED — live pipeline warning; check Live!B11/Method!B62 before betting."",IF(REGEXMATCH(LOWER(Method!$B$63),""missing""),""🛑 PAUSED — feed timestamp missing; refresh feed before betting."",""🛑 PAUSED — feed stale > 25 min — check Live"&" tab; refresh feed before betting.""))),IF(Method!$B$51>=Method!$B$52,""🛑 PAUSED — drawdown ""&TEXT(Method!$B$51,""0.0%"")&"" ≥ ""&TEXT(Method!$B$52,""0.0%"")&"". Set Method!B54=Y to override."",""🛑 PAUSED — see Method!B62/B63/B81 for cause; do not over"&"ride stale/circuit-breaker/pipeline pauses."")),IF(AH28=""BET"",IF(AJ28=0,""Edge found but stake rounds under £""&Method!$B$9&"" — skip"",IF(AND(AE28>=6,AG28>=0.15),""🟡 WAIT — long-shot review: odds ""&TEXT(AE28,""0.00"")&"" + edge ""&TEXT(AG28,""0.0%"")"&"&"" — verify sharp-book + team news + stake comfort before Placed=Y"",""Value found: EV ""&TEXT(AF28,""0.0%"")&"", edge ""&TEXT(AG28,""0.0%""))),IF(OR(AF28>Method!$B$87,IFERROR(INDEX(BC28:BE28,1,AB28)/INDEX(S28:U28,1,AB28),0)>Method!$B$88),""🛑 Tail trap "&"— auto-PASS · EV ""&TEXT(AF28,""0.0%"")&"" (cap ""&TEXT(Method!$B$87,""0%"")&"") · model/market ""&TEXT(IFERROR(INDEX(BC28:BE28,1,AB28)/INDEX(S28:U28,1,AB28),0),""0.0"")&""× (cap ""&TEXT(Method!$B$88,""0.0"")&""×)"",IF(AF28<Method!$B$7,""Price too short —"&" EV ""&TEXT(AF28,""0.0%"")&"" (need ""&TEXT(Method!$B$7,""0.0%"")&""+)"",""Model ≈ market — edge ""&TEXT(AG28,""0.0%"")&"" (need ""&TEXT(Method!$B$8,""0.0%"")&""+)"")))))"),"Model ≈ market — edge 2.0% (need 2.5%+)") -> Model ≈ market — edge 2.0% (need 2.5%+) | AU28: =IF(AN28<>"Y","",IF(AH28="· enter odds","⚠ type the 3 odds (1/X/2) to grade this bet",IF(OR(AV28="",AO28="",AP28=""),"⚠ log backed pick, odds & stake",IF(AZ28<>"BET","⚠ FUN BET — engine said pass · staked £"&AP28&" vs engine £"&BA28,IF(AV28<>IF(AY28="",AC28,AY28),"⚠ backed "&AV28&" but engine pick was "&IF(AY28="",AC28,AY28),IF(AP28>BA28,"⚠ stake over engine £"&BA28,IF(ABS(AO28-IFERROR(INDEX(L28:N28,1,MATCH(AV28,{"H","D","A"},0)),AE28))>0.02,"⚠ odds moved — re-check value","✓ engine bet"))))))) | AV28: =IF(Matchday!O30="","",Matchday!O30) | AZ28: =IF(AW28="",AH28,AW28) -> PASS | BA28: =IF(AX28<>"",AX28,IF(AH28<>"BET",0,IF(AI28*Method!$B$10/100<Method!$B$9,0,ROUND(AI28*Method!$B$10/100,0)))) -> 0 | BB28: -44.06 | BC28: 0.74006846 | BD28: 0.21030562 | BE28: 0.049625924 | BF28: Canada team-wide: -9 · Qatar team-wide: -35 | BG28: 0 | BH28: mild_indoor | BI28: 3356.8
A29: 28 | B29: 46191 | C29: A | D29: Mexico | E29: South Korea | F29: Zapopan | G29: 0.95833333 | H29: 06:00 +1d | I29: 0.58981718 | J29: 0.26243704 | K29: 0.14774578 | L29: =IF(Matchday!E31="","",Matchday!E31) -> 2.13 | M29: =IF(Matchday!F31="","",Matchday!F31) -> 3.3 | N29: =IF(Matchday!G31="","",Matchday!G31) -> 4.2 | O29: =IF(L29="","",1/L29) -> 0.46948357 | P29: =IF(M29="","",1/M29) -> 0.3030303 | Q29: =IF(N29="","",1/N29) -> 0.23809524 | R29: =IF(COUNT(L29:N29)<3,"",O29+P29+Q29) -> 1.0106091 | S29: {=IF($R29="","",IF(Method!$B$56="proportional",O29/$R29,IF(Method!$B$56="power",IFERROR(INDEX(power_devig($L29,$M29,$N29),1,1),O29/$R29),IFERROR(INDEX(shin($L29,$M29,$N29),1,1),O29/$R29))))} -> 0.46559688 | T29: {=IF($R29="","",IF(Method!$B$56="proportional",P29/$R29,IF(Method!$B$56="power",IFERROR(INDEX(power_devig($L29,$M29,$N29),2,1),P29/$R29),IFERROR(INDEX(shin($L29,$M29,$N29),2,1),P29/$R29))))} -> 0.29958266 | U29: {=IF($R29="","",IF(Method!$B$56="proportional",Q29/$R29,IF(Method!$B$56="power",IFERROR(INDEX(power_devig($L29,$M29,$N29),3,1),Q29/$R29),IFERROR(INDEX(shin($L29,$M29,$N29),3,1),Q29/$R29))))} -> 0.23482045 | V29: =IF(S29="","",Method!$B$4*IF(BC29="",I29,BC29)+(1-Method!$B$4)*S29/($S29+$T29+$U29)) -> 0.50160209 | W29: =IF(T29="","",Method!$B$4*IF(BD29="",J29,BD29)+(1-Method!$B$4)*T29/($S29+$T29+$U29)) -> 0.29258278 | X29: =IF(U29="","",Method!$B$4*IF(BE29="",K29,BE29)+(1-Method!$B$4)*U29/($S29+$T29+$U29)) -> 0.20581513 | Y29: =IF(V29="","",V29*L29-1) -> 0.06841246 | Z29: =IF(W29="","",W29*M29-1) -> -0.034476825 | AA29: =IF(X29="","",X29*N29-1) -> -0.13557647 | AB29: =IF(Y29="","",MATCH(MAX(Y29:AA29),Y29:AA29,0)) -> 1 | AC29: =IF(AB29="","",CHOOSE(AB29,"H","D","A")) -> H | AD29: =IF(AB29="","",CHOOSE(AB29,"1 "&D29,"X Draw","2 "&E29)) -> 1 Mexico | AE29: =IF(AB29="","",INDEX(L29:N29,1,AB29)) -> 2.13 | AF29: =IF(AB29="","",INDEX(Y29:AA29,1,AB29)) -> 0.06841246 | AG29: =IF(AB29="","",INDEX(V29:X29,1,AB29)-INDEX(S29:U29,1,AB29)) -> 0.03600521 | AH29: {=IF(AB29="","· enter odds",IF(OR(AF29>Method!$B$87,IFERROR(INDEX(BC29:BE29,1,AB29)/INDEX(S29:U29,1,AB29),0)>Method!$B$88),"PASS",IF(AND(AF29>=Method!$B$7,AG29>=Method!$B$8),"BET","PASS")))} -> BET | AI29: =IF(AH29<>"BET",0,ROUND(MIN(Method!$B$6,Method!$B$5*AL29)*100,1)) -> 1.5 | AJ29: =IF(OR(AH29<>"BET",Method!$B$55=TRUE()),0,IF(AI29*Method!$B$10/100<Method!$B$9,0,ROUND(AI29*Method!$B$10/100,0))) -> 15 | AK29: =IF(AB29="","",INDEX(V29:X29,1,AB29)) -> 0.50160209 | AL29: =IF(AH29<>"BET","",MAX(0,(AK29*AE29-1)/(AE29-1))) -> 0.060542 | AM29: =IF(AH29="BET",AF29+A29/1000000,"") -> 0.06844046 | AN29: =IF(Matchday!N31="","",Matchday!N31) | AO29: =IF(Matchday!P31="","",Matchday!P31) | AP29: =IF(Matchday!Q31="","",Matchday!Q31) | AQ29: =IF(Matchday!R31="","",Matchday!R31) -> H | AR29: =IF(OR(AN29<>"Y",AQ29="",AV29=""),"",IF(AQ29="Void",0,IF(AQ29=AV29,ROUND(AP29*(AO29-1),2),-AP29))) | AS29: =IF(AR29="","",SUM($AR$2:AR29)) | AT29: =IFERROR(__xludf.DUMMYFUNCTION("IF(AB29="""",""Type the 3 odds on the Matchday tab"",IF(Method!$B$55=TRUE(),IF(Method!$B$81=TRUE(),IF(REGEXMATCH(LOWER(Method!$B$63),""circuit""),""🛑 PAUSED — circuit breaker upstream; wait for a clean live refresh."",IF(REGEXMATCH(LOWER(Method!$B$63),"""&"pipeline""),""🛑 PAUSED — live pipeline warning; check Live!B11/Method!B62 before betting."",IF(REGEXMATCH(LOWER(Method!$B$63),""missing""),""🛑 PAUSED — feed timestamp missing; refresh feed before betting."",""🛑 PAUSED — feed stale > 25 min — check Live"&" tab; refresh feed before betting.""))),IF(Method!$B$51>=Method!$B$52,""🛑 PAUSED — drawdown ""&TEXT(Method!$B$51,""0.0%"")&"" ≥ ""&TEXT(Method!$B$52,""0.0%"")&"". Set Method!B54=Y to override."",""🛑 PAUSED — see Method!B62/B63/B81 for cause; do not over"&"ride stale/circuit-breaker/pipeline pauses."")),IF(AH29=""BET"",IF(AJ29=0,""Edge found but stake rounds under £""&Method!$B$9&"" — skip"",IF(AND(AE29>=6,AG29>=0.15),""🟡 WAIT — long-shot review: odds ""&TEXT(AE29,""0.00"")&"" + edge ""&TEXT(AG29,""0.0%"")"&"&"" — verify sharp-book + team news + stake comfort before Placed=Y"",""Value found: EV ""&TEXT(AF29,""0.0%"")&"", edge ""&TEXT(AG29,""0.0%""))),IF(OR(AF29>Method!$B$87,IFERROR(INDEX(BC29:BE29,1,AB29)/INDEX(S29:U29,1,AB29),0)>Method!$B$88),""🛑 Tail trap "&"— auto-PASS · EV ""&TEXT(AF29,""0.0%"")&"" (cap ""&TEXT(Method!$B$87,""0%"")&"") · model/market ""&TEXT(IFERROR(INDEX(BC29:BE29,1,AB29)/INDEX(S29:U29,1,AB29),0),""0.0"")&""× (cap ""&TEXT(Method!$B$88,""0.0"")&""×)"",IF(AF29<Method!$B$7,""Price too short —"&" EV ""&TEXT(AF29,""0.0%"")&"" (need ""&TEXT(Method!$B$7,""0.0%"")&""+)"",""Model ≈ market — edge ""&TEXT(AG29,""0.0%"")&"" (need ""&TEXT(Method!$B$8,""0.0%"")&""+)"")))))"),"Value found: EV 6.8%, edge 3.6%") -> Value found: EV 6.8%, edge 3.6% | AU29: =IF(AN29<>"Y","",IF(AH29="· enter odds","⚠ type the 3 odds (1/X/2) to grade this bet",IF(OR(AV29="",AO29="",AP29=""),"⚠ log backed pick, odds & stake",IF(AZ29<>"BET","⚠ FUN BET — engine said pass · staked £"&AP29&" vs engine £"&BA29,IF(AV29<>IF(AY29="",AC29,AY29),"⚠ backed "&AV29&" but engine pick was "&IF(AY29="",AC29,AY29),IF(AP29>BA29,"⚠ stake over engine £"&BA29,IF(ABS(AO29-IFERROR(INDEX(L29:N29,1,MATCH(AV29,{"H","D","A"},0)),AE29))>0.02,"⚠ odds moved — re-check value","✓ engine bet"))))))) | AV29: =IF(Matchday!O31="","",Matchday!O31) | AZ29: =IF(AW29="",AH29,AW29) -> BET | BA29: =IF(AX29<>"",AX29,IF(AH29<>"BET",0,IF(AI29*Method!$B$10/100<Method!$B$9,0,ROUND(AI29*Method!$B$10/100,0)))) -> 15 | BB29: 3.08 | BC29: 0.56846891 | BD29: 0.279583 | BE29: 0.15194809 | BF29: Mexico team-wide: +7 · Mexico suspension: -3 · South Korea team-wide: +1 · South Korea weather: -1 | BG29: 1560 | BH29: warm_humid | BI29: 475.9
A30: 29 | B30: 46192 | C30: D | D30: United States | E30: Australia | F30: Seattle | G30: 0.625 | H30: 0.95833333 | I30: 0.47685607 | J30: 0.28231277 | K30: 0.24083116 | L30: =IF(Matchday!E32="","",Matchday!E32) -> 1.61 | M30: =IF(Matchday!F32="","",Matchday!F32) -> 4.4 | N30: =IF(Matchday!G32="","",Matchday!G32) -> 6.5 | O30: =IF(L30="","",1/L30) -> 0.62111801 | P30: =IF(M30="","",1/M30) -> 0.22727273 | Q30: =IF(N30="","",1/N30) -> 0.15384615 | R30: =IF(COUNT(L30:N30)<3,"",O30+P30+Q30) -> 1.0022369 | S30: {=IF($R30="","",IF(Method!$B$56="proportional",O30/$R30,IF(Method!$B$56="power",IFERROR(INDEX(power_devig($L30,$M30,$N30),1,1),O30/$R30),IFERROR(INDEX(shin($L30,$M30,$N30),1,1),O30/$R30))))} -> 0.62021203 | T30: {=IF($R30="","",IF(Method!$B$56="proportional",P30/$R30,IF(Method!$B$56="power",IFERROR(INDEX(power_devig($L30,$M30,$N30),2,1),P30/$R30),IFERROR(INDEX(shin($L30,$M30,$N30),2,1),P30/$R30))))} -> 0.22658665 | U30: {=IF($R30="","",IF(Method!$B$56="proportional",Q30/$R30,IF(Method!$B$56="power",IFERROR(INDEX(power_devig($L30,$M30,$N30),3,1),Q30/$R30),IFERROR(INDEX(shin($L30,$M30,$N30),3,1),Q30/$R30))))} -> 0.15320132 | V30: =IF(S30="","",Method!$B$4*IF(BC30="",I30,BC30)+(1-Method!$B$4)*S30/($S30+$T30+$U30)) -> 0.56976535 | W30: =IF(T30="","",Method!$B$4*IF(BD30="",J30,BD30)+(1-Method!$B$4)*T30/($S30+$T30+$U30)) -> 0.24180063 | X30: =IF(U30="","",Method!$B$4*IF(BE30="",K30,BE30)+(1-Method!$B$4)*U30/($S30+$T30+$U30)) -> 0.18843402 | Y30: =IF(V30="","",V30*L30-1) -> -0.082677788 | Z30: =IF(W30="","",W30*M30-1) -> 0.063922776 | AA30: =IF(X30="","",X30*N30-1) -> 0.22482113 | AB30: =IF(Y30="","",MATCH(MAX(Y30:AA30),Y30:AA30,0)) -> 3 | AC30: =IF(AB30="","",CHOOSE(AB30,"H","D","A")) -> A | AD30: =IF(AB30="","",CHOOSE(AB30,"1 "&D30,"X Draw","2 "&E30)) -> 2 Australia | AE30: =IF(AB30="","",INDEX(L30:N30,1,AB30)) -> 6.5 | AF30: =IF(AB30="","",INDEX(Y30:AA30,1,AB30)) -> 0.22482113 | AG30: =IF(AB30="","",INDEX(V30:X30,1,AB30)-INDEX(S30:U30,1,AB30)) -> 0.035232701 | AH30: {=IF(AB30="","· enter odds",IF(OR(AF30>Method!$B$87,IFERROR(INDEX(BC30:BE30,1,AB30)/INDEX(S30:U30,1,AB30),0)>Method!$B$88),"PASS",IF(AND(AF30>=Method!$B$7,AG30>=Method!$B$8),"BET","PASS")))} -> BET | AI30: =IF(AH30<>"BET",0,ROUND(MIN(Method!$B$6,Method!$B$5*AL30)*100,1)) -> 1 | AJ30: =IF(OR(AH30<>"BET",Method!$B$55=TRUE()),0,IF(AI30*Method!$B$10/100<Method!$B$9,0,ROUND(AI30*Method!$B$10/100,0))) -> 10 | AK30: =IF(AB30="","",INDEX(V30:X30,1,AB30)) -> 0.18843402 | AL30: =IF(AH30<>"BET","",MAX(0,(AK30*AE30-1)/(AE30-1))) -> 0.040876569 | AM30: =IF(AH30="BET",AF30+A30/1000000,"") -> 0.22485013 | AN30: =IF(Matchday!N32="","",Matchday!N32) | AO30: =IF(Matchday!P32="","",Matchday!P32) | AP30: =IF(Matchday!Q32="","",Matchday!Q32) | AQ30: =IF(Matchday!R32="","",Matchday!R32) -> H | AR30: =IF(OR(AN30<>"Y",AQ30="",AV30=""),"",IF(AQ30="Void",0,IF(AQ30=AV30,ROUND(AP30*(AO30-1),2),-AP30))) | AS30: =IF(AR30="","",SUM($AR$2:AR30)) | AT30: =IFERROR(__xludf.DUMMYFUNCTION("IF(AB30="""",""Type the 3 odds on the Matchday tab"",IF(Method!$B$55=TRUE(),IF(Method!$B$81=TRUE(),IF(REGEXMATCH(LOWER(Method!$B$63),""circuit""),""🛑 PAUSED — circuit breaker upstream; wait for a clean live refresh."",IF(REGEXMATCH(LOWER(Method!$B$63),"""&"pipeline""),""🛑 PAUSED — live pipeline warning; check Live!B11/Method!B62 before betting."",IF(REGEXMATCH(LOWER(Method!$B$63),""missing""),""🛑 PAUSED — feed timestamp missing; refresh feed before betting."",""🛑 PAUSED — feed stale > 25 min — check Live"&" tab; refresh feed before betting.""))),IF(Method!$B$51>=Method!$B$52,""🛑 PAUSED — drawdown ""&TEXT(Method!$B$51,""0.0%"")&"" ≥ ""&TEXT(Method!$B$52,""0.0%"")&"". Set Method!B54=Y to override."",""🛑 PAUSED — see Method!B62/B63/B81 for cause; do not over"&"ride stale/circuit-breaker/pipeline pauses."")),IF(AH30=""BET"",IF(AJ30=0,""Edge found but stake rounds under £""&Method!$B$9&"" — skip"",IF(AND(AE30>=6,AG30>=0.15),""🟡 WAIT — long-shot review: odds ""&TEXT(AE30,""0.00"")&"" + edge ""&TEXT(AG30,""0.0%"")"&"&"" — verify sharp-book + team news + stake comfort before Placed=Y"",""Value found: EV ""&TEXT(AF30,""0.0%"")&"", edge ""&TEXT(AG30,""0.0%""))),IF(OR(AF30>Method!$B$87,IFERROR(INDEX(BC30:BE30,1,AB30)/INDEX(S30:U30,1,AB30),0)>Method!$B$88),""🛑 Tail trap "&"— auto-PASS · EV ""&TEXT(AF30,""0.0%"")&"" (cap ""&TEXT(Method!$B$87,""0%"")&"") · model/market ""&TEXT(IFERROR(INDEX(BC30:BE30,1,AB30)/INDEX(S30:U30,1,AB30),0),""0.0"")&""× (cap ""&TEXT(Method!$B$88,""0.0"")&""×)"",IF(AF30<Method!$B$7,""Price too short —"&" EV ""&TEXT(AF30,""0.0%"")&"" (need ""&TEXT(Method!$B$7,""0.0%"")&""+)"",""Model ≈ market — edge ""&TEXT(AG30,""0.0%"")&"" (need ""&TEXT(Method!$B$8,""0.0%"")&""+)"")))))"),"Value found: EV 22.5%, edge 3.5%") -> Value found: EV 22.5%, edge 3.5% | AU30: =IF(AN30<>"Y","",IF(AH30="· enter odds","⚠ type the 3 odds (1/X/2) to grade this bet",IF(OR(AV30="",AO30="",AP30=""),"⚠ log backed pick, odds & stake",IF(AZ30<>"BET","⚠ FUN BET — engine said pass · staked £"&AP30&" vs engine £"&BA30,IF(AV30<>IF(AY30="",AC30,AY30),"⚠ backed "&AV30&" but engine pick was "&IF(AY30="",AC30,AY30),IF(AP30>BA30,"⚠ stake over engine £"&BA30,IF(ABS(AO30-IFERROR(INDEX(L30:N30,1,MATCH(AV30,{"H","D","A"},0)),AE30))>0.02,"⚠ odds moved — re-check value","✓ engine bet"))))))) | AV30: =IF(Matchday!O32="","",Matchday!O32) | AZ30: =IF(AW30="",AH30,AW30) -> BET | BA30: =IF(AX30<>"",AX30,IF(AH30<>"BET",0,IF(AI30*Method!$B$10/100<Method!$B$9,0,ROUND(AI30*Method!$B$10/100,0)))) -> 10 | BB30: -46.9 | BC30: 0.47607865 | BD30: 0.27005517 | BE30: 0.25386618 | BF30: Australia team-wide: -26 · United States team-wide: -21 | BG30: 5 | BH30: mild | BI30: 1553.1
A31: 30 | B31: 46192 | C31: C | D31: Scotland | E31: Morocco | F31: Foxborough | G31: 0.75 | H31: 0.95833333 | I31: 0.19335466 | J31: 0.28086569 | K31: 0.52577965 | L31: =IF(Matchday!E33="","",Matchday!E33) -> 5.8 | M31: =IF(Matchday!F33="","",Matchday!F33) -> 3.8 | N31: =IF(Matchday!G33="","",Matchday!G33) -> 1.72 | O31: =IF(L31="","",1/L31) -> 0.17241379 | P31: =IF(M31="","",1/M31) -> 0.26315789 | Q31: =IF(N31="","",1/N31) -> 0.58139535 | R31: =IF(COUNT(L31:N31)<3,"",O31+P31+Q31) -> 1.016967 | S31: {=IF($R31="","",IF(Method!$B$56="proportional",O31/$R31,IF(Method!$B$56="power",IFERROR(INDEX(power_devig($L31,$M31,$N31),1,1),O31/$R31),IFERROR(INDEX(shin($L31,$M31,$N31),1,1),O31/$R31))))} -> 0.16746519 | T31: {=IF($R31="","",IF(Method!$B$56="proportional",P31/$R31,IF(Method!$B$56="power",IFERROR(INDEX(power_devig($L31,$M31,$N31),2,1),P31/$R31),IFERROR(INDEX(shin($L31,$M31,$N31),2,1),P31/$R31))))} -> 0.25781583 | U31: {=IF($R31="","",IF(Method!$B$56="proportional",Q31/$R31,IF(Method!$B$56="power",IFERROR(INDEX(power_devig($L31,$M31,$N31),3,1),Q31/$R31),IFERROR(INDEX(shin($L31,$M31,$N31),3,1),Q31/$R31))))} -> 0.57471899 | V31: =IF(S31="","",Method!$B$4*IF(BC31="",I31,BC31)+(1-Method!$B$4)*S31/($S31+$T31+$U31)) -> 0.17179089 | W31: =IF(T31="","",Method!$B$4*IF(BD31="",J31,BD31)+(1-Method!$B$4)*T31/($S31+$T31+$U31)) -> 0.26454692 | X31: =IF(U31="","",Method!$B$4*IF(BE31="",K31,BE31)+(1-Method!$B$4)*U31/($S31+$T31+$U31)) -> 0.56366219 | Y31: =IF(V31="","",V31*L31-1) -> -0.0036128517 | Z31: =IF(W31="","",W31*M31-1) -> 0.0052783053 | AA31: =IF(X31="","",X31*N31-1) -> -0.030501033 | AB31: =IF(Y31="","",MATCH(MAX(Y31:AA31),Y31:AA31,0)) -> 2 | AC31: =IF(AB31="","",CHOOSE(AB31,"H","D","A")) -> D | AD31: =IF(AB31="","",CHOOSE(AB31,"1 "&D31,"X Draw","2 "&E31)) -> X Draw | AE31: =IF(AB31="","",INDEX(L31:N31,1,AB31)) -> 3.8 | AF31: =IF(AB31="","",INDEX(Y31:AA31,1,AB31)) -> 0.0052783053 | AG31: =IF(AB31="","",INDEX(V31:X31,1,AB31)-INDEX(S31:U31,1,AB31)) -> 0.0067310958 | AH31: {=IF(AB31="","· enter odds",IF(OR(AF31>Method!$B$87,IFERROR(INDEX(BC31:BE31,1,AB31)/INDEX(S31:U31,1,AB31),0)>Method!$B$88),"PASS",IF(AND(AF31>=Method!$B$7,AG31>=Method!$B$8),"BET","PASS")))} -> PASS | AI31: =IF(AH31<>"BET",0,ROUND(MIN(Method!$B$6,Method!$B$5*AL31)*100,1)) -> 0 | AJ31: =IF(OR(AH31<>"BET",Method!$B$55=TRUE()),0,IF(AI31*Method!$B$10/100<Method!$B$9,0,ROUND(AI31*Method!$B$10/100,0))) -> 0 | AK31: =IF(AB31="","",INDEX(V31:X31,1,AB31)) -> 0.26454692 | AL31: =IF(AH31<>"BET","",MAX(0,(AK31*AE31-1)/(AE31-1))) | AM31: =IF(AH31="BET",AF31+A31/1000000,"") | AN31: =IF(Matchday!N33="","",Matchday!N33) | AO31: =IF(Matchday!P33="","",Matchday!P33) | AP31: =IF(Matchday!Q33="","",Matchday!Q33) | AQ31: =IF(Matchday!R33="","",Matchday!R33) -> A | AR31: =IF(OR(AN31<>"Y",AQ31="",AV31=""),"",IF(AQ31="Void",0,IF(AQ31=AV31,ROUND(AP31*(AO31-1),2),-AP31))) | AS31: =IF(AR31="","",SUM($AR$2:AR31)) | AT31: =IFERROR(__xludf.DUMMYFUNCTION("IF(AB31="""",""Type the 3 odds on the Matchday tab"",IF(Method!$B$55=TRUE(),IF(Method!$B$81=TRUE(),IF(REGEXMATCH(LOWER(Method!$B$63),""circuit""),""🛑 PAUSED — circuit breaker upstream; wait for a clean live refresh."",IF(REGEXMATCH(LOWER(Method!$B$63),"""&"pipeline""),""🛑 PAUSED — live pipeline warning; check Live!B11/Method!B62 before betting."",IF(REGEXMATCH(LOWER(Method!$B$63),""missing""),""🛑 PAUSED — feed timestamp missing; refresh feed before betting."",""🛑 PAUSED — feed stale > 25 min — check Live"&" tab; refresh feed before betting.""))),IF(Method!$B$51>=Method!$B$52,""🛑 PAUSED — drawdown ""&TEXT(Method!$B$51,""0.0%"")&"" ≥ ""&TEXT(Method!$B$52,""0.0%"")&"". Set Method!B54=Y to override."",""🛑 PAUSED — see Method!B62/B63/B81 for cause; do not over"&"ride stale/circuit-breaker/pipeline pauses."")),IF(AH31=""BET"",IF(AJ31=0,""Edge found but stake rounds under £""&Method!$B$9&"" — skip"",IF(AND(AE31>=6,AG31>=0.15),""🟡 WAIT — long-shot review: odds ""&TEXT(AE31,""0.00"")&"" + edge ""&TEXT(AG31,""0.0%"")"&"&"" — verify sharp-book + team news + stake comfort before Placed=Y"",""Value found: EV ""&TEXT(AF31,""0.0%"")&"", edge ""&TEXT(AG31,""0.0%""))),IF(OR(AF31>Method!$B$87,IFERROR(INDEX(BC31:BE31,1,AB31)/INDEX(S31:U31,1,AB31),0)>Method!$B$88),""🛑 Tail trap "&"— auto-PASS · EV ""&TEXT(AF31,""0.0%"")&"" (cap ""&TEXT(Method!$B$87,""0%"")&"") · model/market ""&TEXT(IFERROR(INDEX(BC31:BE31,1,AB31)/INDEX(S31:U31,1,AB31),0),""0.0"")&""× (cap ""&TEXT(Method!$B$88,""0.0"")&""×)"",IF(AF31<Method!$B$7,""Price too short —"&" EV ""&TEXT(AF31,""0.0%"")&"" (need ""&TEXT(Method!$B$7,""0.0%"")&""+)"",""Model ≈ market — edge ""&TEXT(AG31,""0.0%"")&"" (need ""&TEXT(Method!$B$8,""0.0%"")&""+)"")))))"),"Price too short — EV 0.5% (need 2.5%+)") -> Price too short — EV 0.5% (need 2.5%+) | AU31: =IF(AN31<>"Y","",IF(AH31="· enter odds","⚠ type the 3 odds (1/X/2) to grade this bet",IF(OR(AV31="",AO31="",AP31=""),"⚠ log backed pick, odds & stake",IF(AZ31<>"BET","⚠ FUN BET — engine said pass · staked £"&AP31&" vs engine £"&BA31,IF(AV31<>IF(AY31="",AC31,AY31),"⚠ backed "&AV31&" but engine pick was "&IF(AY31="",AC31,AY31),IF(AP31>BA31,"⚠ stake over engine £"&BA31,IF(ABS(AO31-IFERROR(INDEX(L31:N31,1,MATCH(AV31,{"H","D","A"},0)),AE31))>0.02,"⚠ odds moved — re-check value","✓ engine bet"))))))) | AV31: =IF(Matchday!O33="","",Matchday!O33) | AZ31: =IF(AW31="",AH31,AW31) -> PASS | BA31: =IF(AX31<>"",AX31,IF(AH31<>"BET",0,IF(AI31*Method!$B$10/100<Method!$B$9,0,ROUND(AI31*Method!$B$10/100,0)))) -> 0 | BB31: -11.1 | BC31: 0.17982433 | BD31: 0.27704753 | BE31: 0.54312814 | BF31: Morocco team-wide: -7 · Scotland team-wide: -4 | BG31: 40 | BH31: warm | BI31: 0
