Workbook

Sheet READ ME
A2: READ ME — 1 MINUTE
A3: The ONLY tab you use is MATCHDAY. (Bets = engine audit · Dashboard = scoreboard · Method = settings & rules · Model vs Market = context.)
A5: YELLOW CELLS = YOU TYPE. There are only 5 things, all on the Matchday tab:
A6: 1. Odds 1 / X / 2 — the three DECIMAL prices from your betting app (1 = home, X = draw, 2 = away). 21/50 → 1.42 · 7/2 → 4.50 · 15/2 → 8.50. Bet365: Settings → Odds format → Decimal.
A7: 2. Team news OK? — Y or N. Only needed when DECISION says BET.
A8: 3. Placed? + Backed (H/D/A) + Odds you got + Stake you placed — your log AFTER you bet. "Backed" = the outcome on your slip; P&L grades against it, so model updates can never rewrite your record.
A9: 4. Result — H, D, A or Void, after full time.
A10: 5. Closing odds (optional) — the price just before kickoff, for the CLV homework.
A12: EVERYTHING ELSE IS AUTOMATIC: PICK, DECISION, ENGINE STAKE, WHY, FINAL ACTION, STATUS, CLV, the whole Dashboard and your bankroll.
A14: HOW TO READ THE ANSWER
A15: · ENGINE STAKE "–" + FINAL ACTION "❌ NO BET" → the engine DID respond: do not bet this match. Example: South Korea v Czechia at 2.70 / 3.10 / 2.80 → EV +1.6%, below the 2.5% bar → NO BET. Nothing is broken.
A16: · FINAL ACTION "🟢 PLACE £x on [pick]" → bet exactly that amount on exactly that pick, after the team-news check.
... A32: v2.2 — last-mile hardening: pause can no longer distort the STATUS text for un-snapshotted bets; First-time setup now retro-snapshots any bet placed before the script existed; snapshot cells stay writable for shared editors (share view-only with friends regardless — they scale stakes via "£ / £100 bank").

Sheet Dashboard
A1: WC26 GROUP STAGE — VALUE BETTING DASHBOARD
A2: Model snapshot 2026-06-10 14:10 UTC · type odds on the MATCHDAY tab on game day · stakes auto-size from current bankroll
A4: Current bankroll | B4: =Method!B10 -> 1058.3 | C4: Matches today | D4: =COUNTIF(Bets!B2:B73,TODAY()) -> 4 | E4: Engine bets placed | F4: =SUMPRODUCT(--(Bets!AN2:AN73="Y"),--(Bets!AZ2:AZ73="BET")) -> 5 | G4: =IF(F5=0,"","⚠ "&F5&" fun bet(s) logged — excluded from engine quality. Judge the engine on Engine P&L and ✓ rows only.") -> ⚠ 4 fun bet(s) logged — excluded from engine quality. Judge the engine on Engine P&L and ✓ rows only.
A5: Staked (placed) | B5: =SUMIF(Bets!AN2:AN73,"Y",Bets!AP2:AP73) -> 140 | C5: Next match day | D5: =IFERROR(SMALL(Bets!B2:B73,COUNTIF(Bets!B2:B73,"<"&TODAY())+1),"finished") -> 46189 | E5: Fun bets placed | F5: =SUMPRODUCT(--(Bets!AN2:AN73="Y"),--(Bets!AZ2:AZ73<>"BET")) -> 4
A6: Settled P&L | B6: =SUM(Bets!AR2:AR73) -> 58.3 | C6: BET signals live | D6: =COUNTIF(Bets!AH2:AH73,"BET") -> 8 | E6: Avg CLV (logged) | F6: =IFERROR(AVERAGE(Matchday!U4:U75),"–") -> 0.86505467
A7: ROI (settled) | B7: =IF(SUMPRODUCT(--(Bets!AN2:AN73="Y"),--(Bets!AQ2:AQ73<>""),Bets!AP2:AP73)=0,"–",B6/SUMPRODUCT(--(Bets!AN2:AN73="Y"),--(Bets!AQ2:AQ73<>""),Bets!AP2:AP73)) -> 0.41642857 | C7: PASS | D7: =COUNTIF(Bets!AH2:AH73,"PASS") -> 14 | E7: Engine P&L | F7: =SUMIF(Bets!AZ2:AZ73,"BET",Bets!AR2:AR73) -> 48.9
A8: Record W–L | B8: =COUNTIF(Bets!AR2:AR73,">0")&" – "&COUNTIF(Bets!AR2:AR73,"<0") -> 5 – 3 | C8: Awaiting odds | D8: =COUNTIF(Bets!AH2:AH73,"· enter odds") -> 50 | E8: Fun-bet P&L | F8: =SUMIFS(Bets!AR2:AR73,Bets!AN2:AN73,"Y",Bets!AZ2:AZ73,"<>BET") -> 9.4
A9: Open bets | B9: =SUMPRODUCT(--(Bets!AN2:AN73="Y"),--(Bets!AQ2:AQ73="")) -> 1 | C9: Sum of BET stakes | D9: =SUM(Bets!AJ2:AJ73) -> 0
A11: LIVE VALUE BOARD — top BET signals right now (fills as you enter odds)
A12: # | B12: Date | C12: Group | D12: Match | E12: Pick | F12: Odds | G12: EV | H12: Edge | I12: Stake £
A13: {=IFERROR(INDEX(Bets!$A$2:$A$73,MATCH(LARGE(Bets!$AM$2:$AM$73,1),Bets!$AM$2:$AM$73,0)),"")} -> 9 | B13: {=IFERROR(INDEX(Bets!$B$2:$B$73,MATCH(LARGE(Bets!$AM$2:$AM$73,1),Bets!$AM$2:$AM$73,0)),"")} -> 46187 | C13: {=IFERROR(INDEX(Bets!$C$2:$C$73,MATCH(LARGE(Bets!$AM$2:$AM$73,1),Bets!$AM$2:$AM$73,0)),"")} -> E | D13: {=IFERROR(INDEX(Bets!$D$2:$D$73,MATCH(LARGE(Bets!$AM$2:$AM$73,1),Bets!$AM$2:$AM$73,0))&" v "&INDEX(Bets!$E$2:$E$73,MATCH(LARGE(Bets!$AM$2:$AM$73,1),Bets!$AM$2:$AM$73,0)),"")} -> Germany v Curacao | E13: {=IFERROR(INDEX(Bets!$AD$2:$AD$73,MATCH(LARGE(Bets!$AM$2:$AM$73,1),Bets!$AM$2:$AM$73,0)),"")} -> X Draw | F13: {=IFERROR(INDEX(Bets!$AE$2:$AE$73,MATCH(LARGE(Bets!$AM$2:$AM$73,1),Bets!$AM$2:$AM$73,0)),"")} -> 19 | G13: {=IFERROR(INDEX(Bets!$AF$2:$AF$73,MATCH(LARGE(Bets!$AM$2:$AM$73,1),Bets!$AM$2:$AM$73,0)),"")} -> 0.66307727 | H13: {=IFERROR(INDEX(Bets!$AG$2:$AG$73,MATCH(LARGE(Bets!$AM$2:$AM$73,1),Bets!$AM$2:$AM$73,0)),"")} -> 0.049597147 | I13: {=IFERROR(INDEX(Bets!$AJ$2:$AJ$73,MATCH(LARGE(Bets!$AM$2:$AM$73,1),Bets!$AM$2:$AM$73,0)),"")} -> 0
A14: {=IFERROR(INDEX(Bets!$A$2:$A$73,MATCH(LARGE(Bets!$AM$2:$AM$73,2),Bets!$AM$2:$AM$73,0)),"")} -> 13 | B14: {=IFERROR(INDEX(Bets!$B$2:$B$73,MATCH(LARGE(Bets!$AM$2:$AM$73,2),Bets!$AM$2:$AM$73,0)),"")} -> 46188 | C14: {=IFERROR(INDEX(Bets!$C$2:$C$73,MATCH(LARGE(Bets!$AM$2:$AM$73,2),Bets!$AM$2:$AM$73,0)),"")} -> H | D14: {=IFERROR(INDEX(Bets!$D$2:$D$73,MATCH(LARGE(Bets!$AM$2:$AM$73,2),Bets!$AM$2:$AM$73,0))&" v "&INDEX(Bets!$E$2:$E$73,MATCH(LARGE(Bets!$AM$2:$AM$73,2),Bets!$AM$2:$AM$73,0)),"")} -> Spain v Cape Verde | E14: {=IFERROR(INDEX(Bets!$AD$2:$AD$73,MATCH(LARGE(Bets!$AM$2:$AM$73,2),Bets!$AM$2:$AM$73,0)),"")} -> X Draw | F14: {=IFERROR(INDEX(Bets!$AE$2:$AE$73,MATCH(LARGE(Bets!$AM$2:$AM$73,2),Bets!$AM$2:$AM$73,0)),"")} -> 14 | G14: {=IFERROR(INDEX(Bets!$AF$2:$AF$73,MATCH(LARGE(Bets!$AM$2:$AM$73,2),Bets!$AM$2:$AM$73,0)),"")} -> 0.40171 | H14: {=IFERROR(INDEX(Bets!$AG$2:$AG$73,MATCH(LARGE(Bets!$AM$2:$AM$73,2),Bets!$AM$2:$AM$73,0)),"")} -> 0.035180648 | I14: {=IFERROR(INDEX(Bets!$AJ$2:$AJ$73,MATCH(LARGE(Bets!$AM$2:$AM$73,2),Bets!$AM$2:$AM$73,0)),"")} -> 0
A15: {=IFERROR(INDEX(Bets!$A$2:$A$73,MATCH(LARGE(Bets!$AM$2:$AM$73,3),Bets!$AM$2:$AM$73,0)),"")} -> 8 | B15: {=IFERROR(INDEX(Bets!$B$2:$B$73,MATCH(LARGE(Bets!$AM$2:$AM$73,3),Bets!$AM$2:$AM$73,0)),"")} -> 46186 | C15: {=IFERROR(INDEX(Bets!$C$2:$C$73,MATCH(LARGE(Bets!$AM$2:$AM$73,3),Bets!$AM$2:$AM$73,0)),"")} -> D | D15: {=IFERROR(INDEX(Bets!$D$2:$D$73,MATCH(LARGE(Bets!$AM$2:$AM$73,3),Bets!$AM$2:$AM$73,0))&" v "&INDEX(Bets!$E$2:$E$73,MATCH(LARGE(Bets!$AM$2:$AM$73,3),Bets!$AM$2:$AM$73,0)),"")} -> Australia v Turkey | E15: {=IFERROR(INDEX(Bets!$AD$2:$AD$73,MATCH(LARGE(Bets!$AM$2:$AM$73,3),Bets!$AM$2:$AM$73,0)),"")} -> 1 Australia | F15: {=IFERROR(INDEX(Bets!$AE$2:$AE$73,MATCH(LARGE(Bets!$AM$2:$AM$73,3),Bets!$AM$2:$AM$73,0)),"")} -> 5.25 | G15: {=IFERROR(INDEX(Bets!$AF$2:$AF$73,MATCH(LARGE(Bets!$AM$2:$AM$73,3),Bets!$AM$2:$AM$73,0)),"")} -> 0.25800572 | H15: {=IFERROR(INDEX(Bets!$AG$2:$AG$73,MATCH(LARGE(Bets!$AM$2:$AM$73,3),Bets!$AM$2:$AM$73,0)),"")} -> 0.065570164 | I15: {=IFERROR(INDEX(Bets!$AJ$2:$AJ$73,MATCH(LARGE(Bets!$AM$2:$AM$73,3),Bets!$AM$2:$AM$73,0)),"")} -> 0
A16: {=IFERROR(INDEX(Bets!$A$2:$A$73,MATCH(LARGE(Bets!$AM$2:$AM$73,4),Bets!$AM$2:$AM$73,0)),"")} -> 5 | B16: {=IFERROR(INDEX(Bets!$B$2:$B$73,MATCH(LARGE(Bets!$AM$2:$AM$73,4),Bets!$AM$2:$AM$73,0)),"")} -> 46186 | C16: {=IFERROR(INDEX(Bets!$C$2:$C$73,MATCH(LARGE(Bets!$AM$2:$AM$73,4),Bets!$AM$2:$AM$73,0)),"")} -> B | D16: {=IFERROR(INDEX(Bets!$D$2:$D$73,MATCH(LARGE(Bets!$AM$2:$AM$73,4),Bets!$AM$2:$AM$73,0))&" v "&INDEX(Bets!$E$2:$E$73,MATCH(LARGE(Bets!$AM$2:$AM$73,4),Bets!$AM$2:$AM$73,0)),"")} -> Qatar v Switzerland | E16: {=IFERROR(INDEX(Bets!$AD$2:$AD$73,MATCH(LARGE(Bets!$AM$2:$AM$73,4),Bets!$AM$2:$AM$73,0)),"")} -> X Draw | F16: {=IFERROR(INDEX(Bets!$AE$2:$AE$73,MATCH(LARGE(Bets!$AM$2:$AM$73,4),Bets!$AM$2:$AM$73,0)),"")} -> 7.5 | G16: {=IFERROR(INDEX(Bets!$AF$2:$AF$73,MATCH(LARGE(Bets!$AM$2:$AM$73,4),Bets!$AM$2:$AM$73,0)),"")} -> 0.11654745 | H16: {=IFERROR(INDEX(Bets!$AG$2:$AG$73,MATCH(LARGE(Bets!$AM$2:$AM$73,4),Bets!$AM$2:$AM$73,0)),"")} -> 0.026396158 | I16: {=IFERROR(INDEX(Bets!$AJ$2:$AJ$73,MATCH(LARGE(Bets!$AM$2:$AM$73,4),Bets!$AM$2:$AM$73,0)),"")} -> 0
A17: {=IFERROR(INDEX(Bets!$A$2:$A$73,MATCH(LARGE(Bets!$AM$2:$AM$73,5),Bets!$AM$2:$AM$73,0)),"")} -> 6 | B17: {=IFERROR(INDEX(Bets!$B$2:$B$73,MATCH(LARGE(Bets!$AM$2:$AM$73,5),Bets!$AM$2:$AM$73,0)),"")} -> 46186 | C17: {=IFERROR(INDEX(Bets!$C$2:$C$73,MATCH(LARGE(Bets!$AM$2:$AM$73,5),Bets!$AM$2:$AM$73,0)),"")} -> C | D17: {=IFERROR(INDEX(Bets!$D$2:$D$73,MATCH(LARGE(Bets!$AM$2:$AM$73,5),Bets!$AM$2:$AM$73,0))&" v "&INDEX(Bets!$E$2:$E$73,MATCH(LARGE(Bets!$AM$2:$AM$73,5),Bets!$AM$2:$AM$73,0)),"")} -> Brazil v Morocco | E17: {=IFERROR(INDEX(Bets!$AD$2:$AD$73,MATCH(LARGE(Bets!$AM$2:$AM$73,5),Bets!$AM$2:$AM$73,0)),"")} -> 2 Morocco | F17: {=IFERROR(INDEX(Bets!$AE$2:$AE$73,MATCH(LARGE(Bets!$AM$2:$AM$73,5),Bets!$AM$2:$AM$73,0)),"")} -> 5.5 | G17: {=IFERROR(INDEX(Bets!$AF$2:$AF$73,MATCH(LARGE(Bets!$AM$2:$AM$73,5),Bets!$AM$2:$AM$73,0)),"")} -> 0.10709084 | H17: {=IFERROR(INDEX(Bets!$AG$2:$AG$73,MATCH(LARGE(Bets!$AM$2:$AM$73,5),Bets!$AM$2:$AM$73,0)),"")} -> 0.030207955 | I17: {=IFERROR(INDEX(Bets!$AJ$2:$AJ$73,MATCH(LARGE(Bets!$AM$2:$AM$73,5),Bets!$AM$2:$AM$73,0)),"")} -> 0
A18: {=IFERROR(INDEX(Bets!$A$2:$A$73,MATCH(LARGE(Bets!$AM$2:$AM$73,6),Bets!$AM$2:$AM$73,0)),"")} -> 3 | B18: {=IFERROR(INDEX(Bets!$B$2:$B$73,MATCH(LARGE(Bets!$AM$2:$AM$73,6),Bets!$AM$2:$AM$73,0)),"")} -> 46185 | C18: {=IFERROR(INDEX(Bets!$C$2:$C$73,MATCH(LARGE(Bets!$AM$2:$AM$73,6),Bets!$AM$2:$AM$73,0)),"")} -> B | D18: {=IFERROR(INDEX(Bets!$D$2:$D$73,MATCH(LARGE(Bets!$AM$2:$AM$73,6),Bets!$AM$2:$AM$73,0))&" v "&INDEX(Bets!$E$2:$E$73,MATCH(LARGE(Bets!$AM$2:$AM$73,6),Bets!$AM$2:$AM$73,0)),"")} -> Canada v Bosnia and Herzegovina | E18: {=IFERROR(INDEX(Bets!$AD$2:$AD$73,MATCH(LARGE(Bets!$AM$2:$AM$73,6),Bets!$AM$2:$AM$73,0)),"")} -> 1 Canada | F18: {=IFERROR(INDEX(Bets!$AE$2:$AE$73,MATCH(LARGE(Bets!$AM$2:$AM$73,6),Bets!$AM$2:$AM$73,0)),"")} -> 1.85 | G18: {=IFERROR(INDEX(Bets!$AF$2:$AF$73,MATCH(LARGE(Bets!$AM$2:$AM$73,6),Bets!$AM$2:$AM$73,0)),"")} -> 0.079476281 | H18: {=IFERROR(INDEX(Bets!$AG$2:$AG$73,MATCH(LARGE(Bets!$AM$2:$AM$73,6),Bets!$AM$2:$AM$73,0)),"")} -> 0.061387805 | I18: {=IFERROR(INDEX(Bets!$AJ$2:$AJ$73,MATCH(LARGE(Bets!$AM$2:$AM$73,6),Bets!$AM$2:$AM$73,0)),"")} -> 0
A19: {=IFERROR(INDEX(Bets!$A$2:$A$73,MATCH(LARGE(Bets!$AM$2:$AM$73,7),Bets!$AM$2:$AM$73,0)),"")} -> 12 | B19: {=IFERROR(INDEX(Bets!$B$2:$B$73,MATCH(LARGE(Bets!$AM$2:$AM$73,7),Bets!$AM$2:$AM$73,0)),"")} -> 46187 | C19: {=IFERROR(INDEX(Bets!$C$2:$C$73,MATCH(LARGE(Bets!$AM$2:$AM$73,7),Bets!$AM$2:$AM$73,0)),"")} -> F | D19: {=IFERROR(INDEX(Bets!$D$2:$D$73,MATCH(LARGE(Bets!$AM$2:$AM$73,7),Bets!$AM$2:$AM$73,0))&" v "&INDEX(Bets!$E$2:$E$73,MATCH(LARGE(Bets!$AM$2:$AM$73,7),Bets!$AM$2:$AM$73,0)),"")} -> Sweden v Tunisia | E19: {=IFERROR(INDEX(Bets!$AD$2:$AD$73,MATCH(LARGE(Bets!$AM$2:$AM$73,7),Bets!$AM$2:$AM$73,0)),"")} -> 2 Tunisia | F19: {=IFERROR(INDEX(Bets!$AE$2:$AE$73,MATCH(LARGE(Bets!$AM$2:$AM$73,7),Bets!$AM$2:$AM$73,0)),"")} -> 4.33 | G19: {=IFERROR(INDEX(Bets!$AF$2:$AF$73,MATCH(LARGE(Bets!$AM$2:$AM$73,7),Bets!$AM$2:$AM$73,0)),"")} -> 0.054579994 | H19: {=IFERROR(INDEX(Bets!$AG$2:$AG$73,MATCH(LARGE(Bets!$AM$2:$AM$73,7),Bets!$AM$2:$AM$73,0)),"")} -> 0.028208356 | I19: {=IFERROR(INDEX(Bets!$AJ$2:$AJ$73,MATCH(LARGE(Bets!$AM$2:$AM$73,7),Bets!$AM$2:$AM$73,0)),"")} -> 0
A20: {=IFERROR(INDEX(Bets!$A$2:$A$73,MATCH(LARGE(Bets!$AM$2:$AM$73,8),Bets!$AM$2:$AM$73,0)),"")} -> 2 | B20: {=IFERROR(INDEX(Bets!$B$2:$B$73,MATCH(LARGE(Bets!$AM$2:$AM$73,8),Bets!$AM$2:$AM$73,0)),"")} -> 46184 | C20: {=IFERROR(INDEX(Bets!$C$2:$C$73,MATCH(LARGE(Bets!$AM$2:$AM$73,8),Bets!$AM$2:$AM$73,0)),"")} -> A | D20: {=IFERROR(INDEX(Bets!$D$2:$D$73,MATCH(LARGE(Bets!$AM$2:$AM$73,8),Bets!$AM$2:$AM$73,0))&" v "&INDEX(Bets!$E$2:$E$73,MATCH(LARGE(Bets!$AM$2:$AM$73,8),Bets!$AM$2:$AM$73,0)),"")} -> South Korea v Czechia | E20: {=IFERROR(INDEX(Bets!$AD$2:$AD$73,MATCH(LARGE(Bets!$AM$2:$AM$73,8),Bets!$AM$2:$AM$73,0)),"")} -> 1 South Korea | F20: {=IFERROR(INDEX(Bets!$AE$2:$AE$73,MATCH(LARGE(Bets!$AM$2:$AM$73,8),Bets!$AM$2:$AM$73,0)),"")} -> 2.7 | G20: {=IFERROR(INDEX(Bets!$AF$2:$AF$73,MATCH(LARGE(Bets!$AM$2:$AM$73,8),Bets!$AM$2:$AM$73,0)),"")} -> 0.039558709 | H20: {=IFERROR(INDEX(Bets!$AG$2:$AG$73,MATCH(LARGE(Bets!$AM$2:$AM$73,8),Bets!$AM$2:$AM$73,0)),"")} -> 0.031600929 | I20: {=IFERROR(INDEX(Bets!$AJ$2:$AJ$73,MATCH(LARGE(Bets!$AM$2:$AM$73,8),Bets!$AM$2:$AM$73,0)),"")} -> 0
A22: MATCHDAY LEDGER — stakes & P&L by day | G22: HOUSE RULES
A23: Date | B23: Games | C23: Staked £ | D23: P&L £ | G23: · Only stake when FINAL ACTION shows 🟢 PLACE.
A24: 46184 | B24: =COUNTIF(Bets!$B$2:$B$73,$A24) -> 2 | C24: =SUMIFS(Bets!$AP$2:$AP$73,Bets!$B$2:$B$73,$A24,Bets!$AN$2:$AN$73,"Y") -> 30 | D24: =SUMIFS(Bets!$AR$2:$AR$73,Bets!$B$2:$B$73,$A24) -> 24.4 | E24: =IF(D24>0,REPT("█",MIN(25,ROUND(D24/4,0))),REPT("░",MIN(25,ROUND(-D24/4,0)))) -> ██████ | G24: · "—" or PASS on most matches = the filter working, not a fault.
A25: 46185 | B25: =COUNTIF(Bets!$B$2:$B$73,$A25) -> 2 | C25: =SUMIFS(Bets!$AP$2:$AP$73,Bets!$B$2:$B$73,$A25,Bets!$AN$2:$AN$73,"Y") -> 44 | D25: =SUMIFS(Bets!$AR$2:$AR$73,Bets!$B$2:$B$73,$A25) -> -3 | E25: =IF(D25>0,REPT("█",MIN(25,ROUND(D25/4,0))),REPT("░",MIN(25,ROUND(-D25/4,0)))) -> ░ | G25: · Fun bets are allowed — small (≤ £5), and STATUS labels them honestly.
A26: 46186 | B26: =COUNTIF(Bets!$B$2:$B$73,$A26) -> 4 | C26: =SUMIFS(Bets!$AP$2:$AP$73,Bets!$B$2:$B$73,$A26,Bets!$AN$2:$AN$73,"Y") -> 60 | D26: =SUMIFS(Bets!$AR$2:$AR$73,Bets!$B$2:$B$73,$A26) -> 42.9 | E26: =IF(D26>0,REPT("█",MIN(25,ROUND(D26/4,0))),REPT("░",MIN(25,ROUND(-D26/4,0)))) -> ███████████ | G26: · Never exceed the stake shown. Never chase a loss.
A27: 46187 | B27: =COUNTIF(Bets!$B$2:$B$73,$A27) -> 4 | C27: =SUMIFS(Bets!$AP$2:$AP$73,Bets!$B$2:$B$73,$A27,Bets!$AN$2:$AN$73,"Y") -> 6 | D27: =SUMIFS(Bets!$AR$2:$AR$73,Bets!$B$2:$B$73,$A27) -> -6 | E27: =IF(D27>0,REPT("█",MIN(25,ROUND(D27/4,0))),REPT("░",MIN(25,ROUND(-D27/4,0)))) -> ░░ | G27: · Friends: stake = "£ per £100" × (their bankroll ÷ 100).
A28: 46188 | B28: =COUNTIF(Bets!$B$2:$B$73,$A28) -> 4 | C28: =SUMIFS(Bets!$AP$2:$AP$73,Bets!$B$2:$B$73,$A28,Bets!$AN$2:$AN$73,"Y") -> 0 | D28: =SUMIFS(Bets!$AR$2:$AR$73,Bets!$B$2:$B$73,$A28) -> 0 | E28: =IF(D28>0,REPT("█",MIN(25,ROUND(D28/4,0))),REPT("░",MIN(25,ROUND(-D28/4,0)))) | G28: · 18+ · not financial advice · BeGambleAware.org
A29: 46189 | B29: =COUNTIF(Bets!$B$2:$B$73,$A29) -> 4 | C29: =SUMIFS(Bets!$AP$2:$AP$73,Bets!$B$2:$B$73,$A29,Bets!$AN$2:$AN$73,"Y") -> 0 | D29: =SUMIFS(Bets!$AR$2:$AR$73,Bets!$B$2:$B$73,$A29) -> 0 | E29: =IF(D29>0,REPT("█",MIN(25,ROUND(D29/4,0))),REPT("░",MIN(25,ROUND(-D29/4,0))))
A30: 46190 | B30: =COUNTIF(Bets!$B$2:$B$73,$A30) -> 4 | C30: =SUMIFS(Bets!$AP$2:$AP$73,Bets!$B$2:$B$73,$A30,Bets!$AN$2:$AN$73,"Y") -> 0 | D30: =SUMIFS(Bets!$AR$2:$AR$73,Bets!$B$2:$B$73,$A30) -> 0 | E30: =IF(D30>0,REPT("█",MIN(25,ROUND(D30/4,0))),REPT("░",MIN(25,ROUND(-D30/4,0))))
A31: 46191 | B31: =COUNTIF(Bets!$B$2:$B$73,$A31) -> 4 | C31: =SUMIFS(Bets!$AP$2:$AP$73,Bets!$B$2:$B$73,$A31,Bets!$AN$2:$AN$73,"Y") -> 0 | D31: =SUMIFS(Bets!$AR$2:$AR$73,Bets!$B$2:$B$73,$A31) -> 0 | E31: =IF(D31>0,REPT("█",MIN(25,ROUND(D31/4,0))),REPT("░",MIN(25,ROUND(-D31/4,0))))
A32: 46192 | B32: =COUNTIF(Bets!$B$2:$B$73,$A32) -> 4 | C32: =SUMIFS(Bets!$AP$2:$AP$73,Bets!$B$2:$B$73,$A32,Bets!$AN$2:$AN$73,"Y") -> 0 | D32: =SUMIFS(Bets!$AR$2:$AR$73,Bets!$B$2:$B$73,$A32) -> 0 | E32: =IF(D32>0,REPT("█",MIN(25,ROUND(D32/4,0))),REPT("░",MIN(25,ROUND(-D32/4,0))))
A33: 46193 | B33: =COUNTIF(Bets!$B$2:$B$73,$A33) -> 4 | C33: =SUMIFS(Bets!$AP$2:$AP$73,Bets!$B$2:$B$73,$A33,Bets!$AN$2:$AN$73,"Y") -> 0 | D33: =SUMIFS(Bets!$AR$2:$AR$73,Bets!$B$2:$B$73,$A33) -> 0 | E33: =IF(D33>0,REPT("█",MIN(25,ROUND(D33/4,0))),REPT("░",MIN(25,ROUND(-D33/4,0))))
A34: 46194 | B34: =COUNTIF(Bets!$B$2:$B$73,$A34) -> 4 | C34: =SUMIFS(Bets!$AP$2:$AP$73,Bets!$B$2:$B$73,$A34,Bets!$AN$2:$AN$73,"Y") -> 0 | D34: =SUMIFS(Bets!$AR$2:$AR$73,Bets!$B$2:$B$73,$A34) -> 0 | E34: =IF(D34>0,REPT("█",MIN(25,ROUND(D34/4,0))),REPT("░",MIN(25,ROUND(-D34/4,0))))
A35: 46195 | B35: =COUNTIF(Bets!$B$2:$B$73,$A35) -> 4 | C35: =SUMIFS(Bets!$AP$2:$AP$73,Bets!$B$2:$B$73,$A35,Bets!$AN$2:$AN$73,"Y") -> 0 | D35: =SUMIFS(Bets!$AR$2:$AR$73,Bets!$B$2:$B$73,$A35) -> 0 | E35: =IF(D35>0,REPT("█",MIN(25,ROUND(D35/4,0))),REPT("░",MIN(25,ROUND(-D35/4,0))))
A36: 46196 | B36: =COUNTIF(Bets!$B$2:$B$73,$A36) -> 4 | C36: =SUMIFS(Bets!$AP$2:$AP$73,Bets!$B$2:$B$73,$A36,Bets!$AN$2:$AN$73,"Y") -> 0 | D36: =SUMIFS(Bets!$AR$2:$AR$73,Bets!$B$2:$B$73,$A36) -> 0 | E36: =IF(D36>0,REPT("█",MIN(25,ROUND(D36/4,0))),REPT("░",MIN(25,ROUND(-D36/4,0))))
A37: 46197 | B37: =COUNTIF(Bets!$B$2:$B$73,$A37) -> 6 | C37: =SUMIFS(Bets!$AP$2:$AP$73,Bets!$B$2:$B$73,$A37,Bets!$AN$2:$AN$73,"Y") -> 0 | D37: =SUMIFS(Bets!$AR$2:$AR$73,Bets!$B$2:$B$73,$A37) -> 0 | E37: =IF(D37>0,REPT("█",MIN(25,ROUND(D37/4,0))),REPT("░",MIN(25,ROUND(-D37/4,0))))
A38: 46198 | B38: =COUNTIF(Bets!$B$2:$B$73,$A38) -> 6 | C38: =SUMIFS(Bets!$AP$2:$AP$73,Bets!$B$2:$B$73,$A38,Bets!$AN$2:$AN$73,"Y") -> 0 | D38: =SUMIFS(Bets!$AR$2:$AR$73,Bets!$B$2:$B$73,$A38) -> 0 | E38: =IF(D38>0,REPT("█",MIN(25,ROUND(D38/4,0))),REPT("░",MIN(25,ROUND(-D38/4,0))))
A39: 46199 | B39: =COUNTIF(Bets!$B$2:$B$73,$A39) -> 6 | C39: =SUMIFS(Bets!$AP$2:$AP$73,Bets!$B$2:$B$73,$A39,Bets!$AN$2:$AN$73,"Y") -> 0 | D39: =SUMIFS(Bets!$AR$2:$AR$73,Bets!$B$2:$B$73,$A39) -> 0 | E39: =IF(D39>0,REPT("█",MIN(25,ROUND(D39/4,0))),REPT("░",MIN(25,ROUND(-D39/4,0))))
A40: 46200 | B40: =COUNTIF(Bets!$B$2:$B$73,$A40) -> 6 | C40: =SUMIFS(Bets!$AP$2:$AP$73,Bets!$B$2:$B$73,$A40,Bets!$AN$2:$AN$73,"Y") -> 0 | D40: =SUMIFS(Bets!$AR$2:$AR$73,Bets!$B$2:$B$73,$A40) -> 0 | E40: =IF(D40>0,REPT("█",MIN(25,ROUND(D40/4,0))),REPT("░",MIN(25,ROUND(-D40/4,0))))

Sheet Live
A1: LIVE STATE — auto-polled from /live_state.json
A3: Source URL | B3: https://wc26-matchday-intelligence.vercel.app/live_state.json
A4: Predictions URL | B4: https://wc26-matchday-intelligence.vercel.app/predictions_live.json
A5: Intel URL | B5: https://wc26-matchday-intelligence.vercel.app/matchday_intelligence.json
A6: Field | B6: Value | C6: Mirrors to Method
A7: Last poll (UTC) | B7: 46189.585 | C7: B58
A8: Mode | B8: live | C8: B59
A9: Completed matches | B9: 16 | C9: B60
A10: Provider mode | B10: active | C10: B61
A11: Warnings (joined) | C11: B62
A12: Source | B12: api_football
A13: Last model refresh (UTC) | C13: B57
A14: Simulation rerun this tick | B14: TRUE
A15: live_state last_updated_utc | B15: 2026-06-16T13:37:22.742806+00:00
A17: STATUS | B17: =IF(B7="","⚠ Apps Script not run yet — open Extensions ▸ Apps Script ▸ run installEngine()","✓ live polling active · last poll "&TEXT(B7,"yyyy-mm-dd hh:mm")) -> ✓ live polling active · last poll 2026-06-16 14:02
A18: — MATCHDAY INTELLIGENCE (auto) —
A19: Intel generated at (UTC) | B19: 2026-06-16T11:13:56.346678+00:00 | C19: mirrors to Method!B67
A20: Intel total components | B20: 52 | C20: B68
A21: Intel teams affected | B21: 38 | C21: B69
A22: Intel matches affected | B22: 14 | C22: B70
A23: Intel aggregate caps hit | B23: 0 | C23: B71
A24: Intel warnings | B24: [object Object]
A25: Matches in play right now | B25: 0 | C25: see In-Play sheet
A26: Stale-feed warning | B26: ⚠ STALE feed (25 min old) — model paused | C26: >15 min trips PAUSE
A28: Endpoints — clear B3/B4/B5 to revert to v2.3 defaults.
A30: This sheet is read-only output from the Apps Script poller. If the values stay blank, open Extensions ▸ Apps Script and run installEngine() once. The script then refreshes model probabilities into Bets!I:K (skipping any row already flagged as Placed=Y) and writes a snapshot of /live_state.json here every 5 minutes.

Sheet Bets
A1: # | B1: Date | C1: Grp | D1: Home | E1: Away | F1: Venue | G1: KO local | H1: KO UK | I1: Model pH | J1: Model pD | K1: Model pA | L1: Odds H | M1: Odds D | N1: Odds A | O1: imp H | P1: imp D | Q1: imp A | R1: Overround | S1: mkt H | T1: mkt D | U1: mkt A | V1: blend H | W1: blend D | X1: blend A | Y1: EV H | Z1: EV D | AA1: EV A | AB1: pick# | AC1: code | AD1: PICK | AE1: Odds | AF1: EV % | AG1: Edge pp | AH1: DECISION | AI1: £ / £100 bank | AJ1: ENGINE STAKE £ | AK1: p(blend) | AL1: Kelly f | AM1: rankkey | AN1: Placed? | AO1: Odds taken | AP1: Stake £ | AQ1: Result | AR1: P&L £ | AS1: Cum P&L | AT1: WHY (plain English) | AU1: STATUS | AV1: Backed | AW1: dec@bet | AX1: eng£@bet | AY1: pick@bet | AZ1: class | BA1: eng£ eff | BB1: intel Δ | BC1: pH (cal) | BD1: pD (cal) | BE1: pA (cal) | BF1: intel breakdown | BG1: altitude m | BH1: climate | BI1: home travel km
A2: 1 | B2: 46184 | C2: A | D2: Mexico | E2: South Africa | F2: Mexico City | G2: 13:00 | H2: 20:00 | I2: 0.7008 | J2: 0.2117 | K2: 0.0876 | L2: =IF(Matchday!E4="","",Matchday!E4) -> 1.42 | M2: =IF(Matchday!F4="","",Matchday!F4) -> 4.5 | N2: =IF(Matchday!G4="","",Matchday!G4) -> 8.5 | O2: =IF(L2="","",1/L2) -> 0.70422535 | P2: =IF(M2="","",1/M2) -> 0.22222222 | Q2: =IF(N2="","",1/N2) -> 0.11764706 | R2: =IF(COUNT(L2:N2)<3,"",O2+P2+Q2) -> 1.0440946 | S2: {=IF($R2="","",IF(Method!$B$56="proportional",O2/$R2,IF(Method!$B$56="power",IFERROR(INDEX(power_devig($L2,$M2,$N2),1,1),O2/$R2),IFERROR(INDEX(shin($L2,$M2,$N2),1,1),O2/$R2))))} -> 0.68567733 | T2: {=IF($R2="","",IF(Method!$B$56="proportional",P2/$R2,IF(Method!$B$56="power",IFERROR(INDEX(power_devig($L2,$M2,$N2),2,1),P2/$R2),IFERROR(INDEX(shin($L2,$M2,$N2),2,1),P2/$R2))))} -> 0.20878432 | U2: {=IF($R2="","",IF(Method!$B$56="proportional",Q2/$R2,IF(Method!$B$56="power",IFERROR(INDEX(power_devig($L2,$M2,$N2),3,1),Q2/$R2),IFERROR(INDEX(shin($L2,$M2,$N2),3,1),Q2/$R2))))} -> 0.10553835 | V2: =IF(S2="","",Method!$B$4*I2+(1-Method!$B$4)*S2/($S2+$T2+$U2)) -> 0.69097026 | W2: =IF(T2="","",Method!$B$4*J2+(1-Method!$B$4)*T2/($S2+$T2+$U2)) -> 0.20980481 | X2: =IF(U2="","",Method!$B$4*K2+(1-Method!$B$4)*U2/($S2+$T2+$U2)) -> 0.099259929 | Y2: =IF(V2="","",V2*L2-1) -> -0.018822225 | Z2: =IF(W2="","",W2*M2-1) -> -0.055878369 | AA2: =IF(X2="","",X2*N2-1) -> -0.1562906 | AB2: =IF(Y2="","",MATCH(MAX(Y2:AA2),Y2:AA2,0)) -> 1 | AC2: =IF(AB2="","",CHOOSE(AB2,"H","D","A")) -> H | AD2: =IF(AB2="","",CHOOSE(AB2,"1 "&D2,"X Draw","2 "&E2)) -> 1 Mexico | AE2: =IF(AB2="","",INDEX(L2:N2,1,AB2)) -> 1.42 | AF2: =IF(AB2="","",INDEX(Y2:AA2,1,AB2)) -> -0.018822225 | AG2: =IF(AB2="","",INDEX(V2:X2,1,AB2)-INDEX(S2:U2,1,AB2)) -> 0.0052929349 | AH2: =IF(AB2="","· enter odds",IF(AND(AF2>=Method!$B$7,AG2>=Method!$B$8),"BET","PASS")) -> PASS | AI2: =IF(AH2<>"BET",0,ROUND(MIN(Method!$B$6,Method!$B$5*AL2)*100,1)) -> 0 | AJ2: =IF(OR(AH2<>"BET",Method!$B$55=TRUE()),0,IF(AI2*Method!$B$10/100<Method!$B$9,0,ROUND(AI2*Method!$B$10/100,0))) -> 0 | AK2: =IF(AB2="","",INDEX(V2:X2,1,AB2)) -> 0.69097026 | AL2: =IF(AH2<>"BET","",MAX(0,(AK2*AE2-1)/(AE2-1))) | AM2: =IF(AH2="BET",AF2+A2/1000000,"") | AN2: =IF(Matchday!N4="","",Matchday!N4) -> Y | AO2: =IF(Matchday!P4="","",Matchday!P4) -> 1.42 | AP2: =IF(Matchday!Q4="","",Matchday!Q4) -> 20 | AQ2: =IF(Matchday!R4="","",Matchday!R4) -> H | AR2: =IF(OR(AN2<>"Y",AQ2="",AV2=""),"",IF(AQ2="Void",0,IF(AQ2=AV2,ROUND(AP2*(AO2-1),2),-AP2))) -> 8.4 | AS2: =IF(AR2="","",SUM($AR$2:AR2)) -> 8.4 | AT2: =IF(AB2="","Type the 3 odds on the Matchday tab",IF(Method!$B$55=TRUE(),"🛑 PAUSED — drawdown "&TEXT(Method!$B$51,"0.0%")&" ≥ "&TEXT(Method!$B$52,"0.0%")&". Set Method!B54=Y to override.",IF(AH2="BET",IF(AJ2=0,"Edge found but stake rounds under £"&Method!$B$9&" — skip","Value found: EV "&TEXT(AF2,"0.0%")&", edge "&TEXT(AG2,"0.0%")),IF(AF2<Method!$B$7,"Price too short — EV "&TEXT(AF2,"0.0%")&" (need "&TEXT(Method!$B$7,"0.0%")&"+)","Model ≈ market — edge "&TEXT(AG2,"0.0%")&" (need "&TEXT(Method!$B$8,"0.0%")&"+)")))) -> 🛑 PAUSED — drawdown 0.6% ≥ 15.0%. Set Method!B54=Y to override. | AU2: =IF(AN2<>"Y","",IF(AH2="· enter odds","⚠ type the 3 odds (1/X/2) to grade this bet",IF(OR(AV2="",AO2="",AP2=""),"⚠ log backed pick, odds & stake",IF(AZ2<>"BET","⚠ FUN BET — engine said pass · staked £"&AP2&" vs engine £"&BA2,IF(AV2<>IF(AY2="",AC2,AY2),"⚠ backed "&AV2&" but engine pick was "&IF(AY2="",AC2,AY2),IF(AP2>BA2,"⚠ stake over engine £"&BA2,IF(ABS(AO2-IFERROR(INDEX(L2:N2,1,MATCH(AV2,{"H","D","A"},0)),AE2))>0.02,"⚠ odds moved — re-check value","✓ engine bet"))))))) -> ⚠ FUN BET — engine said pass · staked £20 vs engine £0 | AV2: =IF(Matchday!O4="","",Matchday!O4) -> H | AW2: PASS | AX2: 0 | AY2: H | AZ2: =IF(AW2="",AH2,AW2) -> PASS | BA2: =IF(AX2<>"",AX2,IF(AH2<>"BET",0,IF(AI2*Method!$B$10/100<Method!$B$9,0,ROUND(AI2*Method!$B$10/100,0)))) -> 0 | BB2: 0 | BC2: 0.650274 | BD2: 0.23507441 | BE2: 0.088686139 | BG2: 2240 | BH2: high_altitude_mild | BI2: 0
A3: 2 | B3: 46184 | C3: A | D3: South Korea | E3: Czechia | F3: Zapopan | G3: 20:00 | H3: 03:00 +1d | I3: 0.44370918 | J3: 0.29067093 | K3: 0.26561988 | L3: =IF(Matchday!E5="","",Matchday!E5) -> 2.7 | M3: =IF(Matchday!F5="","",Matchday!F5) -> 3.1 | N3: =IF(Matchday!G5="","",Matchday!G5) -> 2.8 | O3: =IF(L3="","",1/L3) -> 0.37037037 | P3: =IF(M3="","",1/M3) -> 0.32258065 | Q3: =IF(N3="","",1/N3) -> 0.35714286 | R3: =IF(COUNT(L3:N3)<3,"",O3+P3+Q3) -> 1.0500939 | S3: {=IF($R3="","",IF(Method!$B$56="proportional",O3/$R3,IF(Method!$B$56="power",IFERROR(INDEX(power_devig($L3,$M3,$N3),1,1),O3/$R3),IFERROR(INDEX(shin($L3,$M3,$N3),1,1),O3/$R3))))} -> 0.35342082 | T3: {=IF($R3="","",IF(Method!$B$56="proportional",P3/$R3,IF(Method!$B$56="power",IFERROR(INDEX(power_devig($L3,$M3,$N3),2,1),P3/$R3),IFERROR(INDEX(shin($L3,$M3,$N3),2,1),P3/$R3))))} -> 0.30622296 | U3: {=IF($R3="","",IF(Method!$B$56="proportional",Q3/$R3,IF(Method!$B$56="power",IFERROR(INDEX(power_devig($L3,$M3,$N3),3,1),Q3/$R3),IFERROR(INDEX(shin($L3,$M3,$N3),3,1),Q3/$R3))))} -> 0.34035623 | V3: =IF(S3="","",Method!$B$4*I3+(1-Method!$B$4)*S3/($S3+$T3+$U3)) -> 0.38502174 | W3: =IF(T3="","",Method!$B$4*J3+(1-Method!$B$4)*T3/($S3+$T3+$U3)) -> 0.30077975 | X3: =IF(U3="","",Method!$B$4*K3+(1-Method!$B$4)*U3/($S3+$T3+$U3)) -> 0.31419851 | Y3: =IF(V3="","",V3*L3-1) -> 0.039558709 | Z3: =IF(W3="","",W3*M3-1) -> -0.067582783 | AA3: =IF(X3="","",X3*N3-1) -> -0.12024418 | AB3: =IF(Y3="","",MATCH(MAX(Y3:AA3),Y3:AA3,0)) -> 1 | AC3: =IF(AB3="","",CHOOSE(AB3,"H","D","A")) -> H | AD3: =IF(AB3="","",CHOOSE(AB3,"1 "&D3,"X Draw","2 "&E3)) -> 1 South Korea | AE3: =IF(AB3="","",INDEX(L3:N3,1,AB3)) -> 2.7 | AF3: =IF(AB3="","",INDEX(Y3:AA3,1,AB3)) -> 0.039558709 | AG3: =IF(AB3="","",INDEX(V3:X3,1,AB3)-INDEX(S3:U3,1,AB3)) -> 0.031600929 | AH3: =IF(AB3="","· enter odds",IF(AND(AF3>=Method!$B$7,AG3>=Method!$B$8),"BET","PASS")) -> BET | AI3: =IF(AH3<>"BET",0,ROUND(MIN(Method!$B$6,Method!$B$5*AL3)*100,1)) -> 0.6 | AJ3: =IF(OR(AH3<>"BET",Method!$B$55=TRUE()),0,IF(AI3*Method!$B$10/100<Method!$B$9,0,ROUND(AI3*Method!$B$10/100,0))) -> 0 | AK3: =IF(AB3="","",INDEX(V3:X3,1,AB3)) -> 0.38502174 | AL3: =IF(AH3<>"BET","",MAX(0,(AK3*AE3-1)/(AE3-1))) -> 0.023269829 | AM3: =IF(AH3="BET",AF3+A3/1000000,"") -> 0.039560709 | AN3: =IF(Matchday!N5="","",Matchday!N5) -> Y | AO3: =IF(Matchday!P5="","",Matchday!P5) -> 2.6 | AP3: =IF(Matchday!Q5="","",Matchday!Q5) -> 10 | AQ3: =IF(Matchday!R5="","",Matchday!R5) -> H | AR3: =IF(OR(AN3<>"Y",AQ3="",AV3=""),"",IF(AQ3="Void",0,IF(AQ3=AV3,ROUND(AP3*(AO3-1),2),-AP3))) -> 16 | AS3: =IF(AR3="","",SUM($AR$2:AR3)) -> 24.4 | AT3: =IF(AB3="","Type the 3 odds on the Matchday tab",IF(Method!$B$55=TRUE(),"🛑 PAUSED — drawdown "&TEXT(Method!$B$51,"0.0%")&" ≥ "&TEXT(Method!$B$52,"0.0%")&". Set Method!B54=Y to override.",IF(AH3="BET",IF(AJ3=0,"Edge found but stake rounds under £"&Method!$B$9&" — skip","Value found: EV "&TEXT(AF3,"0.0%")&", edge "&TEXT(AG3,"0.0%")),IF(AF3<Method!$B$7,"Price too short — EV "&TEXT(AF3,"0.0%")&" (need "&TEXT(Method!$B$7,"0.0%")&"+)","Model ≈ market — edge "&TEXT(AG3,"0.0%")&" (need "&TEXT(Method!$B$8,"0.0%")&"+)")))) -> 🛑 PAUSED — drawdown 0.6% ≥ 15.0%. Set Method!B54=Y to override. | AU3: =IF(AN3<>"Y","",IF(AH3="· enter odds","⚠ type the 3 odds (1/X/2) to grade this bet",IF(OR(AV3="",AO3="",AP3=""),"⚠ log backed pick, odds & stake",IF(AZ3<>"BET","⚠ FUN BET — engine said pass · staked £"&AP3&" vs engine £"&BA3,IF(AV3<>IF(AY3="",AC3,AY3),"⚠ backed "&AV3&" but engine pick was "&IF(AY3="",AC3,AY3),IF(AP3>BA3,"⚠ stake over engine £"&BA3,IF(ABS(AO3-IFERROR(INDEX(L3:N3,1,MATCH(AV3,{"H","D","A"},0)),AE3))>0.02,"⚠ odds moved — re-check value","✓ engine bet"))))))) -> ⚠ stake over engine £3 | AV3: =IF(Matchday!O5="","",Matchday!O5) -> H | AW3: BET | AX3: 3 | AY3: H | AZ3: =IF(AW3="",AH3,AW3) -> BET | BA3: =IF(AX3<>"",AX3,IF(AH3<>"BET",0,IF(AI3*Method!$B$10/100<Method!$B$9,0,ROUND(AI3*Method!$B$10/100,0)))) -> 3 | BB3: -5 | BC3: 0.42788052 | BD3: 0.29013376 | BE3: 0.2706498 | BF3: Czechia weather: -4 · South Korea weather: -1 | BG3: 1560 | BH3: warm_humid | BI3: 0
A4: 3 | B4: 46185 | C4: B | D4: Canada | E4: Bosnia and Herzegovina | F4: Toronto | G4: 15:00 | H4: 20:00 | I4: 0.69750662 | J4: 0.2132834 | K4: 0.089209979 | L4: =IF(Matchday!E6="","",Matchday!E6) -> 1.85 | M4: =IF(Matchday!F6="","",Matchday!F6) -> 3.5 | N4: =IF(Matchday!G6="","",Matchday!G6) -> 4.5 | O4: =IF(L4="","",1/L4) -> 0.54054054 | P4: =IF(M4="","",1/M4) -> 0.28571429 | Q4: =IF(N4="","",1/N4) -> 0.22222222 | R4: =IF(COUNT(L4:N4)<3,"",O4+P4+Q4) -> 1.048477 | S4: {=IF($R4="","",IF(Method!$B$56="proportional",O4/$R4,IF(Method!$B$56="power",IFERROR(INDEX(power_devig($L4,$M4,$N4),1,1),O4/$R4),IFERROR(INDEX(shin($L4,$M4,$N4),1,1),O4/$R4))))} -> 0.52211289 | T4: {=IF($R4="","",IF(Method!$B$56="proportional",P4/$R4,IF(Method!$B$56="power",IFERROR(INDEX(power_devig($L4,$M4,$N4),2,1),P4/$R4),IFERROR(INDEX(shin($L4,$M4,$N4),2,1),P4/$R4))))} -> 0.27029207 | U4: {=IF($R4="","",IF(Method!$B$56="proportional",Q4/$R4,IF(Method!$B$56="power",IFERROR(INDEX(power_devig($L4,$M4,$N4),3,1),Q4/$R4),IFERROR(INDEX(shin($L4,$M4,$N4),3,1),Q4/$R4))))} -> 0.20759504 | V4: =IF(S4="","",Method!$B$4*I4+(1-Method!$B$4)*S4/($S4+$T4+$U4)) -> 0.58350069 | W4: =IF(T4="","",Method!$B$4*J4+(1-Method!$B$4)*T4/($S4+$T4+$U4)) -> 0.25033904 | X4: =IF(U4="","",Method!$B$4*K4+(1-Method!$B$4)*U4/($S4+$T4+$U4)) -> 0.16616027 | Y4: =IF(V4="","",V4*L4-1) -> 0.079476281 | Z4: =IF(W4="","",W4*M4-1) -> -0.12381337 | AA4: =IF(X4="","",X4*N4-1) -> -0.25227878 | AB4: =IF(Y4="","",MATCH(MAX(Y4:AA4),Y4:AA4,0)) -> 1 | AC4: =IF(AB4="","",CHOOSE(AB4,"H","D","A")) -> H | AD4: =IF(AB4="","",CHOOSE(AB4,"1 "&D4,"X Draw","2 "&E4)) -> 1 Canada | AE4: =IF(AB4="","",INDEX(L4:N4,1,AB4)) -> 1.85 | AF4: =IF(AB4="","",INDEX(Y4:AA4,1,AB4)) -> 0.079476281 | AG4: =IF(AB4="","",INDEX(V4:X4,1,AB4)-INDEX(S4:U4,1,AB4)) -> 0.061387805 | AH4: =IF(AB4="","· enter odds",IF(AND(AF4>=Method!$B$7,AG4>=Method!$B$8),"BET","PASS")) -> BET | AI4: =IF(AH4<>"BET",0,ROUND(MIN(Method!$B$6,Method!$B$5*AL4)*100,1)) -> 2.3 | AJ4: =IF(OR(AH4<>"BET",Method!$B$55=TRUE()),0,IF(AI4*Method!$B$10/100<Method!$B$9,0,ROUND(AI4*Method!$B$10/100,0))) -> 0 | AK4: =IF(AB4="","",INDEX(V4:X4,1,AB4)) -> 0.58350069 | AL4: =IF(AH4<>"BET","",MAX(0,(AK4*AE4-1)/(AE4-1))) -> 0.093501507 | AM4: =IF(AH4="BET",AF4+A4/1000000,"") -> 0.079479281 | AN4: =IF(Matchday!N6="","",Matchday!N6) -> Y | AO4: =IF(Matchday!P6="","",Matchday!P6) -> 1.85 | AP4: =IF(Matchday!Q6="","",Matchday!Q6) -> 24 | AQ4: =IF(Matchday!R6="","",Matchday!R6) -> D | AR4: =IF(OR(AN4<>"Y",AQ4="",AV4=""),"",IF(AQ4="Void",0,IF(AQ4=AV4,ROUND(AP4*(AO4-1),2),-AP4))) -> -24 | AS4: =IF(AR4="","",SUM($AR$2:AR4)) -> 0.4 | AT4: =IF(AB4="","Type the 3 odds on the Matchday tab",IF(Method!$B$55=TRUE(),"🛑 PAUSED — drawdown "&TEXT(Method!$B$51,"0.0%")&" ≥ "&TEXT(Method!$B$52,"0.0%")&". Set Method!B54=Y to override.",IF(AH4="BET",IF(AJ4=0,"Edge found but stake rounds under £"&Method!$B$9&" — skip","Value found: EV "&TEXT(AF4,"0.0%")&", edge "&TEXT(AG4,"0.0%")),IF(AF4<Method!$B$7,"Price too short — EV "&TEXT(AF4,"0.0%")&" (need "&TEXT(Method!$B$7,"0.0%")&"+)","Model ≈ market — edge "&TEXT(AG4,"0.0%")&" (need "&TEXT(Method!$B$8,"0.0%")&"+)")))) -> 🛑 PAUSED — drawdown 0.6% ≥ 15.0%. Set Method!B54=Y to override. | AU4: =IF(AN4<>"Y","",IF(AH4="· enter odds","⚠ type the 3 odds (1/X/2) to grade this bet",IF(OR(AV4="",AO4="",AP4=""),"⚠ log backed pick, odds & stake",IF(AZ4<>"BET","⚠ FUN BET — engine said pass · staked £"&AP4&" vs engine £"&BA4,IF(AV4<>IF(AY4="",AC4,AY4),"⚠ backed "&AV4&" but engine pick was "&IF(AY4="",AC4,AY4),IF(AP4>BA4,"⚠ stake over engine £"&BA4,IF(ABS(AO4-IFERROR(INDEX(L4:N4,1,MATCH(AV4,{"H","D","A"},0)),AE4))>0.02,"⚠ odds moved — re-check value","✓ engine bet"))))))) -> ⚠ stake over engine £12 | AV4: =IF(Matchday!O6="","",Matchday!O6) -> H | AW4: BET | AX4: 12 | AY4: H | AZ4: =IF(AW4="",AH4,AW4) -> BET | BA4: =IF(AX4<>"",AX4,IF(AH4<>"BET",0,IF(AI4*Method!$B$10/100<Method!$B$9,0,ROUND(AI4*Method!$B$10/100,0)))) -> 12 | BB4: 0 | BC4: 0.64681174 | BD4: 0.23660731 | BE4: 0.090414781 | BG4: 76 | BH4: mild | BI4: 0
A5: 4 | B5: 46185 | C5: D | D5: United States | E5: Paraguay | F5: Inglewood | G5: 18:00 | H5: 02:00 +1d | I5: 0.48548732 | J5: 0.2800987 | K5: 0.23441398 | L5: =IF(Matchday!E7="","",Matchday!E7) -> 2.18 | M5: =IF(Matchday!F7="","",Matchday!F7) -> 3.3 | N5: =IF(Matchday!G7="","",Matchday!G7) -> 4.1 | O5: =IF(L5="","",1/L5) -> 0.4587156 | P5: =IF(M5="","",1/M5) -> 0.3030303 | Q5: =IF(N5="","",1/N5) -> 0.24390244 | R5: =IF(COUNT(L5:N5)<3,"",O5+P5+Q5) -> 1.0056483 | S5: {=IF($R5="","",IF(Method!$B$56="proportional",O5/$R5,IF(Method!$B$56="power",IFERROR(INDEX(power_devig($L5,$M5,$N5),1,1),O5/$R5),IFERROR(INDEX(shin($L5,$M5,$N5),1,1),O5/$R5))))} -> 0.4566588 | T5: {=IF($R5="","",IF(Method!$B$56="proportional",P5/$R5,IF(Method!$B$56="power",IFERROR(INDEX(power_devig($L5,$M5,$N5),2,1),P5/$R5),IFERROR(INDEX(shin($L5,$M5,$N5),2,1),P5/$R5))))} -> 0.30119272 | U5: {=IF($R5="","",IF(Method!$B$56="proportional",Q5/$R5,IF(Method!$B$56="power",IFERROR(INDEX(power_devig($L5,$M5,$N5),3,1),Q5/$R5),IFERROR(INDEX(shin($L5,$M5,$N5),3,1),Q5/$R5))))} -> 0.24214849 | V5: =IF(S5="","",Method!$B$4*I5+(1-Method!$B$4)*S5/($S5+$T5+$U5)) -> 0.46674878 | W5: =IF(T5="","",Method!$B$4*J5+(1-Method!$B$4)*T5/($S5+$T5+$U5)) -> 0.29380981 | X5: =IF(U5="","",Method!$B$4*K5+(1-Method!$B$4)*U5/($S5+$T5+$U5)) -> 0.23944141 | Y5: =IF(V5="","",V5*L5-1) -> 0.01751234 | Z5: =IF(W5="","",W5*M5-1) -> -0.030427623 | AA5: =IF(X5="","",X5*N5-1) -> -0.018290222 | AB5: =IF(Y5="","",MATCH(MAX(Y5:AA5),Y5:AA5,0)) -> 1 | AC5: =IF(AB5="","",CHOOSE(AB5,"H","D","A")) -> H | AD5: =IF(AB5="","",CHOOSE(AB5,"1 "&D5,"X Draw","2 "&E5)) -> 1 United States | AE5: =IF(AB5="","",INDEX(L5:N5,1,AB5)) -> 2.18 | AF5: =IF(AB5="","",INDEX(Y5:AA5,1,AB5)) -> 0.01751234 | AG5: =IF(AB5="","",INDEX(V5:X5,1,AB5)-INDEX(S5:U5,1,AB5)) -> 0.010089984 | AH5: =IF(AB5="","· enter odds",IF(AND(AF5>=Method!$B$7,AG5>=Method!$B$8),"BET","PASS")) -> PASS | AI5: =IF(AH5<>"BET",0,ROUND(MIN(Method!$B$6,Method!$B$5*AL5)*100,1)) -> 0 | AJ5: =IF(OR(AH5<>"BET",Method!$B$55=TRUE()),0,IF(AI5*Method!$B$10/100<Method!$B$9,0,ROUND(AI5*Method!$B$10/100,0))) -> 0 | AK5: =IF(AB5="","",INDEX(V5:X5,1,AB5)) -> 0.46674878 | AL5: =IF(AH5<>"BET","",MAX(0,(AK5*AE5-1)/(AE5-1))) | AM5: =IF(AH5="BET",AF5+A5/1000000,"") | AN5: =IF(Matchday!N7="","",Matchday!N7) -> Y | AO5: =IF(Matchday!P7="","",Matchday!P7) -> 2.05 | AP5: =IF(Matchday!Q7="","",Matchday!Q7) -> 20 | AQ5: =IF(Matchday!R7="","",Matchday!R7) -> H | AR5: =IF(OR(AN5<>"Y",AQ5="",AV5=""),"",IF(AQ5="Void",0,IF(AQ5=AV5,ROUND(AP5*(AO5-1),2),-AP5))) -> 21 | AS5: =IF(AR5="","",SUM($AR$2:AR5)) -> 21.4 | AT5: =IF(AB5="","Type the 3 odds on the Matchday tab",IF(Method!$B$55=TRUE(),"🛑 PAUSED — drawdown "&TEXT(Method!$B$51,"0.0%")&" ≥ "&TEXT(Method!$B$52,"0.0%")&". Set Method!B54=Y to override.",IF(AH5="BET",IF(AJ5=0,"Edge found but stake rounds under £"&Method!$B$9&" — skip","Value found: EV "&TEXT(AF5,"0.0%")&", edge "&TEXT(AG5,"0.0%")),IF(AF5<Method!$B$7,"Price too short — EV "&TEXT(AF5,"0.0%")&" (need "&TEXT(Method!$B$7,"0.0%")&"+)","Model ≈ market — edge "&TEXT(AG5,"0.0%")&" (need "&TEXT(Method!$B$8,"0.0%")&"+)")))) -> 🛑 PAUSED — drawdown 0.6% ≥ 15.0%. Set Method!B54=Y to override. | AU5: =IF(AN5<>"Y","",IF(AH5="· enter odds","⚠ type the 3 odds (1/X/2) to grade this bet",IF(OR(AV5="",AO5="",AP5=""),"⚠ log backed pick, odds & stake",IF(AZ5<>"BET","⚠ FUN BET — engine said pass · staked £"&AP5&" vs engine £"&BA5,IF(AV5<>IF(AY5="",AC5,AY5),"⚠ backed "&AV5&" but engine pick was "&IF(AY5="",AC5,AY5),IF(AP5>BA5,"⚠ stake over engine £"&BA5,IF(ABS(AO5-IFERROR(INDEX(L5:N5,1,MATCH(AV5,{"H","D","A"},0)),AE5))>0.02,"⚠ odds moved — re-check value","✓ engine bet"))))))) -> ⚠ FUN BET — engine said pass · staked £20 vs engine £0 | AV5: =IF(Matchday!O7="","",Matchday!O7) -> H | AW5: PASS | AX5: 0 | AY5: H | AZ5: =IF(AW5="",AH5,AW5) -> PASS | BA5: =IF(AX5<>"",AX5,IF(AH5<>"BET",0,IF(AI5*Method!$B$10/100<Method!$B$9,0,ROUND(AI5*Method!$B$10/100,0)))) -> 0 | BB5: 0 | BC5: 0.46952562 | BD5: 0.28613659 | BE5: 0.23853258 | BG5: 30 | BH5: warm_dry_indoor | BI5: 0
A6: 5 | B6: 46186 | C6: B | D6: Qatar | E6: Switzerland | F6: Santa Clara | G6: 12:00 | H6: 20:00 | I6: 0.07585287 | J6: 0.19789443 | K6: 0.7262527 | L6: =IF(Matchday!E8="","",Matchday!E8) -> 14 | M6: =IF(Matchday!F8="","",Matchday!F8) -> 7.5 | N6: =IF(Matchday!G8="","",Matchday!G8) -> 1.2 | O6: =IF(L6="","",1/L6) -> 0.071428571 | P6: =IF(M6="","",1/M6) -> 0.13333333 | Q6: =IF(N6="","",1/N6) -> 0.83333333 | R6: =IF(COUNT(L6:N6)<3,"",O6+P6+Q6) -> 1.0380952 | S6: {=IF($R6="","",IF(Method!$B$56="proportional",O6/$R6,IF(Method!$B$56="power",IFERROR(INDEX(power_devig($L6,$M6,$N6),1,1),O6/$R6),IFERROR(INDEX(shin($L6,$M6,$N6),1,1),O6/$R6))))} -> 0.061439258 | T6: {=IF($R6="","",IF(Method!$B$56="proportional",P6/$R6,IF(Method!$B$56="power",IFERROR(INDEX(power_devig($L6,$M6,$N6),2,1),P6/$R6),IFERROR(INDEX(shin($L6,$M6,$N6),2,1),P6/$R6))))} -> 0.12247683 | U6: {=IF($R6="","",IF(Method!$B$56="proportional",Q6/$R6,IF(Method!$B$56="power",IFERROR(INDEX(power_devig($L6,$M6,$N6),3,1),Q6/$R6),IFERROR(INDEX(shin($L6,$M6,$N6),3,1),Q6/$R6))))} -> 0.81608391 | V6: =IF(S6="","",Method!$B$4*I6+(1-Method!$B$4)*S6/($S6+$T6+$U6)) -> 0.066484022 | W6: =IF(T6="","",Method!$B$4*J6+(1-Method!$B$4)*T6/($S6+$T6+$U6)) -> 0.14887299 | X6: =IF(U6="","",Method!$B$4*K6+(1-Method!$B$4)*U6/($S6+$T6+$U6)) -> 0.78464298 | Y6: =IF(V6="","",V6*L6-1) -> -0.069223691 | Z6: =IF(W6="","",W6*M6-1) -> 0.11654745 | AA6: =IF(X6="","",X6*N6-1) -> -0.058428418 | AB6: =IF(Y6="","",MATCH(MAX(Y6:AA6),Y6:AA6,0)) -> 2 | AC6: =IF(AB6="","",CHOOSE(AB6,"H","D","A")) -> D | AD6: =IF(AB6="","",CHOOSE(AB6,"1 "&D6,"X Draw","2 "&E6)) -> X Draw | AE6: =IF(AB6="","",INDEX(L6:N6,1,AB6)) -> 7.5 | AF6: =IF(AB6="","",INDEX(Y6:AA6,1,AB6)) -> 0.11654745 | AG6: =IF(AB6="","",INDEX(V6:X6,1,AB6)-INDEX(S6:U6,1,AB6)) -> 0.026396158 | AH6: =IF(AB6="","· enter odds",IF(AND(AF6>=Method!$B$7,AG6>=Method!$B$8),"BET","PASS")) -> BET | AI6: =IF(AH6<>"BET",0,ROUND(MIN(Method!$B$6,Method!$B$5*AL6)*100,1)) -> 0.4 | AJ6: =IF(OR(AH6<>"BET",Method!$B$55=TRUE()),0,IF(AI6*Method!$B$10/100<Method!$B$9,0,ROUND(AI6*Method!$B$10/100,0))) -> 0 | AK6: =IF(AB6="","",INDEX(V6:X6,1,AB6)) -> 0.14887299 | AL6: =IF(AH6<>"BET","",MAX(0,(AK6*AE6-1)/(AE6-1))) -> 0.017930377 | AM6: =IF(AH6="BET",AF6+A6/1000000,"") -> 0.11655245 | AN6: =IF(Matchday!N8="","",Matchday!N8) -> Y | AO6: =IF(Matchday!P8="","",Matchday!P8) -> 7.5 | AP6: =IF(Matchday!Q8="","",Matchday!Q8) -> 20 | AQ6: =IF(Matchday!R8="","",Matchday!R8) -> D | AR6: =IF(OR(AN6<>"Y",AQ6="",AV6=""),"",IF(AQ6="Void",0,IF(AQ6=AV6,ROUND(AP6*(AO6-1),2),-AP6))) -> -20 | AS6: =IF(AR6="","",SUM($AR$2:AR6)) -> 1.4 | AT6: =IF(AB6="","Type the 3 odds on the Matchday tab",IF(Method!$B$55=TRUE(),"🛑 PAUSED — drawdown "&TEXT(Method!$B$51,"0.0%")&" ≥ "&TEXT(Method!$B$52,"0.0%")&". Set Method!B54=Y to override.",IF(AH6="BET",IF(AJ6=0,"Edge found but stake rounds under £"&Method!$B$9&" — skip","Value found: EV "&TEXT(AF6,"0.0%")&", edge "&TEXT(AG6,"0.0%")),IF(AF6<Method!$B$7,"Price too short — EV "&TEXT(AF6,"0.0%")&" (need "&TEXT(Method!$B$7,"0.0%")&"+)","Model ≈ market — edge "&TEXT(AG6,"0.0%")&" (need "&TEXT(Method!$B$8,"0.0%")&"+)")))) -> 🛑 PAUSED — drawdown 0.6% ≥ 15.0%. Set Method!B54=Y to override. | AU6: =IF(AN6<>"Y","",IF(AH6="· enter odds","⚠ type the 3 odds (1/X/2) to grade this bet",IF(OR(AV6="",AO6="",AP6=""),"⚠ log backed pick, odds & stake",IF(AZ6<>"BET","⚠ FUN BET — engine said pass · staked £"&AP6&" vs engine £"&BA6,IF(AV6<>IF(AY6="",AC6,AY6),"⚠ backed "&AV6&" but engine pick was "&IF(AY6="",AC6,AY6),IF(AP6>BA6,"⚠ stake over engine £"&BA6,IF(ABS(AO6-IFERROR(INDEX(L6:N6,1,MATCH(AV6,{"H","D","A"},0)),AE6))>0.02,"⚠ odds moved — re-check value","✓ engine bet"))))))) -> ⚠ FUN BET — engine said pass · staked £20 vs engine £0 | AV6: =IF(Matchday!O8="","",Matchday!O8) -> A | AW6: PASS | AX6: 0 | AY6: D | AZ6: =IF(AW6="",AH6,AW6) -> PASS | BA6: =IF(AX6<>"",AX6,IF(AH6<>"BET",0,IF(AI6*Method!$B$10/100<Method!$B$9,0,ROUND(AI6*Method!$B$10/100,0)))) -> 0 | BB6: 0 | BC6: 0.069112865 | BD6: 0.22170919 | BE6: 0.70571282 | BG6: 8 | BH6: mild_dry | BI6: 0
A7: 6 | B7: 46186 | C7: C | D7: Brazil | E7: Morocco | F7: East Rutherford | G7: 18:00 | H7: 23:00 | I7: 0.45124668 | J7: 0.29136359 | K7: 0.25738973 | L7: =IF(Matchday!E9="","",Matchday!E9) -> 1.7 | M7: =IF(Matchday!F9="","",Matchday!F9) -> 3.75 | N7: =IF(Matchday!G9="","",Matchday!G9) -> 5.5 | O7: =IF(L7="","",1/L7) -> 0.58823529 | P7: =IF(M7="","",1/M7) -> 0.26666667 | Q7: =IF(N7="","",1/N7) -> 0.18181818 | R7: =IF(COUNT(L7:N7)<3,"",O7+P7+Q7) -> 1.0367201 | S7: {=IF($R7="","",IF(Method!$B$56="proportional",O7/$R7,IF(Method!$B$56="power",IFERROR(INDEX(power_devig($L7,$M7,$N7),1,1),O7/$R7),IFERROR(INDEX(shin($L7,$M7,$N7),1,1),O7/$R7))))} -> 0.57380303 | T7: {=IF($R7="","",IF(Method!$B$56="proportional",P7/$R7,IF(Method!$B$56="power",IFERROR(INDEX(power_devig($L7,$M7,$N7),2,1),P7/$R7),IFERROR(INDEX(shin($L7,$M7,$N7),2,1),P7/$R7))))} -> 0.25511569 | U7: {=IF($R7="","",IF(Method!$B$56="proportional",Q7/$R7,IF(Method!$B$56="power",IFERROR(INDEX(power_devig($L7,$M7,$N7),3,1),Q7/$R7),IFERROR(INDEX(shin($L7,$M7,$N7),3,1),Q7/$R7))))} -> 0.17108129 | V7: =IF(S7="","",Method!$B$4*I7+(1-Method!$B$4)*S7/($S7+$T7+$U7)) -> 0.5309083 | W7: =IF(T7="","",Method!$B$4*J7+(1-Method!$B$4)*T7/($S7+$T7+$U7)) -> 0.26780245 | X7: =IF(U7="","",Method!$B$4*K7+(1-Method!$B$4)*U7/($S7+$T7+$U7)) -> 0.20128924 | Y7: =IF(V7="","",V7*L7-1) -> -0.097455883 | Z7: =IF(W7="","",W7*M7-1) -> 0.004259198 | AA7: =IF(X7="","",X7*N7-1) -> 0.10709084 | AB7: =IF(Y7="","",MATCH(MAX(Y7:AA7),Y7:AA7,0)) -> 3 | AC7: =IF(AB7="","",CHOOSE(AB7,"H","D","A")) -> A | AD7: =IF(AB7="","",CHOOSE(AB7,"1 "&D7,"X Draw","2 "&E7)) -> 2 Morocco | AE7: =IF(AB7="","",INDEX(L7:N7,1,AB7)) -> 5.5 | AF7: =IF(AB7="","",INDEX(Y7:AA7,1,AB7)) -> 0.10709084 | AG7: =IF(AB7="","",INDEX(V7:X7,1,AB7)-INDEX(S7:U7,1,AB7)) -> 0.030207955 | AH7: =IF(AB7="","· enter odds",IF(AND(AF7>=Method!$B$7,AG7>=Method!$B$8),"BET","PASS")) -> BET | AI7: =IF(AH7<>"BET",0,ROUND(MIN(Method!$B$6,Method!$B$5*AL7)*100,1)) -> 0.6 | AJ7: =IF(OR(AH7<>"BET",Method!$B$55=TRUE()),0,IF(AI7*Method!$B$10/100<Method!$B$9,0,ROUND(AI7*Method!$B$10/100,0))) -> 0 | AK7: =IF(AB7="","",INDEX(V7:X7,1,AB7)) -> 0.20128924 | AL7: =IF(AH7<>"BET","",MAX(0,(AK7*AE7-1)/(AE7-1))) -> 0.023797964 | AM7: =IF(AH7="BET",AF7+A7/1000000,"") -> 0.10709684 | AN7: =IF(Matchday!N9="","",Matchday!N9) -> Y | AO7: =IF(Matchday!P9="","",Matchday!P9) -> 1.68 | AP7: =IF(Matchday!Q9="","",Matchday!Q9) -> 30 | AQ7: =IF(Matchday!R9="","",Matchday!R9) -> H | AR7: =IF(OR(AN7<>"Y",AQ7="",AV7=""),"",IF(AQ7="Void",0,IF(AQ7=AV7,ROUND(AP7*(AO7-1),2),-AP7))) -> 20.4 | AS7: =IF(AR7="","",SUM($AR$2:AR7)) -> 21.8 | AT7: =IF(AB7="","Type the 3 odds on the Matchday tab",IF(Method!$B$55=TRUE(),"🛑 PAUSED — drawdown "&TEXT(Method!$B$51,"0.0%")&" ≥ "&TEXT(Method!$B$52,"0.0%")&". Set Method!B54=Y to override.",IF(AH7="BET",IF(AJ7=0,"Edge found but stake rounds under £"&Method!$B$9&" — skip","Value found: EV "&TEXT(AF7,"0.0%")&", edge "&TEXT(AG7,"0.0%")),IF(AF7<Method!$B$7,"Price too short — EV "&TEXT(AF7,"0.0%")&" (need "&TEXT(Method!$B$7,"0.0%")&"+)","Model ≈ market — edge "&TEXT(AG7,"0.0%")&" (need "&TEXT(Method!$B$8,"0.0%")&"+)")))) -> 🛑 PAUSED — drawdown 0.6% ≥ 15.0%. Set Method!B54=Y to override. | AU7: =IF(AN7<>"Y","",IF(AH7="· enter odds","⚠ type the 3 odds (1/X/2) to grade this bet",IF(OR(AV7="",AO7="",AP7=""),"⚠ log backed pick, odds & stake",IF(AZ7<>"BET","⚠ FUN BET — engine said pass · staked £"&AP7&" vs engine £"&BA7,IF(AV7<>IF(AY7="",AC7,AY7),"⚠ backed "&AV7&" but engine pick was "&IF(AY7="",AC7,AY7),IF(AP7>BA7,"⚠ stake over engine £"&BA7,IF(ABS(AO7-IFERROR(INDEX(L7:N7,1,MATCH(AV7,{"H","D","A"},0)),AE7))>0.02,"⚠ odds moved — re-check value","✓ engine bet"))))))) -> ⚠ backed H but engine pick was A | AV7: =IF(Matchday!O9="","",Matchday!O9) -> H | AW7: BET | AX7: 5 | AY7: A | AZ7: =IF(AW7="",AH7,AW7) -> BET | BA7: =IF(AX7<>"",AX7,IF(AH7<>"BET",0,IF(AI7*Method!$B$10/100<Method!$B$9,0,ROUND(AI7*Method!$B$10/100,0)))) -> 5 | BB7: 0 | BC7: 0.43491952 | BD7: 0.29039564 | BE7: 0.26176671 | BG7: 7 | BH7: warm_humid | BI7: 0
A8: 7 | B8: 46186 | C8: C | D8: Haiti | E8: Scotland | F8: Foxborough | G8: 21:00 | H8: 02:00 +1d | I8: 0.20669861 | J8: 0.26588249 | K8: 0.5274189 | L8: =IF(Matchday!E10="","",Matchday!E10) -> 6 | M8: =IF(Matchday!F10="","",Matchday!F10) -> 4.5 | N8: =IF(Matchday!G10="","",Matchday!G10) -> 0.53 | O8: =IF(L8="","",1/L8) -> 0.16666667 | P8: =IF(M8="","",1/M8) -> 0.22222222 | Q8: =IF(N8="","",1/N8) -> 1.8867925 | R8: =IF(COUNT(L8:N8)<3,"",O8+P8+Q8) -> 2.2756813 | S8: {=IF($R8="","",IF(Method!$B$56="proportional",O8/$R8,IF(Method!$B$56="power",IFERROR(INDEX(power_devig($L8,$M8,$N8),1,1),O8/$R8),IFERROR(INDEX(shin($L8,$M8,$N8),1,1),O8/$R8))))} -> 0.073238139 | T8: {=IF($R8="","",IF(Method!$B$56="proportional",P8/$R8,IF(Method!$B$56="power",IFERROR(INDEX(power_devig($L8,$M8,$N8),2,1),P8/$R8),IFERROR(INDEX(shin($L8,$M8,$N8),2,1),P8/$R8))))} -> 0.097650852 | U8: {=IF($R8="","",IF(Method!$B$56="proportional",Q8/$R8,IF(Method!$B$56="power",IFERROR(INDEX(power_devig($L8,$M8,$N8),3,1),Q8/$R8),IFERROR(INDEX(shin($L8,$M8,$N8),3,1),Q8/$R8))))} -> 0.82911101 | V8: =IF(S8="","",Method!$B$4*I8+(1-Method!$B$4)*S8/($S8+$T8+$U8)) -> 0.1199493 | W8: =IF(T8="","",Method!$B$4*J8+(1-Method!$B$4)*T8/($S8+$T8+$U8)) -> 0.15653193 | X8: =IF(U8="","",Method!$B$4*K8+(1-Method!$B$4)*U8/($S8+$T8+$U8)) -> 0.72351877 | Y8: =IF(V8="","",V8*L8-1) -> -0.28030418 | Z8: =IF(W8="","",W8*M8-1) -> -0.29560633 | AA8: =IF(X8="","",X8*N8-1) -> -0.61653505 | AB8: =IF(Y8="","",MATCH(MAX(Y8:AA8),Y8:AA8,0)) -> 1 | AC8: =IF(AB8="","",CHOOSE(AB8,"H","D","A")) -> H | AD8: =IF(AB8="","",CHOOSE(AB8,"1 "&D8,"X Draw","2 "&E8)) -> 1 Haiti | AE8: =IF(AB8="","",INDEX(L8:N8,1,AB8)) -> 6 | AF8: =IF(AB8="","",INDEX(Y8:AA8,1,AB8)) -> -0.28030418 | AG8: =IF(AB8="","",INDEX(V8:X8,1,AB8)-INDEX(S8:U8,1,AB8)) -> 0.046711164 | AH8: =IF(AB8="","· enter odds",IF(AND(AF8>=Method!$B$7,AG8>=Method!$B$8),"BET","PASS")) -> PASS | AI8: =IF(AH8<>"BET",0,ROUND(MIN(Method!$B$6,Method!$B$5*AL8)*100,1)) -> 0 | AJ8: =IF(OR(AH8<>"BET",Method!$B$55=TRUE()),0,IF(AI8*Method!$B$10/100<Method!$B$9,0,ROUND(AI8*Method!$B$10/100,0))) -> 0 | AK8: =IF(AB8="","",INDEX(V8:X8,1,AB8)) -> 0.1199493 | AL8: =IF(AH8<>"BET","",MAX(0,(AK8*AE8-1)/(AE8-1))) | AM8: =IF(AH8="BET",AF8+A8/1000000,"") | AN8: =IF(Matchday!N10="","",Matchday!N10) -> N | AO8: =IF(Matchday!P10="","",Matchday!P10) | AP8: =IF(Matchday!Q10="","",Matchday!Q10) | AQ8: =IF(Matchday!R10="","",Matchday!R10) | AR8: =IF(OR(AN8<>"Y",AQ8="",AV8=""),"",IF(AQ8="Void",0,IF(AQ8=AV8,ROUND(AP8*(AO8-1),2),-AP8))) | AS8: =IF(AR8="","",SUM($AR$2:AR8)) | AT8: =IF(AB8="","Type the 3 odds on the Matchday tab",IF(Method!$B$55=TRUE(),"🛑 PAUSED — drawdown "&TEXT(Method!$B$51,"0.0%")&" ≥ "&TEXT(Method!$B$52,"0.0%")&". Set Method!B54=Y to override.",IF(AH8="BET",IF(AJ8=0,"Edge found but stake rounds under £"&Method!$B$9&" — skip","Value found: EV "&TEXT(AF8,"0.0%")&", edge "&TEXT(AG8,"0.0%")),IF(AF8<Method!$B$7,"Price too short — EV "&TEXT(AF8,"0.0%")&" (need "&TEXT(Method!$B$7,"0.0%")&"+)","Model ≈ market — edge "&TEXT(AG8,"0.0%")&" (need "&TEXT(Method!$B$8,"0.0%")&"+)")))) -> 🛑 PAUSED — drawdown 0.6% ≥ 15.0%. Set Method!B54=Y to override. | AU8: =IF(AN8<>"Y","",IF(AH8="· enter odds","⚠ type the 3 odds (1/X/2) to grade this bet",IF(OR(AV8="",AO8="",AP8=""),"⚠ log backed pick, odds & stake",IF(AZ8<>"BET","⚠ FUN BET — engine said pass · staked £"&AP8&" vs engine £"&BA8,IF(AV8<>IF(AY8="",AC8,AY8),"⚠ backed "&AV8&" but engine pick was "&IF(AY8="",AC8,AY8),IF(AP8>BA8,"⚠ stake over engine £"&BA8,IF(ABS(AO8-IFERROR(INDEX(L8:N8,1,MATCH(AV8,{"H","D","A"},0)),AE8))>0.02,"⚠ odds moved — re-check value","✓ engine bet"))))))) | AV8: =IF(Matchday!O10="","",Matchday!O10) | AZ8: =IF(AW8="",AH8,AW8) -> PASS | BA8: =IF(AX8<>"",AX8,IF(AH8<>"BET",0,IF(AI8*Method!$B$10/100<Method!$B$9,0,ROUND(AI8*Method!$B$10/100,0)))) -> 0 | BB8: 0 | BC8: 0.18941496 | BD8: 0.28076171 | BE8: 0.51170651 | BG8: 40 | BH8: warm | BI8: 0
A9: 8 | B9: 46186 | C9: D | D9: Australia | E9: Turkey | F9: Vancouver | G9: 21:00 | H9: 05:00 +1d | I9: 0.3613933 | J9: 0.30639872 | K9: 0.33220798 | L9: =IF(Matchday!E11="","",Matchday!E11) -> 5.25 | M9: =IF(Matchday!F11="","",Matchday!F11) -> 3.8 | N9: =IF(Matchday!G11="","",Matchday!G11) -> 1.66 | O9: =IF(L9="","",1/L9) -> 0.19047619 | P9: =IF(M9="","",1/M9) -> 0.26315789 | Q9: =IF(N9="","",1/N9) -> 0.60240964 | R9: =IF(COUNT(L9:N9)<3,"",O9+P9+Q9) -> 1.0560437 | S9: {=IF($R9="","",IF(Method!$B$56="proportional",O9/$R9,IF(Method!$B$56="power",IFERROR(INDEX(power_devig($L9,$M9,$N9),1,1),O9/$R9),IFERROR(INDEX(shin($L9,$M9,$N9),1,1),O9/$R9))))} -> 0.17404997 | T9: {=IF($R9="","",IF(Method!$B$56="proportional",P9/$R9,IF(Method!$B$56="power",IFERROR(INDEX(power_devig($L9,$M9,$N9),2,1),P9/$R9),IFERROR(INDEX(shin($L9,$M9,$N9),2,1),P9/$R9))))} -> 0.24564306 | U9: {=IF($R9="","",IF(Method!$B$56="proportional",Q9/$R9,IF(Method!$B$56="power",IFERROR(INDEX(power_devig($L9,$M9,$N9),3,1),Q9/$R9),IFERROR(INDEX(shin($L9,$M9,$N9),3,1),Q9/$R9))))} -> 0.58030697 | V9: =IF(S9="","",Method!$B$4*I9+(1-Method!$B$4)*S9/($S9+$T9+$U9)) -> 0.23962014 | W9: =IF(T9="","",Method!$B$4*J9+(1-Method!$B$4)*T9/($S9+$T9+$U9)) -> 0.26690754 | X9: =IF(U9="","",Method!$B$4*K9+(1-Method!$B$4)*U9/($S9+$T9+$U9)) -> 0.49347232 | Y9: =IF(V9="","",V9*L9-1) -> 0.25800572 | Z9: =IF(W9="","",W9*M9-1) -> 0.014248645 | AA9: =IF(X9="","",X9*N9-1) -> -0.18083594 | AB9: =IF(Y9="","",MATCH(MAX(Y9:AA9),Y9:AA9,0)) -> 1 | AC9: =IF(AB9="","",CHOOSE(AB9,"H","D","A")) -> H | AD9: =IF(AB9="","",CHOOSE(AB9,"1 "&D9,"X Draw","2 "&E9)) -> 1 Australia | AE9: =IF(AB9="","",INDEX(L9:N9,1,AB9)) -> 5.25 | AF9: =IF(AB9="","",INDEX(Y9:AA9,1,AB9)) -> 0.25800572 | AG9: =IF(AB9="","",INDEX(V9:X9,1,AB9)-INDEX(S9:U9,1,AB9)) -> 0.065570164 | AH9: =IF(AB9="","· enter odds",IF(AND(AF9>=Method!$B$7,AG9>=Method!$B$8),"BET","PASS")) -> BET | AI9: =IF(AH9<>"BET",0,ROUND(MIN(Method!$B$6,Method!$B$5*AL9)*100,1)) -> 1.5 | AJ9: =IF(OR(AH9<>"BET",Method!$B$55=TRUE()),0,IF(AI9*Method!$B$10/100<Method!$B$9,0,ROUND(AI9*Method!$B$10/100,0))) -> 0 | AK9: =IF(AB9="","",INDEX(V9:X9,1,AB9)) -> 0.23962014 | AL9: =IF(AH9<>"BET","",MAX(0,(AK9*AE9-1)/(AE9-1))) -> 0.060707229 | AM9: =IF(AH9="BET",AF9+A9/1000000,"") -> 0.25801372 | AN9: =IF(Matchday!N11="","",Matchday!N11) -> Y | AO9: =IF(Matchday!P11="","",Matchday!P11) -> 5.25 | AP9: =IF(Matchday!Q11="","",Matchday!Q11) -> 10 | AQ9: =IF(Matchday!R11="","",Matchday!R11) -> H | AR9: =IF(OR(AN9<>"Y",AQ9="",AV9=""),"",IF(AQ9="Void",0,IF(AQ9=AV9,ROUND(AP9*(AO9-1),2),-AP9))) -> 42.5 | AS9: =IF(AR9="","",SUM($AR$2:AR9)) -> 64.3 | AT9: =IF(AB9="","Type the 3 odds on the Matchday tab",IF(Method!$B$55=TRUE(),"🛑 PAUSED — drawdown "&TEXT(Method!$B$51,"0.0%")&" ≥ "&TEXT(Method!$B$52,"0.0%")&". Set Method!B54=Y to override.",IF(AH9="BET",IF(AJ9=0,"Edge found but stake rounds under £"&Method!$B$9&" — skip","Value found: EV "&TEXT(AF9,"0.0%")&", edge "&TEXT(AG9,"0.0%")),IF(AF9<Method!$B$7,"Price too short — EV "&TEXT(AF9,"0.0%")&" (need "&TEXT(Method!$B$7,"0.0%")&"+)","Model ≈ market — edge "&TEXT(AG9,"0.0%")&" (need "&TEXT(Method!$B$8,"0.0%")&"+)")))) -> 🛑 PAUSED — drawdown 0.6% ≥ 15.0%. Set Method!B54=Y to override. | AU9: =IF(AN9<>"Y","",IF(AH9="· enter odds","⚠ type the 3 odds (1/X/2) to grade this bet",IF(OR(AV9="",AO9="",AP9=""),"⚠ log backed pick, odds & stake",IF(AZ9<>"BET","⚠ FUN BET — engine said pass · staked £"&AP9&" vs engine £"&BA9,IF(AV9<>IF(AY9="",AC9,AY9),"⚠ backed "&AV9&" but engine pick was "&IF(AY9="",AC9,AY9),IF(AP9>BA9,"⚠ stake over engine £"&BA9,IF(ABS(AO9-IFERROR(INDEX(L9:N9,1,MATCH(AV9,{"H","D","A"},0)),AE9))>0.02,"⚠ odds moved — re-check value","✓ engine bet"))))))) -> ⚠ stake over engine £0 | AV9: =IF(Matchday!O11="","",Matchday!O11) -> H | AW9: BET | AX9: 0 | AY9: H | AZ9: =IF(AW9="",AH9,AW9) -> BET | BA9: =IF(AX9<>"",AX9,IF(AH9<>"BET",0,IF(AI9*Method!$B$10/100<Method!$B$9,0,ROUND(AI9*Method!$B$10/100,0)))) -> 0 | BB9: 0 | BC9: 0.3514023 | BD9: 0.29608015 | BE9: 0.34252063 | BG9: 0 | BH9: mild_indoor | BI9: 0
A10: 9 | B10: 46187 | C10: E | D10: Germany | E10: Curacao | F10: Houston | G10: 12:00 | H10: 18:00 | I10: 0.73873705 | J10: 0.17963937 | K10: 0.081623574 | L10: =IF(Matchday!E12="","",Matchday!E12) -> 1.03 | M10: =IF(Matchday!F12="","",Matchday!F12) -> 19 | N10: =IF(Matchday!G12="","",Matchday!G12) -> 34 | O10: =IF(L10="","",1/L10) -> 0.97087379 | P10: =IF(M10="","",1/M10) -> 0.052631579 | Q10: =IF(N10="","",1/N10) -> 0.029411765 | R10: =IF(COUNT(L10:N10)<3,"",O10+P10+Q10) -> 1.0529171 | S10: {=IF($R10="","",IF(Method!$B$56="proportional",O10/$R10,IF(Method!$B$56="power",IFERROR(INDEX(power_devig($L10,$M10,$N10),1,1),O10/$R10),IFERROR(INDEX(shin($L10,$M10,$N10),1,1),O10/$R10))))} -> 0.94526903 | T10: {=IF($R10="","",IF(Method!$B$56="proportional",P10/$R10,IF(Method!$B$56="power",IFERROR(INDEX(power_devig($L10,$M10,$N10),2,1),P10/$R10),IFERROR(INDEX(shin($L10,$M10,$N10),2,1),P10/$R10))))} -> 0.037933235 | U10: {=IF($R10="","",IF(Method!$B$56="proportional",Q10/$R10,IF(Method!$B$56="power",IFERROR(INDEX(power_devig($L10,$M10,$N10),3,1),Q10/$R10),IFERROR(INDEX(shin($L10,$M10,$N10),3,1),Q10/$R10))))} -> 0.016797735 | V10: =IF(S10="","",Method!$B$4*I10+(1-Method!$B$4)*S10/($S10+$T10+$U10)) -> 0.87298284 | W10: =IF(T10="","",Method!$B$4*J10+(1-Method!$B$4)*T10/($S10+$T10+$U10)) -> 0.087530383 | X10: =IF(U10="","",Method!$B$4*K10+(1-Method!$B$4)*U10/($S10+$T10+$U10)) -> 0.039486779 | Y10: =IF(V10="","",V10*L10-1) -> -0.10082768 | Z10: =IF(W10="","",W10*M10-1) -> 0.66307727 | AA10: =IF(X10="","",X10*N10-1) -> 0.34255048 | AB10: =IF(Y10="","",MATCH(MAX(Y10:AA10),Y10:AA10,0)) -> 2 | AC10: =IF(AB10="","",CHOOSE(AB10,"H","D","A")) -> D | AD10: =IF(AB10="","",CHOOSE(AB10,"1 "&D10,"X Draw","2 "&E10)) -> X Draw | AE10: =IF(AB10="","",INDEX(L10:N10,1,AB10)) -> 19 | AF10: =IF(AB10="","",INDEX(Y10:AA10,1,AB10)) -> 0.66307727 | AG10: =IF(AB10="","",INDEX(V10:X10,1,AB10)-INDEX(S10:U10,1,AB10)) -> 0.049597147 | AH10: =IF(AB10="","· enter odds",IF(AND(AF10>=Method!$B$7,AG10>=Method!$B$8),"BET","PASS")) -> BET | AI10: =IF(AH10<>"BET",0,ROUND(MIN(Method!$B$6,Method!$B$5*AL10)*100,1)) -> 0.9 | AJ10: =IF(OR(AH10<>"BET",Method!$B$55=TRUE()),0,IF(AI10*Method!$B$10/100<Method!$B$9,0,ROUND(AI10*Method!$B$10/100,0))) -> 0 | AK10: =IF(AB10="","",INDEX(V10:X10,1,AB10)) -> 0.087530383 | AL10: =IF(AH10<>"BET","",MAX(0,(AK10*AE10-1)/(AE10-1))) -> 0.036837626 | AM10: =IF(AH10="BET",AF10+A10/1000000,"") -> 0.66308627 | AN10: =IF(Matchday!N12="","",Matchday!N12) -> Y | AO10: =IF(Matchday!P12="","",Matchday!P12) -> 19 | AP10: =IF(Matchday!Q12="","",Matchday!Q12) -> 6 | AQ10: =IF(Matchday!R12="","",Matchday!R12) -> H | AR10: =IF(OR(AN10<>"Y",AQ10="",AV10=""),"",IF(AQ10="Void",0,IF(AQ10=AV10,ROUND(AP10*(AO10-1),2),-AP10))) -> -6 | AS10: =IF(AR10="","",SUM($AR$2:AR10)) -> 58.3 | AT10: =IF(AB10="","Type the 3 odds on the Matchday tab",IF(Method!$B$55=TRUE(),"🛑 PAUSED — drawdown "&TEXT(Method!$B$51,"0.0%")&" ≥ "&TEXT(Method!$B$52,"0.0%")&". Set Method!B54=Y to override.",IF(AH10="BET",IF(AJ10=0,"Edge found but stake rounds under £"&Method!$B$9&" — skip","Value found: EV "&TEXT(AF10,"0.0%")&", edge "&TEXT(AG10,"0.0%")),IF(AF10<Method!$B$7,"Price too short — EV "&TEXT(AF10,"0.0%")&" (need "&TEXT(Method!$B$7,"0.0%")&"+)","Model ≈ market — edge "&TEXT(AG10,"0.0%")&" (need "&TEXT(Method!$B$8,"0.0%")&"+)")))) -> 🛑 PAUSED — drawdown 0.6% ≥ 15.0%. Set Method!B54=Y to override. | AU10: =IF(AN10<>"Y","",IF(AH10="· enter odds","⚠ type the 3 odds (1/X/2) to grade this bet",IF(OR(AV10="",AO10="",AP10=""),"⚠ log backed pick, odds & stake",IF(AZ10<>"BET","⚠ FUN BET — engine said pass · staked £"&AP10&" vs engine £"&BA10,IF(AV10<>IF(AY10="",AC10,AY10),"⚠ backed "&AV10&" but engine pick was "&IF(AY10="",AC10,AY10),IF(AP10>BA10,"⚠ stake over engine £"&BA10,IF(ABS(AO10-IFERROR(INDEX(L10:N10,1,MATCH(AV10,{"H","D","A"},0)),AE10))>0.02,"⚠ odds moved — re-check value","✓ engine bet"))))))) -> ✓ engine bet | AV10: =IF(Matchday!O12="","",Matchday!O12) -> D | AW10: BET | AX10: 6 | AY10: D | AZ10: =IF(AW10="",AH10,AW10) -> BET | BA10: =IF(AX10<>"",AX10,IF(AH10<>"BET",0,IF(AI10*Method!$B$10/100<Method!$B$9,0,ROUND(AI10*Method!$B$10/100,0)))) -> 6 | BB10: 0 | BC10: 0.69015642 | BD10: 0.20403639 | BE10: 0.082269221 | BG10: 15 | BH10: very_hot_humid_indoor | BI10: 0
A11: 10 | B11: 46187 | C11: F | D11: Netherlands | E11: Japan | F11: Arlington | G11: 15:00 | H11: 21:00 | I11: 0.43212683 | J11: 0.28878547 | K11: 0.2790877 | L11: =IF(Matchday!E13="","",Matchday!E13) -> 2.05 | M11: =IF(Matchday!F13="","",Matchday!F13) -> 3.5 | N11: =IF(Matchday!G13="","",Matchday!G13) -> 3.7 | O11: =IF(L11="","",1/L11) -> 0.48780488 | P11: =IF(M11="","",1/M11) -> 0.28571429 | Q11: =IF(N11="","",1/N11) -> 0.27027027 | R11: =IF(COUNT(L11:N11)<3,"",O11+P11+Q11) -> 1.0437894 | S11: {=IF($R11="","",IF(Method!$B$56="proportional",O11/$R11,IF(Method!$B$56="power",IFERROR(INDEX(power_devig($L11,$M11,$N11),1,1),O11/$R11),IFERROR(INDEX(shin($L11,$M11,$N11),1,1),O11/$R11))))} -> 0.47170405 | T11: {=IF($R11="","",IF(Method!$B$56="proportional",P11/$R11,IF(Method!$B$56="power",IFERROR(INDEX(power_devig($L11,$M11,$N11),2,1),P11/$R11),IFERROR(INDEX(shin($L11,$M11,$N11),2,1),P11/$R11))))} -> 0.27178421 | U11: {=IF($R11="","",IF(Method!$B$56="proportional",Q11/$R11,IF(Method!$B$56="power",IFERROR(INDEX(power_devig($L11,$M11,$N11),3,1),Q11/$R11),IFERROR(INDEX(shin($L11,$M11,$N11),3,1),Q11/$R11))))} -> 0.25651174 | V11: =IF(S11="","",Method!$B$4*I11+(1-Method!$B$4)*S11/($S11+$T11+$U11)) -> 0.45785202 | W11: =IF(T11="","",Method!$B$4*J11+(1-Method!$B$4)*T11/($S11+$T11+$U11)) -> 0.27773465 | X11: =IF(U11="","",Method!$B$4*K11+(1-Method!$B$4)*U11/($S11+$T11+$U11)) -> 0.26441333 | Y11: =IF(V11="","",V11*L11-1) -> -0.061403359 | Z11: =IF(W11="","",W11*M11-1) -> -0.027928716 | AA11: =IF(X11="","",X11*N11-1) -> -0.021670688 | AB11: =IF(Y11="","",MATCH(MAX(Y11:AA11),Y11:AA11,0)) -> 3 | AC11: =IF(AB11="","",CHOOSE(AB11,"H","D","A")) -> A | AD11: =IF(AB11="","",CHOOSE(AB11,"1 "&D11,"X Draw","2 "&E11)) -> 2 Japan | AE11: =IF(AB11="","",INDEX(L11:N11,1,AB11)) -> 3.7 | AF11: =IF(AB11="","",INDEX(Y11:AA11,1,AB11)) -> -0.021670688 | AG11: =IF(AB11="","",INDEX(V11:X11,1,AB11)-INDEX(S11:U11,1,AB11)) -> 0.0079015845 | AH11: =IF(AB11="","· enter odds",IF(AND(AF11>=Method!$B$7,AG11>=Method!$B$8),"BET","PASS")) -> PASS | AI11: =IF(AH11<>"BET",0,ROUND(MIN(Method!$B$6,Method!$B$5*AL11)*100,1)) -> 0 | AJ11: =IF(OR(AH11<>"BET",Method!$B$55=TRUE()),0,IF(AI11*Method!$B$10/100<Method!$B$9,0,ROUND(AI11*Method!$B$10/100,0))) -> 0 | AK11: =IF(AB11="","",INDEX(V11:X11,1,AB11)) -> 0.26441333 | AL11: =IF(AH11<>"BET","",MAX(0,(AK11*AE11-1)/(AE11-1))) | AM11: =IF(AH11="BET",AF11+A11/1000000,"") | AN11: =IF(Matchday!N13="","",Matchday!N13) -> Y | AO11: =IF(Matchday!P13="","",Matchday!P13) -> 1 | AP11: =IF(Matchday!Q13="","",Matchday!Q13) | AQ11: =IF(Matchday!R13="","",Matchday!R13) | AR11: =IF(OR(AN11<>"Y",AQ11="",AV11=""),"",IF(AQ11="Void",0,IF(AQ11=AV11,ROUND(AP11*(AO11-1),2),-AP11))) | AS11: =IF(AR11="","",SUM($AR$2:AR11)) | AT11: =IF(AB11="","Type the 3 odds on the Matchday tab",IF(Method!$B$55=TRUE(),"🛑 PAUSED — drawdown "&TEXT(Method!$B$51,"0.0%")&" ≥ "&TEXT(Method!$B$52,"0.0%")&". Set Method!B54=Y to override.",IF(AH11="BET",IF(AJ11=0,"Edge found but stake rounds under £"&Method!$B$9&" — skip","Value found: EV "&TEXT(AF11,"0.0%")&", edge "&TEXT(AG11,"0.0%")),IF(AF11<Method!$B$7,"Price too short — EV "&TEXT(AF11,"0.0%")&" (need "&TEXT(Method!$B$7,"0.0%")&"+)","Model ≈ market — edge "&TEXT(AG11,"0.0%")&" (need "&TEXT(Method!$B$8,"0.0%")&"+)")))) -> 🛑 PAUSED — drawdown 0.6% ≥ 15.0%. Set Method!B54=Y to override. | AU11: =IF(AN11<>"Y","",IF(AH11="· enter odds","⚠ type the 3 odds (1/X/2) to grade this bet",IF(OR(AV11="",AO11="",AP11=""),"⚠ log backed pick, odds & stake",IF(AZ11<>"BET","⚠ FUN BET — engine said pass · staked £"&AP11&" vs engine £"&BA11,IF(AV11<>IF(AY11="",AC11,AY11),"⚠ backed "&AV11&" but engine pick was "&IF(AY11="",AC11,AY11),IF(AP11>BA11,"⚠ stake over engine £"&BA11,IF(ABS(AO11-IFERROR(INDEX(L11:N11,1,MATCH(AV11,{"H","D","A"},0)),AE11))>0.02,"⚠ odds moved — re-check value","✓ engine bet"))))))) -> ⚠ log backed pick, odds & stake | AV11: =IF(Matchday!O13="","",Matchday!O13) -> H | AW11: PASS | AX11: 0 | AY11: A | AZ11: =IF(AW11="",AH11,AW11) -> PASS | BA11: =IF(AX11<>"",AX11,IF(AH11<>"BET",0,IF(AI11*Method!$B$10/100<Method!$B$9,0,ROUND(AI11*Method!$B$10/100,0)))) -> 0 | BB11: 0 | BC11: 0.41711956 | BD11: 0.2894209 | BE11: 0.28518608 | BG11: 175 | BH11: very_hot_indoor | BI11: 0
A12: 11 | B12: 46187 | C12: E | D12: Ivory Coast | E12: Ecuador | F12: Philadelphia | G12: 19:00 | H12: 00:00 +1d | I12: 0.26645317 | J12: 0.29936431 | K12: 0.43418252 | L12: =IF(Matchday!E14="","",Matchday!E14) -> 2.1 | M12: =IF(Matchday!F14="","",Matchday!F14) -> 1.75 | N12: =IF(Matchday!G14="","",Matchday!G14) -> 1.6 | O12: =IF(L12="","",1/L12) -> 0.47619048 | P12: =IF(M12="","",1/M12) -> 0.57142857 | Q12: =IF(N12="","",1/N12) -> 0.625 | R12: =IF(COUNT(L12:N12)<3,"",O12+P12+Q12) -> 1.672619 | S12: {=IF($R12="","",IF(Method!$B$56="proportional",O12/$R12,IF(Method!$B$56="power",IFERROR(INDEX(power_devig($L12,$M12,$N12),1,1),O12/$R12),IFERROR(INDEX(shin($L12,$M12,$N12),1,1),O12/$R12))))} -> 0.2642016 | T12: {=IF($R12="","",IF(Method!$B$56="proportional",P12/$R12,IF(Method!$B$56="power",IFERROR(INDEX(power_devig($L12,$M12,$N12),2,1),P12/$R12),IFERROR(INDEX(shin($L12,$M12,$N12),2,1),P12/$R12))))} -> 0.34468019 | U12: {=IF($R12="","",IF(Method!$B$56="proportional",Q12/$R12,IF(Method!$B$56="power",IFERROR(INDEX(power_devig($L12,$M12,$N12),3,1),Q12/$R12),IFERROR(INDEX(shin($L12,$M12,$N12),3,1),Q12/$R12))))} -> 0.3911182 | V12: =IF(S12="","",Method!$B$4*I12+(1-Method!$B$4)*S12/($S12+$T12+$U12)) -> 0.26498965 | W12: =IF(T12="","",Method!$B$4*J12+(1-Method!$B$4)*T12/($S12+$T12+$U12)) -> 0.32881963 | X12: =IF(U12="","",Method!$B$4*K12+(1-Method!$B$4)*U12/($S12+$T12+$U12)) -> 0.40619071 | Y12: =IF(V12="","",V12*L12-1) -> -0.44352173 | Z12: =IF(W12="","",W12*M12-1) -> -0.42456564 | AA12: =IF(X12="","",X12*N12-1) -> -0.35009486 | AB12: =IF(Y12="","",MATCH(MAX(Y12:AA12),Y12:AA12,0)) -> 3 | AC12: =IF(AB12="","",CHOOSE(AB12,"H","D","A")) -> A | AD12: =IF(AB12="","",CHOOSE(AB12,"1 "&D12,"X Draw","2 "&E12)) -> 2 Ecuador | AE12: =IF(AB12="","",INDEX(L12:N12,1,AB12)) -> 1.6 | AF12: =IF(AB12="","",INDEX(Y12:AA12,1,AB12)) -> -0.35009486 | AG12: =IF(AB12="","",INDEX(V12:X12,1,AB12)-INDEX(S12:U12,1,AB12)) -> 0.01507251 | AH12: =IF(AB12="","· enter odds",IF(AND(AF12>=Method!$B$7,AG12>=Method!$B$8),"BET","PASS")) -> PASS | AI12: =IF(AH12<>"BET",0,ROUND(MIN(Method!$B$6,Method!$B$5*AL12)*100,1)) -> 0 | AJ12: =IF(OR(AH12<>"BET",Method!$B$55=TRUE()),0,IF(AI12*Method!$B$10/100<Method!$B$9,0,ROUND(AI12*Method!$B$10/100,0))) -> 0 | AK12: =IF(AB12="","",INDEX(V12:X12,1,AB12)) -> 0.40619071 | AL12: =IF(AH12<>"BET","",MAX(0,(AK12*AE12-1)/(AE12-1))) | AM12: =IF(AH12="BET",AF12+A12/1000000,"") | AN12: =IF(Matchday!N14="","",Matchday!N14) | AO12: =IF(Matchday!P14="","",Matchday!P14) | AP12: =IF(Matchday!Q14="","",Matchday!Q14) | AQ12: =IF(Matchday!R14="","",Matchday!R14) | AR12: =IF(OR(AN12<>"Y",AQ12="",AV12=""),"",IF(AQ12="Void",0,IF(AQ12=AV12,ROUND(AP12*(AO12-1),2),-AP12))) | AS12: =IF(AR12="","",SUM($AR$2:AR12)) | AT12: =IF(AB12="","Type the 3 odds on the Matchday tab",IF(Method!$B$55=TRUE(),"🛑 PAUSED — drawdown "&TEXT(Method!$B$51,"0.0%")&" ≥ "&TEXT(Method!$B$52,"0.0%")&". Set Method!B54=Y to override.",IF(AH12="BET",IF(AJ12=0,"Edge found but stake rounds under £"&Method!$B$9&" — skip","Value found: EV "&TEXT(AF12,"0.0%")&", edge "&TEXT(AG12,"0.0%")),IF(AF12<Method!$B$7,"Price too short — EV "&TEXT(AF12,"0.0%")&" (need "&TEXT(Method!$B$7,"0.0%")&"+)","Model ≈ market — edge "&TEXT(AG12,"0.0%")&" (need "&TEXT(Method!$B$8,"0.0%")&"+)")))) -> 🛑 PAUSED — drawdown 0.6% ≥ 15.0%. Set Method!B54=Y to override. | AU12: =IF(AN12<>"Y","",IF(AH12="· enter odds","⚠ type the 3 odds (1/X/2) to grade this bet",IF(OR(AV12="",AO12="",AP12=""),"⚠ log backed pick, odds & stake",IF(AZ12<>"BET","⚠ FUN BET — engine said pass · staked £"&AP12&" vs engine £"&BA12,IF(AV12<>IF(AY12="",AC12,AY12),"⚠ backed "&AV12&" but engine pick was "&IF(AY12="",AC12,AY12),IF(AP12>BA12,"⚠ stake over engine £"&BA12,IF(ABS(AO12-IFERROR(INDEX(L12:N12,1,MATCH(AV12,{"H","D","A"},0)),AE12))>0.02,"⚠ odds moved — re-check value","✓ engine bet"))))))) | AV12: =IF(Matchday!O14="","",Matchday!O14) | AZ12: =IF(AW12="",AH12,AW12) -> PASS | BA12: =IF(AX12<>"",AX12,IF(AH12<>"BET",0,IF(AI12*Method!$B$10/100<Method!$B$9,0,ROUND(AI12*Method!$B$10/100,0)))) -> 0 | BB12: 0 | BC12: 0.25222707 | BD12: 0.29342056 | BE12: 0.43456737 | BG12: 12 | BH12: warm_humid | BI12: 0
A13: 12 | B13: 46187 | C13: F | D13: Sweden | E13: Tunisia | F13: Guadalupe | G13: 20:00 | H13: 03:00 +1d | I13: 0.41581549 | J13: 0.28824561 | K13: 0.29593891 | L13: =IF(Matchday!E15="","",Matchday!E15) -> 1.9 | M13: =IF(Matchday!F15="","",Matchday!F15) -> 3.4 | N13: =IF(Matchday!G15="","",Matchday!G15) -> 4.33 | O13: =IF(L13="","",1/L13) -> 0.52631579 | P13: =IF(M13="","",1/M13) -> 0.29411765 | Q13: =IF(N13="","",1/N13) -> 0.23094688 | R13: =IF(COUNT(L13:N13)<3,"",O13+P13+Q13) -> 1.0513803 | S13: {=IF($R13="","",IF(Method!$B$56="proportional",O13/$R13,IF(Method!$B$56="power",IFERROR(INDEX(power_devig($L13,$M13,$N13),1,1),O13/$R13),IFERROR(INDEX(shin($L13,$M13,$N13),1,1),O13/$R13))))} -> 0.50697717 | T13: {=IF($R13="","",IF(Method!$B$56="proportional",P13/$R13,IF(Method!$B$56="power",IFERROR(INDEX(power_devig($L13,$M13,$N13),2,1),P13/$R13),IFERROR(INDEX(shin($L13,$M13,$N13),2,1),P13/$R13))))} -> 0.27767923 | U13: {=IF($R13="","",IF(Method!$B$56="proportional",Q13/$R13,IF(Method!$B$56="power",IFERROR(INDEX(power_devig($L13,$M13,$N13),3,1),Q13/$R13),IFERROR(INDEX(shin($L13,$M13,$N13),3,1),Q13/$R13))))} -> 0.21534361 | V13: =IF(S13="","",Method!$B$4*I13+(1-Method!$B$4)*S13/($S13+$T13+$U13)) -> 0.47507058 | W13: =IF(T13="","",Method!$B$4*J13+(1-Method!$B$4)*T13/($S13+$T13+$U13)) -> 0.28137746 | X13: =IF(U13="","",Method!$B$4*K13+(1-Method!$B$4)*U13/($S13+$T13+$U13)) -> 0.24355196 | Y13: =IF(V13="","",V13*L13-1) -> -0.097365902 | Z13: =IF(W13="","",W13*M13-1) -> -0.043316635 | AA13: =IF(X13="","",X13*N13-1) -> 0.054579994 | AB13: =IF(Y13="","",MATCH(MAX(Y13:AA13),Y13:AA13,0)) -> 3 | AC13: =IF(AB13="","",CHOOSE(AB13,"H","D","A")) -> A | AD13: =IF(AB13="","",CHOOSE(AB13,"1 "&D13,"X Draw","2 "&E13)) -> 2 Tunisia | AE13: =IF(AB13="","",INDEX(L13:N13,1,AB13)) -> 4.33 | AF13: =IF(AB13="","",INDEX(Y13:AA13,1,AB13)) -> 0.054579994 | AG13: =IF(AB13="","",INDEX(V13:X13,1,AB13)-INDEX(S13:U13,1,AB13)) -> 0.028208356 | AH13: =IF(AB13="","· enter odds",IF(AND(AF13>=Method!$B$7,AG13>=Method!$B$8),"BET","PASS")) -> BET | AI13: =IF(AH13<>"BET",0,ROUND(MIN(Method!$B$6,Method!$B$5*AL13)*100,1)) -> 0.4 | AJ13: =IF(OR(AH13<>"BET",Method!$B$55=TRUE()),0,IF(AI13*Method!$B$10/100<Method!$B$9,0,ROUND(AI13*Method!$B$10/100,0))) -> 0 | AK13: =IF(AB13="","",INDEX(V13:X13,1,AB13)) -> 0.24355196 | AL13: =IF(AH13<>"BET","",MAX(0,(AK13*AE13-1)/(AE13-1))) -> 0.016390388 | AM13: =IF(AH13="BET",AF13+A13/1000000,"") -> 0.054591994 | AN13: =IF(Matchday!N15="","",Matchday!N15) | AO13: =IF(Matchday!P15="","",Matchday!P15) | AP13: =IF(Matchday!Q15="","",Matchday!Q15) | AQ13: =IF(Matchday!R15="","",Matchday!R15) | AR13: =IF(OR(AN13<>"Y",AQ13="",AV13=""),"",IF(AQ13="Void",0,IF(AQ13=AV13,ROUND(AP13*(AO13-1),2),-AP13))) | AS13: =IF(AR13="","",SUM($AR$2:AR13)) | AT13: =IF(AB13="","Type the 3 odds on the Matchday tab",IF(Method!$B$55=TRUE(),"🛑 PAUSED — drawdown "&TEXT(Method!$B$51,"0.0%")&" ≥ "&TEXT(Method!$B$52,"0.0%")&". Set Method!B54=Y to override.",IF(AH13="BET",IF(AJ13=0,"Edge found but stake rounds under £"&Method!$B$9&" — skip","Value found: EV "&TEXT(AF13,"0.0%")&", edge "&TEXT(AG13,"0.0%")),IF(AF13<Method!$B$7,"Price too short — EV "&TEXT(AF13,"0.0%")&" (need "&TEXT(Method!$B$7,"0.0%")&"+)","Model ≈ market — edge "&TEXT(AG13,"0.0%")&" (need "&TEXT(Method!$B$8,"0.0%")&"+)")))) -> 🛑 PAUSED — drawdown 0.6% ≥ 15.0%. Set Method!B54=Y to override. | AU13: =IF(AN13<>"Y","",IF(AH13="· enter odds","⚠ type the 3 odds (1/X/2) to grade this bet",IF(OR(AV13="",AO13="",AP13=""),"⚠ log backed pick, odds & stake",IF(AZ13<>"BET","⚠ FUN BET — engine said pass · staked £"&AP13&" vs engine £"&BA13,IF(AV13<>IF(AY13="",AC13,AY13),"⚠ backed "&AV13&" but engine pick was "&IF(AY13="",AC13,AY13),IF(AP13>BA13,"⚠ stake over engine £"&BA13,IF(ABS(AO13-IFERROR(INDEX(L13:N13,1,MATCH(AV13,{"H","D","A"},0)),AE13))>0.02,"⚠ odds moved — re-check value","✓ engine bet"))))))) | AV13: =IF(Matchday!O15="","",Matchday!O15) | AZ13: =IF(AW13="",AH13,AW13) -> BET | BA13: =IF(AX13<>"",AX13,IF(AH13<>"BET",0,IF(AI13*Method!$B$10/100<Method!$B$9,0,ROUND(AI13*Method!$B$10/100,0)))) -> 4 | BB13: -4 | BC13: 0.40196498 | BD13: 0.28921679 | BE13: 0.30337417 | BF13: Sweden weather: -4 | BG13: 540 | BH13: very_hot | BI13: 0
A14: 13 | B14: 46188 | C14: H | D14: Spain | E14: Cape Verde | F14: Atlanta | G14: 12:00 | H14: 17:00 | I14: 0.76381505 | J14: 0.16545763 | K14: 0.070727316 | L14: =IF(Matchday!E16="","",Matchday!E16) -> 1.1 | M14: =IF(Matchday!F16="","",Matchday!F16) -> 14 | N14: =IF(Matchday!G16="","",Matchday!G16) -> 23 | O14: =IF(L14="","",1/L14) -> 0.90909091 | P14: =IF(M14="","",1/M14) -> 0.071428571 | Q14: =IF(N14="","",1/N14) -> 0.043478261 | R14: =IF(COUNT(L14:N14)<3,"",O14+P14+Q14) -> 1.0239977 | S14: {=IF($R14="","",IF(Method!$B$56="proportional",O14/$R14,IF(Method!$B$56="power",IFERROR(INDEX(power_devig($L14,$M14,$N14),1,1),O14/$R14),IFERROR(INDEX(shin($L14,$M14,$N14),1,1),O14/$R14))))} -> 0.89773131 | T14: {=IF($R14="","",IF(Method!$B$56="proportional",P14/$R14,IF(Method!$B$56="power",IFERROR(INDEX(power_devig($L14,$M14,$N14),2,1),P14/$R14),IFERROR(INDEX(shin($L14,$M14,$N14),2,1),P14/$R14))))} -> 0.064941495 | U14: {=IF($R14="","",IF(Method!$B$56="proportional",Q14/$R14,IF(Method!$B$56="power",IFERROR(INDEX(power_devig($L14,$M14,$N14),3,1),Q14/$R14),IFERROR(INDEX(shin($L14,$M14,$N14),3,1),Q14/$R14))))} -> 0.0373272 | V14: =IF(S14="","",Method!$B$4*I14+(1-Method!$B$4)*S14/($S14+$T14+$U14)) -> 0.85086062 | W14: =IF(T14="","",Method!$B$4*J14+(1-Method!$B$4)*T14/($S14+$T14+$U14)) -> 0.10012214 | X14: =IF(U14="","",Method!$B$4*K14+(1-Method!$B$4)*U14/($S14+$T14+$U14)) -> 0.049017241 | Y14: =IF(V14="","",V14*L14-1) -> -0.064053322 | Z14: =IF(W14="","",W14*M14-1) -> 0.40171 | AA14: =IF(X14="","",X14*N14-1) -> 0.12739653 | AB14: =IF(Y14="","",MATCH(MAX(Y14:AA14),Y14:AA14,0)) -> 2 | AC14: =IF(AB14="","",CHOOSE(AB14,"H","D","A")) -> D | AD14: =IF(AB14="","",CHOOSE(AB14,"1 "&D14,"X Draw","2 "&E14)) -> X Draw | AE14: =IF(AB14="","",INDEX(L14:N14,1,AB14)) -> 14 | AF14: =IF(AB14="","",INDEX(Y14:AA14,1,AB14)) -> 0.40171 | AG14: =IF(AB14="","",INDEX(V14:X14,1,AB14)-INDEX(S14:U14,1,AB14)) -> 0.035180648 | AH14: =IF(AB14="","· enter odds",IF(AND(AF14>=Method!$B$7,AG14>=Method!$B$8),"BET","PASS")) -> BET | AI14: =IF(AH14<>"BET",0,ROUND(MIN(Method!$B$6,Method!$B$5*AL14)*100,1)) -> 0.8 | AJ14: =IF(OR(AH14<>"BET",Method!$B$55=TRUE()),0,IF(AI14*Method!$B$10/100<Method!$B$9,0,ROUND(AI14*Method!$B$10/100,0))) -> 0 | AK14: =IF(AB14="","",INDEX(V14:X14,1,AB14)) -> 0.10012214 | AL14: =IF(AH14<>"BET","",MAX(0,(AK14*AE14-1)/(AE14-1))) -> 0.030900769 | AM14: =IF(AH14="BET",AF14+A14/1000000,"") -> 0.401723 | AN14: =IF(Matchday!N16="","",Matchday!N16) | AO14: =IF(Matchday!P16="","",Matchday!P16) | AP14: =IF(Matchday!Q16="","",Matchday!Q16) | AQ14: =IF(Matchday!R16="","",Matchday!R16) | AR14: =IF(OR(AN14<>"Y",AQ14="",AV14=""),"",IF(AQ14="Void",0,IF(AQ14=AV14,ROUND(AP14*(AO14-1),2),-AP14))) | AS14: =IF(AR14="","",SUM($AR$2:AR14)) | AT14: =IF(AB14="","Type the 3 odds on the Matchday tab",IF(Method!$B$55=TRUE(),"🛑 PAUSED — drawdown "&TEXT(Method!$B$51,"0.0%")&" ≥ "&TEXT(Method!$B$52,"0.0%")&". Set Method!B54=Y to override.",IF(AH14="BET",IF(AJ14=0,"Edge found but stake rounds under £"&Method!$B$9&" — skip","Value found: EV "&TEXT(AF14,"0.0%")&", edge "&TEXT(AG14,"0.0%")),IF(AF14<Method!$B$7,"Price too short — EV "&TEXT(AF14,"0.0%")&" (need "&TEXT(Method!$B$7,"0.0%")&"+)","Model ≈ market — edge "&TEXT(AG14,"0.0%")&" (need "&TEXT(Method!$B$8,"0.0%")&"+)")))) -> 🛑 PAUSED — drawdown 0.6% ≥ 15.0%. Set Method!B54=Y to override. | AU14: =IF(AN14<>"Y","",IF(AH14="· enter odds","⚠ type the 3 odds (1/X/2) to grade this bet",IF(OR(AV14="",AO14="",AP14=""),"⚠ log backed pick, odds & stake",IF(AZ14<>"BET","⚠ FUN BET — engine said pass · staked £"&AP14&" vs engine £"&BA14,IF(AV14<>IF(AY14="",AC14,AY14),"⚠ backed "&AV14&" but engine pick was "&IF(AY14="",AC14,AY14),IF(AP14>BA14,"⚠ stake over engine £"&BA14,IF(ABS(AO14-IFERROR(INDEX(L14:N14,1,MATCH(AV14,{"H","D","A"},0)),AE14))>0.02,"⚠ odds moved — re-check value","✓ engine bet"))))))) | AV14: =IF(Matchday!O16="","",Matchday!O16) | AZ14: =IF(AW14="",AH14,AW14) -> BET | BA14: =IF(AX14<>"",AX14,IF(AH14<>"BET",0,IF(AI14*Method!$B$10/100<Method!$B$9,0,ROUND(AI14*Method!$B$10/100,0)))) -> 8 | BB14: 0 | BC14: 0.72463855 | BD14: 0.190307 | BE14: 0.070569856 | BG14: 320 | BH14: hot_humid_indoor | BI14: 0
A15: 14 | B15: 46188 | C15: G | D15: Belgium | E15: Egypt | F15: Seattle | G15: 15:00 | H15: 23:00 | I15: 0.46984896 | J15: 0.29964928 | K15: 0.23050176 | L15: =IF(Matchday!E17="","",Matchday!E17) -> 1.61 | M15: =IF(Matchday!F17="","",Matchday!F17) -> 4 | N15: =IF(Matchday!G17="","",Matchday!G17) -> 5.75 | O15: =IF(L15="","",1/L15) -> 0.62111801 | P15: =IF(M15="","",1/M15) -> 0.25 | Q15: =IF(N15="","",1/N15) -> 0.17391304 | R15: =IF(COUNT(L15:N15)<3,"",O15+P15+Q15) -> 1.0450311 | S15: {=IF($R15="","",IF(Method!$B$56="proportional",O15/$R15,IF(Method!$B$56="power",IFERROR(INDEX(power_devig($L15,$M15,$N15),1,1),O15/$R15),IFERROR(INDEX(shin($L15,$M15,$N15),1,1),O15/$R15))))} -> 0.60309946 | T15: {=IF($R15="","",IF(Method!$B$56="proportional",P15/$R15,IF(Method!$B$56="power",IFERROR(INDEX(power_devig($L15,$M15,$N15),2,1),P15/$R15),IFERROR(INDEX(shin($L15,$M15,$N15),2,1),P15/$R15))))} -> 0.23603536 | U15: {=IF($R15="","",IF(Method!$B$56="proportional",Q15/$R15,IF(Method!$B$56="power",IFERROR(INDEX(power_devig($L15,$M15,$N15),3,1),Q15/$R15),IFERROR(INDEX(shin($L15,$M15,$N15),3,1),Q15/$R15))))} -> 0.16086518 | V15: =IF(S15="","",Method!$B$4*I15+(1-Method!$B$4)*S15/($S15+$T15+$U15)) -> 0.55646178 | W15: =IF(T15="","",Method!$B$4*J15+(1-Method!$B$4)*T15/($S15+$T15+$U15)) -> 0.25830023 | X15: =IF(U15="","",Method!$B$4*K15+(1-Method!$B$4)*U15/($S15+$T15+$U15)) -> 0.18523799 | Y15: =IF(V15="","",V15*L15-1) -> -0.10409653 | Z15: =IF(W15="","",W15*M15-1) -> 0.033200928 | AA15: =IF(X15="","",X15*N15-1) -> 0.06511842 | AB15: =IF(Y15="","",MATCH(MAX(Y15:AA15),Y15:AA15,0)) -> 3 | AC15: =IF(AB15="","",CHOOSE(AB15,"H","D","A")) -> A | AD15: =IF(AB15="","",CHOOSE(AB15,"1 "&D15,"X Draw","2 "&E15)) -> 2 Egypt | AE15: =IF(AB15="","",INDEX(L15:N15,1,AB15)) -> 5.75 | AF15: =IF(AB15="","",INDEX(Y15:AA15,1,AB15)) -> 0.06511842 | AG15: =IF(AB15="","",INDEX(V15:X15,1,AB15)-INDEX(S15:U15,1,AB15)) -> 0.024372803 | AH15: =IF(AB15="","· enter odds",IF(AND(AF15>=Method!$B$7,AG15>=Method!$B$8),"BET","PASS")) -> PASS | AI15: =IF(AH15<>"BET",0,ROUND(MIN(Method!$B$6,Method!$B$5*AL15)*100,1)) -> 0 | AJ15: =IF(OR(AH15<>"BET",Method!$B$55=TRUE()),0,IF(AI15*Method!$B$10/100<Method!$B$9,0,ROUND(AI15*Method!$B$10/100,0))) -> 0 | AK15: =IF(AB15="","",INDEX(V15:X15,1,AB15)) -> 0.18523799 | AL15: =IF(AH15<>"BET","",MAX(0,(AK15*AE15-1)/(AE15-1))) | AM15: =IF(AH15="BET",AF15+A15/1000000,"") | AN15: =IF(Matchday!N17="","",Matchday!N17) | AO15: =IF(Matchday!P17="","",Matchday!P17) | AP15: =IF(Matchday!Q17="","",Matchday!Q17) | AQ15: =IF(Matchday!R17="","",Matchday!R17) | AR15: =IF(OR(AN15<>"Y",AQ15="",AV15=""),"",IF(AQ15="Void",0,IF(AQ15=AV15,ROUND(AP15*(AO15-1),2),-AP15))) | AS15: =IF(AR15="","",SUM($AR$2:AR15)) | AT15: =IF(AB15="","Type the 3 odds on the Matchday tab",IF(Method!$B$55=TRUE(),"🛑 PAUSED — drawdown "&TEXT(Method!$B$51,"0.0%")&" ≥ "&TEXT(Method!$B$52,"0.0%")&". Set Method!B54=Y to override.",IF(AH15="BET",IF(AJ15=0,"Edge found but stake rounds under £"&Method!$B$9&" — skip","Value found: EV "&TEXT(AF15,"0.0%")&", edge "&TEXT(AG15,"0.0%")),IF(AF15<Method!$B$7,"Price too short — EV "&TEXT(AF15,"0.0%")&" (need "&TEXT(Method!$B$7,"0.0%")&"+)","Model ≈ market — edge "&TEXT(AG15,"0.0%")&" (need "&TEXT(Method!$B$8,"0.0%")&"+)")))) -> 🛑 PAUSED — drawdown 0.6% ≥ 15.0%. Set Method!B54=Y to override. | AU15: =IF(AN15<>"Y","",IF(AH15="· enter odds","⚠ type the 3 odds (1/X/2) to grade this bet",IF(OR(AV15="",AO15="",AP15=""),"⚠ log backed pick, odds & stake",IF(AZ15<>"BET","⚠ FUN BET — engine said pass · staked £"&AP15&" vs engine £"&BA15,IF(AV15<>IF(AY15="",AC15,AY15),"⚠ backed "&AV15&" but engine pick was "&IF(AY15="",AC15,AY15),IF(AP15>BA15,"⚠ stake over engine £"&BA15,IF(ABS(AO15-IFERROR(INDEX(L15:N15,1,MATCH(AV15,{"H","D","A"},0)),AE15))>0.02,"⚠ odds moved — re-check value","✓ engine bet"))))))) | AV15: =IF(Matchday!O17="","",Matchday!O17) | AZ15: =IF(AW15="",AH15,AW15) -> PASS | BA15: =IF(AX15<>"",AX15,IF(AH15<>"BET",0,IF(AI15*Method!$B$10/100<Method!$B$9,0,ROUND(AI15*Method!$B$10/100,0)))) -> 0 | BB15: 0 | BC15: 0.45372034 | BD15: 0.29352831 | BE15: 0.23468123 | BG15: 5 | BH15: mild | BI15: 0
A16: 15 | B16: 46188 | C16: H | D16: Saudi Arabia | E16: Uruguay | F16: Miami Gardens | G16: 18:00 | H16: 23:00 | I16: 0.13478751 | J16: 0.25088969 | K16: 0.61432279 | L16: =IF(Matchday!E18="","",Matchday!E18) -> 7.5 | M16: =IF(Matchday!F18="","",Matchday!F18) -> 4.2 | N16: =IF(Matchday!G18="","",Matchday!G18) -> 1.48 | O16: =IF(L16="","",1/L16) -> 0.13333333 | P16: =IF(M16="","",1/M16) -> 0.23809524 | Q16: =IF(N16="","",1/N16) -> 0.67567568 | R16: =IF(COUNT(L16:N16)<3,"",O16+P16+Q16) -> 1.0471042 | S16: {=IF($R16="","",IF(Method!$B$56="proportional",O16/$R16,IF(Method!$B$56="power",IFERROR(INDEX(power_devig($L16,$M16,$N16),1,1),O16/$R16),IFERROR(INDEX(shin($L16,$M16,$N16),1,1),O16/$R16))))} -> 0.1202088 | T16: {=IF($R16="","",IF(Method!$B$56="proportional",P16/$R16,IF(Method!$B$56="power",IFERROR(INDEX(power_devig($L16,$M16,$N16),2,1),P16/$R16),IFERROR(INDEX(shin($L16,$M16,$N16),2,1),P16/$R16))))} -> 0.22358408 | U16: {=IF($R16="","",IF(Method!$B$56="proportional",Q16/$R16,IF(Method!$B$56="power",IFERROR(INDEX(power_devig($L16,$M16,$N16),3,1),Q16/$R16),IFERROR(INDEX(shin($L16,$M16,$N16),3,1),Q16/$R16))))} -> 0.65620713 | V16: =IF(S16="","",Method!$B$4*I16+(1-Method!$B$4)*S16/($S16+$T16+$U16)) -> 0.12531135 | W16: =IF(T16="","",Method!$B$4*J16+(1-Method!$B$4)*T16/($S16+$T16+$U16)) -> 0.23314104 | X16: =IF(U16="","",Method!$B$4*K16+(1-Method!$B$4)*U16/($S16+$T16+$U16)) -> 0.64154761 | Y16: =IF(V16="","",V16*L16-1) -> -0.060164893 | Z16: =IF(W16="","",W16*M16-1) -> -0.020807624 | AA16: =IF(X16="","",X16*N16-1) -> -0.050509536 | AB16: =IF(Y16="","",MATCH(MAX(Y16:AA16),Y16:AA16,0)) -> 2 | AC16: =IF(AB16="","",CHOOSE(AB16,"H","D","A")) -> D | AD16: =IF(AB16="","",CHOOSE(AB16,"1 "&D16,"X Draw","2 "&E16)) -> X Draw | AE16: =IF(AB16="","",INDEX(L16:N16,1,AB16)) -> 4.2 | AF16: =IF(AB16="","",INDEX(Y16:AA16,1,AB16)) -> -0.020807624 | AG16: =IF(AB16="","",INDEX(V16:X16,1,AB16)-INDEX(S16:U16,1,AB16)) -> 0.0095569654 | AH16: =IF(AB16="","· enter odds",IF(AND(AF16>=Method!$B$7,AG16>=Method!$B$8),"BET","PASS")) -> PASS | AI16: =IF(AH16<>"BET",0,ROUND(MIN(Method!$B$6,Method!$B$5*AL16)*100,1)) -> 0 | AJ16: =IF(OR(AH16<>"BET",Method!$B$55=TRUE()),0,IF(AI16*Method!$B$10/100<Method!$B$9,0,ROUND(AI16*Method!$B$10/100,0))) -> 0 | AK16: =IF(AB16="","",INDEX(V16:X16,1,AB16)) -> 0.23314104 | AL16: =IF(AH16<>"BET","",MAX(0,(AK16*AE16-1)/(AE16-1))) | AM16: =IF(AH16="BET",AF16+A16/1000000,"") | AN16: =IF(Matchday!N18="","",Matchday!N18) | AO16: =IF(Matchday!P18="","",Matchday!P18) | AP16: =IF(Matchday!Q18="","",Matchday!Q18) | AQ16: =IF(Matchday!R18="","",Matchday!R18) | AR16: =IF(OR(AN16<>"Y",AQ16="",AV16=""),"",IF(AQ16="Void",0,IF(AQ16=AV16,ROUND(AP16*(AO16-1),2),-AP16))) | AS16: =IF(AR16="","",SUM($AR$2:AR16)) | AT16: =IF(AB16="","Type the 3 odds on the Matchday tab",IF(Method!$B$55=TRUE(),"🛑 PAUSED — drawdown "&TEXT(Method!$B$51,"0.0%")&" ≥ "&TEXT(Method!$B$52,"0.0%")&". Set Method!B54=Y to override.",IF(AH16="BET",IF(AJ16=0,"Edge found but stake rounds under £"&Method!$B$9&" — skip","Value found: EV "&TEXT(AF16,"0.0%")&", edge "&TEXT(AG16,"0.0%")),IF(AF16<Method!$B$7,"Price too short — EV "&TEXT(AF16,"0.0%")&" (need "&TEXT(Method!$B$7,"0.0%")&"+)","Model ≈ market — edge "&TEXT(AG16,"0.0%")&" (need "&TEXT(Method!$B$8,"0.0%")&"+)")))) -> 🛑 PAUSED — drawdown 0.6% ≥ 15.0%. Set Method!B54=Y to override. | AU16: =IF(AN16<>"Y","",IF(AH16="· enter odds","⚠ type the 3 odds (1/X/2) to grade this bet",IF(OR(AV16="",AO16="",AP16=""),"⚠ log backed pick, odds & stake",IF(AZ16<>"BET","⚠ FUN BET — engine said pass · staked £"&AP16&" vs engine £"&BA16,IF(AV16<>IF(AY16="",AC16,AY16),"⚠ backed "&AV16&" but engine pick was "&IF(AY16="",AC16,AY16),IF(AP16>BA16,"⚠ stake over engine £"&BA16,IF(ABS(AO16-IFERROR(INDEX(L16:N16,1,MATCH(AV16,{"H","D","A"},0)),AE16))>0.02,"⚠ odds moved — re-check value","✓ engine bet"))))))) | AV16: =IF(Matchday!O18="","",Matchday!O18) | AZ16: =IF(AW16="",AH16,AW16) -> PASS | BA16: =IF(AX16<>"",AX16,IF(AH16<>"BET",0,IF(AI16*Method!$B$10/100<Method!$B$9,0,ROUND(AI16*Method!$B$10/100,0)))) -> 0 | BB16: 0 | BC16: 0.11772922 | BD16: 0.2730141 | BE16: 0.60017822 | BG16: 2 | BH16: very_hot_humid | BI16: 0
A17: 16 | B17: 46188 | C17: G | D17: Iran | E17: New Zealand | F17: Inglewood | G17: 21:00 | H17: 05:00 +1d | I17: 0.43712192 | J17: 0.30651135 | K17: 0.25636673 | L17: =IF(Matchday!E19="","",Matchday!E19) -> 1.8 | M17: =IF(Matchday!F19="","",Matchday!F19) -> 3.5 | N17: =IF(Matchday!G19="","",Matchday!G19) -> 5 | O17: =IF(L17="","",1/L17) -> 0.55555556 | P17: =IF(M17="","",1/M17) -> 0.28571429 | Q17: =IF(N17="","",1/N17) -> 0.2 | R17: =IF(COUNT(L17:N17)<3,"",O17+P17+Q17) -> 1.0412698 | S17: {=IF($R17="","",IF(Method!$B$56="proportional",O17/$R17,IF(Method!$B$56="power",IFERROR(INDEX(power_devig($L17,$M17,$N17),1,1),O17/$R17),IFERROR(INDEX(shin($L17,$M17,$N17),1,1),O17/$R17))))} -> 0.53968463 | T17: {=IF($R17="","",IF(Method!$B$56="proportional",P17/$R17,IF(Method!$B$56="power",IFERROR(INDEX(power_devig($L17,$M17,$N17),2,1),P17/$R17),IFERROR(INDEX(shin($L17,$M17,$N17),2,1),P17/$R17))))} -> 0.27255678 | U17: {=IF($R17="","",IF(Method!$B$56="proportional",Q17/$R17,IF(Method!$B$56="power",IFERROR(INDEX(power_devig($L17,$M17,$N17),3,1),Q17/$R17),IFERROR(INDEX(shin($L17,$M17,$N17),3,1),Q17/$R17))))} -> 0.18775859 | V17: =IF(S17="","",Method!$B$4*I17+(1-Method!$B$4)*S17/($S17+$T17+$U17)) -> 0.50378768 | W17: =IF(T17="","",Method!$B$4*J17+(1-Method!$B$4)*T17/($S17+$T17+$U17)) -> 0.28444088 | X17: =IF(U17="","",Method!$B$4*K17+(1-Method!$B$4)*U17/($S17+$T17+$U17)) -> 0.21177144 | Y17: =IF(V17="","",V17*L17-1) -> -0.093182167 | Z17: =IF(W17="","",W17*M17-1) -> -0.0044569253 | AA17: =IF(X17="","",X17*N17-1) -> 0.058857184 | AB17: =IF(Y17="","",MATCH(MAX(Y17:AA17),Y17:AA17,0)) -> 3 | AC17: =IF(AB17="","",CHOOSE(AB17,"H","D","A")) -> A | AD17: =IF(AB17="","",CHOOSE(AB17,"1 "&D17,"X Draw","2 "&E17)) -> 2 New Zealand | AE17: =IF(AB17="","",INDEX(L17:N17,1,AB17)) -> 5 | AF17: =IF(AB17="","",INDEX(Y17:AA17,1,AB17)) -> 0.058857184 | AG17: =IF(AB17="","",INDEX(V17:X17,1,AB17)-INDEX(S17:U17,1,AB17)) -> 0.02401285 | AH17: =IF(AB17="","· enter odds",IF(AND(AF17>=Method!$B$7,AG17>=Method!$B$8),"BET","PASS")) -> PASS | AI17: =IF(AH17<>"BET",0,ROUND(MIN(Method!$B$6,Method!$B$5*AL17)*100,1)) -> 0 | AJ17: =IF(OR(AH17<>"BET",Method!$B$55=TRUE()),0,IF(AI17*Method!$B$10/100<Method!$B$9,0,ROUND(AI17*Method!$B$10/100,0))) -> 0 | AK17: =IF(AB17="","",INDEX(V17:X17,1,AB17)) -> 0.21177144 | AL17: =IF(AH17<>"BET","",MAX(0,(AK17*AE17-1)/(AE17-1))) | AM17: =IF(AH17="BET",AF17+A17/1000000,"") | AN17: =IF(Matchday!N19="","",Matchday!N19) | AO17: =IF(Matchday!P19="","",Matchday!P19) | AP17: =IF(Matchday!Q19="","",Matchday!Q19) | AQ17: =IF(Matchday!R19="","",Matchday!R19) | AR17: =IF(OR(AN17<>"Y",AQ17="",AV17=""),"",IF(AQ17="Void",0,IF(AQ17=AV17,ROUND(AP17*(AO17-1),2),-AP17))) | AS17: =IF(AR17="","",SUM($AR$2:AR17)) | AT17: =IF(AB17="","Type the 3 odds on the Matchday tab",IF(Method!$B$55=TRUE(),"🛑 PAUSED — drawdown "&TEXT(Method!$B$51,"0.0%")&" ≥ "&TEXT(Method!$B$52,"0.0%")&". Set Method!B54=Y to override.",IF(AH17="BET",IF(AJ17=0,"Edge found but stake rounds under £"&Method!$B$9&" — skip","Value found: EV "&TEXT(AF17,"0.0%")&", edge "&TEXT(AG17,"0.0%")),IF(AF17<Method!$B$7,"Price too short — EV "&TEXT(AF17,"0.0%")&" (need "&TEXT(Method!$B$7,"0.0%")&"+)","Model ≈ market — edge "&TEXT(AG17,"0.0%")&" (need "&TEXT(Method!$B$8,"0.0%")&"+)")))) -> 🛑 PAUSED — drawdown 0.6% ≥ 15.0%. Set Method!B54=Y to override. | AU17: =IF(AN17<>"Y","",IF(AH17="· enter odds","⚠ type the 3 odds (1/X/2) to grade this bet",IF(OR(AV17="",AO17="",AP17=""),"⚠ log backed pick, odds & stake",IF(AZ17<>"BET","⚠ FUN BET — engine said pass · staked £"&AP17&" vs engine £"&BA17,IF(AV17<>IF(AY17="",AC17,AY17),"⚠ backed "&AV17&" but engine pick was "&IF(AY17="",AC17,AY17),IF(AP17>BA17,"⚠ stake over engine £"&BA17,IF(ABS(AO17-IFERROR(INDEX(L17:N17,1,MATCH(AV17,{"H","D","A"},0)),AE17))>0.02,"⚠ odds moved — re-check value","✓ engine bet"))))))) | AV17: =IF(Matchday!O19="","",Matchday!O19) | AZ17: =IF(AW17="",AH17,AW17) -> PASS | BA17: =IF(AX17<>"",AX17,IF(AH17<>"BET",0,IF(AI17*Method!$B$10/100<Method!$B$9,0,ROUND(AI17*Method!$B$10/100,0)))) -> 0 | BB17: 0 | BC17: 0.42176041 | BD17: 0.29612273 | BE17: 0.26066255 | BG17: 30 | BH17: warm_dry_indoor | BI17: 0
A18: 17 | B18: 46189 | C18: I | D18: France | E18: Senegal | F18: East Rutherford | G18: 15:00 | H18: 20:00 | I18: 0.70354502 | J18: 0.18717378 | K18: 0.10928121 | L18: =IF(Matchday!E20="","",Matchday!E20) -> 0.44444444 | M18: =IF(Matchday!F20="","",Matchday!F20) -> 3.3333333 | N18: =IF(Matchday!G20="","",Matchday!G20) -> 6 | O18: =IF(L18="","",1/L18) -> 2.25 | P18: =IF(M18="","",1/M18) -> 0.3 | Q18: =IF(N18="","",1/N18) -> 0.16666667 | R18: =IF(COUNT(L18:N18)<3,"",O18+P18+Q18) -> 2.7166667 | S18: {=IF($R18="","",IF(Method!$B$56="proportional",O18/$R18,IF(Method!$B$56="power",IFERROR(INDEX(power_devig($L18,$M18,$N18),1,1),O18/$R18),IFERROR(INDEX(shin($L18,$M18,$N18),1,1),O18/$R18))))} -> 0.82822086 | T18: {=IF($R18="","",IF(Method!$B$56="proportional",P18/$R18,IF(Method!$B$56="power",IFERROR(INDEX(power_devig($L18,$M18,$N18),2,1),P18/$R18),IFERROR(INDEX(shin($L18,$M18,$N18),2,1),P18/$R18))))} -> 0.11042945 | U18: {=IF($R18="","",IF(Method!$B$56="proportional",Q18/$R18,IF(Method!$B$56="power",IFERROR(INDEX(power_devig($L18,$M18,$N18),3,1),Q18/$R18),IFERROR(INDEX(shin($L18,$M18,$N18),3,1),Q18/$R18))))} -> 0.061349693 | V18: =IF(S18="","",Method!$B$4*I18+(1-Method!$B$4)*S18/($S18+$T18+$U18)) -> 0.78458432 | W18: =IF(T18="","",Method!$B$4*J18+(1-Method!$B$4)*T18/($S18+$T18+$U18)) -> 0.13728996 | X18: =IF(U18="","",Method!$B$4*K18+(1-Method!$B$4)*U18/($S18+$T18+$U18)) -> 0.078125722 | Y18: =IF(V18="","",V18*L18-1) -> -0.65129586 | Z18: =IF(W18="","",W18*M18-1) -> -0.54236679 | AA18: =IF(X18="","",X18*N18-1) -> -0.53124567 | AB18: =IF(Y18="","",MATCH(MAX(Y18:AA18),Y18:AA18,0)) -> 3 | AC18: =IF(AB18="","",CHOOSE(AB18,"H","D","A")) -> A | AD18: =IF(AB18="","",CHOOSE(AB18,"1 "&D18,"X Draw","2 "&E18)) -> 2 Senegal | AE18: =IF(AB18="","",INDEX(L18:N18,1,AB18)) -> 6 | AF18: =IF(AB18="","",INDEX(Y18:AA18,1,AB18)) -> -0.53124567 | AG18: =IF(AB18="","",INDEX(V18:X18,1,AB18)-INDEX(S18:U18,1,AB18)) -> 0.016776029 | AH18: =IF(AB18="","· enter odds",IF(AND(AF18>=Method!$B$7,AG18>=Method!$B$8),"BET","PASS")) -> PASS | AI18: =IF(AH18<>"BET",0,ROUND(MIN(Method!$B$6,Method!$B$5*AL18)*100,1)) -> 0 | AJ18: =IF(OR(AH18<>"BET",Method!$B$55=TRUE()),0,IF(AI18*Method!$B$10/100<Method!$B$9,0,ROUND(AI18*Method!$B$10/100,0))) -> 0 | AK18: =IF(AB18="","",INDEX(V18:X18,1,AB18)) -> 0.078125722 | AL18: =IF(AH18<>"BET","",MAX(0,(AK18*AE18-1)/(AE18-1))) | AM18: =IF(AH18="BET",AF18+A18/1000000,"") | AN18: =IF(Matchday!N20="","",Matchday!N20) | AO18: =IF(Matchday!P20="","",Matchday!P20) | AP18: =IF(Matchday!Q20="","",Matchday!Q20) | AQ18: =IF(Matchday!R20="","",Matchday!R20) | AR18: =IF(OR(AN18<>"Y",AQ18="",AV18=""),"",IF(AQ18="Void",0,IF(AQ18=AV18,ROUND(AP18*(AO18-1),2),-AP18))) | AS18: =IF(AR18="","",SUM($AR$2:AR18)) | AT18: =IF(AB18="","Type the 3 odds on the Matchday tab",IF(Method!$B$55=TRUE(),"🛑 PAUSED — drawdown "&TEXT(Method!$B$51,"0.0%")&" ≥ "&TEXT(Method!$B$52,"0.0%")&". Set Method!B54=Y to override.",IF(AH18="BET",IF(AJ18=0,"Edge found but stake rounds under £"&Method!$B$9&" — skip","Value found: EV "&TEXT(AF18,"0.0%")&", edge "&TEXT(AG18,"0.0%")),IF(AF18<Method!$B$7,"Price too short — EV "&TEXT(AF18,"0.0%")&" (need "&TEXT(Method!$B$7,"0.0%")&"+)","Model ≈ market — edge "&TEXT(AG18,"0.0%")&" (need "&TEXT(Method!$B$8,"0.0%")&"+)")))) -> 🛑 PAUSED — drawdown 0.6% ≥ 15.0%. Set Method!B54=Y to override. | AU18: =IF(AN18<>"Y","",IF(AH18="· enter odds","⚠ type the 3 odds (1/X/2) to grade this bet",IF(OR(AV18="",AO18="",AP18=""),"⚠ log backed pick, odds & stake",IF(AZ18<>"BET","⚠ FUN BET — engine said pass · staked £"&AP18&" vs engine £"&BA18,IF(AV18<>IF(AY18="",AC18,AY18),"⚠ backed "&AV18&" but engine pick was "&IF(AY18="",AC18,AY18),IF(AP18>BA18,"⚠ stake over engine £"&BA18,IF(ABS(AO18-IFERROR(INDEX(L18:N18,1,MATCH(AV18,{"H","D","A"},0)),AE18))>0.02,"⚠ odds moved — re-check value","✓ engine bet"))))))) | AV18: =IF(Matchday!O20="","",Matchday!O20) | AZ18: =IF(AW18="",AH18,AW18) -> PASS | BA18: =IF(AX18<>"",AX18,IF(AH18<>"BET",0,IF(AI18*Method!$B$10/100<Method!$B$9,0,ROUND(AI18*Method!$B$10/100,0)))) -> 0 | BB18: 0 | BC18: 0.65315978 | BD18: 0.21133048 | BE18: 0.11196535 | BG18: 7 | BH18: warm_humid | BI18: 0
A19: 18 | B19: 46189 | C19: I | D19: Iraq | E19: Norway | F19: Foxborough | G19: 18:00 | H19: 23:00 | I19: 0.1487524 | J19: 0.27151261 | K19: 0.57973499 | L19: =IF(Matchday!E21="","",Matchday!E21) -> 14 | M19: =IF(Matchday!F21="","",Matchday!F21) -> 5.5 | N19: =IF(Matchday!G21="","",Matchday!G21) -> 0.2 | O19: =IF(L19="","",1/L19) -> 0.071428571 | P19: =IF(M19="","",1/M19) -> 0.18181818 | Q19: =IF(N19="","",1/N19) -> 5 | R19: =IF(COUNT(L19:N19)<3,"",O19+P19+Q19) -> 5.2532468 | S19: {=IF($R19="","",IF(Method!$B$56="proportional",O19/$R19,IF(Method!$B$56="power",IFERROR(INDEX(power_devig($L19,$M19,$N19),1,1),O19/$R19),IFERROR(INDEX(shin($L19,$M19,$N19),1,1),O19/$R19))))} -> 0.013597033 | T19: {=IF($R19="","",IF(Method!$B$56="proportional",P19/$R19,IF(Method!$B$56="power",IFERROR(INDEX(power_devig($L19,$M19,$N19),2,1),P19/$R19),IFERROR(INDEX(shin($L19,$M19,$N19),2,1),P19/$R19))))} -> 0.03461063 | U19: {=IF($R19="","",IF(Method!$B$56="proportional",Q19/$R19,IF(Method!$B$56="power",IFERROR(INDEX(power_devig($L19,$M19,$N19),3,1),Q19/$R19),IFERROR(INDEX(shin($L19,$M19,$N19),3,1),Q19/$R19))))} -> 0.95179234 | V19: =IF(S19="","",Method!$B$4*I19+(1-Method!$B$4)*S19/($S19+$T19+$U19)) -> 0.060901413 | W19: =IF(T19="","",Method!$B$4*J19+(1-Method!$B$4)*T19/($S19+$T19+$U19)) -> 0.11752632 | X19: =IF(U19="","",Method!$B$4*K19+(1-Method!$B$4)*U19/($S19+$T19+$U19)) -> 0.82157226 | Y19: =IF(V19="","",V19*L19-1) -> -0.14738022 | Z19: =IF(W19="","",W19*M19-1) -> -0.35360523 | AA19: =IF(X19="","",X19*N19-1) -> -0.83568555 | AB19: =IF(Y19="","",MATCH(MAX(Y19:AA19),Y19:AA19,0)) -> 1 | AC19: =IF(AB19="","",CHOOSE(AB19,"H","D","A")) -> H | AD19: =IF(AB19="","",CHOOSE(AB19,"1 "&D19,"X Draw","2 "&E19)) -> 1 Iraq | AE19: =IF(AB19="","",INDEX(L19:N19,1,AB19)) -> 14 | AF19: =IF(AB19="","",INDEX(Y19:AA19,1,AB19)) -> -0.14738022 | AG19: =IF(AB19="","",INDEX(V19:X19,1,AB19)-INDEX(S19:U19,1,AB19)) -> 0.04730438 | AH19: =IF(AB19="","· enter odds",IF(AND(AF19>=Method!$B$7,AG19>=Method!$B$8),"BET","PASS")) -> PASS | AI19: =IF(AH19<>"BET",0,ROUND(MIN(Method!$B$6,Method!$B$5*AL19)*100,1)) -> 0 | AJ19: =IF(OR(AH19<>"BET",Method!$B$55=TRUE()),0,IF(AI19*Method!$B$10/100<Method!$B$9,0,ROUND(AI19*Method!$B$10/100,0))) -> 0 | AK19: =IF(AB19="","",INDEX(V19:X19,1,AB19)) -> 0.060901413 | AL19: =IF(AH19<>"BET","",MAX(0,(AK19*AE19-1)/(AE19-1))) | AM19: =IF(AH19="BET",AF19+A19/1000000,"") | AN19: =IF(Matchday!N21="","",Matchday!N21) | AO19: =IF(Matchday!P21="","",Matchday!P21) | AP19: =IF(Matchday!Q21="","",Matchday!Q21) | AQ19: =IF(Matchday!R21="","",Matchday!R21) | AR19: =IF(OR(AN19<>"Y",AQ19="",AV19=""),"",IF(AQ19="Void",0,IF(AQ19=AV19,ROUND(AP19*(AO19-1),2),-AP19))) | AS19: =IF(AR19="","",SUM($AR$2:AR19)) | AT19: =IF(AB19="","Type the 3 odds on the Matchday tab",IF(Method!$B$55=TRUE(),"🛑 PAUSED — drawdown "&TEXT(Method!$B$51,"0.0%")&" ≥ "&TEXT(Method!$B$52,"0.0%")&". Set Method!B54=Y to override.",IF(AH19="BET",IF(AJ19=0,"Edge found but stake rounds under £"&Method!$B$9&" — skip","Value found: EV "&TEXT(AF19,"0.0%")&", edge "&TEXT(AG19,"0.0%")),IF(AF19<Method!$B$7,"Price too short — EV "&TEXT(AF19,"0.0%")&" (need "&TEXT(Method!$B$7,"0.0%")&"+)","Model ≈ market — edge "&TEXT(AG19,"0.0%")&" (need "&TEXT(Method!$B$8,"0.0%")&"+)")))) -> 🛑 PAUSED — drawdown 0.6% ≥ 15.0%. Set Method!B54=Y to override. | AU19: =IF(AN19<>"Y","",IF(AH19="· enter odds","⚠ type the 3 odds (1/X/2) to grade this bet",IF(OR(AV19="",AO19="",AP19=""),"⚠ log backed pick, odds & stake",IF(AZ19<>"BET","⚠ FUN BET — engine said pass · staked £"&AP19&" vs engine £"&BA19,IF(AV19<>IF(AY19="",AC19,AY19),"⚠ backed "&AV19&" but engine pick was "&IF(AY19="",AC19,AY19),IF(AP19>BA19,"⚠ stake over engine £"&BA19,IF(ABS(AO19-IFERROR(INDEX(L19:N19,1,MATCH(AV19,{"H","D","A"},0)),AE19))>0.02,"⚠ odds moved — re-check value","✓ engine bet"))))))) | AV19: =IF(Matchday!O21="","",Matchday!O21) | AZ19: =IF(AW19="",AH19,AW19) -> PASS | BA19: =IF(AX19<>"",AX19,IF(AH19<>"BET",0,IF(AI19*Method!$B$10/100<Method!$B$9,0,ROUND(AI19*Method!$B$10/100,0)))) -> 0 | BB19: 0 | BC19: 0.12924914 | BD19: 0.28289035 | BE19: 0.56367809 | BG19: 40 | BH19: warm | BI19: 0
A20: 19 | B20: 46189 | C20: J | D20: Argentina | E20: Algeria | F20: Kansas City | G20: 20:00 | H20: 02:00 +1d | I20: 0.65005399 | J20: 0.22623162 | K20: 0.12371439 | L20: =IF(Matchday!E22="","",Matchday!E22) -> 0.4 | M20: =IF(Matchday!F22="","",Matchday!F22) -> 3.3333333 | N20: =IF(Matchday!G22="","",Matchday!G22) -> 7.5 | O20: =IF(L20="","",1/L20) -> 2.5 | P20: =IF(M20="","",1/M20) -> 0.3 | Q20: =IF(N20="","",1/N20) -> 0.13333333 | R20: =IF(COUNT(L20:N20)<3,"",O20+P20+Q20) -> 2.9333333 | S20: {=IF($R20="","",IF(Method!$B$56="proportional",O20/$R20,IF(Method!$B$56="power",IFERROR(INDEX(power_devig($L20,$M20,$N20),1,1),O20/$R20),IFERROR(INDEX(shin($L20,$M20,$N20),1,1),O20/$R20))))} -> 0.85227273 | T20: {=IF($R20="","",IF(Method!$B$56="proportional",P20/$R20,IF(Method!$B$56="power",IFERROR(INDEX(power_devig($L20,$M20,$N20),2,1),P20/$R20),IFERROR(INDEX(shin($L20,$M20,$N20),2,1),P20/$R20))))} -> 0.10227273 | U20: {=IF($R20="","",IF(Method!$B$56="proportional",Q20/$R20,IF(Method!$B$56="power",IFERROR(INDEX(power_devig($L20,$M20,$N20),3,1),Q20/$R20),IFERROR(INDEX(shin($L20,$M20,$N20),3,1),Q20/$R20))))} -> 0.045454545 | V20: =IF(S20="","",Method!$B$4*I20+(1-Method!$B$4)*S20/($S20+$T20+$U20)) -> 0.78149617 | W20: =IF(T20="","",Method!$B$4*J20+(1-Method!$B$4)*T20/($S20+$T20+$U20)) -> 0.14565834 | X20: =IF(U20="","",Method!$B$4*K20+(1-Method!$B$4)*U20/($S20+$T20+$U20)) -> 0.07284549 | Y20: =IF(V20="","",V20*L20-1) -> -0.68740153 | Z20: =IF(W20="","",W20*M20-1) -> -0.5144722 | AA20: =IF(X20="","",X20*N20-1) -> -0.45365883 | AB20: =IF(Y20="","",MATCH(MAX(Y20:AA20),Y20:AA20,0)) -> 3 | AC20: =IF(AB20="","",CHOOSE(AB20,"H","D","A")) -> A | AD20: =IF(AB20="","",CHOOSE(AB20,"1 "&D20,"X Draw","2 "&E20)) -> 2 Algeria | AE20: =IF(AB20="","",INDEX(L20:N20,1,AB20)) -> 7.5 | AF20: =IF(AB20="","",INDEX(Y20:AA20,1,AB20)) -> -0.45365883 | AG20: =IF(AB20="","",INDEX(V20:X20,1,AB20)-INDEX(S20:U20,1,AB20)) -> 0.027390944 | AH20: =IF(AB20="","· enter odds",IF(AND(AF20>=Method!$B$7,AG20>=Method!$B$8),"BET","PASS")) -> PASS | AI20: =IF(AH20<>"BET",0,ROUND(MIN(Method!$B$6,Method!$B$5*AL20)*100,1)) -> 0 | AJ20: =IF(OR(AH20<>"BET",Method!$B$55=TRUE()),0,IF(AI20*Method!$B$10/100<Method!$B$9,0,ROUND(AI20*Method!$B$10/100,0))) -> 0 | AK20: =IF(AB20="","",INDEX(V20:X20,1,AB20)) -> 0.07284549 | AL20: =IF(AH20<>"BET","",MAX(0,(AK20*AE20-1)/(AE20-1))) | AM20: =IF(AH20="BET",AF20+A20/1000000,"") | AN20: =IF(Matchday!N22="","",Matchday!N22) | AO20: =IF(Matchday!P22="","",Matchday!P22) | AP20: =IF(Matchday!Q22="","",Matchday!Q22) | AQ20: =IF(Matchday!R22="","",Matchday!R22) | AR20: =IF(OR(AN20<>"Y",AQ20="",AV20=""),"",IF(AQ20="Void",0,IF(AQ20=AV20,ROUND(AP20*(AO20-1),2),-AP20))) | AS20: =IF(AR20="","",SUM($AR$2:AR20)) | AT20: =IF(AB20="","Type the 3 odds on the Matchday tab",IF(Method!$B$55=TRUE(),"🛑 PAUSED — drawdown "&TEXT(Method!$B$51,"0.0%")&" ≥ "&TEXT(Method!$B$52,"0.0%")&". Set Method!B54=Y to override.",IF(AH20="BET",IF(AJ20=0,"Edge found but stake rounds under £"&Method!$B$9&" — skip","Value found: EV "&TEXT(AF20,"0.0%")&", edge "&TEXT(AG20,"0.0%")),IF(AF20<Method!$B$7,"Price too short — EV "&TEXT(AF20,"0.0%")&" (need "&TEXT(Method!$B$7,"0.0%")&"+)","Model ≈ market — edge "&TEXT(AG20,"0.0%")&" (need "&TEXT(Method!$B$8,"0.0%")&"+)")))) -> 🛑 PAUSED — drawdown 0.6% ≥ 15.0%. Set Method!B54=Y to override. | AU20: =IF(AN20<>"Y","",IF(AH20="· enter odds","⚠ type the 3 odds (1/X/2) to grade this bet",IF(OR(AV20="",AO20="",AP20=""),"⚠ log backed pick, odds & stake",IF(AZ20<>"BET","⚠ FUN BET — engine said pass · staked £"&AP20&" vs engine £"&BA20,IF(AV20<>IF(AY20="",AC20,AY20),"⚠ backed "&AV20&" but engine pick was "&IF(AY20="",AC20,AY20),IF(AP20>BA20,"⚠ stake over engine £"&BA20,IF(ABS(AO20-IFERROR(INDEX(L20:N20,1,MATCH(AV20,{"H","D","A"},0)),AE20))>0.02,"⚠ odds moved — re-check value","✓ engine bet"))))))) | AV20: =IF(Matchday!O22="","",Matchday!O22) | AZ20: =IF(AW20="",AH20,AW20) -> PASS | BA20: =IF(AX20<>"",AX20,IF(AH20<>"BET",0,IF(AI20*Method!$B$10/100<Method!$B$9,0,ROUND(AI20*Method!$B$10/100,0)))) -> 0 | BB20: 0 | BC20: 0.59692582 | BD20: 0.24914253 | BE20: 0.12746233 | BG20: 270 | BH20: hot | BI20: 0
A21: 20 | B21: 46189 | C21: J | D21: Austria | E21: Jordan | F21: Santa Clara | G21: 21:00 | H21: 05:00 +1d | I21: 0.43202009 | J21: 0.30264021 | K21: 0.2653397 | L21: =IF(Matchday!E23="","",Matchday!E23) -> 0.36363636 | M21: =IF(Matchday!F23="","",Matchday!F23) -> 3.6 | N21: =IF(Matchday!G23="","",Matchday!G23) -> 8 | O21: =IF(L21="","",1/L21) -> 2.75 | P21: =IF(M21="","",1/M21) -> 0.27777778 | Q21: =IF(N21="","",1/N21) -> 0.125 | R21: =IF(COUNT(L21:N21)<3,"",O21+P21+Q21) -> 3.1527778 | S21: {=IF($R21="","",IF(Method!$B$56="proportional",O21/$R21,IF(Method!$B$56="power",IFERROR(INDEX(power_devig($L21,$M21,$N21),1,1),O21/$R21),IFERROR(INDEX(shin($L21,$M21,$N21),1,1),O21/$R21))))} -> 0.8722467 | T21: {=IF($R21="","",IF(Method!$B$56="proportional",P21/$R21,IF(Method!$B$56="power",IFERROR(INDEX(power_devig($L21,$M21,$N21),2,1),P21/$R21),IFERROR(INDEX(shin($L21,$M21,$N21),2,1),P21/$R21))))} -> 0.088105727 | U21: {=IF($R21="","",IF(Method!$B$56="proportional",Q21/$R21,IF(Method!$B$56="power",IFERROR(INDEX(power_devig($L21,$M21,$N21),3,1),Q21/$R21),IFERROR(INDEX(shin($L21,$M21,$N21),3,1),Q21/$R21))))} -> 0.039647577 | V21: =IF(S21="","",Method!$B$4*I21+(1-Method!$B$4)*S21/($S21+$T21+$U21)) -> 0.71816739 | W21: =IF(T21="","",Method!$B$4*J21+(1-Method!$B$4)*T21/($S21+$T21+$U21)) -> 0.1631928 | X21: =IF(U21="","",Method!$B$4*K21+(1-Method!$B$4)*U21/($S21+$T21+$U21)) -> 0.11863982 | Y21: =IF(V21="","",V21*L21-1) -> -0.73884822 | Z21: =IF(W21="","",W21*M21-1) -> -0.41250593 | AA21: =IF(X21="","",X21*N21-1) -> -0.050881451 | AB21: =IF(Y21="","",MATCH(MAX(Y21:AA21),Y21:AA21,0)) -> 3 | AC21: =IF(AB21="","",CHOOSE(AB21,"H","D","A")) -> A | AD21: =IF(AB21="","",CHOOSE(AB21,"1 "&D21,"X Draw","2 "&E21)) -> 2 Jordan | AE21: =IF(AB21="","",INDEX(L21:N21,1,AB21)) -> 8 | AF21: =IF(AB21="","",INDEX(Y21:AA21,1,AB21)) -> -0.050881451 | AG21: =IF(AB21="","",INDEX(V21:X21,1,AB21)-INDEX(S21:U21,1,AB21)) -> 0.078992241 | AH21: =IF(AB21="","· enter odds",IF(AND(AF21>=Method!$B$7,AG21>=Method!$B$8),"BET","PASS")) -> PASS | AI21: =IF(AH21<>"BET",0,ROUND(MIN(Method!$B$6,Method!$B$5*AL21)*100,1)) -> 0 | AJ21: =IF(OR(AH21<>"BET",Method!$B$55=TRUE()),0,IF(AI21*Method!$B$10/100<Method!$B$9,0,ROUND(AI21*Method!$B$10/100,0))) -> 0 | AK21: =IF(AB21="","",INDEX(V21:X21,1,AB21)) -> 0.11863982 | AL21: =IF(AH21<>"BET","",MAX(0,(AK21*AE21-1)/(AE21-1))) | AM21: =IF(AH21="BET",AF21+A21/1000000,"") | AN21: =IF(Matchday!N23="","",Matchday!N23) | AO21: =IF(Matchday!P23="","",Matchday!P23) | AP21: =IF(Matchday!Q23="","",Matchday!Q23) | AQ21: =IF(Matchday!R23="","",Matchday!R23) | AR21: =IF(OR(AN21<>"Y",AQ21="",AV21=""),"",IF(AQ21="Void",0,IF(AQ21=AV21,ROUND(AP21*(AO21-1),2),-AP21))) | AS21: =IF(AR21="","",SUM($AR$2:AR21)) | AT21: =IF(AB21="","Type the 3 odds on the Matchday tab",IF(Method!$B$55=TRUE(),"🛑 PAUSED — drawdown "&TEXT(Method!$B$51,"0.0%")&" ≥ "&TEXT(Method!$B$52,"0.0%")&". Set Method!B54=Y to override.",IF(AH21="BET",IF(AJ21=0,"Edge found but stake rounds under £"&Method!$B$9&" — skip","Value found: EV "&TEXT(AF21,"0.0%")&", edge "&TEXT(AG21,"0.0%")),IF(AF21<Method!$B$7,"Price too short — EV "&TEXT(AF21,"0.0%")&" (need "&TEXT(Method!$B$7,"0.0%")&"+)","Model ≈ market — edge "&TEXT(AG21,"0.0%")&" (need "&TEXT(Method!$B$8,"0.0%")&"+)")))) -> 🛑 PAUSED — drawdown 0.6% ≥ 15.0%. Set Method!B54=Y to override. | AU21: =IF(AN21<>"Y","",IF(AH21="· enter odds","⚠ type the 3 odds (1/X/2) to grade this bet",IF(OR(AV21="",AO21="",AP21=""),"⚠ log backed pick, odds & stake",IF(AZ21<>"BET","⚠ FUN BET — engine said pass · staked £"&AP21&" vs engine £"&BA21,IF(AV21<>IF(AY21="",AC21,AY21),"⚠ backed "&AV21&" but engine pick was "&IF(AY21="",AC21,AY21),IF(AP21>BA21,"⚠ stake over engine £"&BA21,IF(ABS(AO21-IFERROR(INDEX(L21:N21,1,MATCH(AV21,{"H","D","A"},0)),AE21))>0.02,"⚠ odds moved — re-check value","✓ engine bet"))))))) | AV21: =IF(Matchday!O23="","",Matchday!O23) | AZ21: =IF(AW21="",AH21,AW21) -> PASS | BA21: =IF(AX21<>"",AX21,IF(AH21<>"BET",0,IF(AI21*Method!$B$10/100<Method!$B$9,0,ROUND(AI21*Method!$B$10/100,0)))) -> 0 | BB21: 0 | BC21: 0.41702039 | BD21: 0.29465912 | BE21: 0.27034738 | BG21: 8 | BH21: mild_dry | BI21: 0
A22: 21 | B22: 46190 | C22: K | D22: Portugal | E22: DR Congo | F22: Houston | G22: 12:00 | H22: 18:00 | I22: 0.63198636 | J22: 0.23925899 | K22: 0.12875465 | L22: =IF(Matchday!E24="","",Matchday!E24) -> 0.28571429 | M22: =IF(Matchday!F24="","",Matchday!F24) -> 4.5 | N22: =IF(Matchday!G24="","",Matchday!G24) -> 10 | O22: =IF(L22="","",1/L22) -> 3.5 | P22: =IF(M22="","",1/M22) -> 0.22222222 | Q22: =IF(N22="","",1/N22) -> 0.1 | R22: =IF(COUNT(L22:N22)<3,"",O22+P22+Q22) -> 3.8222222 | S22: {=IF($R22="","",IF(Method!$B$56="proportional",O22/$R22,IF(Method!$B$56="power",IFERROR(INDEX(power_devig($L22,$M22,$N22),1,1),O22/$R22),IFERROR(INDEX(shin($L22,$M22,$N22),1,1),O22/$R22))))} -> 0.91569767 | T22: {=IF($R22="","",IF(Method!$B$56="proportional",P22/$R22,IF(Method!$B$56="power",IFERROR(INDEX(power_devig($L22,$M22,$N22),2,1),P22/$R22),IFERROR(INDEX(shin($L22,$M22,$N22),2,1),P22/$R22))))} -> 0.058139535 | U22: {=IF($R22="","",IF(Method!$B$56="proportional",Q22/$R22,IF(Method!$B$56="power",IFERROR(INDEX(power_devig($L22,$M22,$N22),3,1),Q22/$R22),IFERROR(INDEX(shin($L22,$M22,$N22),3,1),Q22/$R22))))} -> 0.026162791 | V22: =IF(S22="","",Method!$B$4*I22+(1-Method!$B$4)*S22/($S22+$T22+$U22)) -> 0.81639871 | W22: =IF(T22="","",Method!$B$4*J22+(1-Method!$B$4)*T22/($S22+$T22+$U22)) -> 0.12153134 | X22: =IF(U22="","",Method!$B$4*K22+(1-Method!$B$4)*U22/($S22+$T22+$U22)) -> 0.062069943 | Y22: =IF(V22="","",V22*L22-1) -> -0.76674322 | Z22: =IF(W22="","",W22*M22-1) -> -0.45310896 | AA22: =IF(X22="","",X22*N22-1) -> -0.37930057 | AB22: =IF(Y22="","",MATCH(MAX(Y22:AA22),Y22:AA22,0)) -> 3 | AC22: =IF(AB22="","",CHOOSE(AB22,"H","D","A")) -> A | AD22: =IF(AB22="","",CHOOSE(AB22,"1 "&D22,"X Draw","2 "&E22)) -> 2 DR Congo | AE22: =IF(AB22="","",INDEX(L22:N22,1,AB22)) -> 10 | AF22: =IF(AB22="","",INDEX(Y22:AA22,1,AB22)) -> -0.37930057 | AG22: =IF(AB22="","",INDEX(V22:X22,1,AB22)-INDEX(S22:U22,1,AB22)) -> 0.035907152 | AH22: =IF(AB22="","· enter odds",IF(AND(AF22>=Method!$B$7,AG22>=Method!$B$8),"BET","PASS")) -> PASS | AI22: =IF(AH22<>"BET",0,ROUND(MIN(Method!$B$6,Method!$B$5*AL22)*100,1)) -> 0 | AJ22: =IF(OR(AH22<>"BET",Method!$B$55=TRUE()),0,IF(AI22*Method!$B$10/100<Method!$B$9,0,ROUND(AI22*Method!$B$10/100,0))) -> 0 | AK22: =IF(AB22="","",INDEX(V22:X22,1,AB22)) -> 0.062069943 | AL22: =IF(AH22<>"BET","",MAX(0,(AK22*AE22-1)/(AE22-1))) | AM22: =IF(AH22="BET",AF22+A22/1000000,"") | AN22: =IF(Matchday!N24="","",Matchday!N24) | AO22: =IF(Matchday!P24="","",Matchday!P24) | AP22: =IF(Matchday!Q24="","",Matchday!Q24) | AQ22: =IF(Matchday!R24="","",Matchday!R24) | AR22: =IF(OR(AN22<>"Y",AQ22="",AV22=""),"",IF(AQ22="Void",0,IF(AQ22=AV22,ROUND(AP22*(AO22-1),2),-AP22))) | AS22: =IF(AR22="","",SUM($AR$2:AR22)) | AT22: =IF(AB22="","Type the 3 odds on the Matchday tab",IF(Method!$B$55=TRUE(),"🛑 PAUSED — drawdown "&TEXT(Method!$B$51,"0.0%")&" ≥ "&TEXT(Method!$B$52,"0.0%")&". Set Method!B54=Y to override.",IF(AH22="BET",IF(AJ22=0,"Edge found but stake rounds under £"&Method!$B$9&" — skip","Value found: EV "&TEXT(AF22,"0.0%")&", edge "&TEXT(AG22,"0.0%")),IF(AF22<Method!$B$7,"Price too short — EV "&TEXT(AF22,"0.0%")&" (need "&TEXT(Method!$B$7,"0.0%")&"+)","Model ≈ market — edge "&TEXT(AG22,"0.0%")&" (need "&TEXT(Method!$B$8,"0.0%")&"+)")))) -> 🛑 PAUSED — drawdown 0.6% ≥ 15.0%. Set Method!B54=Y to override. | AU22: =IF(AN22<>"Y","",IF(AH22="· enter odds","⚠ type the 3 odds (1/X/2) to grade this bet",IF(OR(AV22="",AO22="",AP22=""),"⚠ log backed pick, odds & stake",IF(AZ22<>"BET","⚠ FUN BET — engine said pass · staked £"&AP22&" vs engine £"&BA22,IF(AV22<>IF(AY22="",AC22,AY22),"⚠ backed "&AV22&" but engine pick was "&IF(AY22="",AC22,AY22),IF(AP22>BA22,"⚠ stake over engine £"&BA22,IF(ABS(AO22-IFERROR(INDEX(L22:N22,1,MATCH(AV22,{"H","D","A"},0)),AE22))>0.02,"⚠ odds moved — re-check value","✓ engine bet"))))))) | AV22: =IF(Matchday!O24="","",Matchday!O24) | AZ22: =IF(AW22="",AH22,AW22) -> PASS | BA22: =IF(AX22<>"",AX22,IF(AH22<>"BET",0,IF(AI22*Method!$B$10/100<Method!$B$9,0,ROUND(AI22*Method!$B$10/100,0)))) -> 0 | BB22: -8 | BC22: 0.58506681 | BD22: 0.26175437 | BE22: 0.13287409 | BF22: Portugal weather: -8 | BG22: 15 | BH22: very_hot_humid_indoor | BI22: 0
A23: 22 | B23: 46190 | C23: L | D23: England | E23: Croatia | F23: Arlington | G23: 15:00 | H23: 21:00 | I23: 0.42187478 | J23: 0.29126656 | K23: 0.28685865 | L23: =IF(Matchday!E25="","",Matchday!E25) -> 0.72727273 | M23: =IF(Matchday!F25="","",Matchday!F25) -> 2.6 | N23: =IF(Matchday!G25="","",Matchday!G25) -> 4 | O23: =IF(L23="","",1/L23) -> 1.375 | P23: =IF(M23="","",1/M23) -> 0.38461538 | Q23: =IF(N23="","",1/N23) -> 0.25 | R23: =IF(COUNT(L23:N23)<3,"",O23+P23+Q23) -> 2.0096154 | S23: {=IF($R23="","",IF(Method!$B$56="proportional",O23/$R23,IF(Method!$B$56="power",IFERROR(INDEX(power_devig($L23,$M23,$N23),1,1),O23/$R23),IFERROR(INDEX(shin($L23,$M23,$N23),1,1),O23/$R23))))} -> 0.68421053 | T23: {=IF($R23="","",IF(Method!$B$56="proportional",P23/$R23,IF(Method!$B$56="power",IFERROR(INDEX(power_devig($L23,$M23,$N23),2,1),P23/$R23),IFERROR(INDEX(shin($L23,$M23,$N23),2,1),P23/$R23))))} -> 0.19138756 | U23: {=IF($R23="","",IF(Method!$B$56="proportional",Q23/$R23,IF(Method!$B$56="power",IFERROR(INDEX(power_devig($L23,$M23,$N23),3,1),Q23/$R23),IFERROR(INDEX(shin($L23,$M23,$N23),3,1),Q23/$R23))))} -> 0.12440191 | V23: =IF(S23="","",Method!$B$4*I23+(1-Method!$B$4)*S23/($S23+$T23+$U23)) -> 0.59239302 | W23: =IF(T23="","",Method!$B$4*J23+(1-Method!$B$4)*T23/($S23+$T23+$U23)) -> 0.22634521 | X23: =IF(U23="","",Method!$B$4*K23+(1-Method!$B$4)*U23/($S23+$T23+$U23)) -> 0.18126177 | Y23: =IF(V23="","",V23*L23-1) -> -0.56916871 | Z23: =IF(W23="","",W23*M23-1) -> -0.41150245 | AA23: =IF(X23="","",X23*N23-1) -> -0.27495291 | AB23: =IF(Y23="","",MATCH(MAX(Y23:AA23),Y23:AA23,0)) -> 3 | AC23: =IF(AB23="","",CHOOSE(AB23,"H","D","A")) -> A | AD23: =IF(AB23="","",CHOOSE(AB23,"1 "&D23,"X Draw","2 "&E23)) -> 2 Croatia | AE23: =IF(AB23="","",INDEX(L23:N23,1,AB23)) -> 4 | AF23: =IF(AB23="","",INDEX(Y23:AA23,1,AB23)) -> -0.27495291 | AG23: =IF(AB23="","",INDEX(V23:X23,1,AB23)-INDEX(S23:U23,1,AB23)) -> 0.056859858 | AH23: =IF(AB23="","· enter odds",IF(AND(AF23>=Method!$B$7,AG23>=Method!$B$8),"BET","PASS")) -> PASS | AI23: =IF(AH23<>"BET",0,ROUND(MIN(Method!$B$6,Method!$B$5*AL23)*100,1)) -> 0 | AJ23: =IF(OR(AH23<>"BET",Method!$B$55=TRUE()),0,IF(AI23*Method!$B$10/100<Method!$B$9,0,ROUND(AI23*Method!$B$10/100,0))) -> 0 | AK23: =IF(AB23="","",INDEX(V23:X23,1,AB23)) -> 0.18126177 | AL23: =IF(AH23<>"BET","",MAX(0,(AK23*AE23-1)/(AE23-1))) | AM23: =IF(AH23="BET",AF23+A23/1000000,"") | AN23: =IF(Matchday!N25="","",Matchday!N25) | AO23: =IF(Matchday!P25="","",Matchday!P25) | AP23: =IF(Matchday!Q25="","",Matchday!Q25) | AQ23: =IF(Matchday!R25="","",Matchday!R25) | AR23: =IF(OR(AN23<>"Y",AQ23="",AV23=""),"",IF(AQ23="Void",0,IF(AQ23=AV23,ROUND(AP23*(AO23-1),2),-AP23))) | AS23: =IF(AR23="","",SUM($AR$2:AR23)) | AT23: =IF(AB23="","Type the 3 odds on the Matchday tab",IF(Method!$B$55=TRUE(),"🛑 PAUSED — drawdown "&TEXT(Method!$B$51,"0.0%")&" ≥ "&TEXT(Method!$B$52,"0.0%")&". Set Method!B54=Y to override.",IF(AH23="BET",IF(AJ23=0,"Edge found but stake rounds under £"&Method!$B$9&" — skip","Value found: EV "&TEXT(AF23,"0.0%")&", edge "&TEXT(AG23,"0.0%")),IF(AF23<Method!$B$7,"Price too short — EV "&TEXT(AF23,"0.0%")&" (need "&TEXT(Method!$B$7,"0.0%")&"+)","Model ≈ market — edge "&TEXT(AG23,"0.0%")&" (need "&TEXT(Method!$B$8,"0.0%")&"+)")))) -> 🛑 PAUSED — drawdown 0.6% ≥ 15.0%. Set Method!B54=Y to override. | AU23: =IF(AN23<>"Y","",IF(AH23="· enter odds","⚠ type the 3 odds (1/X/2) to grade this bet",IF(OR(AV23="",AO23="",AP23=""),"⚠ log backed pick, odds & stake",IF(AZ23<>"BET","⚠ FUN BET — engine said pass · staked £"&AP23&" vs engine £"&BA23,IF(AV23<>IF(AY23="",AC23,AY23),"⚠ backed "&AV23&" but engine pick was "&IF(AY23="",AC23,AY23),IF(AP23>BA23,"⚠ stake over engine £"&BA23,IF(ABS(AO23-IFERROR(INDEX(L23:N23,1,MATCH(AV23,{"H","D","A"},0)),AE23))>0.02,"⚠ odds moved — re-check value","✓ engine bet"))))))) | AV23: =IF(Matchday!O25="","",Matchday!O25) | AZ23: =IF(AW23="",AH23,AW23) -> PASS | BA23: =IF(AX23<>"",AX23,IF(AH23<>"BET",0,IF(AI23*Method!$B$10/100<Method!$B$9,0,ROUND(AI23*Method!$B$10/100,0)))) -> 0 | BB23: -8 | BC23: 0.40759457 | BD23: 0.29035896 | BE23: 0.29357353 | BF23: Croatia weather: -4 · England weather: -4 | BG23: 175 | BH23: very_hot_indoor | BI23: 0
A24: 23 | B24: 46190 | C24: L | D24: Ghana | E24: Panama | F24: Toronto | G24: 19:00 | H24: 00:00 +1d | I24: 0.23948774 | J24: 0.28162898 | K24: 0.47888328 | L24: =IF(Matchday!E26="","",Matchday!E26) | M24: =IF(Matchday!F26="","",Matchday!F26) | N24: =IF(Matchday!G26="","",Matchday!G26) | O24: =IF(L24="","",1/L24) | P24: =IF(M24="","",1/M24) | Q24: =IF(N24="","",1/N24) | R24: =IF(COUNT(L24:N24)<3,"",O24+P24+Q24) | S24: {=IF($R24="","",IF(Method!$B$56="proportional",O24/$R24,IF(Method!$B$56="power",IFERROR(INDEX(power_devig($L24,$M24,$N24),1,1),O24/$R24),IFERROR(INDEX(shin($L24,$M24,$N24),1,1),O24/$R24))))} | T24: {=IF($R24="","",IF(Method!$B$56="proportional",P24/$R24,IF(Method!$B$56="power",IFERROR(INDEX(power_devig($L24,$M24,$N24),2,1),P24/$R24),IFERROR(INDEX(shin($L24,$M24,$N24),2,1),P24/$R24))))} | U24: {=IF($R24="","",IF(Method!$B$56="proportional",Q24/$R24,IF(Method!$B$56="power",IFERROR(INDEX(power_devig($L24,$M24,$N24),3,1),Q24/$R24),IFERROR(INDEX(shin($L24,$M24,$N24),3,1),Q24/$R24))))} | V24: =IF(S24="","",Method!$B$4*I24+(1-Method!$B$4)*S24/($S24+$T24+$U24)) | W24: =IF(T24="","",Method!$B$4*J24+(1-Method!$B$4)*T24/($S24+$T24+$U24)) | X24: =IF(U24="","",Method!$B$4*K24+(1-Method!$B$4)*U24/($S24+$T24+$U24)) | Y24: =IF(V24="","",V24*L24-1) | Z24: =IF(W24="","",W24*M24-1) | AA24: =IF(X24="","",X24*N24-1) | AB24: =IF(Y24="","",MATCH(MAX(Y24:AA24),Y24:AA24,0)) | AC24: =IF(AB24="","",CHOOSE(AB24,"H","D","A")) | AD24: =IF(AB24="","",CHOOSE(AB24,"1 "&D24,"X Draw","2 "&E24)) | AE24: =IF(AB24="","",INDEX(L24:N24,1,AB24)) | AF24: =IF(AB24="","",INDEX(Y24:AA24,1,AB24)) | AG24: =IF(AB24="","",INDEX(V24:X24,1,AB24)-INDEX(S24:U24,1,AB24)) | AH24: =IF(AB24="","· enter odds",IF(AND(AF24>=Method!$B$7,AG24>=Method!$B$8),"BET","PASS")) -> · enter odds | AI24: =IF(AH24<>"BET",0,ROUND(MIN(Method!$B$6,Method!$B$5*AL24)*100,1)) -> 0 | AJ24: =IF(OR(AH24<>"BET",Method!$B$55=TRUE()),0,IF(AI24*Method!$B$10/100<Method!$B$9,0,ROUND(AI24*Method!$B$10/100,0))) -> 0 | AK24: =IF(AB24="","",INDEX(V24:X24,1,AB24)) | AL24: =IF(AH24<>"BET","",MAX(0,(AK24*AE24-1)/(AE24-1))) | AM24: =IF(AH24="BET",AF24+A24/1000000,"") | AN24: =IF(Matchday!N26="","",Matchday!N26) | AO24: =IF(Matchday!P26="","",Matchday!P26) | AP24: =IF(Matchday!Q26="","",Matchday!Q26) | AQ24: =IF(Matchday!R26="","",Matchday!R26) | AR24: =IF(OR(AN24<>"Y",AQ24="",AV24=""),"",IF(AQ24="Void",0,IF(AQ24=AV24,ROUND(AP24*(AO24-1),2),-AP24))) | AS24: =IF(AR24="","",SUM($AR$2:AR24)) | AT24: =IF(AB24="","Type the 3 odds on the Matchday tab",IF(Method!$B$55=TRUE(),"🛑 PAUSED — drawdown "&TEXT(Method!$B$51,"0.0%")&" ≥ "&TEXT(Method!$B$52,"0.0%")&". Set Method!B54=Y to override.",IF(AH24="BET",IF(AJ24=0,"Edge found but stake rounds under £"&Method!$B$9&" — skip","Value found: EV "&TEXT(AF24,"0.0%")&", edge "&TEXT(AG24,"0.0%")),IF(AF24<Method!$B$7,"Price too short — EV "&TEXT(AF24,"0.0%")&" (need "&TEXT(Method!$B$7,"0.0%")&"+)","Model ≈ market — edge "&TEXT(AG24,"0.0%")&" (need "&TEXT(Method!$B$8,"0.0%")&"+)")))) -> Type the 3 odds on the Matchday tab | AU24: =IF(AN24<>"Y","",IF(AH24="· enter odds","⚠ type the 3 odds (1/X/2) to grade this bet",IF(OR(AV24="",AO24="",AP24=""),"⚠ log backed pick, odds & stake",IF(AZ24<>"BET","⚠ FUN BET — engine said pass · staked £"&AP24&" vs engine £"&BA24,IF(AV24<>IF(AY24="",AC24,AY24),"⚠ backed "&AV24&" but engine pick was "&IF(AY24="",AC24,AY24),IF(AP24>BA24,"⚠ stake over engine £"&BA24,IF(ABS(AO24-IFERROR(INDEX(L24:N24,1,MATCH(AV24,{"H","D","A"},0)),AE24))>0.02,"⚠ odds moved — re-check value","✓ engine bet"))))))) | AV24: =IF(Matchday!O26="","",Matchday!O26) | AZ24: =IF(AW24="",AH24,AW24) -> · enter odds | BA24: =IF(AX24<>"",AX24,IF(AH24<>"BET",0,IF(AI24*Method!$B$10/100<Method!$B$9,0,ROUND(AI24*Method!$B$10/100,0)))) -> 0 | BB24: 0 | BC24: 0.22372862 | BD24: 0.28671516 | BE24: 0.47196798 | BG24: 76 | BH24: mild | BI24: 0
A25: 24 | B25: 46190 | C25: K | D25: Uzbekistan | E25: Colombia | F25: Mexico City | G25: 20:00 | H25: 03:00 +1d | I25: 0.14615465 | J25: 0.23925291 | K25: 0.61459244 | L25: =IF(Matchday!E27="","",Matchday!E27) | M25: =IF(Matchday!F27="","",Matchday!F27) | N25: =IF(Matchday!G27="","",Matchday!G27) | O25: =IF(L25="","",1/L25) | P25: =IF(M25="","",1/M25) | Q25: =IF(N25="","",1/N25) | R25: =IF(COUNT(L25:N25)<3,"",O25+P25+Q25) | S25: {=IF($R25="","",IF(Method!$B$56="proportional",O25/$R25,IF(Method!$B$56="power",IFERROR(INDEX(power_devig($L25,$M25,$N25),1,1),O25/$R25),IFERROR(INDEX(shin($L25,$M25,$N25),1,1),O25/$R25))))} | T25: {=IF($R25="","",IF(Method!$B$56="proportional",P25/$R25,IF(Method!$B$56="power",IFERROR(INDEX(power_devig($L25,$M25,$N25),2,1),P25/$R25),IFERROR(INDEX(shin($L25,$M25,$N25),2,1),P25/$R25))))} | U25: {=IF($R25="","",IF(Method!$B$56="proportional",Q25/$R25,IF(Method!$B$56="power",IFERROR(INDEX(power_devig($L25,$M25,$N25),3,1),Q25/$R25),IFERROR(INDEX(shin($L25,$M25,$N25),3,1),Q25/$R25))))} | V25: =IF(S25="","",Method!$B$4*I25+(1-Method!$B$4)*S25/($S25+$T25+$U25)) | W25: =IF(T25="","",Method!$B$4*J25+(1-Method!$B$4)*T25/($S25+$T25+$U25)) | X25: =IF(U25="","",Method!$B$4*K25+(1-Method!$B$4)*U25/($S25+$T25+$U25)) | Y25: =IF(V25="","",V25*L25-1) | Z25: =IF(W25="","",W25*M25-1) | AA25: =IF(X25="","",X25*N25-1) | AB25: =IF(Y25="","",MATCH(MAX(Y25:AA25),Y25:AA25,0)) | AC25: =IF(AB25="","",CHOOSE(AB25,"H","D","A")) | AD25: =IF(AB25="","",CHOOSE(AB25,"1 "&D25,"X Draw","2 "&E25)) | AE25: =IF(AB25="","",INDEX(L25:N25,1,AB25)) | AF25: =IF(AB25="","",INDEX(Y25:AA25,1,AB25)) | AG25: =IF(AB25="","",INDEX(V25:X25,1,AB25)-INDEX(S25:U25,1,AB25)) | AH25: =IF(AB25="","· enter odds",IF(AND(AF25>=Method!$B$7,AG25>=Method!$B$8),"BET","PASS")) -> · enter odds | AI25: =IF(AH25<>"BET",0,ROUND(MIN(Method!$B$6,Method!$B$5*AL25)*100,1)) -> 0 | AJ25: =IF(OR(AH25<>"BET",Method!$B$55=TRUE()),0,IF(AI25*Method!$B$10/100<Method!$B$9,0,ROUND(AI25*Method!$B$10/100,0))) -> 0 | AK25: =IF(AB25="","",INDEX(V25:X25,1,AB25)) | AL25: =IF(AH25<>"BET","",MAX(0,(AK25*AE25-1)/(AE25-1))) | AM25: =IF(AH25="BET",AF25+A25/1000000,"") | AN25: =IF(Matchday!N27="","",Matchday!N27) | AO25: =IF(Matchday!P27="","",Matchday!P27) | AP25: =IF(Matchday!Q27="","",Matchday!Q27) | AQ25: =IF(Matchday!R27="","",Matchday!R27) | AR25: =IF(OR(AN25<>"Y",AQ25="",AV25=""),"",IF(AQ25="Void",0,IF(AQ25=AV25,ROUND(AP25*(AO25-1),2),-AP25))) | AS25: =IF(AR25="","",SUM($AR$2:AR25)) | AT25: =IF(AB25="","Type the 3 odds on the Matchday tab",IF(Method!$B$55=TRUE(),"🛑 PAUSED — drawdown "&TEXT(Method!$B$51,"0.0%")&" ≥ "&TEXT(Method!$B$52,"0.0%")&". Set Method!B54=Y to override.",IF(AH25="BET",IF(AJ25=0,"Edge found but stake rounds under £"&Method!$B$9&" — skip","Value found: EV "&TEXT(AF25,"0.0%")&", edge "&TEXT(AG25,"0.0%")),IF(AF25<Method!$B$7,"Price too short — EV "&TEXT(AF25,"0.0%")&" (need "&TEXT(Method!$B$7,"0.0%")&"+)","Model ≈ market — edge "&TEXT(AG25,"0.0%")&" (need "&TEXT(Method!$B$8,"0.0%")&"+)")))) -> Type the 3 odds on the Matchday tab | AU25: =IF(AN25<>"Y","",IF(AH25="· enter odds","⚠ type the 3 odds (1/X/2) to grade this bet",IF(OR(AV25="",AO25="",AP25=""),"⚠ log backed pick, odds & stake",IF(AZ25<>"BET","⚠ FUN BET — engine said pass · staked £"&AP25&" vs engine £"&BA25,IF(AV25<>IF(AY25="",AC25,AY25),"⚠ backed "&AV25&" but engine pick was "&IF(AY25="",AC25,AY25),IF(AP25>BA25,"⚠ stake over engine £"&BA25,IF(ABS(AO25-IFERROR(INDEX(L25:N25,1,MATCH(AV25,{"H","D","A"},0)),AE25))>0.02,"⚠ odds moved — re-check value","✓ engine bet"))))))) | AV25: =IF(Matchday!O27="","",Matchday!O27) | AZ25: =IF(AW25="",AH25,AW25) -> · enter odds | BA25: =IF(AX25<>"",AX25,IF(AH25<>"BET",0,IF(AI25*Method!$B$10/100<Method!$B$9,0,ROUND(AI25*Method!$B$10/100,0)))) -> 0 | BB25: 0 | BC25: 0.1271062 | BD25: 0.26174849 | BE25: 0.60046277 | BG25: 2240 | BH25: high_altitude_mild | BI25: 0
A26: 25 | B26: 46191 | C26: A | D26: Czechia | E26: South Africa | F26: Atlanta | G26: 12:00 | H26: 17:00 | I26: 0.50695698 | J26: 0.29312501 | K26: 0.19991801 | L26: =IF(Matchday!E28="","",Matchday!E28) | M26: =IF(Matchday!F28="","",Matchday!F28) | N26: =IF(Matchday!G28="","",Matchday!G28) | O26: =IF(L26="","",1/L26) | P26: =IF(M26="","",1/M26) | Q26: =IF(N26="","",1/N26) | R26: =IF(COUNT(L26:N26)<3,"",O26+P26+Q26) | S26: {=IF($R26="","",IF(Method!$B$56="proportional",O26/$R26,IF(Method!$B$56="power",IFERROR(INDEX(power_devig($L26,$M26,$N26),1,1),O26/$R26),IFERROR(INDEX(shin($L26,$M26,$N26),1,1),O26/$R26))))} | T26: {=IF($R26="","",IF(Method!$B$56="proportional",P26/$R26,IF(Method!$B$56="power",IFERROR(INDEX(power_devig($L26,$M26,$N26),2,1),P26/$R26),IFERROR(INDEX(shin($L26,$M26,$N26),2,1),P26/$R26))))} | U26: {=IF($R26="","",IF(Method!$B$56="proportional",Q26/$R26,IF(Method!$B$56="power",IFERROR(INDEX(power_devig($L26,$M26,$N26),3,1),Q26/$R26),IFERROR(INDEX(shin($L26,$M26,$N26),3,1),Q26/$R26))))} | V26: =IF(S26="","",Method!$B$4*I26+(1-Method!$B$4)*S26/($S26+$T26+$U26)) | W26: =IF(T26="","",Method!$B$4*J26+(1-Method!$B$4)*T26/($S26+$T26+$U26)) | X26: =IF(U26="","",Method!$B$4*K26+(1-Method!$B$4)*U26/($S26+$T26+$U26)) | Y26: =IF(V26="","",V26*L26-1) | Z26: =IF(W26="","",W26*M26-1) | AA26: =IF(X26="","",X26*N26-1) | AB26: =IF(Y26="","",MATCH(MAX(Y26:AA26),Y26:AA26,0)) | AC26: =IF(AB26="","",CHOOSE(AB26,"H","D","A")) | AD26: =IF(AB26="","",CHOOSE(AB26,"1 "&D26,"X Draw","2 "&E26)) | AE26: =IF(AB26="","",INDEX(L26:N26,1,AB26)) | AF26: =IF(AB26="","",INDEX(Y26:AA26,1,AB26)) | AG26: =IF(AB26="","",INDEX(V26:X26,1,AB26)-INDEX(S26:U26,1,AB26)) | AH26: =IF(AB26="","· enter odds",IF(AND(AF26>=Method!$B$7,AG26>=Method!$B$8),"BET","PASS")) -> · enter odds | AI26: =IF(AH26<>"BET",0,ROUND(MIN(Method!$B$6,Method!$B$5*AL26)*100,1)) -> 0 | AJ26: =IF(OR(AH26<>"BET",Method!$B$55=TRUE()),0,IF(AI26*Method!$B$10/100<Method!$B$9,0,ROUND(AI26*Method!$B$10/100,0))) -> 0 | AK26: =IF(AB26="","",INDEX(V26:X26,1,AB26)) | AL26: =IF(AH26<>"BET","",MAX(0,(AK26*AE26-1)/(AE26-1))) | AM26: =IF(AH26="BET",AF26+A26/1000000,"") | AN26: =IF(Matchday!N28="","",Matchday!N28) | AO26: =IF(Matchday!P28="","",Matchday!P28) | AP26: =IF(Matchday!Q28="","",Matchday!Q28) | AQ26: =IF(Matchday!R28="","",Matchday!R28) | AR26: =IF(OR(AN26<>"Y",AQ26="",AV26=""),"",IF(AQ26="Void",0,IF(AQ26=AV26,ROUND(AP26*(AO26-1),2),-AP26))) | AS26: =IF(AR26="","",SUM($AR$2:AR26)) | AT26: =IF(AB26="","Type the 3 odds on the Matchday tab",IF(Method!$B$55=TRUE(),"🛑 PAUSED — drawdown "&TEXT(Method!$B$51,"0.0%")&" ≥ "&TEXT(Method!$B$52,"0.0%")&". Set Method!B54=Y to override.",IF(AH26="BET",IF(AJ26=0,"Edge found but stake rounds under £"&Method!$B$9&" — skip","Value found: EV "&TEXT(AF26,"0.0%")&", edge "&TEXT(AG26,"0.0%")),IF(AF26<Method!$B$7,"Price too short — EV "&TEXT(AF26,"0.0%")&" (need "&TEXT(Method!$B$7,"0.0%")&"+)","Model ≈ market — edge "&TEXT(AG26,"0.0%")&" (need "&TEXT(Method!$B$8,"0.0%")&"+)")))) -> Type the 3 odds on the Matchday tab | AU26: =IF(AN26<>"Y","",IF(AH26="· enter odds","⚠ type the 3 odds (1/X/2) to grade this bet",IF(OR(AV26="",AO26="",AP26=""),"⚠ log backed pick, odds & stake",IF(AZ26<>"BET","⚠ FUN BET — engine said pass · staked £"&AP26&" vs engine £"&BA26,IF(AV26<>IF(AY26="",AC26,AY26),"⚠ backed "&AV26&" but engine pick was "&IF(AY26="",AC26,AY26),IF(AP26>BA26,"⚠ stake over engine £"&BA26,IF(ABS(AO26-IFERROR(INDEX(L26:N26,1,MATCH(AV26,{"H","D","A"},0)),AE26))>0.02,"⚠ odds moved — re-check value","✓ engine bet"))))))) | AV26: =IF(Matchday!O28="","",Matchday!O28) | AZ26: =IF(AW26="",AH26,AW26) -> · enter odds | BA26: =IF(AX26<>"",AX26,IF(AH26<>"BET",0,IF(AI26*Method!$B$10/100<Method!$B$9,0,ROUND(AI26*Method!$B$10/100,0)))) -> 0 | BB26: 0 | BC26: 0.49122442 | BD26: 0.2910616 | BE26: 0.20457331 | BG26: 320 | BH26: hot_humid_indoor | BI26: 2373.1
A27: 26 | B27: 46191 | C27: B | D27: Switzerland | E27: Bosnia and Herzegovina | F27: Inglewood | G27: 15:00 | H27: 23:00 | I27: 0.63922398 | J27: 0.23865207 | K27: 0.12212395 | L27: =IF(Matchday!E29="","",Matchday!E29) | M27: =IF(Matchday!F29="","",Matchday!F29) | N27: =IF(Matchday!G29="","",Matchday!G29) | O27: =IF(L27="","",1/L27) | P27: =IF(M27="","",1/M27) | Q27: =IF(N27="","",1/N27) | R27: =IF(COUNT(L27:N27)<3,"",O27+P27+Q27) | S27: {=IF($R27="","",IF(Method!$B$56="proportional",O27/$R27,IF(Method!$B$56="power",IFERROR(INDEX(power_devig($L27,$M27,$N27),1,1),O27/$R27),IFERROR(INDEX(shin($L27,$M27,$N27),1,1),O27/$R27))))} | T27: {=IF($R27="","",IF(Method!$B$56="proportional",P27/$R27,IF(Method!$B$56="power",IFERROR(INDEX(power_devig($L27,$M27,$N27),2,1),P27/$R27),IFERROR(INDEX(shin($L27,$M27,$N27),2,1),P27/$R27))))} | U27: {=IF($R27="","",IF(Method!$B$56="proportional",Q27/$R27,IF(Method!$B$56="power",IFERROR(INDEX(power_devig($L27,$M27,$N27),3,1),Q27/$R27),IFERROR(INDEX(shin($L27,$M27,$N27),3,1),Q27/$R27))))} | V27: =IF(S27="","",Method!$B$4*I27+(1-Method!$B$4)*S27/($S27+$T27+$U27)) | W27: =IF(T27="","",Method!$B$4*J27+(1-Method!$B$4)*T27/($S27+$T27+$U27)) | X27: =IF(U27="","",Method!$B$4*K27+(1-Method!$B$4)*U27/($S27+$T27+$U27)) | Y27: =IF(V27="","",V27*L27-1) | Z27: =IF(W27="","",W27*M27-1) | AA27: =IF(X27="","",X27*N27-1) | AB27: =IF(Y27="","",MATCH(MAX(Y27:AA27),Y27:AA27,0)) | AC27: =IF(AB27="","",CHOOSE(AB27,"H","D","A")) | AD27: =IF(AB27="","",CHOOSE(AB27,"1 "&D27,"X Draw","2 "&E27)) | AE27: =IF(AB27="","",INDEX(L27:N27,1,AB27)) | AF27: =IF(AB27="","",INDEX(Y27:AA27,1,AB27)) | AG27: =IF(AB27="","",INDEX(V27:X27,1,AB27)-INDEX(S27:U27,1,AB27)) | AH27: =IF(AB27="","· enter odds",IF(AND(AF27>=Method!$B$7,AG27>=Method!$B$8),"BET","PASS")) -> · enter odds | AI27: =IF(AH27<>"BET",0,ROUND(MIN(Method!$B$6,Method!$B$5*AL27)*100,1)) -> 0 | AJ27: =IF(OR(AH27<>"BET",Method!$B$55=TRUE()),0,IF(AI27*Method!$B$10/100<Method!$B$9,0,ROUND(AI27*Method!$B$10/100,0))) -> 0 | AK27: =IF(AB27="","",INDEX(V27:X27,1,AB27)) | AL27: =IF(AH27<>"BET","",MAX(0,(AK27*AE27-1)/(AE27-1))) | AM27: =IF(AH27="BET",AF27+A27/1000000,"") | AN27: =IF(Matchday!N29="","",Matchday!N29) | AO27: =IF(Matchday!P29="","",Matchday!P29) | AP27: =IF(Matchday!Q29="","",Matchday!Q29) | AQ27: =IF(Matchday!R29="","",Matchday!R29) | AR27: =IF(OR(AN27<>"Y",AQ27="",AV27=""),"",IF(AQ27="Void",0,IF(AQ27=AV27,ROUND(AP27*(AO27-1),2),-AP27))) | AS27: =IF(AR27="","",SUM($AR$2:AR27)) | AT27: =IF(AB27="","Type the 3 odds on the Matchday tab",IF(Method!$B$55=TRUE(),"🛑 PAUSED — drawdown "&TEXT(Method!$B$51,"0.0%")&" ≥ "&TEXT(Method!$B$52,"0.0%")&". Set Method!B54=Y to override.",IF(AH27="BET",IF(AJ27=0,"Edge found but stake rounds under £"&Method!$B$9&" — skip","Value found: EV "&TEXT(AF27,"0.0%")&", edge "&TEXT(AG27,"0.0%")),IF(AF27<Method!$B$7,"Price too short — EV "&TEXT(AF27,"0.0%")&" (need "&TEXT(Method!$B$7,"0.0%")&"+)","Model ≈ market — edge "&TEXT(AG27,"0.0%")&" (need "&TEXT(Method!$B$8,"0.0%")&"+)")))) -> Type the 3 odds on the Matchday tab | AU27: =IF(AN27<>"Y","",IF(AH27="· enter odds","⚠ type the 3 odds (1/X/2) to grade this bet",IF(OR(AV27="",AO27="",AP27=""),"⚠ log backed pick, odds & stake",IF(AZ27<>"BET","⚠ FUN BET — engine said pass · staked £"&AP27&" vs engine £"&BA27,IF(AV27<>IF(AY27="",AC27,AY27),"⚠ backed "&AV27&" but engine pick was "&IF(AY27="",AC27,AY27),IF(AP27>BA27,"⚠ stake over engine £"&BA27,IF(ABS(AO27-IFERROR(INDEX(L27:N27,1,MATCH(AV27,{"H","D","A"},0)),AE27))>0.02,"⚠ odds moved — re-check value","✓ engine bet"))))))) | AV27: =IF(Matchday!O29="","",Matchday!O29) | AZ27: =IF(AW27="",AH27,AW27) -> · enter odds | BA27: =IF(AX27<>"",AX27,IF(AH27<>"BET",0,IF(AI27*Method!$B$10/100<Method!$B$9,0,ROUND(AI27*Method!$B$10/100,0)))) -> 0 | BB27: 0 | BC27: 0.58955406 | BD27: 0.26116681 | BE27: 0.12575468 | BG27: 30 | BH27: warm_dry_indoor | BI27: 504.6
A28: 27 | B28: 46191 | C28: B | D28: Canada | E28: Qatar | F28: Vancouver | G28: 18:00 | H28: 02:00 +1d | I28: 0.73446928 | J28: 0.20197551 | K28: 0.063555213 | L28: =IF(Matchday!E30="","",Matchday!E30) | M28: =IF(Matchday!F30="","",Matchday!F30) | N28: =IF(Matchday!G30="","",Matchday!G30) | O28: =IF(L28="","",1/L28) | P28: =IF(M28="","",1/M28) | Q28: =IF(N28="","",1/N28) | R28: =IF(COUNT(L28:N28)<3,"",O28+P28+Q28) | S28: {=IF($R28="","",IF(Method!$B$56="proportional",O28/$R28,IF(Method!$B$56="power",IFERROR(INDEX(power_devig($L28,$M28,$N28),1,1),O28/$R28),IFERROR(INDEX(shin($L28,$M28,$N28),1,1),O28/$R28))))} | T28: {=IF($R28="","",IF(Method!$B$56="proportional",P28/$R28,IF(Method!$B$56="power",IFERROR(INDEX(power_devig($L28,$M28,$N28),2,1),P28/$R28),IFERROR(INDEX(shin($L28,$M28,$N28),2,1),P28/$R28))))} | U28: {=IF($R28="","",IF(Method!$B$56="proportional",Q28/$R28,IF(Method!$B$56="power",IFERROR(INDEX(power_devig($L28,$M28,$N28),3,1),Q28/$R28),IFERROR(INDEX(shin($L28,$M28,$N28),3,1),Q28/$R28))))} | V28: =IF(S28="","",Method!$B$4*I28+(1-Method!$B$4)*S28/($S28+$T28+$U28)) | W28: =IF(T28="","",Method!$B$4*J28+(1-Method!$B$4)*T28/($S28+$T28+$U28)) | X28: =IF(U28="","",Method!$B$4*K28+(1-Method!$B$4)*U28/($S28+$T28+$U28)) | Y28: =IF(V28="","",V28*L28-1) | Z28: =IF(W28="","",W28*M28-1) | AA28: =IF(X28="","",X28*N28-1) | AB28: =IF(Y28="","",MATCH(MAX(Y28:AA28),Y28:AA28,0)) | AC28: =IF(AB28="","",CHOOSE(AB28,"H","D","A")) | AD28: =IF(AB28="","",CHOOSE(AB28,"1 "&D28,"X Draw","2 "&E28)) | AE28: =IF(AB28="","",INDEX(L28:N28,1,AB28)) | AF28: =IF(AB28="","",INDEX(Y28:AA28,1,AB28)) | AG28: =IF(AB28="","",INDEX(V28:X28,1,AB28)-INDEX(S28:U28,1,AB28)) | AH28: =IF(AB28="","· enter odds",IF(AND(AF28>=Method!$B$7,AG28>=Method!$B$8),"BET","PASS")) -> · enter odds | AI28: =IF(AH28<>"BET",0,ROUND(MIN(Method!$B$6,Method!$B$5*AL28)*100,1)) -> 0 | AJ28: =IF(OR(AH28<>"BET",Method!$B$55=TRUE()),0,IF(AI28*Method!$B$10/100<Method!$B$9,0,ROUND(AI28*Method!$B$10/100,0))) -> 0 | AK28: =IF(AB28="","",INDEX(V28:X28,1,AB28)) | AL28: =IF(AH28<>"BET","",MAX(0,(AK28*AE28-1)/(AE28-1))) | AM28: =IF(AH28="BET",AF28+A28/1000000,"") | AN28: =IF(Matchday!N30="","",Matchday!N30) | AO28: =IF(Matchday!P30="","",Matchday!P30) | AP28: =IF(Matchday!Q30="","",Matchday!Q30) | AQ28: =IF(Matchday!R30="","",Matchday!R30) | AR28: =IF(OR(AN28<>"Y",AQ28="",AV28=""),"",IF(AQ28="Void",0,IF(AQ28=AV28,ROUND(AP28*(AO28-1),2),-AP28))) | AS28: =IF(AR28="","",SUM($AR$2:AR28)) | AT28: =IF(AB28="","Type the 3 odds on the Matchday tab",IF(Method!$B$55=TRUE(),"🛑 PAUSED — drawdown "&TEXT(Method!$B$51,"0.0%")&" ≥ "&TEXT(Method!$B$52,"0.0%")&". Set Method!B54=Y to override.",IF(AH28="BET",IF(AJ28=0,"Edge found but stake rounds under £"&Method!$B$9&" — skip","Value found: EV "&TEXT(AF28,"0.0%")&", edge "&TEXT(AG28,"0.0%")),IF(AF28<Method!$B$7,"Price too short — EV "&TEXT(AF28,"0.0%")&" (need "&TEXT(Method!$B$7,"0.0%")&"+)","Model ≈ market — edge "&TEXT(AG28,"0.0%")&" (need "&TEXT(Method!$B$8,"0.0%")&"+)")))) -> Type the 3 odds on the Matchday tab | AU28: =IF(AN28<>"Y","",IF(AH28="· enter odds","⚠ type the 3 odds (1/X/2) to grade this bet",IF(OR(AV28="",AO28="",AP28=""),"⚠ log backed pick, odds & stake",IF(AZ28<>"BET","⚠ FUN BET — engine said pass · staked £"&AP28&" vs engine £"&BA28,IF(AV28<>IF(AY28="",AC28,AY28),"⚠ backed "&AV28&" but engine pick was "&IF(AY28="",AC28,AY28),IF(AP28>BA28,"⚠ stake over engine £"&BA28,IF(ABS(AO28-IFERROR(INDEX(L28:N28,1,MATCH(AV28,{"H","D","A"},0)),AE28))>0.02,"⚠ odds moved — re-check value","✓ engine bet"))))))) | AV28: =IF(Matchday!O30="","",Matchday!O30) | AZ28: =IF(AW28="",AH28,AW28) -> · enter odds | BA28: =IF(AX28<>"",AX28,IF(AH28<>"BET",0,IF(AI28*Method!$B$10/100<Method!$B$9,0,ROUND(AI28*Method!$B$10/100,0)))) -> 0 | BB28: 0 | BC28: 0.68566979 | BD28: 0.22566009 | BE28: 0.062869134 | BG28: 0 | BH28: mild_indoor | BI28: 3356.8
A29: 28 | B29: 46191 | C29: A | D29: Mexico | E29: South Korea | F29: Zapopan | G29: 23:00 | H29: 06:00 +1d | I29: 0.54857591 | J29: 0.2823916 | K29: 0.16903249 | L29: =IF(Matchday!E31="","",Matchday!E31) | M29: =IF(Matchday!F31="","",Matchday!F31) | N29: =IF(Matchday!G31="","",Matchday!G31) | O29: =IF(L29="","",1/L29) | P29: =IF(M29="","",1/M29) | Q29: =IF(N29="","",1/N29) | R29: =IF(COUNT(L29:N29)<3,"",O29+P29+Q29) | S29: {=IF($R29="","",IF(Method!$B$56="proportional",O29/$R29,IF(Method!$B$56="power",IFERROR(INDEX(power_devig($L29,$M29,$N29),1,1),O29/$R29),IFERROR(INDEX(shin($L29,$M29,$N29),1,1),O29/$R29))))} | T29: {=IF($R29="","",IF(Method!$B$56="proportional",P29/$R29,IF(Method!$B$56="power",IFERROR(INDEX(power_devig($L29,$M29,$N29),2,1),P29/$R29),IFERROR(INDEX(shin($L29,$M29,$N29),2,1),P29/$R29))))} | U29: {=IF($R29="","",IF(Method!$B$56="proportional",Q29/$R29,IF(Method!$B$56="power",IFERROR(INDEX(power_devig($L29,$M29,$N29),3,1),Q29/$R29),IFERROR(INDEX(shin($L29,$M29,$N29),3,1),Q29/$R29))))} | V29: =IF(S29="","",Method!$B$4*I29+(1-Method!$B$4)*S29/($S29+$T29+$U29)) | W29: =IF(T29="","",Method!$B$4*J29+(1-Method!$B$4)*T29/($S29+$T29+$U29)) | X29: =IF(U29="","",Method!$B$4*K29+(1-Method!$B$4)*U29/($S29+$T29+$U29)) | Y29: =IF(V29="","",V29*L29-1) | Z29: =IF(W29="","",W29*M29-1) | AA29: =IF(X29="","",X29*N29-1) | AB29: =IF(Y29="","",MATCH(MAX(Y29:AA29),Y29:AA29,0)) | AC29: =IF(AB29="","",CHOOSE(AB29,"H","D","A")) | AD29: =IF(AB29="","",CHOOSE(AB29,"1 "&D29,"X Draw","2 "&E29)) | AE29: =IF(AB29="","",INDEX(L29:N29,1,AB29)) | AF29: =IF(AB29="","",INDEX(Y29:AA29,1,AB29)) | AG29: =IF(AB29="","",INDEX(V29:X29,1,AB29)-INDEX(S29:U29,1,AB29)) | AH29: =IF(AB29="","· enter odds",IF(AND(AF29>=Method!$B$7,AG29>=Method!$B$8),"BET","PASS")) -> · enter odds | AI29: =IF(AH29<>"BET",0,ROUND(MIN(Method!$B$6,Method!$B$5*AL29)*100,1)) -> 0 | AJ29: =IF(OR(AH29<>"BET",Method!$B$55=TRUE()),0,IF(AI29*Method!$B$10/100<Method!$B$9,0,ROUND(AI29*Method!$B$10/100,0))) -> 0 | AK29: =IF(AB29="","",INDEX(V29:X29,1,AB29)) | AL29: =IF(AH29<>"BET","",MAX(0,(AK29*AE29-1)/(AE29-1))) | AM29: =IF(AH29="BET",AF29+A29/1000000,"") | AN29: =IF(Matchday!N31="","",Matchday!N31) | AO29: =IF(Matchday!P31="","",Matchday!P31) | AP29: =IF(Matchday!Q31="","",Matchday!Q31) | AQ29: =IF(Matchday!R31="","",Matchday!R31) | AR29: =IF(OR(AN29<>"Y",AQ29="",AV29=""),"",IF(AQ29="Void",0,IF(AQ29=AV29,ROUND(AP29*(AO29-1),2),-AP29))) | AS29: =IF(AR29="","",SUM($AR$2:AR29)) | AT29: =IF(AB29="","Type the 3 odds on the Matchday tab",IF(Method!$B$55=TRUE(),"🛑 PAUSED — drawdown "&TEXT(Method!$B$51,"0.0%")&" ≥ "&TEXT(Method!$B$52,"0.0%")&". Set Method!B54=Y to override.",IF(AH29="BET",IF(AJ29=0,"Edge found but stake rounds under £"&Method!$B$9&" — skip","Value found: EV "&TEXT(AF29,"0.0%")&", edge "&TEXT(AG29,"0.0%")),IF(AF29<Method!$B$7,"Price too short — EV "&TEXT(AF29,"0.0%")&" (need "&TEXT(Method!$B$7,"0.0%")&"+)","Model ≈ market — edge "&TEXT(AG29,"0.0%")&" (need "&TEXT(Method!$B$8,"0.0%")&"+)")))) -> Type the 3 odds on the Matchday tab | AU29: =IF(AN29<>"Y","",IF(AH29="· enter odds","⚠ type the 3 odds (1/X/2) to grade this bet",IF(OR(AV29="",AO29="",AP29=""),"⚠ log backed pick, odds & stake",IF(AZ29<>"BET","⚠ FUN BET — engine said pass · staked £"&AP29&" vs engine £"&BA29,IF(AV29<>IF(AY29="",AC29,AY29),"⚠ backed "&AV29&" but engine pick was "&IF(AY29="",AC29,AY29),IF(AP29>BA29,"⚠ stake over engine £"&BA29,IF(ABS(AO29-IFERROR(INDEX(L29:N29,1,MATCH(AV29,{"H","D","A"},0)),AE29))>0.02,"⚠ odds moved — re-check value","✓ engine bet"))))))) | AV29: =IF(Matchday!O31="","",Matchday!O31) | AZ29: =IF(AW29="",AH29,AW29) -> · enter odds | BA29: =IF(AX29<>"",AX29,IF(AH29<>"BET",0,IF(AI29*Method!$B$10/100<Method!$B$9,0,ROUND(AI29*Method!$B$10/100,0)))) -> 0 | BB29: 0 | BC29: 0.53328756 | BD29: 0.2870035 | BE29: 0.17416832 | BG29: 1560 | BH29: warm_humid | BI29: 475.9
A30: 29 | B30: 46192 | C30: D | D30: United States | E30: Australia | F30: Seattle | G30: 15:00 | H30: 23:00 | I30: 0.46587982 | J30: 0.28170995 | K30: 0.25241023 | L30: =IF(Matchday!E32="","",Matchday!E32) | M30: =IF(Matchday!F32="","",Matchday!F32) | N30: =IF(Matchday!G32="","",Matchday!G32) | O30: =IF(L30="","",1/L30) | P30: =IF(M30="","",1/M30) | Q30: =IF(N30="","",1/N30) | R30: =IF(COUNT(L30:N30)<3,"",O30+P30+Q30) | S30: {=IF($R30="","",IF(Method!$B$56="proportional",O30/$R30,IF(Method!$B$56="power",IFERROR(INDEX(power_devig($L30,$M30,$N30),1,1),O30/$R30),IFERROR(INDEX(shin($L30,$M30,$N30),1,1),O30/$R30))))} | T30: {=IF($R30="","",IF(Method!$B$56="proportional",P30/$R30,IF(Method!$B$56="power",IFERROR(INDEX(power_devig($L30,$M30,$N30),2,1),P30/$R30),IFERROR(INDEX(shin($L30,$M30,$N30),2,1),P30/$R30))))} | U30: {=IF($R30="","",IF(Method!$B$56="proportional",Q30/$R30,IF(Method!$B$56="power",IFERROR(INDEX(power_devig($L30,$M30,$N30),3,1),Q30/$R30),IFERROR(INDEX(shin($L30,$M30,$N30),3,1),Q30/$R30))))} | V30: =IF(S30="","",Method!$B$4*I30+(1-Method!$B$4)*S30/($S30+$T30+$U30)) | W30: =IF(T30="","",Method!$B$4*J30+(1-Method!$B$4)*T30/($S30+$T30+$U30)) | X30: =IF(U30="","",Method!$B$4*K30+(1-Method!$B$4)*U30/($S30+$T30+$U30)) | Y30: =IF(V30="","",V30*L30-1) | Z30: =IF(W30="","",W30*M30-1) | AA30: =IF(X30="","",X30*N30-1) | AB30: =IF(Y30="","",MATCH(MAX(Y30:AA30),Y30:AA30,0)) | AC30: =IF(AB30="","",CHOOSE(AB30,"H","D","A")) | AD30: =IF(AB30="","",CHOOSE(AB30,"1 "&D30,"X Draw","2 "&E30)) | AE30: =IF(AB30="","",INDEX(L30:N30,1,AB30)) | AF30: =IF(AB30="","",INDEX(Y30:AA30,1,AB30)) | AG30: =IF(AB30="","",INDEX(V30:X30,1,AB30)-INDEX(S30:U30,1,AB30)) | AH30: =IF(AB30="","· enter odds",IF(AND(AF30>=Method!$B$7,AG30>=Method!$B$8),"BET","PASS")) -> · enter odds | AI30: =IF(AH30<>"BET",0,ROUND(MIN(Method!$B$6,Method!$B$5*AL30)*100,1)) -> 0 | AJ30: =IF(OR(AH30<>"BET",Method!$B$55=TRUE()),0,IF(AI30*Method!$B$10/100<Method!$B$9,0,ROUND(AI30*Method!$B$10/100,0))) -> 0 | AK30: =IF(AB30="","",INDEX(V30:X30,1,AB30)) | AL30: =IF(AH30<>"BET","",MAX(0,(AK30*AE30-1)/(AE30-1))) | AM30: =IF(AH30="BET",AF30+A30/1000000,"") | AN30: =IF(Matchday!N32="","",Matchday!N32) | AO30: =IF(Matchday!P32="","",Matchday!P32) | AP30: =IF(Matchday!Q32="","",Matchday!Q32) | AQ30: =IF(Matchday!R32="","",Matchday!R32) | AR30: =IF(OR(AN30<>"Y",AQ30="",AV30=""),"",IF(AQ30="Void",0,IF(AQ30=AV30,ROUND(AP30*(AO30-1),2),-AP30))) | AS30: =IF(AR30="","",SUM($AR$2:AR30)) | AT30: =IF(AB30="","Type the 3 odds on the Matchday tab",IF(Method!$B$55=TRUE(),"🛑 PAUSED — drawdown "&TEXT(Method!$B$51,"0.0%")&" ≥ "&TEXT(Method!$B$52,"0.0%")&". Set Method!B54=Y to override.",IF(AH30="BET",IF(AJ30=0,"Edge found but stake rounds under £"&Method!$B$9&" — skip","Value found: EV "&TEXT(AF30,"0.0%")&", edge "&TEXT(AG30,"0.0%")),IF(AF30<Method!$B$7,"Price too short — EV "&TEXT(AF30,"0.0%")&" (need "&TEXT(Method!$B$7,"0.0%")&"+)","Model ≈ market — edge "&TEXT(AG30,"0.0%")&" (need "&TEXT(Method!$B$8,"0.0%")&"+)")))) -> Type the 3 odds on the Matchday tab | AU30: =IF(AN30<>"Y","",IF(AH30="· enter odds","⚠ type the 3 odds (1/X/2) to grade this bet",IF(OR(AV30="",AO30="",AP30=""),"⚠ log backed pick, odds & stake",IF(AZ30<>"BET","⚠ FUN BET — engine said pass · staked £"&AP30&" vs engine £"&BA30,IF(AV30<>IF(AY30="",AC30,AY30),"⚠ backed "&AV30&" but engine pick was "&IF(AY30="",AC30,AY30),IF(AP30>BA30,"⚠ stake over engine £"&BA30,IF(ABS(AO30-IFERROR(INDEX(L30:N30,1,MATCH(AV30,{"H","D","A"},0)),AE30))>0.02,"⚠ odds moved — re-check value","✓ engine bet"))))))) | AV30: =IF(Matchday!O32="","",Matchday!O32) | AZ30: =IF(AW30="",AH30,AW30) -> · enter odds | BA30: =IF(AX30<>"",AX30,IF(AH30<>"BET",0,IF(AI30*Method!$B$10/100<Method!$B$9,0,ROUND(AI30*Method!$B$10/100,0)))) -> 0 | BB30: 0 | BC30: 0.44970884 | BD30: 0.28674578 | BE30: 0.25639216 | BG30: 5 | BH30: mild | BI30: 1553.1
A31: 30 | B31: 46192 | C31: C | D31: Scotland | E31: Morocco | F31: Foxborough | G31: 18:00 | H31: 23:00 | I31: 0.24522788 | J31: 0.30460764 | K31: 0.45016448 | L31: =IF(Matchday!E33="","",Matchday!E33) | M31: =IF(Matchday!F33="","",Matchday!F33) | N31: =IF(Matchday!G33="","",Matchday!G33) | O31: =IF(L31="","",1/L31) | P31: =IF(M31="","",1/M31) | Q31: =IF(N31="","",1/N31) | R31: =IF(COUNT(L31:N31)<3,"",O31+P31+Q31) | S31: {=IF($R31="","",IF(Method!$B$56="proportional",O31/$R31,IF(Method!$B$56="power",IFERROR(INDEX(power_devig($L31,$M31,$N31),1,1),O31/$R31),IFERROR(INDEX(shin($L31,$M31,$N31),1,1),O31/$R31))))} | T31: {=IF($R31="","",IF(Method!$B$56="proportional",P31/$R31,IF(Method!$B$56="power",IFERROR(INDEX(power_devig($L31,$M31,$N31),2,1),P31/$R31),IFERROR(INDEX(shin($L31,$M31,$N31),2,1),P31/$R31))))} | U31: {=IF($R31="","",IF(Method!$B$56="proportional",Q31/$R31,IF(Method!$B$56="power",IFERROR(INDEX(power_devig($L31,$M31,$N31),3,1),Q31/$R31),IFERROR(INDEX(shin($L31,$M31,$N31),3,1),Q31/$R31))))} | V31: =IF(S31="","",Method!$B$4*I31+(1-Method!$B$4)*S31/($S31+$T31+$U31)) | W31: =IF(T31="","",Method!$B$4*J31+(1-Method!$B$4)*T31/($S31+$T31+$U31)) | X31: =IF(U31="","",Method!$B$4*K31+(1-Method!$B$4)*U31/($S31+$T31+$U31)) | Y31: =IF(V31="","",V31*L31-1) | Z31: =IF(W31="","",W31*M31-1) | AA31: =IF(X31="","",X31*N31-1) | AB31: =IF(Y31="","",MATCH(MAX(Y31:AA31),Y31:AA31,0)) | AC31: =IF(AB31="","",CHOOSE(AB31,"H","D","A")) | AD31: =IF(AB31="","",CHOOSE(AB31,"1 "&D31,"X Draw","2 "&E31)) | AE31: =IF(AB31="","",INDEX(L31:N31,1,AB31)) | AF31: =IF(AB31="","",INDEX(Y31:AA31,1,AB31)) | AG31: =IF(AB31="","",INDEX(V31:X31,1,AB31)-INDEX(S31:U31,1,AB31)) | AH31: =IF(AB31="","· enter odds",IF(AND(AF31>=Method!$B$7,AG31>=Method!$B$8),"BET","PASS")) -> · enter odds | AI31: =IF(AH31<>"BET",0,ROUND(MIN(Method!$B$6,Method!$B$5*AL31)*100,1)) -> 0 | AJ31: =IF(OR(AH31<>"BET",Method!$B$55=TRUE()),0,IF(AI31*Method!$B$10/100<Method!$B$9,0,ROUND(AI31*Method!$B$10/100,0))) -> 0 | AK31: =IF(AB31="","",INDEX(V31:X31,1,AB31)) | AL31: =IF(AH31<>"BET","",MAX(0,(AK31*AE31-1)/(AE31-1))) | AM31: =IF(AH31="BET",AF31+A31/1000000,"") | AN31: =IF(Matchday!N33="","",Matchday!N33) | AO31: =IF(Matchday!P33="","",Matchday!P33) | AP31: =IF(Matchday!Q33="","",Matchday!Q33) | AQ31: =IF(Matchday!R33="","",Matchday!R33) | AR31: =IF(OR(AN31<>"Y",AQ31="",AV31=""),"",IF(AQ31="Void",0,IF(AQ31=AV31,ROUND(AP31*(AO31-1),2),-AP31))) | AS31: =IF(AR31="","",SUM($AR$2:AR31)) | AT31: =IF(AB31="","Type the 3 odds on the Matchday tab",IF(Method!$B$55=TRUE(),"🛑 PAUSED — drawdown "&TEXT(Method!$B$51,"0.0%")&" ≥ "&TEXT(Method!$B$52,"0.0%")&". Set Method!B54=Y to override.",IF(AH31="BET",IF(AJ31=0,"Edge found but stake rounds under £"&Method!$B$9&" — skip","Value found: EV "&TEXT(AF31,"0.0%")&", edge "&TEXT(AG31,"0.0%")),IF(AF31<Method!$B$7,"Price too short — EV "&TEXT(AF31,"0.0%")&" (need "&TEXT(Method!$B$7,"0.0%")&"+)","Model ≈ market — edge "&TEXT(AG31,"0.0%")&" (need "&TEXT(Method!$B$8,"0.0%")&"+)")))) -> Type the 3 odds on the Matchday tab | AU31: =IF(AN31<>"Y","",IF(AH31="· enter odds","⚠ type the 3 odds (1/X/2) to grade this bet",IF(OR(AV31="",AO31="",AP31=""),"⚠ log backed pick, odds & stake",IF(AZ31<>"BET","⚠ FUN BET — engine said pass · staked £"&AP31&" vs engine £"&BA31,IF(AV31<>IF(AY31="",AC31,AY31),"⚠ backed "&AV31&" but engine pick was "&IF(AY31="",AC31,AY31),IF(AP31>BA31,"⚠ stake over engine £"&BA31,IF(ABS(AO31-IFERROR(INDEX(L31:N31,1,MATCH(AV31,{"H","D","A"},0)),AE31))>0.02,"⚠ odds moved — re-check value","✓ engine bet"))))))) | AV31: =IF(Matchday!O33="","",Matchday!O33) | AZ31: =IF(AW31="",AH31,AW31) -> · enter odds | BA31: =IF(AX31<>"",AX31,IF(AH31<>"BET",0,IF(AI31*Method!$B$10/100<Method!$B$9,0,ROUND(AI31*Method!$B$10/100,0)))) -> 0 | BB31: 0 | BC31: 0.22973565 | BD31: 0.29540297 | BE31: 0.44845447 | BG31: 40 | BH31: warm | BI31: 0
A32: 31 | B32: 46192 | C32: C | D32: Brazil | E32: Haiti | F32: Philadelphia | G32: 21:00 | H32: 02:00 +1d | I32: 0.70799612 | J32: 0.20281693 | K32: 0.089186955 | L32: =IF(Matchday!E34="","",Matchday!E34) | M32: =IF(Matchday!F34="","",Matchday!F34) | N32: =IF(Matchday!G34="","",Matchday!G34) | O32: =IF(L32="","",1/L32) | P32: =IF(M32="","",1/M32) | Q32: =IF(N32="","",1/N32) | R32: =IF(COUNT(L32:N32)<3,"",O32+P32+Q32) | S32: {=IF($R32="","",IF(Method!$B$56="proportional",O32/$R32,IF(Method!$B$56="power",IFERROR(INDEX(power_devig($L32,$M32,$N32),1,1),O32/$R32),IFERROR(INDEX(shin($L32,$M32,$N32),1,1),O32/$R32))))} | T32: {=IF($R32="","",IF(Method!$B$56="proportional",P32/$R32,IF(Method!$B$56="power",IFERROR(INDEX(power_devig($L32,$M32,$N32),2,1),P32/$R32),IFERROR(INDEX(shin($L32,$M32,$N32),2,1),P32/$R32))))} | U32: {=IF($R32="","",IF(Method!$B$56="proportional",Q32/$R32,IF(Method!$B$56="power",IFERROR(INDEX(power_devig($L32,$M32,$N32),3,1),Q32/$R32),IFERROR(INDEX(shin($L32,$M32,$N32),3,1),Q32/$R32))))} | V32: =IF(S32="","",Method!$B$4*I32+(1-Method!$B$4)*S32/($S32+$T32+$U32)) | W32: =IF(T32="","",Method!$B$4*J32+(1-Method!$B$4)*T32/($S32+$T32+$U32)) | X32: =IF(U32="","",Method!$B$4*K32+(1-Method!$B$4)*U32/($S32+$T32+$U32)) | Y32: =IF(V32="","",V32*L32-1) | Z32: =IF(W32="","",W32*M32-1) | AA32: =IF(X32="","",X32*N32-1) | AB32: =IF(Y32="","",MATCH(MAX(Y32:AA32),Y32:AA32,0)) | AC32: =IF(AB32="","",CHOOSE(AB32,"H","D","A")) | AD32: =IF(AB32="","",CHOOSE(AB32,"1 "&D32,"X Draw","2 "&E32)) | AE32: =IF(AB32="","",INDEX(L32:N32,1,AB32)) | AF32: =IF(AB32="","",INDEX(Y32:AA32,1,AB32)) | AG32: =IF(AB32="","",INDEX(V32:X32,1,AB32)-INDEX(S32:U32,1,AB32)) | AH32: =IF(AB32="","· enter odds",IF(AND(AF32>=Method!$B$7,AG32>=Method!$B$8),"BET","PASS")) -> · enter odds | AI32: =IF(AH32<>"BET",0,ROUND(MIN(Method!$B$6,Method!$B$5*AL32)*100,1)) -> 0 | AJ32: =IF(OR(AH32<>"BET",Method!$B$55=TRUE()),0,IF(AI32*Method!$B$10/100<Method!$B$9,0,ROUND(AI32*Method!$B$10/100,0))) -> 0 | AK32: =IF(AB32="","",INDEX(V32:X32,1,AB32)) | AL32: =IF(AH32<>"BET","",MAX(0,(AK32*AE32-1)/(AE32-1))) | AM32: =IF(AH32="BET",AF32+A32/1000000,"") | AN32: =IF(Matchday!N34="","",Matchday!N34) | AO32: =IF(Matchday!P34="","",Matchday!P34) | AP32: =IF(Matchday!Q34="","",Matchday!Q34) | AQ32: =IF(Matchday!R34="","",Matchday!R34) | AR32: =IF(OR(AN32<>"Y",AQ32="",AV32=""),"",IF(AQ32="Void",0,IF(AQ32=AV32,ROUND(AP32*(AO32-1),2),-AP32))) | AS32: =IF(AR32="","",SUM($AR$2:AR32)) | AT32: =IF(AB32="","Type the 3 odds on the Matchday tab",IF(Method!$B$55=TRUE(),"🛑 PAUSED — drawdown "&TEXT(Method!$B$51,"0.0%")&" ≥ "&TEXT(Method!$B$52,"0.0%")&". Set Method!B54=Y to override.",IF(AH32="BET",IF(AJ32=0,"Edge found but stake rounds under £"&Method!$B$9&" — skip","Value found: EV "&TEXT(AF32,"0.0%")&", edge "&TEXT(AG32,"0.0%")),IF(AF32<Method!$B$7,"Price too short — EV "&TEXT(AF32,"0.0%")&" (need "&TEXT(Method!$B$7,"0.0%")&"+)","Model ≈ market — edge "&TEXT(AG32,"0.0%")&" (need "&TEXT(Method!$B$8,"0.0%")&"+)")))) -> Type the 3 odds on the Matchday tab | AU32: =IF(AN32<>"Y","",IF(AH32="· enter odds","⚠ type the 3 odds (1/X/2) to grade this bet",IF(OR(AV32="",AO32="",AP32=""),"⚠ log backed pick, odds & stake",IF(AZ32<>"BET","⚠ FUN BET — engine said pass · staked £"&AP32&" vs engine £"&BA32,IF(AV32<>IF(AY32="",AC32,AY32),"⚠ backed "&AV32&" but engine pick was "&IF(AY32="",AC32,AY32),IF(AP32>BA32,"⚠ stake over engine £"&BA32,IF(ABS(AO32-IFERROR(INDEX(L32:N32,1,MATCH(AV32,{"H","D","A"},0)),AE32))>0.02,"⚠ odds moved — re-check value","✓ engine bet"))))))) | AV32: =IF(Matchday!O34="","",Matchday!O34) | AZ32: =IF(AW32="",AH32,AW32) -> · enter odds | BA32: =IF(AX32<>"",AX32,IF(AH32<>"BET",0,IF(AI32*Method!$B$10/100<Method!$B$9,0,ROUND(AI32*Method!$B$10/100,0)))) -> 0 | BB32: 0 | BC32: 0.65783913 | BD32: 0.22647468 | BE32: 0.09039006 | BG32: 12 | BH32: warm_humid | BI32: 137.4
A33: 32 | B33: 46192 | C33: D | D33: Turkey | E33: Paraguay | F33: Santa Clara | G33: 21:00 | H33: 05:00 +1d | I33: 0.43949373 | J33: 0.29406412 | K33: 0.26644215 | L33: =IF(Matchday!E35="","",Matchday!E35) | M33: =IF(Matchday!F35="","",Matchday!F35) | N33: =IF(Matchday!G35="","",Matchday!G35) | O33: =IF(L33="","",1/L33) | P33: =IF(M33="","",1/M33) | Q33: =IF(N33="","",1/N33) | R33: =IF(COUNT(L33:N33)<3,"",O33+P33+Q33) | S33: {=IF($R33="","",IF(Method!$B$56="proportional",O33/$R33,IF(Method!$B$56="power",IFERROR(INDEX(power_devig($L33,$M33,$N33),1,1),O33/$R33),IFERROR(INDEX(shin($L33,$M33,$N33),1,1),O33/$R33))))} | T33: {=IF($R33="","",IF(Method!$B$56="proportional",P33/$R33,IF(Method!$B$56="power",IFERROR(INDEX(power_devig($L33,$M33,$N33),2,1),P33/$R33),IFERROR(INDEX(shin($L33,$M33,$N33),2,1),P33/$R33))))} | U33: {=IF($R33="","",IF(Method!$B$56="proportional",Q33/$R33,IF(Method!$B$56="power",IFERROR(INDEX(power_devig($L33,$M33,$N33),3,1),Q33/$R33),IFERROR(INDEX(shin($L33,$M33,$N33),3,1),Q33/$R33))))} | V33: =IF(S33="","",Method!$B$4*I33+(1-Method!$B$4)*S33/($S33+$T33+$U33)) | W33: =IF(T33="","",Method!$B$4*J33+(1-Method!$B$4)*T33/($S33+$T33+$U33)) | X33: =IF(U33="","",Method!$B$4*K33+(1-Method!$B$4)*U33/($S33+$T33+$U33)) | Y33: =IF(V33="","",V33*L33-1) | Z33: =IF(W33="","",W33*M33-1) | AA33: =IF(X33="","",X33*N33-1) | AB33: =IF(Y33="","",MATCH(MAX(Y33:AA33),Y33:AA33,0)) | AC33: =IF(AB33="","",CHOOSE(AB33,"H","D","A")) | AD33: =IF(AB33="","",CHOOSE(AB33,"1 "&D33,"X Draw","2 "&E33)) | AE33: =IF(AB33="","",INDEX(L33:N33,1,AB33)) | AF33: =IF(AB33="","",INDEX(Y33:AA33,1,AB33)) | AG33: =IF(AB33="","",INDEX(V33:X33,1,AB33)-INDEX(S33:U33,1,AB33)) | AH33: =IF(AB33="","· enter odds",IF(AND(AF33>=Method!$B$7,AG33>=Method!$B$8),"BET","PASS")) -> · enter odds | AI33: =IF(AH33<>"BET",0,ROUND(MIN(Method!$B$6,Method!$B$5*AL33)*100,1)) -> 0 | AJ33: =IF(OR(AH33<>"BET",Method!$B$55=TRUE()),0,IF(AI33*Method!$B$10/100<Method!$B$9,0,ROUND(AI33*Method!$B$10/100,0))) -> 0 | AK33: =IF(AB33="","",INDEX(V33:X33,1,AB33)) | AL33: =IF(AH33<>"BET","",MAX(0,(AK33*AE33-1)/(AE33-1))) | AM33: =IF(AH33="BET",AF33+A33/1000000,"") | AN33: =IF(Matchday!N35="","",Matchday!N35) | AO33: =IF(Matchday!P35="","",Matchday!P35) | AP33: =IF(Matchday!Q35="","",Matchday!Q35) | AQ33: =IF(Matchday!R35="","",Matchday!R35) | AR33: =IF(OR(AN33<>"Y",AQ33="",AV33=""),"",IF(AQ33="Void",0,IF(AQ33=AV33,ROUND(AP33*(AO33-1),2),-AP33))) | AS33: =IF(AR33="","",SUM($AR$2:AR33)) | AT33: =IF(AB33="","Type the 3 odds on the Matchday tab",IF(Method!$B$55=TRUE(),"🛑 PAUSED — drawdown "&TEXT(Method!$B$51,"0.0%")&" ≥ "&TEXT(Method!$B$52,"0.0%")&". Set Method!B54=Y to override.",IF(AH33="BET",IF(AJ33=0,"Edge found but stake rounds under £"&Method!$B$9&" — skip","Value found: EV "&TEXT(AF33,"0.0%")&", edge "&TEXT(AG33,"0.0%")),IF(AF33<Method!$B$7,"Price too short — EV "&TEXT(AF33,"0.0%")&" (need "&TEXT(Method!$B$7,"0.0%")&"+)","Model ≈ market — edge "&TEXT(AG33,"0.0%")&" (need "&TEXT(Method!$B$8,"0.0%")&"+)")))) -> Type the 3 odds on the Matchday tab | AU33: =IF(AN33<>"Y","",IF(AH33="· enter odds","⚠ type the 3 odds (1/X/2) to grade this bet",IF(OR(AV33="",AO33="",AP33=""),"⚠ log backed pick, odds & stake",IF(AZ33<>"BET","⚠ FUN BET — engine said pass · staked £"&AP33&" vs engine £"&BA33,IF(AV33<>IF(AY33="",AC33,AY33),"⚠ backed "&AV33&" but engine pick was "&IF(AY33="",AC33,AY33),IF(AP33>BA33,"⚠ stake over engine £"&BA33,IF(ABS(AO33-IFERROR(INDEX(L33:N33,1,MATCH(AV33,{"H","D","A"},0)),AE33))>0.02,"⚠ odds moved — re-check value","✓ engine bet"))))))) | AV33: =IF(Matchday!O35="","",Matchday!O35) | AZ33: =IF(AW33="",AH33,AW33) -> · enter odds | BA33: =IF(AX33<>"",AX33,IF(AH33<>"BET",0,IF(AI33*Method!$B$10/100<Method!$B$9,0,ROUND(AI33*Method!$B$10/100,0)))) -> 0 | BB33: 0 | BC33: 0.42396401 | BD33: 0.29141666 | BE33: 0.2715373 | BG33: 8 | BH33: mild_dry | BI33: 1323.5
A34: 33 | B34: 46193 | C34: F | D34: Netherlands | E34: Sweden | F34: Houston | G34: 13:00 | H34: 19:00 | I34: 0.63524959 | J34: 0.2157863 | K34: 0.1489641 | L34: =IF(Matchday!E36="","",Matchday!E36) | M34: =IF(Matchday!F36="","",Matchday!F36) | N34: =IF(Matchday!G36="","",Matchday!G36) | O34: =IF(L34="","",1/L34) | P34: =IF(M34="","",1/M34) | Q34: =IF(N34="","",1/N34) | R34: =IF(COUNT(L34:N34)<3,"",O34+P34+Q34) | S34: {=IF($R34="","",IF(Method!$B$56="proportional",O34/$R34,IF(Method!$B$56="power",IFERROR(INDEX(power_devig($L34,$M34,$N34),1,1),O34/$R34),IFERROR(INDEX(shin($L34,$M34,$N34),1,1),O34/$R34))))} | T34: {=IF($R34="","",IF(Method!$B$56="proportional",P34/$R34,IF(Method!$B$56="power",IFERROR(INDEX(power_devig($L34,$M34,$N34),2,1),P34/$R34),IFERROR(INDEX(shin($L34,$M34,$N34),2,1),P34/$R34))))} | U34: {=IF($R34="","",IF(Method!$B$56="proportional",Q34/$R34,IF(Method!$B$56="power",IFERROR(INDEX(power_devig($L34,$M34,$N34),3,1),Q34/$R34),IFERROR(INDEX(shin($L34,$M34,$N34),3,1),Q34/$R34))))} | V34: =IF(S34="","",Method!$B$4*I34+(1-Method!$B$4)*S34/($S34+$T34+$U34)) | W34: =IF(T34="","",Method!$B$4*J34+(1-Method!$B$4)*T34/($S34+$T34+$U34)) | X34: =IF(U34="","",Method!$B$4*K34+(1-Method!$B$4)*U34/($S34+$T34+$U34)) | Y34: =IF(V34="","",V34*L34-1) | Z34: =IF(W34="","",W34*M34-1) | AA34: =IF(X34="","",X34*N34-1) | AB34: =IF(Y34="","",MATCH(MAX(Y34:AA34),Y34:AA34,0)) | AC34: =IF(AB34="","",CHOOSE(AB34,"H","D","A")) | AD34: =IF(AB34="","",CHOOSE(AB34,"1 "&D34,"X Draw","2 "&E34)) | AE34: =IF(AB34="","",INDEX(L34:N34,1,AB34)) | AF34: =IF(AB34="","",INDEX(Y34:AA34,1,AB34)) | AG34: =IF(AB34="","",INDEX(V34:X34,1,AB34)-INDEX(S34:U34,1,AB34)) | AH34: =IF(AB34="","· enter odds",IF(AND(AF34>=Method!$B$7,AG34>=Method!$B$8),"BET","PASS")) -> · enter odds | AI34: =IF(AH34<>"BET",0,ROUND(MIN(Method!$B$6,Method!$B$5*AL34)*100,1)) -> 0 | AJ34: =IF(OR(AH34<>"BET",Method!$B$55=TRUE()),0,IF(AI34*Method!$B$10/100<Method!$B$9,0,ROUND(AI34*Method!$B$10/100,0))) -> 0 | AK34: =IF(AB34="","",INDEX(V34:X34,1,AB34)) | AL34: =IF(AH34<>"BET","",MAX(0,(AK34*AE34-1)/(AE34-1))) | AM34: =IF(AH34="BET",AF34+A34/1000000,"") | AN34: =IF(Matchday!N36="","",Matchday!N36) | AO34: =IF(Matchday!P36="","",Matchday!P36) | AP34: =IF(Matchday!Q36="","",Matchday!Q36) | AQ34: =IF(Matchday!R36="","",Matchday!R36) | AR34: =IF(OR(AN34<>"Y",AQ34="",AV34=""),"",IF(AQ34="Void",0,IF(AQ34=AV34,ROUND(AP34*(AO34-1),2),-AP34))) | AS34: =IF(AR34="","",SUM($AR$2:AR34)) | AT34: =IF(AB34="","Type the 3 odds on the Matchday tab",IF(Method!$B$55=TRUE(),"🛑 PAUSED — drawdown "&TEXT(Method!$B$51,"0.0%")&" ≥ "&TEXT(Method!$B$52,"0.0%")&". Set Method!B54=Y to override.",IF(AH34="BET",IF(AJ34=0,"Edge found but stake rounds under £"&Method!$B$9&" — skip","Value found: EV "&TEXT(AF34,"0.0%")&", edge "&TEXT(AG34,"0.0%")),IF(AF34<Method!$B$7,"Price too short — EV "&TEXT(AF34,"0.0%")&" (need "&TEXT(Method!$B$7,"0.0%")&"+)","Model ≈ market — edge "&TEXT(AG34,"0.0%")&" (need "&TEXT(Method!$B$8,"0.0%")&"+)")))) -> Type the 3 odds on the Matchday tab | AU34: =IF(AN34<>"Y","",IF(AH34="· enter odds","⚠ type the 3 odds (1/X/2) to grade this bet",IF(OR(AV34="",AO34="",AP34=""),"⚠ log backed pick, odds & stake",IF(AZ34<>"BET","⚠ FUN BET — engine said pass · staked £"&AP34&" vs engine £"&BA34,IF(AV34<>IF(AY34="",AC34,AY34),"⚠ backed "&AV34&" but engine pick was "&IF(AY34="",AC34,AY34),IF(AP34>BA34,"⚠ stake over engine £"&BA34,IF(ABS(AO34-IFERROR(INDEX(L34:N34,1,MATCH(AV34,{"H","D","A"},0)),AE34))>0.02,"⚠ odds moved — re-check value","✓ engine bet"))))))) | AV34: =IF(Matchday!O36="","",Matchday!O36) | AZ34: =IF(AW34="",AH34,AW34) -> · enter odds | BA34: =IF(AX34<>"",AX34,IF(AH34<>"BET",0,IF(AI34*Method!$B$10/100<Method!$B$9,0,ROUND(AI34*Method!$B$10/100,0)))) -> 0 | BB34: -8 | BC34: 0.58708998 | BD34: 0.23903037 | BE34: 0.15441216 | BF34: Netherlands weather: -4 · Sweden weather: -4 | BG34: 15 | BH34: very_hot_humid_indoor | BI34: 376.3
A35: 34 | B35: 46193 | C35: E | D35: Germany | E35: Ivory Coast | F35: Toronto | G35: 16:00 | H35: 21:00 | I35: 0.5663704 | J35: 0.26484154 | K35: 0.16878806 | L35: =IF(Matchday!E37="","",Matchday!E37) | M35: =IF(Matchday!F37="","",Matchday!F37) | N35: =IF(Matchday!G37="","",Matchday!G37) | O35: =IF(L35="","",1/L35) | P35: =IF(M35="","",1/M35) | Q35: =IF(N35="","",1/N35) | R35: =IF(COUNT(L35:N35)<3,"",O35+P35+Q35) | S35: {=IF($R35="","",IF(Method!$B$56="proportional",O35/$R35,IF(Method!$B$56="power",IFERROR(INDEX(power_devig($L35,$M35,$N35),1,1),O35/$R35),IFERROR(INDEX(shin($L35,$M35,$N35),1,1),O35/$R35))))} | T35: {=IF($R35="","",IF(Method!$B$56="proportional",P35/$R35,IF(Method!$B$56="power",IFERROR(INDEX(power_devig($L35,$M35,$N35),2,1),P35/$R35),IFERROR(INDEX(shin($L35,$M35,$N35),2,1),P35/$R35))))} | U35: {=IF($R35="","",IF(Method!$B$56="proportional",Q35/$R35,IF(Method!$B$56="power",IFERROR(INDEX(power_devig($L35,$M35,$N35),3,1),Q35/$R35),IFERROR(INDEX(shin($L35,$M35,$N35),3,1),Q35/$R35))))} | V35: =IF(S35="","",Method!$B$4*I35+(1-Method!$B$4)*S35/($S35+$T35+$U35)) | W35: =IF(T35="","",Method!$B$4*J35+(1-Method!$B$4)*T35/($S35+$T35+$U35)) | X35: =IF(U35="","",Method!$B$4*K35+(1-Method!$B$4)*U35/($S35+$T35+$U35)) | Y35: =IF(V35="","",V35*L35-1) | Z35: =IF(W35="","",W35*M35-1) | AA35: =IF(X35="","",X35*N35-1) | AB35: =IF(Y35="","",MATCH(MAX(Y35:AA35),Y35:AA35,0)) | AC35: =IF(AB35="","",CHOOSE(AB35,"H","D","A")) | AD35: =IF(AB35="","",CHOOSE(AB35,"1 "&D35,"X Draw","2 "&E35)) | AE35: =IF(AB35="","",INDEX(L35:N35,1,AB35)) | AF35: =IF(AB35="","",INDEX(Y35:AA35,1,AB35)) | AG35: =IF(AB35="","",INDEX(V35:X35,1,AB35)-INDEX(S35:U35,1,AB35)) | AH35: =IF(AB35="","· enter odds",IF(AND(AF35>=Method!$B$7,AG35>=Method!$B$8),"BET","PASS")) -> · enter odds | AI35: =IF(AH35<>"BET",0,ROUND(MIN(Method!$B$6,Method!$B$5*AL35)*100,1)) -> 0 | AJ35: =IF(OR(AH35<>"BET",Method!$B$55=TRUE()),0,IF(AI35*Method!$B$10/100<Method!$B$9,0,ROUND(AI35*Method!$B$10/100,0))) -> 0 | AK35: =IF(AB35="","",INDEX(V35:X35,1,AB35)) | AL35: =IF(AH35<>"BET","",MAX(0,(AK35*AE35-1)/(AE35-1))) | AM35: =IF(AH35="BET",AF35+A35/1000000,"") | AN35: =IF(Matchday!N37="","",Matchday!N37) | AO35: =IF(Matchday!P37="","",Matchday!P37) | AP35: =IF(Matchday!Q37="","",Matchday!Q37) | AQ35: =IF(Matchday!R37="","",Matchday!R37) | AR35: =IF(OR(AN35<>"Y",AQ35="",AV35=""),"",IF(AQ35="Void",0,IF(AQ35=AV35,ROUND(AP35*(AO35-1),2),-AP35))) | AS35: =IF(AR35="","",SUM($AR$2:AR35)) | AT35: =IF(AB35="","Type the 3 odds on the Matchday tab",IF(Method!$B$55=TRUE(),"🛑 PAUSED — drawdown "&TEXT(Method!$B$51,"0.0%")&" ≥ "&TEXT(Method!$B$52,"0.0%")&". Set Method!B54=Y to override.",IF(AH35="BET",IF(AJ35=0,"Edge found but stake rounds under £"&Method!$B$9&" — skip","Value found: EV "&TEXT(AF35,"0.0%")&", edge "&TEXT(AG35,"0.0%")),IF(AF35<Method!$B$7,"Price too short — EV "&TEXT(AF35,"0.0%")&" (need "&TEXT(Method!$B$7,"0.0%")&"+)","Model ≈ market — edge "&TEXT(AG35,"0.0%")&" (need "&TEXT(Method!$B$8,"0.0%")&"+)")))) -> Type the 3 odds on the Matchday tab | AU35: =IF(AN35<>"Y","",IF(AH35="· enter odds","⚠ type the 3 odds (1/X/2) to grade this bet",IF(OR(AV35="",AO35="",AP35=""),"⚠ log backed pick, odds & stake",IF(AZ35<>"BET","⚠ FUN BET — engine said pass · staked £"&AP35&" vs engine £"&BA35,IF(AV35<>IF(AY35="",AC35,AY35),"⚠ backed "&AV35&" but engine pick was "&IF(AY35="",AC35,AY35),IF(AP35>BA35,"⚠ stake over engine £"&BA35,IF(ABS(AO35-IFERROR(INDEX(L35:N35,1,MATCH(AV35,{"H","D","A"},0)),AE35))>0.02,"⚠ odds moved — re-check value","✓ engine bet"))))))) | AV35: =IF(Matchday!O37="","",Matchday!O37) | AZ35: =IF(AW35="",AH35,AW35) -> · enter odds | BA35: =IF(AX35<>"",AX35,IF(AH35<>"BET",0,IF(AI35*Method!$B$10/100<Method!$B$9,0,ROUND(AI35*Method!$B$10/100,0)))) -> 0 | BB35: 0 | BC35: 0.54438556 | BD35: 0.28036814 | BE35: 0.17392769 | BG35: 76 | BH35: mild | BI35: 2099.8
A36: 35 | B36: 46193 | C36: E | D36: Ecuador | E36: Curacao | F36: Kansas City | G36: 19:00 | H36: 01:00 +1d | I36: 0.72815062 | J36: 0.19208176 | K36: 0.079767621 | L36: =IF(Matchday!E38="","",Matchday!E38) | M36: =IF(Matchday!F38="","",Matchday!F38) | N36: =IF(Matchday!G38="","",Matchday!G38) | O36: =IF(L36="","",1/L36) | P36: =IF(M36="","",1/M36) | Q36: =IF(N36="","",1/N36) | R36: =IF(COUNT(L36:N36)<3,"",O36+P36+Q36) | S36: {=IF($R36="","",IF(Method!$B$56="proportional",O36/$R36,IF(Method!$B$56="power",IFERROR(INDEX(power_devig($L36,$M36,$N36),1,1),O36/$R36),IFERROR(INDEX(shin($L36,$M36,$N36),1,1),O36/$R36))))} | T36: {=IF($R36="","",IF(Method!$B$56="proportional",P36/$R36,IF(Method!$B$56="power",IFERROR(INDEX(power_devig($L36,$M36,$N36),2,1),P36/$R36),IFERROR(INDEX(shin($L36,$M36,$N36),2,1),P36/$R36))))} | U36: {=IF($R36="","",IF(Method!$B$56="proportional",Q36/$R36,IF(Method!$B$56="power",IFERROR(INDEX(power_devig($L36,$M36,$N36),3,1),Q36/$R36),IFERROR(INDEX(shin($L36,$M36,$N36),3,1),Q36/$R36))))} | V36: =IF(S36="","",Method!$B$4*I36+(1-Method!$B$4)*S36/($S36+$T36+$U36)) | W36: =IF(T36="","",Method!$B$4*J36+(1-Method!$B$4)*T36/($S36+$T36+$U36)) | X36: =IF(U36="","",Method!$B$4*K36+(1-Method!$B$4)*U36/($S36+$T36+$U36)) | Y36: =IF(V36="","",V36*L36-1) | Z36: =IF(W36="","",W36*M36-1) | AA36: =IF(X36="","",X36*N36-1) | AB36: =IF(Y36="","",MATCH(MAX(Y36:AA36),Y36:AA36,0)) | AC36: =IF(AB36="","",CHOOSE(AB36,"H","D","A")) | AD36: =IF(AB36="","",CHOOSE(AB36,"1 "&D36,"X Draw","2 "&E36)) | AE36: =IF(AB36="","",INDEX(L36:N36,1,AB36)) | AF36: =IF(AB36="","",INDEX(Y36:AA36,1,AB36)) | AG36: =IF(AB36="","",INDEX(V36:X36,1,AB36)-INDEX(S36:U36,1,AB36)) | AH36: =IF(AB36="","· enter odds",IF(AND(AF36>=Method!$B$7,AG36>=Method!$B$8),"BET","PASS")) -> · enter odds | AI36: =IF(AH36<>"BET",0,ROUND(MIN(Method!$B$6,Method!$B$5*AL36)*100,1)) -> 0 | AJ36: =IF(OR(AH36<>"BET",Method!$B$55=TRUE()),0,IF(AI36*Method!$B$10/100<Method!$B$9,0,ROUND(AI36*Method!$B$10/100,0))) -> 0 | AK36: =IF(AB36="","",INDEX(V36:X36,1,AB36)) | AL36: =IF(AH36<>"BET","",MAX(0,(AK36*AE36-1)/(AE36-1))) | AM36: =IF(AH36="BET",AF36+A36/1000000,"") | AN36: =IF(Matchday!N38="","",Matchday!N38) | AO36: =IF(Matchday!P38="","",Matchday!P38) | AP36: =IF(Matchday!Q38="","",Matchday!Q38) | AQ36: =IF(Matchday!R38="","",Matchday!R38) | AR36: =IF(OR(AN36<>"Y",AQ36="",AV36=""),"",IF(AQ36="Void",0,IF(AQ36=AV36,ROUND(AP36*(AO36-1),2),-AP36))) | AS36: =IF(AR36="","",SUM($AR$2:AR36)) | AT36: =IF(AB36="","Type the 3 odds on the Matchday tab",IF(Method!$B$55=TRUE(),"🛑 PAUSED — drawdown "&TEXT(Method!$B$51,"0.0%")&" ≥ "&TEXT(Method!$B$52,"0.0%")&". Set Method!B54=Y to override.",IF(AH36="BET",IF(AJ36=0,"Edge found but stake rounds under £"&Method!$B$9&" — skip","Value found: EV "&TEXT(AF36,"0.0%")&", edge "&TEXT(AG36,"0.0%")),IF(AF36<Method!$B$7,"Price too short — EV "&TEXT(AF36,"0.0%")&" (need "&TEXT(Method!$B$7,"0.0%")&"+)","Model ≈ market — edge "&TEXT(AG36,"0.0%")&" (need "&TEXT(Method!$B$8,"0.0%")&"+)")))) -> Type the 3 odds on the Matchday tab | AU36: =IF(AN36<>"Y","",IF(AH36="· enter odds","⚠ type the 3 odds (1/X/2) to grade this bet",IF(OR(AV36="",AO36="",AP36=""),"⚠ log backed pick, odds & stake",IF(AZ36<>"BET","⚠ FUN BET — engine said pass · staked £"&AP36&" vs engine £"&BA36,IF(AV36<>IF(AY36="",AC36,AY36),"⚠ backed "&AV36&" but engine pick was "&IF(AY36="",AC36,AY36),IF(AP36>BA36,"⚠ stake over engine £"&BA36,IF(ABS(AO36-IFERROR(INDEX(L36:N36,1,MATCH(AV36,{"H","D","A"},0)),AE36))>0.02,"⚠ odds moved — re-check value","✓ engine bet"))))))) | AV36: =IF(Matchday!O38="","",Matchday!O38) | AZ36: =IF(AW36="",AH36,AW36) -> · enter odds | BA36: =IF(AX36<>"",AX36,IF(AH36<>"BET",0,IF(AI36*Method!$B$10/100<Method!$B$9,0,ROUND(AI36*Method!$B$10/100,0)))) -> 0 | BB36: 0 | BC36: 0.67902713 | BD36: 0.21608191 | BE36: 0.080276475 | BG36: 270 | BH36: hot | BI36: 1657.4
A37: 36 | B37: 46193 | C37: F | D37: Tunisia | E37: Japan | F37: Guadalupe | G37: 22:00 | H37: 05:00 +1d | I37: 0.13585569 | J37: 0.25814022 | K37: 0.6060041 | L37: =IF(Matchday!E39="","",Matchday!E39) | M37: =IF(Matchday!F39="","",Matchday!F39) | N37: =IF(Matchday!G39="","",Matchday!G39) | O37: =IF(L37="","",1/L37) | P37: =IF(M37="","",1/M37) | Q37: =IF(N37="","",1/N37) | R37: =IF(COUNT(L37:N37)<3,"",O37+P37+Q37) | S37: {=IF($R37="","",IF(Method!$B$56="proportional",O37/$R37,IF(Method!$B$56="power",IFERROR(INDEX(power_devig($L37,$M37,$N37),1,1),O37/$R37),IFERROR(INDEX(shin($L37,$M37,$N37),1,1),O37/$R37))))} | T37: {=IF($R37="","",IF(Method!$B$56="proportional",P37/$R37,IF(Method!$B$56="power",IFERROR(INDEX(power_devig($L37,$M37,$N37),2,1),P37/$R37),IFERROR(INDEX(shin($L37,$M37,$N37),2,1),P37/$R37))))} | U37: {=IF($R37="","",IF(Method!$B$56="proportional",Q37/$R37,IF(Method!$B$56="power",IFERROR(INDEX(power_devig($L37,$M37,$N37),3,1),Q37/$R37),IFERROR(INDEX(shin($L37,$M37,$N37),3,1),Q37/$R37))))} | V37: =IF(S37="","",Method!$B$4*I37+(1-Method!$B$4)*S37/($S37+$T37+$U37)) | W37: =IF(T37="","",Method!$B$4*J37+(1-Method!$B$4)*T37/($S37+$T37+$U37)) | X37: =IF(U37="","",Method!$B$4*K37+(1-Method!$B$4)*U37/($S37+$T37+$U37)) | Y37: =IF(V37="","",V37*L37-1) | Z37: =IF(W37="","",W37*M37-1) | AA37: =IF(X37="","",X37*N37-1) | AB37: =IF(Y37="","",MATCH(MAX(Y37:AA37),Y37:AA37,0)) | AC37: =IF(AB37="","",CHOOSE(AB37,"H","D","A")) | AD37: =IF(AB37="","",CHOOSE(AB37,"1 "&D37,"X Draw","2 "&E37)) | AE37: =IF(AB37="","",INDEX(L37:N37,1,AB37)) | AF37: =IF(AB37="","",INDEX(Y37:AA37,1,AB37)) | AG37: =IF(AB37="","",INDEX(V37:X37,1,AB37)-INDEX(S37:U37,1,AB37)) | AH37: =IF(AB37="","· enter odds",IF(AND(AF37>=Method!$B$7,AG37>=Method!$B$8),"BET","PASS")) -> · enter odds | AI37: =IF(AH37<>"BET",0,ROUND(MIN(Method!$B$6,Method!$B$5*AL37)*100,1)) -> 0 | AJ37: =IF(OR(AH37<>"BET",Method!$B$55=TRUE()),0,IF(AI37*Method!$B$10/100<Method!$B$9,0,ROUND(AI37*Method!$B$10/100,0))) -> 0 | AK37: =IF(AB37="","",INDEX(V37:X37,1,AB37)) | AL37: =IF(AH37<>"BET","",MAX(0,(AK37*AE37-1)/(AE37-1))) | AM37: =IF(AH37="BET",AF37+A37/1000000,"") | AN37: =IF(Matchday!N39="","",Matchday!N39) | AO37: =IF(Matchday!P39="","",Matchday!P39) | AP37: =IF(Matchday!Q39="","",Matchday!Q39) | AQ37: =IF(Matchday!R39="","",Matchday!R39) | AR37: =IF(OR(AN37<>"Y",AQ37="",AV37=""),"",IF(AQ37="Void",0,IF(AQ37=AV37,ROUND(AP37*(AO37-1),2),-AP37))) | AS37: =IF(AR37="","",SUM($AR$2:AR37)) | AT37: =IF(AB37="","Type the 3 odds on the Matchday tab",IF(Method!$B$55=TRUE(),"🛑 PAUSED — drawdown "&TEXT(Method!$B$51,"0.0%")&" ≥ "&TEXT(Method!$B$52,"0.0%")&". Set Method!B54=Y to override.",IF(AH37="BET",IF(AJ37=0,"Edge found but stake rounds under £"&Method!$B$9&" — skip","Value found: EV "&TEXT(AF37,"0.0%")&", edge "&TEXT(AG37,"0.0%")),IF(AF37<Method!$B$7,"Price too short — EV "&TEXT(AF37,"0.0%")&" (need "&TEXT(Method!$B$7,"0.0%")&"+)","Model ≈ market — edge "&TEXT(AG37,"0.0%")&" (need "&TEXT(Method!$B$8,"0.0%")&"+)")))) -> Type the 3 odds on the Matchday tab | AU37: =IF(AN37<>"Y","",IF(AH37="· enter odds","⚠ type the 3 odds (1/X/2) to grade this bet",IF(OR(AV37="",AO37="",AP37=""),"⚠ log backed pick, odds & stake",IF(AZ37<>"BET","⚠ FUN BET — engine said pass · staked £"&AP37&" vs engine £"&BA37,IF(AV37<>IF(AY37="",AC37,AY37),"⚠ backed "&AV37&" but engine pick was "&IF(AY37="",AC37,AY37),IF(AP37>BA37,"⚠ stake over engine £"&BA37,IF(ABS(AO37-IFERROR(INDEX(L37:N37,1,MATCH(AV37,{"H","D","A"},0)),AE37))>0.02,"⚠ odds moved — re-check value","✓ engine bet"))))))) | AV37: =IF(Matchday!O39="","",Matchday!O39) | AZ37: =IF(AW37="",AH37,AW37) -> · enter odds | BA37: =IF(AX37<>"",AX37,IF(AH37<>"BET",0,IF(AI37*Method!$B$10/100<Method!$B$9,0,ROUND(AI37*Method!$B$10/100,0)))) -> 0 | BB37: 0 | BC37: 0.11861038 | BD37: 0.27783449 | BE37: 0.59139959 | BG37: 540 | BH37: very_hot | BI37: 0
A38: 37 | B38: 46194 | C38: H | D38: Spain | E38: Saudi Arabia | F38: Atlanta | G38: 12:00 | H38: 17:00 | I38: 0.75376025 | J38: 0.1729898 | K38: 0.073249941 | L38: =IF(Matchday!E40="","",Matchday!E40) | M38: =IF(Matchday!F40="","",Matchday!F40) | N38: =IF(Matchday!G40="","",Matchday!G40) | O38: =IF(L38="","",1/L38) | P38: =IF(M38="","",1/M38) | Q38: =IF(N38="","",1/N38) | R38: =IF(COUNT(L38:N38)<3,"",O38+P38+Q38) | S38: {=IF($R38="","",IF(Method!$B$56="proportional",O38/$R38,IF(Method!$B$56="power",IFERROR(INDEX(power_devig($L38,$M38,$N38),1,1),O38/$R38),IFERROR(INDEX(shin($L38,$M38,$N38),1,1),O38/$R38))))} | T38: {=IF($R38="","",IF(Method!$B$56="proportional",P38/$R38,IF(Method!$B$56="power",IFERROR(INDEX(power_devig($L38,$M38,$N38),2,1),P38/$R38),IFERROR(INDEX(shin($L38,$M38,$N38),2,1),P38/$R38))))} | U38: {=IF($R38="","",IF(Method!$B$56="proportional",Q38/$R38,IF(Method!$B$56="power",IFERROR(INDEX(power_devig($L38,$M38,$N38),3,1),Q38/$R38),IFERROR(INDEX(shin($L38,$M38,$N38),3,1),Q38/$R38))))} | V38: =IF(S38="","",Method!$B$4*I38+(1-Method!$B$4)*S38/($S38+$T38+$U38)) | W38: =IF(T38="","",Method!$B$4*J38+(1-Method!$B$4)*T38/($S38+$T38+$U38)) | X38: =IF(U38="","",Method!$B$4*K38+(1-Method!$B$4)*U38/($S38+$T38+$U38)) | Y38: =IF(V38="","",V38*L38-1) | Z38: =IF(W38="","",W38*M38-1) | AA38: =IF(X38="","",X38*N38-1) | AB38: =IF(Y38="","",MATCH(MAX(Y38:AA38),Y38:AA38,0)) | AC38: =IF(AB38="","",CHOOSE(AB38,"H","D","A")) | AD38: =IF(AB38="","",CHOOSE(AB38,"1 "&D38,"X Draw","2 "&E38)) | AE38: =IF(AB38="","",INDEX(L38:N38,1,AB38)) | AF38: =IF(AB38="","",INDEX(Y38:AA38,1,AB38)) | AG38: =IF(AB38="","",INDEX(V38:X38,1,AB38)-INDEX(S38:U38,1,AB38)) | AH38: =IF(AB38="","· enter odds",IF(AND(AF38>=Method!$B$7,AG38>=Method!$B$8),"BET","PASS")) -> · enter odds | AI38: =IF(AH38<>"BET",0,ROUND(MIN(Method!$B$6,Method!$B$5*AL38)*100,1)) -> 0 | AJ38: =IF(OR(AH38<>"BET",Method!$B$55=TRUE()),0,IF(AI38*Method!$B$10/100<Method!$B$9,0,ROUND(AI38*Method!$B$10/100,0))) -> 0 | AK38: =IF(AB38="","",INDEX(V38:X38,1,AB38)) | AL38: =IF(AH38<>"BET","",MAX(0,(AK38*AE38-1)/(AE38-1))) | AM38: =IF(AH38="BET",AF38+A38/1000000,"") | AN38: =IF(Matchday!N40="","",Matchday!N40) | AO38: =IF(Matchday!P40="","",Matchday!P40) | AP38: =IF(Matchday!Q40="","",Matchday!Q40) | AQ38: =IF(Matchday!R40="","",Matchday!R40) | AR38: =IF(OR(AN38<>"Y",AQ38="",AV38=""),"",IF(AQ38="Void",0,IF(AQ38=AV38,ROUND(AP38*(AO38-1),2),-AP38))) | AS38: =IF(AR38="","",SUM($AR$2:AR38)) | AT38: =IF(AB38="","Type the 3 odds on the Matchday tab",IF(Method!$B$55=TRUE(),"🛑 PAUSED — drawdown "&TEXT(Method!$B$51,"0.0%")&" ≥ "&TEXT(Method!$B$52,"0.0%")&". Set Method!B54=Y to override.",IF(AH38="BET",IF(AJ38=0,"Edge found but stake rounds under £"&Method!$B$9&" — skip","Value found: EV "&TEXT(AF38,"0.0%")&", edge "&TEXT(AG38,"0.0%")),IF(AF38<Method!$B$7,"Price too short — EV "&TEXT(AF38,"0.0%")&" (need "&TEXT(Method!$B$7,"0.0%")&"+)","Model ≈ market — edge "&TEXT(AG38,"0.0%")&" (need "&TEXT(Method!$B$8,"0.0%")&"+)")))) -> Type the 3 odds on the Matchday tab | AU38: =IF(AN38<>"Y","",IF(AH38="· enter odds","⚠ type the 3 odds (1/X/2) to grade this bet",IF(OR(AV38="",AO38="",AP38=""),"⚠ log backed pick, odds & stake",IF(AZ38<>"BET","⚠ FUN BET — engine said pass · staked £"&AP38&" vs engine £"&BA38,IF(AV38<>IF(AY38="",AC38,AY38),"⚠ backed "&AV38&" but engine pick was "&IF(AY38="",AC38,AY38),IF(AP38>BA38,"⚠ stake over engine £"&BA38,IF(ABS(AO38-IFERROR(INDEX(L38:N38,1,MATCH(AV38,{"H","D","A"},0)),AE38))>0.02,"⚠ odds moved — re-check value","✓ engine bet"))))))) | AV38: =IF(Matchday!O40="","",Matchday!O40) | AZ38: =IF(AW38="",AH38,AW38) -> · enter odds | BA38: =IF(AX38<>"",AX38,IF(AH38<>"BET",0,IF(AI38*Method!$B$10/100<Method!$B$9,0,ROUND(AI38*Method!$B$10/100,0)))) -> 0 | BB38: -5 | BC38: 0.7087556 | BD38: 0.19759892 | BE38: 0.07327841 | BF38: Saudi Arabia weather: -1 · Spain weather: -4 | BG38: 320 | BH38: hot_humid_indoor | BI38: 0
A39: 38 | B39: 46194 | C39: G | D39: Belgium | E39: Iran | F39: Inglewood | G39: 15:00 | H39: 23:00 | I39: 0.42391528 | J39: 0.28573119 | K39: 0.29035353 | L39: =IF(Matchday!E41="","",Matchday!E41) | M39: =IF(Matchday!F41="","",Matchday!F41) | N39: =IF(Matchday!G41="","",Matchday!G41) | O39: =IF(L39="","",1/L39) | P39: =IF(M39="","",1/M39) | Q39: =IF(N39="","",1/N39) | R39: =IF(COUNT(L39:N39)<3,"",O39+P39+Q39) | S39: {=IF($R39="","",IF(Method!$B$56="proportional",O39/$R39,IF(Method!$B$56="power",IFERROR(INDEX(power_devig($L39,$M39,$N39),1,1),O39/$R39),IFERROR(INDEX(shin($L39,$M39,$N39),1,1),O39/$R39))))} | T39: {=IF($R39="","",IF(Method!$B$56="proportional",P39/$R39,IF(Method!$B$56="power",IFERROR(INDEX(power_devig($L39,$M39,$N39),2,1),P39/$R39),IFERROR(INDEX(shin($L39,$M39,$N39),2,1),P39/$R39))))} | U39: {=IF($R39="","",IF(Method!$B$56="proportional",Q39/$R39,IF(Method!$B$56="power",IFERROR(INDEX(power_devig($L39,$M39,$N39),3,1),Q39/$R39),IFERROR(INDEX(shin($L39,$M39,$N39),3,1),Q39/$R39))))} | V39: =IF(S39="","",Method!$B$4*I39+(1-Method!$B$4)*S39/($S39+$T39+$U39)) | W39: =IF(T39="","",Method!$B$4*J39+(1-Method!$B$4)*T39/($S39+$T39+$U39)) | X39: =IF(U39="","",Method!$B$4*K39+(1-Method!$B$4)*U39/($S39+$T39+$U39)) | Y39: =IF(V39="","",V39*L39-1) | Z39: =IF(W39="","",W39*M39-1) | AA39: =IF(X39="","",X39*N39-1) | AB39: =IF(Y39="","",MATCH(MAX(Y39:AA39),Y39:AA39,0)) | AC39: =IF(AB39="","",CHOOSE(AB39,"H","D","A")) | AD39: =IF(AB39="","",CHOOSE(AB39,"1 "&D39,"X Draw","2 "&E39)) | AE39: =IF(AB39="","",INDEX(L39:N39,1,AB39)) | AF39: =IF(AB39="","",INDEX(Y39:AA39,1,AB39)) | AG39: =IF(AB39="","",INDEX(V39:X39,1,AB39)-INDEX(S39:U39,1,AB39)) | AH39: =IF(AB39="","· enter odds",IF(AND(AF39>=Method!$B$7,AG39>=Method!$B$8),"BET","PASS")) -> · enter odds | AI39: =IF(AH39<>"BET",0,ROUND(MIN(Method!$B$6,Method!$B$5*AL39)*100,1)) -> 0 | AJ39: =IF(OR(AH39<>"BET",Method!$B$55=TRUE()),0,IF(AI39*Method!$B$10/100<Method!$B$9,0,ROUND(AI39*Method!$B$10/100,0))) -> 0 | AK39: =IF(AB39="","",INDEX(V39:X39,1,AB39)) | AL39: =IF(AH39<>"BET","",MAX(0,(AK39*AE39-1)/(AE39-1))) | AM39: =IF(AH39="BET",AF39+A39/1000000,"") | AN39: =IF(Matchday!N41="","",Matchday!N41) | AO39: =IF(Matchday!P41="","",Matchday!P41) | AP39: =IF(Matchday!Q41="","",Matchday!Q41) | AQ39: =IF(Matchday!R41="","",Matchday!R41) | AR39: =IF(OR(AN39<>"Y",AQ39="",AV39=""),"",IF(AQ39="Void",0,IF(AQ39=AV39,ROUND(AP39*(AO39-1),2),-AP39))) | AS39: =IF(AR39="","",SUM($AR$2:AR39)) | AT39: =IF(AB39="","Type the 3 odds on the Matchday tab",IF(Method!$B$55=TRUE(),"🛑 PAUSED — drawdown "&TEXT(Method!$B$51,"0.0%")&" ≥ "&TEXT(Method!$B$52,"0.0%")&". Set Method!B54=Y to override.",IF(AH39="BET",IF(AJ39=0,"Edge found but stake rounds under £"&Method!$B$9&" — skip","Value found: EV "&TEXT(AF39,"0.0%")&", edge "&TEXT(AG39,"0.0%")),IF(AF39<Method!$B$7,"Price too short — EV "&TEXT(AF39,"0.0%")&" (need "&TEXT(Method!$B$7,"0.0%")&"+)","Model ≈ market — edge "&TEXT(AG39,"0.0%")&" (need "&TEXT(Method!$B$8,"0.0%")&"+)")))) -> Type the 3 odds on the Matchday tab | AU39: =IF(AN39<>"Y","",IF(AH39="· enter odds","⚠ type the 3 odds (1/X/2) to grade this bet",IF(OR(AV39="",AO39="",AP39=""),"⚠ log backed pick, odds & stake",IF(AZ39<>"BET","⚠ FUN BET — engine said pass · staked £"&AP39&" vs engine £"&BA39,IF(AV39<>IF(AY39="",AC39,AY39),"⚠ backed "&AV39&" but engine pick was "&IF(AY39="",AC39,AY39),IF(AP39>BA39,"⚠ stake over engine £"&BA39,IF(ABS(AO39-IFERROR(INDEX(L39:N39,1,MATCH(AV39,{"H","D","A"},0)),AE39))>0.02,"⚠ odds moved — re-check value","✓ engine bet"))))))) | AV39: =IF(Matchday!O41="","",Matchday!O41) | AZ39: =IF(AW39="",AH39,AW39) -> · enter odds | BA39: =IF(AX39<>"",AX39,IF(AH39<>"BET",0,IF(AI39*Method!$B$10/100<Method!$B$9,0,ROUND(AI39*Method!$B$10/100,0)))) -> 0 | BB39: 0 | BC39: 0.40949035 | BD39: 0.28826613 | BE39: 0.29734568 | BG39: 30 | BH39: warm_dry_indoor | BI39: 1553.1
A40: 39 | B40: 46194 | C40: H | D40: Uruguay | E40: Cape Verde | F40: Miami Gardens | G40: 18:00 | H40: 23:00 | I40: 0.62473983 | J40: 0.24624287 | K40: 0.1290173 | L40: =IF(Matchday!E42="","",Matchday!E42) | M40: =IF(Matchday!F42="","",Matchday!F42) | N40: =IF(Matchday!G42="","",Matchday!G42) | O40: =IF(L40="","",1/L40) | P40: =IF(M40="","",1/M40) | Q40: =IF(N40="","",1/N40) | R40: =IF(COUNT(L40:N40)<3,"",O40+P40+Q40) | S40: {=IF($R40="","",IF(Method!$B$56="proportional",O40/$R40,IF(Method!$B$56="power",IFERROR(INDEX(power_devig($L40,$M40,$N40),1,1),O40/$R40),IFERROR(INDEX(shin($L40,$M40,$N40),1,1),O40/$R40))))} | T40: {=IF($R40="","",IF(Method!$B$56="proportional",P40/$R40,IF(Method!$B$56="power",IFERROR(INDEX(power_devig($L40,$M40,$N40),2,1),P40/$R40),IFERROR(INDEX(shin($L40,$M40,$N40),2,1),P40/$R40))))} | U40: {=IF($R40="","",IF(Method!$B$56="proportional",Q40/$R40,IF(Method!$B$56="power",IFERROR(INDEX(power_devig($L40,$M40,$N40),3,1),Q40/$R40),IFERROR(INDEX(shin($L40,$M40,$N40),3,1),Q40/$R40))))} | V40: =IF(S40="","",Method!$B$4*I40+(1-Method!$B$4)*S40/($S40+$T40+$U40)) | W40: =IF(T40="","",Method!$B$4*J40+(1-Method!$B$4)*T40/($S40+$T40+$U40)) | X40: =IF(U40="","",Method!$B$4*K40+(1-Method!$B$4)*U40/($S40+$T40+$U40)) | Y40: =IF(V40="","",V40*L40-1) | Z40: =IF(W40="","",W40*M40-1) | AA40: =IF(X40="","",X40*N40-1) | AB40: =IF(Y40="","",MATCH(MAX(Y40:AA40),Y40:AA40,0)) | AC40: =IF(AB40="","",CHOOSE(AB40,"H","D","A")) | AD40: =IF(AB40="","",CHOOSE(AB40,"1 "&D40,"X Draw","2 "&E40)) | AE40: =IF(AB40="","",INDEX(L40:N40,1,AB40)) | AF40: =IF(AB40="","",INDEX(Y40:AA40,1,AB40)) | AG40: =IF(AB40="","",INDEX(V40:X40,1,AB40)-INDEX(S40:U40,1,AB40)) | AH40: =IF(AB40="","· enter odds",IF(AND(AF40>=Method!$B$7,AG40>=Method!$B$8),"BET","PASS")) -> · enter odds | AI40: =IF(AH40<>"BET",0,ROUND(MIN(Method!$B$6,Method!$B$5*AL40)*100,1)) -> 0 | AJ40: =IF(OR(AH40<>"BET",Method!$B$55=TRUE()),0,IF(AI40*Method!$B$10/100<Method!$B$9,0,ROUND(AI40*Method!$B$10/100,0))) -> 0 | AK40: =IF(AB40="","",INDEX(V40:X40,1,AB40)) | AL40: =IF(AH40<>"BET","",MAX(0,(AK40*AE40-1)/(AE40-1))) | AM40: =IF(AH40="BET",AF40+A40/1000000,"") | AN40: =IF(Matchday!N42="","",Matchday!N42) | AO40: =IF(Matchday!P42="","",Matchday!P42) | AP40: =IF(Matchday!Q42="","",Matchday!Q42) | AQ40: =IF(Matchday!R42="","",Matchday!R42) | AR40: =IF(OR(AN40<>"Y",AQ40="",AV40=""),"",IF(AQ40="Void",0,IF(AQ40=AV40,ROUND(AP40*(AO40-1),2),-AP40))) | AS40: =IF(AR40="","",SUM($AR$2:AR40)) | AT40: =IF(AB40="","Type the 3 odds on the Matchday tab",IF(Method!$B$55=TRUE(),"🛑 PAUSED — drawdown "&TEXT(Method!$B$51,"0.0%")&" ≥ "&TEXT(Method!$B$52,"0.0%")&". Set Method!B54=Y to override.",IF(AH40="BET",IF(AJ40=0,"Edge found but stake rounds under £"&Method!$B$9&" — skip","Value found: EV "&TEXT(AF40,"0.0%")&", edge "&TEXT(AG40,"0.0%")),IF(AF40<Method!$B$7,"Price too short — EV "&TEXT(AF40,"0.0%")&" (need "&TEXT(Method!$B$7,"0.0%")&"+)","Model ≈ market — edge "&TEXT(AG40,"0.0%")&" (need "&TEXT(Method!$B$8,"0.0%")&"+)")))) -> Type the 3 odds on the Matchday tab | AU40: =IF(AN40<>"Y","",IF(AH40="· enter odds","⚠ type the 3 odds (1/X/2) to grade this bet",IF(OR(AV40="",AO40="",AP40=""),"⚠ log backed pick, odds & stake",IF(AZ40<>"BET","⚠ FUN BET — engine said pass · staked £"&AP40&" vs engine £"&BA40,IF(AV40<>IF(AY40="",AC40,AY40),"⚠ backed "&AV40&" but engine pick was "&IF(AY40="",AC40,AY40),IF(AP40>BA40,"⚠ stake over engine £"&BA40,IF(ABS(AO40-IFERROR(INDEX(L40:N40,1,MATCH(AV40,{"H","D","A"},0)),AE40))>0.02,"⚠ odds moved — re-check value","✓ engine bet"))))))) | AV40: =IF(Matchday!O42="","",Matchday!O42) | AZ40: =IF(AW40="",AH40,AW40) -> · enter odds | BA40: =IF(AX40<>"",AX40,IF(AH40<>"BET",0,IF(AI40*Method!$B$10/100<Method!$B$9,0,ROUND(AI40*Method!$B$10/100,0)))) -> 0 | BB40: 0 | BC40: 0.58057403 | BD40: 0.26851549 | BE40: 0.1331561 | BG40: 2 | BH40: very_hot_humid | BI40: 0
A41: 40 | B41: 46194 | C41: G | D41: New Zealand | E41: Egypt | F41: Vancouver | G41: 21:00 | H41: 05:00 +1d | I41: 0.31009365 | J41: 0.30239165 | K41: 0.3875147 | L41: =IF(Matchday!E43="","",Matchday!E43) | M41: =IF(Matchday!F43="","",Matchday!F43) | N41: =IF(Matchday!G43="","",Matchday!G43) | O41: =IF(L41="","",1/L41) | P41: =IF(M41="","",1/M41) | Q41: =IF(N41="","",1/N41) | R41: =IF(COUNT(L41:N41)<3,"",O41+P41+Q41) | S41: {=IF($R41="","",IF(Method!$B$56="proportional",O41/$R41,IF(Method!$B$56="power",IFERROR(INDEX(power_devig($L41,$M41,$N41),1,1),O41/$R41),IFERROR(INDEX(shin($L41,$M41,$N41),1,1),O41/$R41))))} | T41: {=IF($R41="","",IF(Method!$B$56="proportional",P41/$R41,IF(Method!$B$56="power",IFERROR(INDEX(power_devig($L41,$M41,$N41),2,1),P41/$R41),IFERROR(INDEX(shin($L41,$M41,$N41),2,1),P41/$R41))))} | U41: {=IF($R41="","",IF(Method!$B$56="proportional",Q41/$R41,IF(Method!$B$56="power",IFERROR(INDEX(power_devig($L41,$M41,$N41),3,1),Q41/$R41),IFERROR(INDEX(shin($L41,$M41,$N41),3,1),Q41/$R41))))} | V41: =IF(S41="","",Method!$B$4*I41+(1-Method!$B$4)*S41/($S41+$T41+$U41)) | W41: =IF(T41="","",Method!$B$4*J41+(1-Method!$B$4)*T41/($S41+$T41+$U41)) | X41: =IF(U41="","",Method!$B$4*K41+(1-Method!$B$4)*U41/($S41+$T41+$U41)) | Y41: =IF(V41="","",V41*L41-1) | Z41: =IF(W41="","",W41*M41-1) | AA41: =IF(X41="","",X41*N41-1) | AB41: =IF(Y41="","",MATCH(MAX(Y41:AA41),Y41:AA41,0)) | AC41: =IF(AB41="","",CHOOSE(AB41,"H","D","A")) | AD41: =IF(AB41="","",CHOOSE(AB41,"1 "&D41,"X Draw","2 "&E41)) | AE41: =IF(AB41="","",INDEX(L41:N41,1,AB41)) | AF41: =IF(AB41="","",INDEX(Y41:AA41,1,AB41)) | AG41: =IF(AB41="","",INDEX(V41:X41,1,AB41)-INDEX(S41:U41,1,AB41)) | AH41: =IF(AB41="","· enter odds",IF(AND(AF41>=Method!$B$7,AG41>=Method!$B$8),"BET","PASS")) -> · enter odds | AI41: =IF(AH41<>"BET",0,ROUND(MIN(Method!$B$6,Method!$B$5*AL41)*100,1)) -> 0 | AJ41: =IF(OR(AH41<>"BET",Method!$B$55=TRUE()),0,IF(AI41*Method!$B$10/100<Method!$B$9,0,ROUND(AI41*Method!$B$10/100,0))) -> 0 | AK41: =IF(AB41="","",INDEX(V41:X41,1,AB41)) | AL41: =IF(AH41<>"BET","",MAX(0,(AK41*AE41-1)/(AE41-1))) | AM41: =IF(AH41="BET",AF41+A41/1000000,"") | AN41: =IF(Matchday!N43="","",Matchday!N43) | AO41: =IF(Matchday!P43="","",Matchday!P43) | AP41: =IF(Matchday!Q43="","",Matchday!Q43) | AQ41: =IF(Matchday!R43="","",Matchday!R43) | AR41: =IF(OR(AN41<>"Y",AQ41="",AV41=""),"",IF(AQ41="Void",0,IF(AQ41=AV41,ROUND(AP41*(AO41-1),2),-AP41))) | AS41: =IF(AR41="","",SUM($AR$2:AR41)) | AT41: =IF(AB41="","Type the 3 odds on the Matchday tab",IF(Method!$B$55=TRUE(),"🛑 PAUSED — drawdown "&TEXT(Method!$B$51,"0.0%")&" ≥ "&TEXT(Method!$B$52,"0.0%")&". Set Method!B54=Y to override.",IF(AH41="BET",IF(AJ41=0,"Edge found but stake rounds under £"&Method!$B$9&" — skip","Value found: EV "&TEXT(AF41,"0.0%")&", edge "&TEXT(AG41,"0.0%")),IF(AF41<Method!$B$7,"Price too short — EV "&TEXT(AF41,"0.0%")&" (need "&TEXT(Method!$B$7,"0.0%")&"+)","Model ≈ market — edge "&TEXT(AG41,"0.0%")&" (need "&TEXT(Method!$B$8,"0.0%")&"+)")))) -> Type the 3 odds on the Matchday tab | AU41: =IF(AN41<>"Y","",IF(AH41="· enter odds","⚠ type the 3 odds (1/X/2) to grade this bet",IF(OR(AV41="",AO41="",AP41=""),"⚠ log backed pick, odds & stake",IF(AZ41<>"BET","⚠ FUN BET — engine said pass · staked £"&AP41&" vs engine £"&BA41,IF(AV41<>IF(AY41="",AC41,AY41),"⚠ backed "&AV41&" but engine pick was "&IF(AY41="",AC41,AY41),IF(AP41>BA41,"⚠ stake over engine £"&BA41,IF(ABS(AO41-IFERROR(INDEX(L41:N41,1,MATCH(AV41,{"H","D","A"},0)),AE41))>0.02,"⚠ odds moved — re-check value","✓ engine bet"))))))) | AV41: =IF(Matchday!O43="","",Matchday!O43) | AZ41: =IF(AW41="",AH41,AW41) -> · enter odds | BA41: =IF(AX41<>"",AX41,IF(AH41<>"BET",0,IF(AI41*Method!$B$10/100<Method!$B$9,0,ROUND(AI41*Method!$B$10/100,0)))) -> 0 | BB41: 0 | BC41: 0.29860596 | BD41: 0.29456515 | BE41: 0.39380471 | BG41: 0 | BH41: mild_indoor | BI41: 1748.5
A42: 41 | B42: 46195 | C42: J | D42: Argentina | E42: Austria | F42: Arlington | G42: 13:00 | H42: 19:00 | I42: 0.68308113 | J42: 0.20595235 | K42: 0.11096652 | L42: =IF(Matchday!E44="","",Matchday!E44) | M42: =IF(Matchday!F44="","",Matchday!F44) | N42: =IF(Matchday!G44="","",Matchday!G44) | O42: =IF(L42="","",1/L42) | P42: =IF(M42="","",1/M42) | Q42: =IF(N42="","",1/N42) | R42: =IF(COUNT(L42:N42)<3,"",O42+P42+Q42) | S42: {=IF($R42="","",IF(Method!$B$56="proportional",O42/$R42,IF(Method!$B$56="power",IFERROR(INDEX(power_devig($L42,$M42,$N42),1,1),O42/$R42),IFERROR(INDEX(shin($L42,$M42,$N42),1,1),O42/$R42))))} | T42: {=IF($R42="","",IF(Method!$B$56="proportional",P42/$R42,IF(Method!$B$56="power",IFERROR(INDEX(power_devig($L42,$M42,$N42),2,1),P42/$R42),IFERROR(INDEX(shin($L42,$M42,$N42),2,1),P42/$R42))))} | U42: {=IF($R42="","",IF(Method!$B$56="proportional",Q42/$R42,IF(Method!$B$56="power",IFERROR(INDEX(power_devig($L42,$M42,$N42),3,1),Q42/$R42),IFERROR(INDEX(shin($L42,$M42,$N42),3,1),Q42/$R42))))} | V42: =IF(S42="","",Method!$B$4*I42+(1-Method!$B$4)*S42/($S42+$T42+$U42)) | W42: =IF(T42="","",Method!$B$4*J42+(1-Method!$B$4)*T42/($S42+$T42+$U42)) | X42: =IF(U42="","",Method!$B$4*K42+(1-Method!$B$4)*U42/($S42+$T42+$U42)) | Y42: =IF(V42="","",V42*L42-1) | Z42: =IF(W42="","",W42*M42-1) | AA42: =IF(X42="","",X42*N42-1) | AB42: =IF(Y42="","",MATCH(MAX(Y42:AA42),Y42:AA42,0)) | AC42: =IF(AB42="","",CHOOSE(AB42,"H","D","A")) | AD42: =IF(AB42="","",CHOOSE(AB42,"1 "&D42,"X Draw","2 "&E42)) | AE42: =IF(AB42="","",INDEX(L42:N42,1,AB42)) | AF42: =IF(AB42="","",INDEX(Y42:AA42,1,AB42)) | AG42: =IF(AB42="","",INDEX(V42:X42,1,AB42)-INDEX(S42:U42,1,AB42)) | AH42: =IF(AB42="","· enter odds",IF(AND(AF42>=Method!$B$7,AG42>=Method!$B$8),"BET","PASS")) -> · enter odds | AI42: =IF(AH42<>"BET",0,ROUND(MIN(Method!$B$6,Method!$B$5*AL42)*100,1)) -> 0 | AJ42: =IF(OR(AH42<>"BET",Method!$B$55=TRUE()),0,IF(AI42*Method!$B$10/100<Method!$B$9,0,ROUND(AI42*Method!$B$10/100,0))) -> 0 | AK42: =IF(AB42="","",INDEX(V42:X42,1,AB42)) | AL42: =IF(AH42<>"BET","",MAX(0,(AK42*AE42-1)/(AE42-1))) | AM42: =IF(AH42="BET",AF42+A42/1000000,"") | AN42: =IF(Matchday!N44="","",Matchday!N44) | AO42: =IF(Matchday!P44="","",Matchday!P44) | AP42: =IF(Matchday!Q44="","",Matchday!Q44) | AQ42: =IF(Matchday!R44="","",Matchday!R44) | AR42: =IF(OR(AN42<>"Y",AQ42="",AV42=""),"",IF(AQ42="Void",0,IF(AQ42=AV42,ROUND(AP42*(AO42-1),2),-AP42))) | AS42: =IF(AR42="","",SUM($AR$2:AR42)) | AT42: =IF(AB42="","Type the 3 odds on the Matchday tab",IF(Method!$B$55=TRUE(),"🛑 PAUSED — drawdown "&TEXT(Method!$B$51,"0.0%")&" ≥ "&TEXT(Method!$B$52,"0.0%")&". Set Method!B54=Y to override.",IF(AH42="BET",IF(AJ42=0,"Edge found but stake rounds under £"&Method!$B$9&" — skip","Value found: EV "&TEXT(AF42,"0.0%")&", edge "&TEXT(AG42,"0.0%")),IF(AF42<Method!$B$7,"Price too short — EV "&TEXT(AF42,"0.0%")&" (need "&TEXT(Method!$B$7,"0.0%")&"+)","Model ≈ market — edge "&TEXT(AG42,"0.0%")&" (need "&TEXT(Method!$B$8,"0.0%")&"+)")))) -> Type the 3 odds on the Matchday tab | AU42: =IF(AN42<>"Y","",IF(AH42="· enter odds","⚠ type the 3 odds (1/X/2) to grade this bet",IF(OR(AV42="",AO42="",AP42=""),"⚠ log backed pick, odds & stake",IF(AZ42<>"BET","⚠ FUN BET — engine said pass · staked £"&AP42&" vs engine £"&BA42,IF(AV42<>IF(AY42="",AC42,AY42),"⚠ backed "&AV42&" but engine pick was "&IF(AY42="",AC42,AY42),IF(AP42>BA42,"⚠ stake over engine £"&BA42,IF(ABS(AO42-IFERROR(INDEX(L42:N42,1,MATCH(AV42,{"H","D","A"},0)),AE42))>0.02,"⚠ odds moved — re-check value","✓ engine bet"))))))) | AV42: =IF(Matchday!O44="","",Matchday!O44) | AZ42: =IF(AW42="",AH42,AW42) -> · enter odds | BA42: =IF(AX42<>"",AX42,IF(AH42<>"BET",0,IF(AI42*Method!$B$10/100<Method!$B$9,0,ROUND(AI42*Method!$B$10/100,0)))) -> 0 | BB42: -4 | BC42: 0.63164654 | BD42: 0.22951009 | BE42: 0.11377488 | BF42: Austria weather: -4 | BG42: 175 | BH42: very_hot_indoor | BI42: 739
A43: 42 | B43: 46195 | C43: I | D43: France | E43: Iraq | F43: Philadelphia | G43: 17:00 | H43: 22:00 | I43: 0.65677121 | J43: 0.21111184 | K43: 0.13211696 | L43: =IF(Matchday!E45="","",Matchday!E45) | M43: =IF(Matchday!F45="","",Matchday!F45) | N43: =IF(Matchday!G45="","",Matchday!G45) | O43: =IF(L43="","",1/L43) | P43: =IF(M43="","",1/M43) | Q43: =IF(N43="","",1/N43) | R43: =IF(COUNT(L43:N43)<3,"",O43+P43+Q43) | S43: {=IF($R43="","",IF(Method!$B$56="proportional",O43/$R43,IF(Method!$B$56="power",IFERROR(INDEX(power_devig($L43,$M43,$N43),1,1),O43/$R43),IFERROR(INDEX(shin($L43,$M43,$N43),1,1),O43/$R43))))} | T43: {=IF($R43="","",IF(Method!$B$56="proportional",P43/$R43,IF(Method!$B$56="power",IFERROR(INDEX(power_devig($L43,$M43,$N43),2,1),P43/$R43),IFERROR(INDEX(shin($L43,$M43,$N43),2,1),P43/$R43))))} | U43: {=IF($R43="","",IF(Method!$B$56="proportional",Q43/$R43,IF(Method!$B$56="power",IFERROR(INDEX(power_devig($L43,$M43,$N43),3,1),Q43/$R43),IFERROR(INDEX(shin($L43,$M43,$N43),3,1),Q43/$R43))))} | V43: =IF(S43="","",Method!$B$4*I43+(1-Method!$B$4)*S43/($S43+$T43+$U43)) | W43: =IF(T43="","",Method!$B$4*J43+(1-Method!$B$4)*T43/($S43+$T43+$U43)) | X43: =IF(U43="","",Method!$B$4*K43+(1-Method!$B$4)*U43/($S43+$T43+$U43)) | Y43: =IF(V43="","",V43*L43-1) | Z43: =IF(W43="","",W43*M43-1) | AA43: =IF(X43="","",X43*N43-1) | AB43: =IF(Y43="","",MATCH(MAX(Y43:AA43),Y43:AA43,0)) | AC43: =IF(AB43="","",CHOOSE(AB43,"H","D","A")) | AD43: =IF(AB43="","",CHOOSE(AB43,"1 "&D43,"X Draw","2 "&E43)) | AE43: =IF(AB43="","",INDEX(L43:N43,1,AB43)) | AF43: =IF(AB43="","",INDEX(Y43:AA43,1,AB43)) | AG43: =IF(AB43="","",INDEX(V43:X43,1,AB43)-INDEX(S43:U43,1,AB43)) | AH43: =IF(AB43="","· enter odds",IF(AND(AF43>=Method!$B$7,AG43>=Method!$B$8),"BET","PASS")) -> · enter odds | AI43: =IF(AH43<>"BET",0,ROUND(MIN(Method!$B$6,Method!$B$5*AL43)*100,1)) -> 0 | AJ43: =IF(OR(AH43<>"BET",Method!$B$55=TRUE()),0,IF(AI43*Method!$B$10/100<Method!$B$9,0,ROUND(AI43*Method!$B$10/100,0))) -> 0 | AK43: =IF(AB43="","",INDEX(V43:X43,1,AB43)) | AL43: =IF(AH43<>"BET","",MAX(0,(AK43*AE43-1)/(AE43-1))) | AM43: =IF(AH43="BET",AF43+A43/1000000,"") | AN43: =IF(Matchday!N45="","",Matchday!N45) | AO43: =IF(Matchday!P45="","",Matchday!P45) | AP43: =IF(Matchday!Q45="","",Matchday!Q45) | AQ43: =IF(Matchday!R45="","",Matchday!R45) | AR43: =IF(OR(AN43<>"Y",AQ43="",AV43=""),"",IF(AQ43="Void",0,IF(AQ43=AV43,ROUND(AP43*(AO43-1),2),-AP43))) | AS43: =IF(AR43="","",SUM($AR$2:AR43)) | AT43: =IF(AB43="","Type the 3 odds on the Matchday tab",IF(Method!$B$55=TRUE(),"🛑 PAUSED — drawdown "&TEXT(Method!$B$51,"0.0%")&" ≥ "&TEXT(Method!$B$52,"0.0%")&". Set Method!B54=Y to override.",IF(AH43="BET",IF(AJ43=0,"Edge found but stake rounds under £"&Method!$B$9&" — skip","Value found: EV "&TEXT(AF43,"0.0%")&", edge "&TEXT(AG43,"0.0%")),IF(AF43<Method!$B$7,"Price too short — EV "&TEXT(AF43,"0.0%")&" (need "&TEXT(Method!$B$7,"0.0%")&"+)","Model ≈ market — edge "&TEXT(AG43,"0.0%")&" (need "&TEXT(Method!$B$8,"0.0%")&"+)")))) -> Type the 3 odds on the Matchday tab | AU43: =IF(AN43<>"Y","",IF(AH43="· enter odds","⚠ type the 3 odds (1/X/2) to grade this bet",IF(OR(AV43="",AO43="",AP43=""),"⚠ log backed pick, odds & stake",IF(AZ43<>"BET","⚠ FUN BET — engine said pass · staked £"&AP43&" vs engine £"&BA43,IF(AV43<>IF(AY43="",AC43,AY43),"⚠ backed "&AV43&" but engine pick was "&IF(AY43="",AC43,AY43),IF(AP43>BA43,"⚠ stake over engine £"&BA43,IF(ABS(AO43-IFERROR(INDEX(L43:N43,1,MATCH(AV43,{"H","D","A"},0)),AE43))>0.02,"⚠ odds moved — re-check value","✓ engine bet"))))))) | AV43: =IF(Matchday!O45="","",Matchday!O45) | AZ43: =IF(AW43="",AH43,AW43) -> · enter odds | BA43: =IF(AX43<>"",AX43,IF(AH43<>"BET",0,IF(AI43*Method!$B$10/100<Method!$B$9,0,ROUND(AI43*Method!$B$10/100,0)))) -> 0 | BB43: 0 | BC43: 0.60398748 | BD43: 0.23450501 | BE43: 0.13648421 | BG43: 12 | BH43: warm_humid | BI43: 137.4
A44: 43 | B44: 46195 | C44: I | D44: Norway | E44: Senegal | F44: East Rutherford | G44: 20:00 | H44: 01:00 +1d | I44: 0.4641822 | J44: 0.27910243 | K44: 0.25671537 | L44: =IF(Matchday!E46="","",Matchday!E46) | M44: =IF(Matchday!F46="","",Matchday!F46) | N44: =IF(Matchday!G46="","",Matchday!G46) | O44: =IF(L44="","",1/L44) | P44: =IF(M44="","",1/M44) | Q44: =IF(N44="","",1/N44) | R44: =IF(COUNT(L44:N44)<3,"",O44+P44+Q44) | S44: {=IF($R44="","",IF(Method!$B$56="proportional",O44/$R44,IF(Method!$B$56="power",IFERROR(INDEX(power_devig($L44,$M44,$N44),1,1),O44/$R44),IFERROR(INDEX(shin($L44,$M44,$N44),1,1),O44/$R44))))} | T44: {=IF($R44="","",IF(Method!$B$56="proportional",P44/$R44,IF(Method!$B$56="power",IFERROR(INDEX(power_devig($L44,$M44,$N44),2,1),P44/$R44),IFERROR(INDEX(shin($L44,$M44,$N44),2,1),P44/$R44))))} | U44: {=IF($R44="","",IF(Method!$B$56="proportional",Q44/$R44,IF(Method!$B$56="power",IFERROR(INDEX(power_devig($L44,$M44,$N44),3,1),Q44/$R44),IFERROR(INDEX(shin($L44,$M44,$N44),3,1),Q44/$R44))))} | V44: =IF(S44="","",Method!$B$4*I44+(1-Method!$B$4)*S44/($S44+$T44+$U44)) | W44: =IF(T44="","",Method!$B$4*J44+(1-Method!$B$4)*T44/($S44+$T44+$U44)) | X44: =IF(U44="","",Method!$B$4*K44+(1-Method!$B$4)*U44/($S44+$T44+$U44)) | Y44: =IF(V44="","",V44*L44-1) | Z44: =IF(W44="","",W44*M44-1) | AA44: =IF(X44="","",X44*N44-1) | AB44: =IF(Y44="","",MATCH(MAX(Y44:AA44),Y44:AA44,0)) | AC44: =IF(AB44="","",CHOOSE(AB44,"H","D","A")) | AD44: =IF(AB44="","",CHOOSE(AB44,"1 "&D44,"X Draw","2 "&E44)) | AE44: =IF(AB44="","",INDEX(L44:N44,1,AB44)) | AF44: =IF(AB44="","",INDEX(Y44:AA44,1,AB44)) | AG44: =IF(AB44="","",INDEX(V44:X44,1,AB44)-INDEX(S44:U44,1,AB44)) | AH44: =IF(AB44="","· enter odds",IF(AND(AF44>=Method!$B$7,AG44>=Method!$B$8),"BET","PASS")) -> · enter odds | AI44: =IF(AH44<>"BET",0,ROUND(MIN(Method!$B$6,Method!$B$5*AL44)*100,1)) -> 0 | AJ44: =IF(OR(AH44<>"BET",Method!$B$55=TRUE()),0,IF(AI44*Method!$B$10/100<Method!$B$9,0,ROUND(AI44*Method!$B$10/100,0))) -> 0 | AK44: =IF(AB44="","",INDEX(V44:X44,1,AB44)) | AL44: =IF(AH44<>"BET","",MAX(0,(AK44*AE44-1)/(AE44-1))) | AM44: =IF(AH44="BET",AF44+A44/1000000,"") | AN44: =IF(Matchday!N46="","",Matchday!N46) | AO44: =IF(Matchday!P46="","",Matchday!P46) | AP44: =IF(Matchday!Q46="","",Matchday!Q46) | AQ44: =IF(Matchday!R46="","",Matchday!R46) | AR44: =IF(OR(AN44<>"Y",AQ44="",AV44=""),"",IF(AQ44="Void",0,IF(AQ44=AV44,ROUND(AP44*(AO44-1),2),-AP44))) | AS44: =IF(AR44="","",SUM($AR$2:AR44)) | AT44: =IF(AB44="","Type the 3 odds on the Matchday tab",IF(Method!$B$55=TRUE(),"🛑 PAUSED — drawdown "&TEXT(Method!$B$51,"0.0%")&" ≥ "&TEXT(Method!$B$52,"0.0%")&". Set Method!B54=Y to override.",IF(AH44="BET",IF(AJ44=0,"Edge found but stake rounds under £"&Method!$B$9&" — skip","Value found: EV "&TEXT(AF44,"0.0%")&", edge "&TEXT(AG44,"0.0%")),IF(AF44<Method!$B$7,"Price too short — EV "&TEXT(AF44,"0.0%")&" (need "&TEXT(Method!$B$7,"0.0%")&"+)","Model ≈ market — edge "&TEXT(AG44,"0.0%")&" (need "&TEXT(Method!$B$8,"0.0%")&"+)")))) -> Type the 3 odds on the Matchday tab | AU44: =IF(AN44<>"Y","",IF(AH44="· enter odds","⚠ type the 3 odds (1/X/2) to grade this bet",IF(OR(AV44="",AO44="",AP44=""),"⚠ log backed pick, odds & stake",IF(AZ44<>"BET","⚠ FUN BET — engine said pass · staked £"&AP44&" vs engine £"&BA44,IF(AV44<>IF(AY44="",AC44,AY44),"⚠ backed "&AV44&" but engine pick was "&IF(AY44="",AC44,AY44),IF(AP44>BA44,"⚠ stake over engine £"&BA44,IF(ABS(AO44-IFERROR(INDEX(L44:N44,1,MATCH(AV44,{"H","D","A"},0)),AE44))>0.02,"⚠ odds moved — re-check value","✓ engine bet"))))))) | AV44: =IF(Matchday!O46="","",Matchday!O46) | AZ44: =IF(AW44="",AH44,AW44) -> · enter odds | BA44: =IF(AX44<>"",AX44,IF(AH44<>"BET",0,IF(AI44*Method!$B$10/100<Method!$B$9,0,ROUND(AI44*Method!$B$10/100,0)))) -> 0 | BB44: 0 | BC44: 0.4479931 | BD44: 0.28575992 | BE44: 0.26103885 | BG44: 7 | BH44: warm_humid | BI44: 273.9
A45: 44 | B45: 46195 | C45: J | D45: Jordan | E45: Algeria | F45: Santa Clara | G45: 23:00 | H45: 07:00 +1d | I45: 0.291255 | J45: 0.28137242 | K45: 0.42737258 | L45: =IF(Matchday!E47="","",Matchday!E47) | M45: =IF(Matchday!F47="","",Matchday!F47) | N45: =IF(Matchday!G47="","",Matchday!G47) | O45: =IF(L45="","",1/L45) | P45: =IF(M45="","",1/M45) | Q45: =IF(N45="","",1/N45) | R45: =IF(COUNT(L45:N45)<3,"",O45+P45+Q45) | S45: {=IF($R45="","",IF(Method!$B$56="proportional",O45/$R45,IF(Method!$B$56="power",IFERROR(INDEX(power_devig($L45,$M45,$N45),1,1),O45/$R45),IFERROR(INDEX(shin($L45,$M45,$N45),1,1),O45/$R45))))} | T45: {=IF($R45="","",IF(Method!$B$56="proportional",P45/$R45,IF(Method!$B$56="power",IFERROR(INDEX(power_devig($L45,$M45,$N45),2,1),P45/$R45),IFERROR(INDEX(shin($L45,$M45,$N45),2,1),P45/$R45))))} | U45: {=IF($R45="","",IF(Method!$B$56="proportional",Q45/$R45,IF(Method!$B$56="power",IFERROR(INDEX(power_devig($L45,$M45,$N45),3,1),Q45/$R45),IFERROR(INDEX(shin($L45,$M45,$N45),3,1),Q45/$R45))))} | V45: =IF(S45="","",Method!$B$4*I45+(1-Method!$B$4)*S45/($S45+$T45+$U45)) | W45: =IF(T45="","",Method!$B$4*J45+(1-Method!$B$4)*T45/($S45+$T45+$U45)) | X45: =IF(U45="","",Method!$B$4*K45+(1-Method!$B$4)*U45/($S45+$T45+$U45)) | Y45: =IF(V45="","",V45*L45-1) | Z45: =IF(W45="","",W45*M45-1) | AA45: =IF(X45="","",X45*N45-1) | AB45: =IF(Y45="","",MATCH(MAX(Y45:AA45),Y45:AA45,0)) | AC45: =IF(AB45="","",CHOOSE(AB45,"H","D","A")) | AD45: =IF(AB45="","",CHOOSE(AB45,"1 "&D45,"X Draw","2 "&E45)) | AE45: =IF(AB45="","",INDEX(L45:N45,1,AB45)) | AF45: =IF(AB45="","",INDEX(Y45:AA45,1,AB45)) | AG45: =IF(AB45="","",INDEX(V45:X45,1,AB45)-INDEX(S45:U45,1,AB45)) | AH45: =IF(AB45="","· enter odds",IF(AND(AF45>=Method!$B$7,AG45>=Method!$B$8),"BET","PASS")) -> · enter odds | AI45: =IF(AH45<>"BET",0,ROUND(MIN(Method!$B$6,Method!$B$5*AL45)*100,1)) -> 0 | AJ45: =IF(OR(AH45<>"BET",Method!$B$55=TRUE()),0,IF(AI45*Method!$B$10/100<Method!$B$9,0,ROUND(AI45*Method!$B$10/100,0))) -> 0 | AK45: =IF(AB45="","",INDEX(V45:X45,1,AB45)) | AL45: =IF(AH45<>"BET","",MAX(0,(AK45*AE45-1)/(AE45-1))) | AM45: =IF(AH45="BET",AF45+A45/1000000,"") | AN45: =IF(Matchday!N47="","",Matchday!N47) | AO45: =IF(Matchday!P47="","",Matchday!P47) | AP45: =IF(Matchday!Q47="","",Matchday!Q47) | AQ45: =IF(Matchday!R47="","",Matchday!R47) | AR45: =IF(OR(AN45<>"Y",AQ45="",AV45=""),"",IF(AQ45="Void",0,IF(AQ45=AV45,ROUND(AP45*(AO45-1),2),-AP45))) | AS45: =IF(AR45="","",SUM($AR$2:AR45)) | AT45: =IF(AB45="","Type the 3 odds on the Matchday tab",IF(Method!$B$55=TRUE(),"🛑 PAUSED — drawdown "&TEXT(Method!$B$51,"0.0%")&" ≥ "&TEXT(Method!$B$52,"0.0%")&". Set Method!B54=Y to override.",IF(AH45="BET",IF(AJ45=0,"Edge found but stake rounds under £"&Method!$B$9&" — skip","Value found: EV "&TEXT(AF45,"0.0%")&", edge "&TEXT(AG45,"0.0%")),IF(AF45<Method!$B$7,"Price too short — EV "&TEXT(AF45,"0.0%")&" (need "&TEXT(Method!$B$7,"0.0%")&"+)","Model ≈ market — edge "&TEXT(AG45,"0.0%")&" (need "&TEXT(Method!$B$8,"0.0%")&"+)")))) -> Type the 3 odds on the Matchday tab | AU45: =IF(AN45<>"Y","",IF(AH45="· enter odds","⚠ type the 3 odds (1/X/2) to grade this bet",IF(OR(AV45="",AO45="",AP45=""),"⚠ log backed pick, odds & stake",IF(AZ45<>"BET","⚠ FUN BET — engine said pass · staked £"&AP45&" vs engine £"&BA45,IF(AV45<>IF(AY45="",AC45,AY45),"⚠ backed "&AV45&" but engine pick was "&IF(AY45="",AC45,AY45),IF(AP45>BA45,"⚠ stake over engine £"&BA45,IF(ABS(AO45-IFERROR(INDEX(L45:N45,1,MATCH(AV45,{"H","D","A"},0)),AE45))>0.02,"⚠ odds moved — re-check value","✓ engine bet"))))))) | AV45: =IF(Matchday!O47="","",Matchday!O47) | AZ45: =IF(AW45="",AH45,AW45) -> · enter odds | BA45: =IF(AX45<>"",AX45,IF(AH45<>"BET",0,IF(AI45*Method!$B$10/100<Method!$B$9,0,ROUND(AI45*Method!$B$10/100,0)))) -> 0 | BB45: 0 | BC45: 0.27858519 | BD45: 0.28661816 | BE45: 0.42861914 | BG45: 8 | BH45: mild_dry | BI45: 0
